Workbook
Name A_F: mortality!$B$3
Name A_F: 'P01'!$B$29
Name A_F: 'P02'!$B$29
Name A_F: 'P03'!$B$29
Name A_F: 'P04'!$B$29
Name A_F: 'P05'!$B$29
Name A_F: 'P06'!$B$29
Name A_F: 'P07'!$B$29
Name A_F: 'P08'!$B$29
Name A_F: 'P09'!$B$29
Name A_F: 'P10'!$B$29
Name A_M: mortality!$B$2
Name A_M: 'P01'!$B$28
Name A_M: 'P02'!$B$28
Name A_M: 'P03'!$B$28
Name A_M: 'P04'!$B$28
Name A_M: 'P05'!$B$28
Name A_M: 'P06'!$B$28
Name A_M: 'P07'!$B$28
Name A_M: 'P08'!$B$28
Name A_M: 'P09'!$B$28
Name A_M: 'P10'!$B$28
Name age_at_entry: 'P01'!$B$14
Name age_at_entry: 'P02'!$B$14
Name age_at_entry: 'P03'!$B$14
Name age_at_entry: 'P04'!$B$14
Name age_at_entry: 'P05'!$B$14
Name age_at_entry: 'P06'!$B$14
Name age_at_entry: 'P07'!$B$14
Name age_at_entry: 'P08'!$B$14
Name age_at_entry: 'P09'!$B$14
Name age_at_entry: 'P10'!$B$14
Name all_ok: summary!$B$28
Name B_F: mortality!$B$5
Name B_F: 'P01'!$B$31
Name B_F: 'P02'!$B$31
Name B_F: 'P03'!$B$31
Name B_F: 'P04'!$B$31
Name B_F: 'P05'!$B$31
Name B_F: 'P06'!$B$31
Name B_F: 'P07'!$B$31
Name B_F: 'P08'!$B$31
Name B_F: 'P09'!$B$31
Name B_F: 'P10'!$B$31
Name B_M: mortality!$B$4
Name B_M: 'P01'!$B$30
Name B_M: 'P02'!$B$30
Name B_M: 'P03'!$B$30
Name B_M: 'P04'!$B$30
Name B_M: 'P05'!$B$30
Name B_M: 'P06'!$B$30
Name B_M: 'P07'!$B$30
Name B_M: 'P08'!$B$30
Name B_M: 'P09'!$B$30
Name B_M: 'P10'!$B$30
Name birth_date: 'P01'!$B$5
Name birth_date: 'P02'!$B$5
Name birth_date: 'P03'!$B$5
Name birth_date: 'P04'!$B$5
Name birth_date: 'P05'!$B$5

Sheet readme
A1: Halley term assurance: reference workbook for docs/spec/term-assurance.md (version 0.1).
A2: Built from the specification alone: typed cells are its reference inputs (sections 3.3, 6, 13); every other cell is a formula transcribing one formula of the spec.
A4: Sheets
A5: mortality: the 6.1 parameters A and B by sex and c, and the mortality table q_ann(sex, x) materialised for ages 18 to 120 from the 6.1 formula in its stated order (section 11, materialised-block option). The one block shared by the policy sheets: each q_ann cell looks it up by INDEX/MATCH on (sex, age).
A6: P01 .. P10: one sheet per policy, named by policy_id, with the section 11 blocks in order from the top: inputs (3.1, plus the run-level valuation_date of 3.3), typed; derived constants (3.2, 4.3, 5) by formula; basis constants (6) with i_m, v_m, e_m by formula; lapse table (6.2); commission table (6.6); the monthly block (7.1, 11.1) with a header row and rows t = 0 .. rem_m, the row checks of section 12 to its right; scalars (11.2); check cells (12). Every formula reads this sheet's own cells, through sheet-scoped defined names (sex, premium, rem_m, i_m, lapse_table, scale_money, ...) or same-sheet absolute references, except the q_ann lookup on mortality.
A7: summary: the 11.2 scalars per policy by reference, the 11.3 scalar totals in the row labelled total (plain SUMs in ascending policy_id order), the <id>_ok cells per policy by reference with ok per policy and all_ok (defined name all_ok), and the 11.3 totals by t = 0 .. 480 over the ten policies, policies beyond their own rem_m read as zero.
A9: Conventions
A10: q_ann is looked up from the materialised (sex, age, q_ann) block on mortality, ages 18 to 120, each cell the section 6.1 formula in its stated order (section 11 option 2); the 6.1 parameters are typed on mortality (the table reads them) and on every policy sheet (the basis block of section 11).
A11: Row t = 0 holds the state variables only (pols_if, infl, disc, reserve, reserve_pp, reserve_floored); month quantities are blank there (section 4.1).
A12: Tolerance (section 1): |a - b| <= 1e-9 * max(|a|, |b|, scale); inequalities use a <= b + 1e-9 * scale; 'exactly' is a plain = comparison. The scales are the check block's scale_money, scale_pp and scale_count, from the sheet's own inputs.
A13: P7 and P11 are engine-only (rows beyond rem_m, batch independence) and have no cell.
A14: The spec's c is the defined name gm_c because Excel reserves the names R and C.
... A17: Policy sheet blocks (block, rows; column A label or t, B value, C section, D unit)
A18: inputs (3.1, 3.3), typed | B18: 2 to 11
A19: derived constants (3.2, 4.3, 5), by formula | B19: 14 to 20
A20: basis constants (6), i_m, v_m, e_m by formula | B20: 23 to 34
A21: lapse table (6.2) | B21: 38 to 43
A22: commission table (6.6) | B22: 47 to 48
A23: monthly block (7.1, 11.1) and row checks (12) | B23: header 51; row of t is 52 + t
A24: scalars (11.2) | B24: from 55 + rem_m
A25: check cells (12): scales and helpers, then <id>_ok, rows_ok, ok | B25: from 74 + rem_m; <id>_ok from 80 + rem_m
A27: Policy sheet monthly columns (symbol, unit, spec section)
A28: t | B28: Int | C28: 4.1
A29: dur_y | B29: Int | C29: 5
A30: age | B30: Int | C30: 5
A31: q_ann | B31: Prob annual | C31: 6.1
A32: q_m | B32: Prob monthly | C32: 6.1
A33: w_ann | B33: Prob annual | C33: 6.2
A34: w_m | B34: Prob monthly | C34: 6.2
A35: comm_rate | B35: Fraction | C35: 6.6
A36: infl | B36: factor (state; infl(0) = 1) | C36: 6.4
A37: deaths | B37: Count | C37: 7.3
A38: lapses | B38: Count | C38: 7.3
A39: maturities | B39: Count | C39: 7.3
... A62: reserve_floored | B62: Money (state) | C62: 10.5
A64: Policy sheet row check columns (section 12)
A65: H1 | B65: pols_if >= 0 and non-increasing, exactly (t = 0 .. rem_m)
A66: H2 | B66: rates in [0, 1] exactly; deaths + lapses + maturities <= pols_if(t-1) within tolerance
A67: H4_lhs | B67: helper: roll-forward left-hand side
A68: H4 | B68: roll-forward equals reserve(t) within tolerance
A69: H5b_term | B69: helper: month-s term of the H5b sum
A70: H5b_sum | B70: helper: sum of H5b_term over s = t+1 .. rem_m, ascending
A71: H5b | B71: reserve(t) * disc(t) equals the H5b sum within tolerance (t = 0 .. rem_m - 1)
A72: P1 | B72: maturities exactly 0 except at rem_m, where it equals the survivors exactly
A73: P2 | B73: premium, commission and lapse quantities exactly 0 after prem_rem_m; premium_income
A74: P4 | B74: age in 18 .. 120; dur_y steps by 0 or 1
A75: P5_rhs | B75: helper: per-policy recursion right-hand side
A76: P5 | B76: reserve_pp(t) equals the per-policy recursion within tolerance (scale sum_assured)
... A78: P10 | B78: unit identities, exactly
A80: Policy sheet check cells (section 12), repeated on summary
A81: H1_ok | B81: every H1 row cell (t = 0 .. rem_m)
A82: H2_ok | B82: every H2 row cell (t = 1 .. rem_m)
A83: H3_ok | B83: reserve(rem_m) = 0 and pols_if(rem_m) = 0, exactly
A84: H4_ok | B84: every H4 row cell (t = 1 .. rem_m)
A85: H5a_ok | B85: reserve(0) equals -pv_net_cf within tolerance (scale_money)
A86: H5b_ok | B86: every H5b row cell (t = 0 .. rem_m - 1)
A87: P1_ok | B87: every P1 row cell (t = 1 .. rem_m)
A88: P2_ok | B88: every P2 row cell (t = 1 .. rem_m)
A89: P3_ok | B89: the number of months with premium_pp <> 0 equals prem_rem_m
A90: P4_ok | B90: every P4 row cell (t = 1 .. rem_m)
A91: P5_ok | B91: every P5 row cell (t = 0 .. rem_m - 1)
A92: P6_ok | B92: every P6 row cell (t = 0 .. rem_m)
... A97: ok | B97: every cell above

Sheet mortality
A1: Mortality parameters (section 6.1), each in one cell: the table below reads these
A2: A_M | B2: 0.0002 | C2: 6.1 | D2: Gompertz-Makeham A, sex M
A3: A_F | B3: 0.00015 | C3: 6.1 | D3: Gompertz-Makeham A, sex F
A4: B_M | B4: 1.7e-05 | C4: 6.1 | D4: Gompertz-Makeham B, sex M
A5: B_F | B5: 1.1e-05 | C5: 6.1 | D5: Gompertz-Makeham B, sex F
A6: c | B6: 1.1 | C6: 6.1 | D6: Gompertz-Makeham c (both sexes); defined name gm_c
A8: Mortality table q_ann(sex, x) (section 6.1): 1 - exp(-(A + B * c^x * (c - 1) / ln(c))), ages 18 to 120; shared by every policy sheet, which looks it up by (sex, age)
A9: x | B9: M | C9: F
A10: 18 | B10: =1-EXP(-(A_M+B_M*gm_c^$A10*(gm_c-1)/LN(gm_c))) -> 0.00029912472 | C10: =1-EXP(-(A_F+B_F*gm_c^$A10*(gm_c-1)/LN(gm_c))) -> 0.00021414554
A11: 19 | B11: =1-EXP(-(A_M+B_M*gm_c^$A11*(gm_c-1)/LN(gm_c))) -> 0.00030903865 | C11: =1-EXP(-(A_F+B_F*gm_c^$A11*(gm_c-1)/LN(gm_c))) -> 0.000220561
A12: 20 | B12: =1-EXP(-(A_M+B_M*gm_c^$A12*(gm_c-1)/LN(gm_c))) -> 0.00031994386 | C12: =1-EXP(-(A_F+B_F*gm_c^$A12*(gm_c-1)/LN(gm_c))) -> 0.00022761795
A13: 21 | B13: =1-EXP(-(A_M+B_M*gm_c^$A13*(gm_c-1)/LN(gm_c))) -> 0.00033193945 | C13: =1-EXP(-(A_F+B_F*gm_c^$A13*(gm_c-1)/LN(gm_c))) -> 0.00023538054
A14: 22 | B14: =1-EXP(-(A_M+B_M*gm_c^$A14*(gm_c-1)/LN(gm_c))) -> 0.00034513444 | C14: =1-EXP(-(A_F+B_F*gm_c^$A14*(gm_c-1)/LN(gm_c))) -> 0.00024391931
A15: 23 | B15: =1-EXP(-(A_M+B_M*gm_c^$A15*(gm_c-1)/LN(gm_c))) -> 0.00035964872 | C15: =1-EXP(-(A_F+B_F*gm_c^$A15*(gm_c-1)/LN(gm_c))) -> 0.00025331188
A16: 24 | B16: =1-EXP(-(A_M+B_M*gm_c^$A16*(gm_c-1)/LN(gm_c))) -> 0.00037561419 | C16: =1-EXP(-(A_F+B_F*gm_c^$A16*(gm_c-1)/LN(gm_c))) -> 0.00026364361
A17: 25 | B17: =1-EXP(-(A_M+B_M*gm_c^$A17*(gm_c-1)/LN(gm_c))) -> 0.00039317592 | C17: =1-EXP(-(A_F+B_F*gm_c^$A17*(gm_c-1)/LN(gm_c))) -> 0.00027500839
A18: 26 | B18: =1-EXP(-(A_M+B_M*gm_c^$A18*(gm_c-1)/LN(gm_c))) -> 0.00041249345 | C18: =1-EXP(-(A_F+B_F*gm_c^$A18*(gm_c-1)/LN(gm_c))) -> 0.00028750949
A19: 27 | B19: =1-EXP(-(A_M+B_M*gm_c^$A19*(gm_c-1)/LN(gm_c))) -> 0.00043374231 | C19: =1-EXP(-(A_F+B_F*gm_c^$A19*(gm_c-1)/LN(gm_c))) -> 0.00030126052
A20: 28 | B20: =1-EXP(-(A_M+B_M*gm_c^$A20*(gm_c-1)/LN(gm_c))) -> 0.00045711554 | C20: =1-EXP(-(A_F+B_F*gm_c^$A20*(gm_c-1)/LN(gm_c))) -> 0.00031638644
A21: 29 | B21: =1-EXP(-(A_M+B_M*gm_c^$A21*(gm_c-1)/LN(gm_c))) -> 0.00048282546 | C21: =1-EXP(-(A_F+B_F*gm_c^$A21*(gm_c-1)/LN(gm_c))) -> 0.00033302469
... A112: 120 | B112: =1-EXP(-(A_M+B_M*gm_c^$A112*(gm_c-1)/LN(gm_c))) -> 0.80867951 | C112: =1-EXP(-(A_F+B_F*gm_c^$A112*(gm_c-1)/LN(gm_c))) -> 0.65703603

Sheet P01
A1: Inputs (section 3.1, from section 13) and the run-level valuation_date (3.3), typed
A2: valuation_date | B2: 46388 | C2: 3.3 | D2: Date, first of a month (run-level input)
A3: policy_id | B3: P01 | C3: 3.1 | D3: string
A4: sex | B4: M | C4: 3.1 | D4: string, M or F
A5: birth_date | B5: 31486 | C5: 3.1 | D5: Date
A6: entry_date | B6: 45474 | C6: 3.1 | D6: Date
A7: maturity_date | B7: 52779 | C7: 3.1 | D7: Date
A8: prem_term_y | B8: 20 | C8: 3.1 | D8: Int (years)
A9: sum_assured | B9: 250000 | C9: 3.1 | D9: Money per policy
A10: premium | B10: 52.96 | C10: 3.1 | D10: Money per policy, monthly, in advance
A11: pols_if_init | B11: 1 | C11: 3.1 | D11: Count
A13: Derived constants (sections 3.2, 4.3 and 5), by formula
A14: age_at_entry | B14: =YEAR(entry_date)-YEAR(birth_date)-IF(OR(MONTH(entry_date)<MONTH(birth_date),AND(MONTH(entry_date)=MONTH(birth_date),DAY(entry_date)<DAY(birth_date))),1,0) -> 38 | C14: 5 | D14: Int (years)
A15: dur_m | B15: =12*(YEAR(valuation_date)-YEAR(entry_date))+(MONTH(valuation_date)-MONTH(entry_date))-IF(DAY(valuation_date)<DAY(entry_date),1,0) -> 30 | C15: 4.3 | D15: Int (months)
A16: term_m | B16: =12*(YEAR(maturity_date)-YEAR(entry_date))+(MONTH(maturity_date)-MONTH(entry_date))-IF(DAY(maturity_date)<DAY(entry_date),1,0) -> 240 | C16: 4.3 | D16: Int (months)
A17: rem_m | B17: =term_m-dur_m -> 210 | C17: 4.3 | D17: Int (months)
A18: prem_term_m | B18: =12*prem_term_y -> 240 | C18: 4.3 | D18: Int (months)
A19: prem_rem_m | B19: =MAX(prem_term_m-dur_m,0) -> 210 | C19: 4.3 | D19: Int (months)
A20: dur_y_last | B20: =INT((term_m-1)/12) -> 19 | C20: 4.3 | D20: Int (years)
A22: Basis constants (section 6), each in one cell
A23: i | B23: 0.04 | C23: 6 | D23: Rate[Annual]
A24: e | B24: 0.03 | C24: 6 | D24: Rate[Annual]
A25: i_m | B25: =(1+i)^(1/12)-1 -> 0.0032737398 | C25: 6 | D25: Rate[Monthly]
A26: v_m | B26: =(1+i)^(-1/12) -> 0.99673694 | C26: 6 | D26: factor
A27: e_m | B27: =(1+e)^(1/12)-1 -> 0.0024662698 | C27: 6 | D27: Rate[Monthly]
A28: A_M | B28: 0.0002 | C28: 6.1 | D28: Gompertz-Makeham A, sex M
A29: A_F | B29: 0.00015 | C29: 6.1 | D29: Gompertz-Makeham A, sex F
A30: B_M | B30: 1.7e-05 | C30: 6.1 | D30: Gompertz-Makeham B, sex M
A31: B_F | B31: 1.1e-05 | C31: 6.1 | D31: Gompertz-Makeham B, sex F
A32: c | B32: 1.1 | C32: 6.1 | D32: Gompertz-Makeham c (both sexes); defined name gm_c
A33: maint_base | B33: 5 | C33: 6.5 | D33: Money per policy, per month, time-0 prices
A34: claim_exp_base | B34: 250 | C34: 6.5 | D34: Money per policy (per death), time-0 prices
A36: Lapse table (section 6.2): key k = min(dur_y, 5)
A37: k | B37: lapse_table | D37: Prob, annual
A38: 0 | B38: 0.15
A39: 1 | B39: 0.1
A40: 2 | B40: 0.08
A41: 3 | B41: 0.06
A42: 4 | B42: 0.05
A43: 5 | B43: 0.04
A45: Commission table (section 6.6): key k = min(dur_y, 1)
A46: k | B46: comm_table | D46: Fraction
A47: 0 | B47: 0.2
A48: 1 | B48: 0.02
A50: Monthly block (sections 7.1 and 11.1): rows t = 0 .. rem_m, one column per quantity in the 7.1 order; the row-level check cells of section 12 follow the blank column
A51: t | B51: dur_y | C51: age | D51: q_ann | E51: q_m | F51: w_ann | G51: w_m | H51: comm_rate | I51: infl | J51: deaths | K51: lapses | L51: maturities | M51: pols_if | N51: premium_pp | O51: commission_pp | P51: maint_pp | Q51: claim_exp_pp | R51: premium_income | S51: commission | T51: maint_expense | U51: death_outgo | V51: claim_expense | W51: net_cf | X51: net_outgo | Y51: v | Z51: disc | AA51: pv_net_cf_t | AB51: pv_premiums_t | AC51: pv_commission_t | AD51: pv_maint_expense_t | AE51: pv_death_outgo_t | AF51: pv_claim_expense_t | AG51: reserve | AH51: reserve_pp | AI51: reserve_floored | AK51: H1 | AL51: H2 | AM51: H4_lhs | AN51: H4 | AO51: H5b_term | AP51: H5b_sum | AQ51: H5b | AR51: P1 | AS51: P2 | AT51: P4 | AU51: P5_rhs | AV51: P5 | AW51: P6 | AX51: P10
A52: 0 | I52: 1 | M52: =pols_if_init -> 1 | Z52: 1 | AG52: =(AG53+X53)*Y53 -> -653.94869 | AH52: =IF(M52>0,AG52/M52,0) -> -653.94869 | AI52: =IF(AG52>0,AG52,0) -> 0 | AK52: =M52>=0 -> TRUE | AP52: =SUM(AO53:$AO$262) -> -653.94869 | AQ52: =ABS(AG52*Z52-AP52)<=0.000000001*MAX(ABS(AG52*Z52),ABS(AP52),scale_money) -> TRUE | AU52: =-(N53-O53)+v_m*(E53*(sum_assured+Q53)+P53+(1-E53)*(1-G53)*AH53) -> -653.94869 | AV52: =ABS(AH52-AU52)<=0.000000001*MAX(ABS(AH52),ABS(AU52),scale_pp) -> TRUE | AW52: =AND(AI52>=0,AI52>=AG52) -> TRUE
A53: 1 | B53: =MIN(INT((dur_m+A53-1)/12),dur_y_last) -> 2 | C53: =age_at_entry+B53 -> 40 | D53: =INDEX(mort_table,MATCH(C53,mort_age,0),MATCH(sex,mort_sex,0)) -> 0.0010067596 | E53: =IF(A53<=rem_m,1-(1-D53)^(1/12),0) -> 8.3935369e-05 | F53: =IF(A53<=prem_rem_m,INDEX(lapse_table,MATCH(MIN(B53,5),lapse_key,0)),0) -> 0.08 | G53: =1-(1-F53)^(1/12) -> 0.0069243826 | H53: =INDEX(comm_table,MATCH(MIN(B53,1),comm_key,0)) -> 0.02 | I53: =(1+e_m)^A53 -> 1.0024663 | J53: =M52*E53 -> 8.3935369e-05 | K53: =(M52-J53)*G53 -> 0.0069238014 | L53: =IF(A53=rem_m,M52-J53-K53,0) -> 0 | M53: =M52-J53-K53-L53 -> 0.99299226 | N53: =IF(A53<=prem_rem_m,premium,0) -> 52.96 | O53: =N53*H53 -> 1.0592 | P53: =maint_base*I53 -> 5.0123313 | Q53: =claim_exp_base*I53 -> 250.61657 | R53: =M52*N53 -> 52.96 | S53: =R53*H53 -> 1.0592 | T53: =M52*P53 -> 5.0123313 | U53: =J53*sum_assured -> 20.983842 | V53: =J53*Q53 -> 0.021035594 | W53: =R53-S53-T53-U53-V53 -> 25.883591 | X53: =U53+V53+T53-(R53-S53)*(1+i_m) -> -26.053501 | Y53: =v_m -> 0.99673694 | Z53: =v_m^A53 -> 0.99673694 | AA53: =(R53-S53)*Z52-(T53+U53+V53)*Z53 -> 25.968486 | AB53: =R53*Z52 -> 52.96 | AC53: =S53*Z52 -> 1.0592 | AD53: =T53*Z53 -> 4.9959758 | AE53: =U53*Z53 -> 20.915371 | AF53: =V53*Z53 -> 0.020966954 | AG53: =(AG54+X54)*Y54 -> -630.03604 | AH53: =IF(M53>0,AG53/M53,0) -> -634.48233 | AI53: =IF(AG53>0,AG53,0) -> 0 | AK53: =AND(M53>=0,M53<=M52) -> TRUE | AL53: =AND(D53>=0,D53<=1,E53>=0,E53<=1,F53>=0,F53<=1,G53>=0,G53<=1,J53+K53+L53<=M52+0.000000001*scale_count) -> TRUE | AM53: =(AG52+R53-S53)*(1+i_m)-T53-U53-V53 -> -630.03604 | AN53: =ABS(AM53-AG53)<=0.000000001*MAX(ABS(AM53),ABS(AG53),scale_money) -> TRUE | AO53: =(U53+V53+T53)*Z53-(R53-S53)*Z52 -> -25.968486 | AP53: =SUM(AO54:$AO$262) -> -627.9802 | AQ53: =ABS(AG53*Z53-AP53)<=0.000000001*MAX(ABS(AG53*Z53),ABS(AP53),scale_money) -> TRUE | AR53: =IF(A53<>rem_m,L53=0,L53=M52-J53-K53) -> TRUE | AS53: =IF(A53>prem_rem_m,AND(R53=0,S53=0,F53=0,G53=0,K53=0),R53=M52*premium) -> TRUE | AT53: =AND(C53>=18,C53<=120) -> TRUE | AU53: =-(N54-O54)+v_m*(E54*(sum_assured+Q54)+P54+(1-E54)*(1-G54)*AH54) -> -634.48233 | AV53: =ABS(AH53-AU53)<=0.000000001*MAX(ABS(AH53),ABS(AU53),scale_pp) -> TRUE | AW53: =AND(AI53>=0,AI53>=AG53) -> TRUE | AX53: =AND(U53=J53*sum_assured,R53=M52*N53,T53=M52*P53) -> TRUE
A54: 2 | B54: =MIN(INT((dur_m+A54-1)/12),dur_y_last) -> 2 | C54: =age_at_entry+B54 -> 40 | D54: =INDEX(mort_table,MATCH(C54,mort_age,0),MATCH(sex,mort_sex,0)) -> 0.0010067596 | E54: =IF(A54<=rem_m,1-(1-D54)^(1/12),0) -> 8.3935369e-05 | F54: =IF(A54<=prem_rem_m,INDEX(lapse_table,MATCH(MIN(B54,5),lapse_key,0)),0) -> 0.08 | G54: =1-(1-F54)^(1/12) -> 0.0069243826 | H54: =INDEX(comm_table,MATCH(MIN(B54,1),comm_key,0)) -> 0.02 | I54: =(1+e_m)^A54 -> 1.0049386 | J54: =M53*E54 -> 8.3347172e-05 | K54: =(M53-J54)*G54 -> 0.0068752812 | L54: =IF(A54=rem_m,M53-J54-K54,0) -> 0 | M54: =M53-J54-K54-L54 -> 0.98603363 | N54: =IF(A54<=prem_rem_m,premium,0) -> 52.96 | O54: =N54*H54 -> 1.0592 | P54: =maint_base*I54 -> 5.0246931 | Q54: =claim_exp_base*I54 -> 251.23466 | R54: =M53*N54 -> 52.58887 | S54: =R54*H54 -> 1.0517774 | T54: =M53*P54 -> 4.9894814 | U54: =J54*sum_assured -> 20.836793 | V54: =J54*Q54 -> 0.020939698 | W54: =R54-S54-T54-U54-V54 -> 25.689879 | X54: =U54+V54+T54-(R54-S54)*(1+i_m) -> -25.858598 | Y54: =v_m -> 0.99673694 | Z54: =v_m^A54 -> 0.99348453 | AA54: =(R54-S54)*Z53-(T54+U54+V54)*Z54 -> 25.690117 | AB54: =R54*Z53 -> 52.41727 | AC54: =S54*Z53 -> 1.0483454 | AD54: =T54*Z54 -> 4.9569726 | AE54: =U54*Z54 -> 20.701032 | AF54: =V54*Z54 -> 0.020803266 | AG54: =(AG55+X55)*Y55 -> -606.24002 | AH54: =IF(M54>0,AG54/M54,0) -> -614.82692 | AI54: =IF(AG54>0,AG54,0) -> 0 | AK54: =AND(M54>=0,M54<=M53) -> TRUE | AL54: =AND(D54>=0,D54<=1,E54>=0,E54<=1,F54>=0,F54<=1,G54>=0,G54<=1,J54+K54+L54<=M53+0.000000001*scale_count) -> TRUE | AM54: =(AG53+R54-S54)*(1+i_m)-T54-U54-V54 -> -606.24002 | AN54: =ABS(AM54-AG54)<=0.000000001*MAX(ABS(AM54),ABS(AG54),scale_money) -> TRUE | AO54: =(U54+V54+T54)*Z54-(R54-S54)*Z53 -> -25.690117 | AP54: =SUM(AO55:$AO$262) -> -602.29008 | AQ54: =ABS(AG54*Z54-AP54)<=0.000000001*MAX(ABS(AG54*Z54),ABS(AP54),scale_money) -> TRUE | AR54: =IF(A54<>rem_m,L54=0,L54=M53-J54-K54) -> TRUE | AS54: =IF(A54>prem_rem_m,AND(R54=0,S54=0,F54=0,G54=0,K54=0),R54=M53*premium) -> TRUE | AT54: =AND(C54>=18,C54<=120,OR(B54-B53=0,B54-B53=1)) -> TRUE | AU54: =-(N55-O55)+v_m*(E55*(sum_assured+Q55)+P55+(1-E55)*(1-G55)*AH55) -> -614.82692 | AV54: =ABS(AH54-AU54)<=0.000000001*MAX(ABS(AH54),ABS(AU54),scale_pp) -> TRUE | AW54: =AND(AI54>=0,AI54>=AG54) -> TRUE | AX54: =AND(U54=J54*sum_assured,R54=M53*N54,T54=M53*P54) -> TRUE
A55: 3 | B55: =MIN(INT((dur_m+A55-1)/12),dur_y_last) -> 2 | C55: =age_at_entry+B55 -> 40 | D55: =INDEX(mort_table,MATCH(C55,mort_age,0),MATCH(sex,mort_sex,0)) -> 0.0010067596 | E55: =IF(A55<=rem_m,1-(1-D55)^(1/12),0) -> 8.3935369e-05 | F55: =IF(A55<=prem_rem_m,INDEX(lapse_table,MATCH(MIN(B55,5),lapse_key,0)),0) -> 0.08 | G55: =1-(1-F55)^(1/12) -> 0.0069243826 | H55: =INDEX(comm_table,MATCH(MIN(B55,1),comm_key,0)) -> 0.02 | I55: =(1+e_m)^A55 -> 1.0074171 | J55: =M54*E55 -> 8.2763097e-05 | K55: =(M54-J55)*G55 -> 0.0068271011 | L55: =IF(A55=rem_m,M54-J55-K55,0) -> 0 | M55: =M54-J55-K55-L55 -> 0.97912377 | N55: =IF(A55<=prem_rem_m,premium,0) -> 52.96 | O55: =N55*H55 -> 1.0592 | P55: =maint_base*I55 -> 5.0370854 | Q55: =claim_exp_base*I55 -> 251.85427 | R55: =M54*N55 -> 52.220341 | S55: =R55*H55 -> 1.0444068 | T55: =M54*P55 -> 4.9667356 | U55: =J55*sum_assured -> 20.690774 | V55: =J55*Q55 -> 0.020844239 | W55: =R55-S55-T55-U55-V55 -> 25.49758 | X55: =U55+V55+T55-(R55-S55)*(1+i_m) -> -25.665117 | Y55: =v_m -> 0.99673694 | Z55: =v_m^A55 -> 0.99024274 | AA55: =(R55-S55)*Z54-(T55+U55+V55)*Z55 -> 25.414696 | AB55: =R55*Z54 -> 51.880101 | AC55: =S55*Z54 -> 1.037602 | AD55: =T55*Z55 -> 4.9182738 | AE55: =U55*Z55 -> 20.488889 | AF55: =V55*Z55 -> 0.020640856 | AG55: =(AG56+X56)*Y56 -> -582.55958 | AH55: =IF(M55>0,AG55/M55,0) -> -594.98053 | AI55: =IF(AG55>0,AG55,0) -> 0 | AK55: =AND(M55>=0,M55<=M54) -> TRUE | AL55: =AND(D55>=0,D55<=1,E55>=0,E55<=1,F55>=0,F55<=1,G55>=0,G55<=1,J55+K55+L55<=M54+0.000000001*scale_count) -> TRUE | AM55: =(AG54+R55-S55)*(1+i_m)-T55-U55-V55 -> -582.55958 | AN55: =ABS(AM55-AG55)<=0.000000001*MAX(ABS(AM55),ABS(AG55),scale_money) -> TRUE | AO55: =(U55+V55+T55)*Z55-(R55-S55)*Z54 -> -25.414696 | AP55: =SUM(AO56:$AO$262) -> -576.87539 | AQ55: =ABS(AG55*Z55-AP55)<=0.000000001*MAX(ABS(AG55*Z55),ABS(AP55),scale_money) -> TRUE | AR55: =IF(A55<>rem_m,L55=0,L55=M54-J55-K55) -> TRUE | AS55: =IF(A55>prem_rem_m,AND(R55=0,S55=0,F55=0,G55=0,K55=0),R55=M54*premium) -> TRUE | AT55: =AND(C55>=18,C55<=120,OR(B55-B54=0,B55-B54=1)) -> TRUE | AU55: =-(N56-O56)+v_m*(E56*(sum_assured+Q56)+P56+(1-E56)*(1-G56)*AH56) -> -594.98053 | AV55: =ABS(AH55-AU55)<=0.000000001*MAX(ABS(AH55),ABS(AU55),scale_pp) -> TRUE | AW55: =AND(AI55>=0,AI55>=AG55) -> TRUE | AX55: =AND(U55=J55*sum_assured,R55=M54*N55,T55=M54*P55) -> TRUE
A56: 4 | B56: =MIN(INT((dur_m+A56-1)/12),dur_y_last) -> 2 | C56: =age_at_entry+B56 -> 40 | D56: =INDEX(mort_table,MATCH(C56,mort_age,0),MATCH(sex,mort_sex,0)) -> 0.0010067596 | E56: =IF(A56<=rem_m,1-(1-D56)^(1/12),0) -> 8.3935369e-05 | F56: =IF(A56<=prem_rem_m,INDEX(lapse_table,MATCH(MIN(B56,5),lapse_key,0)),0) -> 0.08 | G56: =1-(1-F56)^(1/12) -> 0.0069243826 | H56: =INDEX(comm_table,MATCH(MIN(B56,1),comm_key,0)) -> 0.02 | I56: =(1+e_m)^A56 -> 1.0099016 | J56: =M55*E56 -> 8.2183115e-05 | K56: =(M55-J56)*G56 -> 0.0067792586 | L56: =IF(A56=rem_m,M55-J56-K56,0) -> 0 | M56: =M55-J56-K56-L56 -> 0.97226233 | N56: =IF(A56<=prem_rem_m,premium,0) -> 52.96 | O56: =N56*H56 -> 1.0592 | P56: =maint_base*I56 -> 5.0495082 | Q56: =claim_exp_base*I56 -> 252.47541 | R56: =M55*N56 -> 51.854395 | S56: =R56*H56 -> 1.0370879 | T56: =M55*P56 -> 4.9440935 | U56: =J56*sum_assured -> 20.545779 | V56: =J56*Q56 -> 0.020749216 | W56: =R56-S56-T56-U56-V56 -> 25.306686 | X56: =U56+V56+T56-(R56-S56)*(1+i_m) -> -25.473048 | Y56: =v_m -> 0.99673694 | Z56: =v_m^A56 -> 0.98701152 | AA56: =(R56-S56)*Z55-(T56+U56+V56)*Z56 -> 25.142192 | AB56: =R56*Z55 -> 51.348438 | AC56: =S56*Z55 -> 1.0269688 | AD56: =T56*Z56 -> 4.8798772 | AE56: =U56*Z56 -> 20.27892 | AF56: =V56*Z56 -> 0.020479715 | AG56: =(AG57+X57)*Y57 -> -558.99368 | AH56: =IF(M56>0,AG56/M56,0) -> -574.94121 | AI56: =IF(AG56>0,AG56,0) -> 0 | AK56: =AND(M56>=0,M56<=M55) -> TRUE | AL56: =AND(D56>=0,D56<=1,E56>=0,E56<=1,F56>=0,F56<=1,G56>=0,G56<=1,J56+K56+L56<=M55+0.000000001*scale_count) -> TRUE | AM56: =(AG55+R56-S56)*(1+i_m)-T56-U56-V56 -> -558.99368 | AN56: =ABS(AM56-AG56)<=0.000000001*MAX(ABS(AM56),ABS(AG56),scale_money) -> TRUE | AO56: =(U56+V56+T56)*Z56-(R56-S56)*Z55 -> -25.142192 | AP56: =SUM(AO57:$AO$262) -> -551.7332 | AQ56: =ABS(AG56*Z56-AP56)<=0.000000001*MAX(ABS(AG56*Z56),ABS(AP56),scale_money) -> TRUE | AR56: =IF(A56<>rem_m,L56=0,L56=M55-J56-K56) -> TRUE | AS56: =IF(A56>prem_rem_m,AND(R56=0,S56=0,F56=0,G56=0,K56=0),R56=M55*premium) -> TRUE | AT56: =AND(C56>=18,C56<=120,OR(B56-B55=0,B56-B55=1)) -> TRUE | AU56: =-(N57-O57)+v_m*(E57*(sum_assured+Q57)+P57+(1-E57)*(1-G57)*AH57) -> -574.94121 | AV56: =ABS(AH56-AU56)<=0.000000001*MAX(ABS(AH56),ABS(AU56),scale_pp) -> TRUE | AW56: =AND(AI56>=0,AI56>=AG56) -> TRUE | AX56: =AND(U56=J56*sum_assured,R56=M55*N56,T56=M55*P56) -> TRUE
A57: 5 | B57: =MIN(INT((dur_m+A57-1)/12),dur_y_last) -> 2 | C57: =age_at_entry+B57 -> 40 | D57: =INDEX(mort_table,MATCH(C57,mort_age,0),MATCH(sex,mort_sex,0)) -> 0.0010067596 | E57: =IF(A57<=rem_m,1-(1-D57)^(1/12),0) -> 8.3935369e-05 | F57: =IF(A57<=prem_rem_m,INDEX(lapse_table,MATCH(MIN(B57,5),lapse_key,0)),0) -> 0.08 | G57: =1-(1-F57)^(1/12) -> 0.0069243826 | H57: =INDEX(comm_table,MATCH(MIN(B57,1),comm_key,0)) -> 0.02 | I57: =(1+e_m)^A57 -> 1.0123923 | J57: =M56*E57 -> 8.1607197e-05 | K57: =(M56-J57)*G57 -> 0.0067317513 | L57: =IF(A57=rem_m,M56-J57-K57,0) -> 0 | M57: =M56-J57-K57-L57 -> 0.96544897 | N57: =IF(A57<=prem_rem_m,premium,0) -> 52.96 | O57: =N57*H57 -> 1.0592 | P57: =maint_base*I57 -> 5.0619616 | Q57: =claim_exp_base*I57 -> 253.09808 | R57: =M56*N57 -> 51.491013 | S57: =R57*H57 -> 1.0298203 | T57: =M56*P57 -> 4.9215546 | U57: =J57*sum_assured -> 20.401799 | V57: =J57*Q57 -> 0.020654625 | W57: =R57-S57-T57-U57-V57 -> 25.117184 | X57: =U57+V57+T57-(R57-S57)*(1+i_m) -> -25.282381 | Y57: =v_m -> 0.99673694 | Z57: =v_m^A57 -> 0.98379084 | AA57: =(R57-S57)*Z56-(T57+U57+V57)*Z57 -> 24.872575 | AB57: =R57*Z56 -> 50.822223 | AC57: =S57*Z56 -> 1.0164445 | AD57: =T57*Z57 -> 4.8417803 | AE57: =U57*Z57 -> 20.071103 | AF57: =V57*Z57 -> 0.020319831 | AG57: =(AG58+X58)*Y58 -> -535.54129 | AH57: =IF(M57>0,AG57/M57,0) -> -554.70699 | AI57: =IF(AG57>0,AG57,0) -> 0 | AK57: =AND(M57>=0,M57<=M56) -> TRUE | AL57: =AND(D57>=0,D57<=1,E57>=0,E57<=1,F57>=0,F57<=1,G57>=0,G57<=1,J57+K57+L57<=M56+0.000000001*scale_count) -> TRUE | AM57: =(AG56+R57-S57)*(1+i_m)-T57-U57-V57 -> -535.54129 | AN57: =ABS(AM57-AG57)<=0.000000001*MAX(ABS(AM57),ABS(AG57),scale_money) -> TRUE | AO57: =(U57+V57+T57)*Z57-(R57-S57)*Z56 -> -24.872575 | AP57: =SUM(AO58:$AO$262) -> -526.86062 | AQ57: =ABS(AG57*Z57-AP57)<=0.000000001*MAX(ABS(AG57*Z57),ABS(AP57),scale_money) -> TRUE | AR57: =IF(A57<>rem_m,L57=0,L57=M56-J57-K57) -> TRUE | AS57: =IF(A57>prem_rem_m,AND(R57=0,S57=0,F57=0,G57=0,K57=0),R57=M56*premium) -> TRUE | AT57: =AND(C57>=18,C57<=120,OR(B57-B56=0,B57-B56=1)) -> TRUE | AU57: =-(N58-O58)+v_m*(E58*(sum_assured+Q58)+P58+(1-E58)*(1-G58)*AH58) -> -554.70699 | AV57: =ABS(AH57-AU57)<=0.000000001*MAX(ABS(AH57),ABS(AU57),scale_pp) -> TRUE | AW57: =AND(AI57>=0,AI57>=AG57) -> TRUE | AX57: =AND(U57=J57*sum_assured,R57=M56*N57,T57=M56*P57) -> TRUE
A58: 6 | B58: =MIN(INT((dur_m+A58-1)/12),dur_y_last) -> 2 | C58: =age_at_entry+B58 -> 40 | D58: =INDEX(mort_table,MATCH(C58,mort_age,0),MATCH(sex,mort_sex,0)) -> 0.0010067596 | E58: =IF(A58<=rem_m,1-(1-D58)^(1/12),0) -> 8.3935369e-05 | F58: =IF(A58<=prem_rem_m,INDEX(lapse_table,MATCH(MIN(B58,5),lapse_key,0)),0) -> 0.08 | G58: =1-(1-F58)^(1/12) -> 0.0069243826 | H58: =INDEX(comm_table,MATCH(MIN(B58,1),comm_key,0)) -> 0.02 | I58: =(1+e_m)^A58 -> 1.0148892 | J58: =M57*E58 -> 8.1035316e-05 | K58: =(M57-J58)*G58 -> 0.006684577 | L58: =IF(A58=rem_m,M57-J58-K58,0) -> 0 | M58: =M57-J58-K58-L58 -> 0.95868336 | N58: =IF(A58<=prem_rem_m,premium,0) -> 52.96 | O58: =N58*H58 -> 1.0592 | P58: =maint_base*I58 -> 5.0744458 | Q58: =claim_exp_base*I58 -> 253.72229 | R58: =M57*N58 -> 51.130177 | S58: =R58*H58 -> 1.0226035 | T58: =M57*P58 -> 4.8991185 | U58: =J58*sum_assured -> 20.258829 | V58: =J58*Q58 -> 0.020560466 | W58: =R58-S58-T58-U58-V58 -> 24.929066 | X58: =U58+V58+T58-(R58-S58)*(1+i_m) -> -25.093105 | Y58: =v_m -> 0.99673694 | Z58: =v_m^A58 -> 0.98058068 | AA58: =(R58-S58)*Z57-(T58+U58+V58)*Z58 -> 24.605814 | AB58: =R58*Z57 -> 50.3014 | AC58: =S58*Z57 -> 1.006028 | AD58: =T58*Z58 -> 4.8039809 | AE58: =U58*Z58 -> 19.865416 | AF58: =V58*Z58 -> 0.020161195 | AG58: =(AG59+X59)*Y59 -> -512.20141 | AH58: =IF(M58>0,AG58/M58,0) -> -534.2759 | AI58: =IF(AG58>0,AG58,0) -> 0 | AK58: =AND(M58>=0,M58<=M57) -> TRUE | AL58: =AND(D58>=0,D58<=1,E58>=0,E58<=1,F58>=0,F58<=1,G58>=0,G58<=1,J58+K58+L58<=M57+0.000000001*scale_count) -> TRUE | AM58: =(AG57+R58-S58)*(1+i_m)-T58-U58-V58 -> -512.20141 | AN58: =ABS(AM58-AG58)<=0.000000001*MAX(ABS(AM58),ABS(AG58),scale_money) -> TRUE | AO58: =(U58+V58+T58)*Z58-(R58-S58)*Z57 -> -24.605814 | AP58: =SUM(AO59:$AO$262) -> -502.25481 | AQ58: =ABS(AG58*Z58-AP58)<=0.000000001*MAX(ABS(AG58*Z58),ABS(AP58),scale_money) -> TRUE | AR58: =IF(A58<>rem_m,L58=0,L58=M57-J58-K58) -> TRUE | AS58: =IF(A58>prem_rem_m,AND(R58=0,S58=0,F58=0,G58=0,K58=0),R58=M57*premium) -> TRUE | AT58: =AND(C58>=18,C58<=120,OR(B58-B57=0,B58-B57=1)) -> TRUE | AU58: =-(N59-O59)+v_m*(E59*(sum_assured+Q59)+P59+(1-E59)*(1-G59)*AH59) -> -534.2759 | AV58: =ABS(AH58-AU58)<=0.000000001*MAX(ABS(AH58),ABS(AU58),scale_pp) -> TRUE | AW58: =AND(AI58>=0,AI58>=AG58) -> TRUE | AX58: =AND(U58=J58*sum_assured,R58=M57*N58,T58=M57*P58) -> TRUE
A59: 7 | B59: =MIN(INT((dur_m+A59-1)/12),dur_y_last) -> 3 | C59: =age_at_entry+B59 -> 41 | D59: =INDEX(mort_table,MATCH(C59,mort_age,0),MATCH(sex,mort_sex,0)) -> 0.0010874017 | E59: =IF(A59<=rem_m,1-(1-D59)^(1/12),0) -> 9.0662004e-05 | F59: =IF(A59<=prem_rem_m,INDEX(lapse_table,MATCH(MIN(B59,5),lapse_key,0)),0) -> 0.06 | G59: =1-(1-F59)^(1/12) -> 0.0051430128 | H59: =INDEX(comm_table,MATCH(MIN(B59,1),comm_key,0)) -> 0.02 | I59: =(1+e_m)^A59 -> 1.0173921 | J59: =M58*E59 -> 8.6916155e-05 | K59: =(M58-J59)*G59 -> 0.0049300738 | L59: =IF(A59=rem_m,M58-J59-K59,0) -> 0 | M59: =M58-J59-K59-L59 -> 0.95366637 | N59: =IF(A59<=prem_rem_m,premium,0) -> 52.96 | O59: =N59*H59 -> 1.0592 | P59: =maint_base*I59 -> 5.0869607 | Q59: =claim_exp_base*I59 -> 254.34804 | R59: =M58*N59 -> 50.771871 | S59: =R59*H59 -> 1.0154374 | T59: =M58*P59 -> 4.8767846 | U59: =J59*sum_assured -> 21.729039 | V59: =J59*Q59 -> 0.022106953 | W59: =R59-S59-T59-U59-V59 -> 23.128503 | X59: =U59+V59+T59-(R59-S59)*(1+i_m) -> -23.291393 | Y59: =v_m -> 0.99673694 | Z59: =v_m^A59 -> 0.97738098 | AA59: =(R59-S59)*Z58-(T59+U59+V59)*Z59 -> 22.764564 | AB59: =R59*Z58 -> 49.785915 | AC59: =S59*Z58 -> 0.9957183 | AD59: =T59*Z59 -> 4.7664765 | AE59: =U59*Z59 -> 21.237549 | AF59: =V59*Z59 -> 0.021606916 | AG59: =(AG60+X60)*Y60 -> -490.58683 | AH59: =IF(M59>0,AG59/M59,0) -> -514.42187 | AI59: =IF(AG59>0,AG59,0) -> 0 | AK59: =AND(M59>=0,M59<=M58) -> TRUE | AL59: =AND(D59>=0,D59<=1,E59>=0,E59<=1,F59>=0,F59<=1,G59>=0,G59<=1,J59+K59+L59<=M58+0.000000001*scale_count) -> TRUE | AM59: =(AG58+R59-S59)*(1+i_m)-T59-U59-V59 -> -490.58683 | AN59: =ABS(AM59-AG59)<=0.000000001*MAX(ABS(AM59),ABS(AG59),scale_money) -> TRUE | AO59: =(U59+V59+T59)*Z59-(R59-S59)*Z58 -> -22.764564 | AP59: =SUM(AO60:$AO$262) -> -479.49024 | AQ59: =ABS(AG59*Z59-AP59)<=0.000000001*MAX(ABS(AG59*Z59),ABS(AP59),scale_money) -> TRUE | AR59: =IF(A59<>rem_m,L59=0,L59=M58-J59-K59) -> TRUE | AS59: =IF(A59>prem_rem_m,AND(R59=0,S59=0,F59=0,G59=0,K59=0),R59=M58*premium) -> TRUE | AT59: =AND(C59>=18,C59<=120,OR(B59-B58=0,B59-B58=1)) -> TRUE | AU59: =-(N60-O60)+v_m*(E60*(sum_assured+Q60)+P60+(1-E60)*(1-G60)*AH60) -> -514.42187 | AV59: =ABS(AH59-AU59)<=0.000000001*MAX(ABS(AH59),ABS(AU59),scale_pp) -> TRUE | AW59: =AND(AI59>=0,AI59>=AG59) -> TRUE | AX59: =AND(U59=J59*sum_assured,R59=M58*N59,T59=M58*P59) -> TRUE
A60: 8 | B60: =MIN(INT((dur_m+A60-1)/12),dur_y_last) -> 3 | C60: =age_at_entry+B60 -> 41 | D60: =INDEX(mort_table,MATCH(C60,mort_age,0),MATCH(sex,mort_sex,0)) -> 0.0010874017 | E60: =IF(A60<=rem_m,1-(1-D60)^(1/12),0) -> 9.0662004e-05 | F60: =IF(A60<=prem_rem_m,INDEX(lapse_table,MATCH(MIN(B60,5),lapse_key,0)),0) -> 0.06 | G60: =1-(1-F60)^(1/12) -> 0.0051430128 | H60: =INDEX(comm_table,MATCH(MIN(B60,1),comm_key,0)) -> 0.02 | I60: =(1+e_m)^A60 -> 1.0199013 | J60: =M59*E60 -> 8.6461304e-05 | K60: =(M59-J60)*G60 -> 0.0049042737 | L60: =IF(A60=rem_m,M59-J60-K60,0) -> 0 | M60: =M59-J60-K60-L60 -> 0.94867563 | N60: =IF(A60<=prem_rem_m,premium,0) -> 52.96 | O60: =N60*H60 -> 1.0592 | P60: =maint_base*I60 -> 5.0995066 | Q60: =claim_exp_base*I60 -> 254.97533 | R60: =M59*N60 -> 50.506171 | S60: =R60*H60 -> 1.0101234 | T60: =M59*P60 -> 4.8632279 | U60: =J60*sum_assured -> 21.615326 | V60: =J60*Q60 -> 0.022045499 | W60: =R60-S60-T60-U60-V60 -> 22.995448 | X60: =U60+V60+T60-(R60-S60)*(1+i_m) -> -23.157485 | Y60: =v_m -> 0.99673694 | Z60: =v_m^A60 -> 0.97419173 | AA60: =(R60-S60)*Z59-(T60+U60+V60)*Z60 -> 22.559831 | AB60: =R60*Z59 -> 49.363771 | AC60: =S60*Z59 -> 0.98727542 | AD60: =T60*Z60 -> 4.7377164 | AE60: =U60*Z60 -> 21.057472 | AF60: =V60*Z60 -> 0.021476543 | AG60: =(AG61+X61)*Y61 -> -469.0354 | AH60: =IF(M60>0,AG60/M60,0) -> -494.41072 | AI60: =IF(AG60>0,AG60,0) -> 0 | AK60: =AND(M60>=0,M60<=M59) -> TRUE | AL60: =AND(D60>=0,D60<=1,E60>=0,E60<=1,F60>=0,F60<=1,G60>=0,G60<=1,J60+K60+L60<=M59+0.000000001*scale_count) -> TRUE | AM60: =(AG59+R60-S60)*(1+i_m)-T60-U60-V60 -> -469.0354 | AN60: =ABS(AM60-AG60)<=0.000000001*MAX(ABS(AM60),ABS(AG60),scale_money) -> TRUE | AO60: =(U60+V60+T60)*Z60-(R60-S60)*Z59 -> -22.559831 | AP60: =SUM(AO61:$AO$262) -> -456.93041 | AQ60: =ABS(AG60*Z60-AP60)<=0.000000001*MAX(ABS(AG60*Z60),ABS(AP60),scale_money) -> TRUE | AR60: =IF(A60<>rem_m,L60=0,L60=M59-J60-K60) -> TRUE | AS60: =IF(A60>prem_rem_m,AND(R60=0,S60=0,F60=0,G60=0,K60=0),R60=M59*premium) -> TRUE | AT60: =AND(C60>=18,C60<=120,OR(B60-B59=0,B60-B59=1)) -> TRUE | AU60: =-(N61-O61)+v_m*(E61*(sum_assured+Q61)+P61+(1-E61)*(1-G61)*AH61) -> -494.41072 | AV60: =ABS(AH60-AU60)<=0.000000001*MAX(ABS(AH60),ABS(AU60),scale_pp) -> TRUE | AW60: =AND(AI60>=0,AI60>=AG60) -> TRUE | AX60: =AND(U60=J60*sum_assured,R60=M59*N60,T60=M59*P60) -> TRUE
A61: 9 | B61: =MIN(INT((dur_m+A61-1)/12),dur_y_last) -> 3 | C61: =age_at_entry+B61 -> 41 | D61: =INDEX(mort_table,MATCH(C61,mort_age,0),MATCH(sex,mort_sex,0)) -> 0.0010874017 | E61: =IF(A61<=rem_m,1-(1-D61)^(1/12),0) -> 9.0662004e-05 | F61: =IF(A61<=prem_rem_m,INDEX(lapse_table,MATCH(MIN(B61,5),lapse_key,0)),0) -> 0.06 | G61: =1-(1-F61)^(1/12) -> 0.0051430128 | H61: =INDEX(comm_table,MATCH(MIN(B61,1),comm_key,0)) -> 0.02 | I61: =(1+e_m)^A61 -> 1.0224167 | J61: =M60*E61 -> 8.6008834e-05 | K61: =(M60-J61)*G61 -> 0.0048786086 | L61: =IF(A61=rem_m,M60-J61-K61,0) -> 0 | M61: =M60-J61-K61-L61 -> 0.94371102 | N61: =IF(A61<=prem_rem_m,premium,0) -> 52.96 | O61: =N61*H61 -> 1.0592 | P61: =maint_base*I61 -> 5.1120833 | Q61: =claim_exp_base*I61 -> 255.60417 | R61: =M60*N61 -> 50.241862 | S61: =R61*H61 -> 1.0048372 | T61: =M60*P61 -> 4.8497089 | U61: =J61*sum_assured -> 21.502209 | V61: =J61*Q61 -> 0.021984216 | W61: =R61-S61-T61-U61-V61 -> 22.863123 | X61: =U61+V61+T61-(R61-S61)*(1+i_m) -> -23.024312 | Y61: =v_m -> 0.99673694 | Z61: =v_m^A61 -> 0.97101289 | AA61: =(R61-S61)*Z60-(T61+U61+V61)*Z61 -> 22.356904 | AB61: =R61*Z60 -> 48.945206 | AC61: =S61*Z60 -> 0.97890412 | AD61: =T61*Z61 -> 4.7091298 | AE61: =U61*Z61 -> 20.878922 | AF61: =V61*Z61 -> 0.021346957 | AG61: =(AG62+X62)*Y62 -> -447.54659 | AH61: =IF(M61>0,AG61/M61,0) -> -474.24114 | AI61: =IF(AG61>0,AG61,0) -> 0 | AK61: =AND(M61>=0,M61<=M60) -> TRUE | AL61: =AND(D61>=0,D61<=1,E61>=0,E61<=1,F61>=0,F61<=1,G61>=0,G61<=1,J61+K61+L61<=M60+0.000000001*scale_count) -> TRUE | AM61: =(AG60+R61-S61)*(1+i_m)-T61-U61-V61 -> -447.54659 | AN61: =ABS(AM61-AG61)<=0.000000001*MAX(ABS(AM61),ABS(AG61),scale_money) -> TRUE | AO61: =(U61+V61+T61)*Z61-(R61-S61)*Z60 -> -22.356904 | AP61: =SUM(AO62:$AO$262) -> -434.57351 | AQ61: =ABS(AG61*Z61-AP61)<=0.000000001*MAX(ABS(AG61*Z61),ABS(AP61),scale_money) -> TRUE | AR61: =IF(A61<>rem_m,L61=0,L61=M60-J61-K61) -> TRUE | AS61: =IF(A61>prem_rem_m,AND(R61=0,S61=0,F61=0,G61=0,K61=0),R61=M60*premium) -> TRUE | AT61: =AND(C61>=18,C61<=120,OR(B61-B60=0,B61-B60=1)) -> TRUE | AU61: =-(N62-O62)+v_m*(E62*(sum_assured+Q62)+P62+(1-E62)*(1-G62)*AH62) -> -474.24114 | AV61: =ABS(AH61-AU61)<=0.000000001*MAX(ABS(AH61),ABS(AU61),scale_pp) -> TRUE | AW61: =AND(AI61>=0,AI61>=AG61) -> TRUE | AX61: =AND(U61=J61*sum_assured,R61=M60*N61,T61=M60*P61) -> TRUE
A62: 10 | B62: =MIN(INT((dur_m+A62-1)/12),dur_y_last) -> 3 | C62: =age_at_entry+B62 -> 41 | D62: =INDEX(mort_table,MATCH(C62,mort_age,0),MATCH(sex,mort_sex,0)) -> 0.0010874017 | E62: =IF(A62<=rem_m,1-(1-D62)^(1/12),0) -> 9.0662004e-05 | F62: =IF(A62<=prem_rem_m,INDEX(lapse_table,MATCH(MIN(B62,5),lapse_key,0)),0) -> 0.06 | G62: =1-(1-F62)^(1/12) -> 0.0051430128 | H62: =INDEX(comm_table,MATCH(MIN(B62,1),comm_key,0)) -> 0.02 | I62: =(1+e_m)^A62 -> 1.0249382 | J62: =M61*E62 -> 8.5558732e-05 | K62: =(M61-J62)*G62 -> 0.0048530778 | L62: =IF(A62=rem_m,M61-J62-K62,0) -> 0 | M62: =M61-J62-K62-L62 -> 0.93877238 | N62: =IF(A62<=prem_rem_m,premium,0) -> 52.96 | O62: =N62*H62 -> 1.0592 | P62: =maint_base*I62 -> 5.1246911 | Q62: =claim_exp_base*I62 -> 256.23455 | R62: =M61*N62 -> 49.978935 | S62: =R62*H62 -> 0.99957871 | T62: =M61*P62 -> 4.8362274 | U62: =J62*sum_assured -> 21.389683 | V62: =J62*Q62 -> 0.021923104 | W62: =R62-S62-T62-U62-V62 -> 22.731523 | X62: =U62+V62+T62-(R62-S62)*(1+i_m) -> -22.891869 | Y62: =v_m -> 0.99673694 | Z62: =v_m^A62 -> 0.96784442 | AA62: =(R62-S62)*Z61-(T62+U62+V62)*Z62 -> 22.155767 | AB62: =R62*Z61 -> 48.530191 | AC62: =S62*Z61 -> 0.97060381 | AD62: =T62*Z62 -> 4.6807157 | AE62: =U62*Z62 -> 20.701885 | AF62: =V62*Z62 -> 0.021218153 | AG62: =(AG63+X63)*Y63 -> -426.11987 | AH62: =IF(M62>0,AG62/M62,0) -> -453.91181 | AI62: =IF(AG62>0,AG62,0) -> 0 | AK62: =AND(M62>=0,M62<=M61) -> TRUE | AL62: =AND(D62>=0,D62<=1,E62>=0,E62<=1,F62>=0,F62<=1,G62>=0,G62<=1,J62+K62+L62<=M61+0.000000001*scale_count) -> TRUE | AM62: =(AG61+R62-S62)*(1+i_m)-T62-U62-V62 -> -426.11987 | AN62: =ABS(AM62-AG62)<=0.000000001*MAX(ABS(AM62),ABS(AG62),scale_money) -> TRUE | AO62: =(U62+V62+T62)*Z62-(R62-S62)*Z61 -> -22.155767 | AP62: =SUM(AO63:$AO$262) -> -412.41774 | AQ62: =ABS(AG62*Z62-AP62)<=0.000000001*MAX(ABS(AG62*Z62),ABS(AP62),scale_money) -> TRUE | AR62: =IF(A62<>rem_m,L62=0,L62=M61-J62-K62) -> TRUE | AS62: =IF(A62>prem_rem_m,AND(R62=0,S62=0,F62=0,G62=0,K62=0),R62=M61*premium) -> TRUE | AT62: =AND(C62>=18,C62<=120,OR(B62-B61=0,B62-B61=1)) -> TRUE | AU62: =-(N63-O63)+v_m*(E63*(sum_assured+Q63)+P63+(1-E63)*(1-G63)*AH63) -> -453.91181 | AV62: =ABS(AH62-AU62)<=0.000000001*MAX(ABS(AH62),ABS(AU62),scale_pp) -> TRUE | AW62: =AND(AI62>=0,AI62>=AG62) -> TRUE | AX62: =AND(U62=J62*sum_assured,R62=M61*N62,T62=M61*P62) -> TRUE
A63: 11 | B63: =MIN(INT((dur_m+A63-1)/12),dur_y_last) -> 3 | C63: =age_at_entry+B63 -> 41 | D63: =INDEX(mort_table,MATCH(C63,mort_age,0),MATCH(sex,mort_sex,0)) -> 0.0010874017 | E63: =IF(A63<=rem_m,1-(1-D63)^(1/12),0) -> 9.0662004e-05 | F63: =IF(A63<=prem_rem_m,INDEX(lapse_table,MATCH(MIN(B63,5),lapse_key,0)),0) -> 0.06 | G63: =1-(1-F63)^(1/12) -> 0.0051430128 | H63: =INDEX(comm_table,MATCH(MIN(B63,1),comm_key,0)) -> 0.02 | I63: =(1+e_m)^A63 -> 1.027466 | J63: =M62*E63 -> 8.5110985e-05 | K63: =(M62-J63)*G63 -> 0.0048276807 | L63: =IF(A63=rem_m,M62-J63-K63,0) -> 0 | M63: =M62-J63-K63-L63 -> 0.93385959 | N63: =IF(A63<=prem_rem_m,premium,0) -> 52.96 | O63: =N63*H63 -> 1.0592 | P63: =maint_base*I63 -> 5.13733 | Q63: =claim_exp_base*I63 -> 256.8665 | R63: =M62*N63 -> 49.717385 | S63: =R63*H63 -> 0.9943477 | T63: =M62*P63 -> 4.8227835 | U63: =J63*sum_assured -> 21.277746 | V63: =J63*Q63 -> 0.021862161 | W63: =R63-S63-T63-U63-V63 -> 22.600646 | X63: =U63+V63+T63-(R63-S63)*(1+i_m) -> -22.760152 | Y63: =v_m -> 0.99673694 | Z63: =v_m^A63 -> 0.96468629 | AA63: =(R63-S63)*Z62-(T63+U63+V63)*Z63 -> 21.956407 | AB63: =R63*Z62 -> 48.118694 | AC63: =S63*Z62 -> 0.96237388 | AD63: =T63*Z63 -> 4.6524731 | AE63: =U63*Z63 -> 20.52635 | AF63: =V63*Z63 -> 0.021090127 | AG63: =(AG64+X64)*Y64 -> -404.75473 | AH63: =IF(M63>0,AG63/M63,0) -> -433.4214 | AI63: =IF(AG63>0,AG63,0) -> 0 | AK63: =AND(M63>=0,M63<=M62) -> TRUE | AL63: =AND(D63>=0,D63<=1,E63>=0,E63<=1,F63>=0,F63<=1,G63>=0,G63<=1,J63+K63+L63<=M62+0.000000001*scale_count) -> TRUE | AM63: =(AG62+R63-S63)*(1+i_m)-T63-U63-V63 -> -404.75473 | AN63: =ABS(AM63-AG63)<=0.000000001*MAX(ABS(AM63),ABS(AG63),scale_money) -> TRUE | AO63: =(U63+V63+T63)*Z63-(R63-S63)*Z62 -> -21.956407 | AP63: =SUM(AO64:$AO$262) -> -390.46133 | AQ63: =ABS(AG63*Z63-AP63)<=0.000000001*MAX(ABS(AG63*Z63),ABS(AP63),scale_money) -> TRUE | AR63: =IF(A63<>rem_m,L63=0,L63=M62-J63-K63) -> TRUE | AS63: =IF(A63>prem_rem_m,AND(R63=0,S63=0,F63=0,G63=0,K63=0),R63=M62*premium) -> TRUE | AT63: =AND(C63>=18,C63<=120,OR(B63-B62=0,B63-B62=1)) -> TRUE | AU63: =-(N64-O64)+v_m*(E64*(sum_assured+Q64)+P64+(1-E64)*(1-G64)*AH64) -> -433.4214 | AV63: =ABS(AH63-AU63)<=0.000000001*MAX(ABS(AH63),ABS(AU63),scale_pp) -> TRUE | AW63: =AND(AI63>=0,AI63>=AG63) -> TRUE | AX63: =AND(U63=J63*sum_assured,R63=M62*N63,T63=M62*P63) -> TRUE
A64: 12 | B64: =MIN(INT((dur_m+A64-1)/12),dur_y_last) -> 3 | C64: =age_at_entry+B64 -> 41 | D64: =INDEX(mort_table,MATCH(C64,mort_age,0),MATCH(sex,mort_sex,0)) -> 0.0010874017 | E64: =IF(A64<=rem_m,1-(1-D64)^(1/12),0) -> 9.0662004e-05 | F64: =IF(A64<=prem_rem_m,INDEX(lapse_table,MATCH(MIN(B64,5),lapse_key,0)),0) -> 0.06 | G64: =1-(1-F64)^(1/12) -> 0.0051430128 | H64: =INDEX(comm_table,MATCH(MIN(B64,1),comm_key,0)) -> 0.02 | I64: =(1+e_m)^A64 -> 1.03 | J64: =M63*E64 -> 8.4665582e-05 | K64: =(M63-J64)*G64 -> 0.0048024164 | L64: =IF(A64=rem_m,M63-J64-K64,0) -> 0 | M64: =M63-J64-K64-L64 -> 0.92897251 | N64: =IF(A64<=prem_rem_m,premium,0) -> 52.96 | O64: =N64*H64 -> 1.0592 | P64: =maint_base*I64 -> 5.15 | Q64: =claim_exp_base*I64 -> 257.5 | R64: =M63*N64 -> 49.457204 | S64: =R64*H64 -> 0.98914408 | T64: =M63*P64 -> 4.8093769 | U64: =J64*sum_assured -> 21.166395 | V64: =J64*Q64 -> 0.021801387 | W64: =R64-S64-T64-U64-V64 -> 22.470486 | X64: =U64+V64+T64-(R64-S64)*(1+i_m) -> -22.629158 | Y64: =v_m -> 0.99673694 | Z64: =v_m^A64 -> 0.96153846 | AA64: =(R64-S64)*Z63-(T64+U64+V64)*Z64 -> 21.758806 | AB64: =R64*Z63 -> 47.710686 | AC64: =S64*Z63 -> 0.95421373 | AD64: =T64*Z64 -> 4.6244008 | AE64: =U64*Z64 -> 20.352303 | AF64: =V64*Z64 -> 0.020962872 | AG64: =(AG65+X65)*Y65 -> -383.45063 | AH64: =IF(M64>0,AG64/M64,0) -> -412.76855 | AI64: =IF(AG64>0,AG64,0) -> 0 | AK64: =AND(M64>=0,M64<=M63) -> TRUE | AL64: =AND(D64>=0,D64<=1,E64>=0,E64<=1,F64>=0,F64<=1,G64>=0,G64<=1,J64+K64+L64<=M63+0.000000001*scale_count) -> TRUE | AM64: =(AG63+R64-S64)*(1+i_m)-T64-U64-V64 -> -383.45063 | AN64: =ABS(AM64-AG64)<=0.000000001*MAX(ABS(AM64),ABS(AG64),scale_money) -> TRUE | AO64: =(U64+V64+T64)*Z64-(R64-S64)*Z63 -> -21.758806 | AP64: =SUM(AO65:$AO$262) -> -368.70253 | AQ64: =ABS(AG64*Z64-AP64)<=0.000000001*MAX(ABS(AG64*Z64),ABS(AP64),scale_money) -> TRUE | AR64: =IF(A64<>rem_m,L64=0,L64=M63-J64-K64) -> TRUE | AS64: =IF(A64>prem_rem_m,AND(R64=0,S64=0,F64=0,G64=0,K64=0),R64=M63*premium) -> TRUE | AT64: =AND(C64>=18,C64<=120,OR(B64-B63=0,B64-B63=1)) -> TRUE | AU64: =-(N65-O65)+v_m*(E65*(sum_assured+Q65)+P65+(1-E65)*(1-G65)*AH65) -> -412.76855 | AV64: =ABS(AH64-AU64)<=0.000000001*MAX(ABS(AH64),ABS(AU64),scale_pp) -> TRUE | AW64: =AND(AI64>=0,AI64>=AG64) -> TRUE | AX64: =AND(U64=J64*sum_assured,R64=M63*N64,T64=M63*P64) -> TRUE
A65: 13 | B65: =MIN(INT((dur_m+A65-1)/12),dur_y_last) -> 3 | C65: =age_at_entry+B65 -> 41 | D65: =INDEX(mort_table,MATCH(C65,mort_age,0),MATCH(sex,mort_sex,0)) -> 0.0010874017 | E65: =IF(A65<=rem_m,1-(1-D65)^(1/12),0) -> 9.0662004e-05 | F65: =IF(A65<=prem_rem_m,INDEX(lapse_table,MATCH(MIN(B65,5),lapse_key,0)),0) -> 0.06 | G65: =1-(1-F65)^(1/12) -> 0.0051430128 | H65: =INDEX(comm_table,MATCH(MIN(B65,1),comm_key,0)) -> 0.02 | I65: =(1+e_m)^A65 -> 1.0325403 | J65: =M64*E65 -> 8.4222509e-05 | K65: =(M64-J65)*G65 -> 0.0047772844 | L65: =IF(A65=rem_m,M64-J65-K65,0) -> 0 | M65: =M64-J65-K65-L65 -> 0.924111 | N65: =IF(A65<=prem_rem_m,premium,0) -> 52.96 | O65: =N65*H65 -> 1.0592 | P65: =maint_base*I65 -> 5.1627013 | Q65: =claim_exp_base*I65 -> 258.13506 | R65: =M64*N65 -> 49.198384 | S65: =R65*H65 -> 0.98396768 | T65: =M64*P65 -> 4.7960076 | U65: =J65*sum_assured -> 21.055627 | V65: =J65*Q65 -> 0.021740783 | W65: =R65-S65-T65-U65-V65 -> 22.341041 | X65: =U65+V65+T65-(R65-S65)*(1+i_m) -> -22.498882 | Y65: =v_m -> 0.99673694 | Z65: =v_m^A65 -> 0.95840091 | AA65: =(R65-S65)*Z64-(T65+U65+V65)*Z65 -> 21.562949 | AB65: =R65*Z64 -> 47.306138 | AC65: =S65*Z64 -> 0.94612277 | AD65: =T65*Z65 -> 4.596498 | AE65: =U65*Z65 -> 20.179732 | AF65: =V65*Z65 -> 0.020836386 | AG65: =(AG66+X66)*Y66 -> -362.20707 | AH65: =IF(M65>0,AG65/M65,0) -> -391.9519 | AI65: =IF(AG65>0,AG65,0) -> 0 | AK65: =AND(M65>=0,M65<=M64) -> TRUE | AL65: =AND(D65>=0,D65<=1,E65>=0,E65<=1,F65>=0,F65<=1,G65>=0,G65<=1,J65+K65+L65<=M64+0.000000001*scale_count) -> TRUE | AM65: =(AG64+R65-S65)*(1+i_m)-T65-U65-V65 -> -362.20707 | AN65: =ABS(AM65-AG65)<=0.000000001*MAX(ABS(AM65),ABS(AG65),scale_money) -> TRUE | AO65: =(U65+V65+T65)*Z65-(R65-S65)*Z64 -> -21.562949 | AP65: =SUM(AO66:$AO$262) -> -347.13958 | AQ65: =ABS(AG65*Z65-AP65)<=0.000000001*MAX(ABS(AG65*Z65),ABS(AP65),scale_money) -> TRUE | AR65: =IF(A65<>rem_m,L65=0,L65=M64-J65-K65) -> TRUE | AS65: =IF(A65>prem_rem_m,AND(R65=0,S65=0,F65=0,G65=0,K65=0),R65=M64*premium) -> TRUE | AT65: =AND(C65>=18,C65<=120,OR(B65-B64=0,B65-B64=1)) -> TRUE | AU65: =-(N66-O66)+v_m*(E66*(sum_assured+Q66)+P66+(1-E66)*(1-G66)*AH66) -> -391.9519 | AV65: =ABS(AH65-AU65)<=0.000000001*MAX(ABS(AH65),ABS(AU65),scale_pp) -> TRUE | AW65: =AND(AI65>=0,AI65>=AG65) -> TRUE | AX65: =AND(U65=J65*sum_assured,R65=M64*N65,T65=M64*P65) -> TRUE
... A261: 209 | B261: =MIN(INT((dur_m+A261-1)/12),dur_y_last) -> 19 | C261: =age_at_entry+B261 -> 57 | D261: =INDEX(mort_table,MATCH(C261,mort_age,0),MATCH(sex,mort_sex,0)) -> 0.0042711581 | E261: =IF(A261<=rem_m,1-(1-D261)^(1/12),0) -> 0.00035662852 | F261: =IF(A261<=prem_rem_m,INDEX(lapse_table,MATCH(MIN(B261,5),lapse_key,0)),0) -> 0.04 | G261: =1-(1-F261)^(1/12) -> 0.0033960532 | H261: =INDEX(comm_table,MATCH(MIN(B261,1),comm_key,0)) -> 0.02 | I261: =(1+e_m)^A261 -> 1.6733303 | J261: =M260*E261 -> 0.00016031093 | K261: =(M260-J261)*G261 -> 0.0015260425 | L261: =IF(A261=rem_m,M260-J261-K261,0) -> 0 | M261: =M260-J261-K261-L261 -> 0.44783162 | N261: =IF(A261<=prem_rem_m,premium,0) -> 52.96 | O261: =N261*H261 -> 1.0592 | P261: =maint_base*I261 -> 8.3666513 | Q261: =claim_exp_base*I261 -> 418.33256 | R261: =M260*N261 -> 23.806472 | S261: =R261*H261 -> 0.47612944 | T261: =M260*P261 -> 3.7609602 | U261: =J261*sum_assured -> 40.077733 | V261: =J261*Q261 -> 0.067063283 | W261: =R261-S261-T261-U261-V261 -> -20.575414 | X261: =U261+V261+T261-(R261-S261)*(1+i_m) -> 20.499036 | Y261: =v_m -> 0.99673694 | Z261: =v_m^A261 -> 0.5050519 | AA261: =(R261-S261)*Z260-(T261+U261+V261)*Z261 -> -10.353077 | AB261: =R261*Z260 -> 12.062866 | AC261: =S261*Z260 -> 0.24125731 | AD261: =T261*Z261 -> 1.8994801 | AE261: =U261*Z261 -> 20.241335 | AF261: =V261*Z261 -> 0.033870438 | AG261: =(AG262+X262)*Y262 -> 20.364871 | AH261: =IF(M261>0,AG261/M261,0) -> 45.474393 | AI261: =IF(AG261>0,AG261,0) -> 20.364871 | AK261: =AND(M261>=0,M261<=M260) -> TRUE | AL261: =AND(D261>=0,D261<=1,E261>=0,E261<=1,F261>=0,F261<=1,G261>=0,G261<=1,J261+K261+L261<=M260+0.000000001*scale_count) -> TRUE | AM261: =(AG260+R261-S261)*(1+i_m)-T261-U261-V261 -> 20.364871 | AN261: =ABS(AM261-AG261)<=0.000000001*MAX(ABS(AM261),ABS(AG261),scale_money) -> TRUE | AO261: =(U261+V261+T261)*Z261-(R261-S261)*Z260 -> 10.353077 | AP261: =SUM(AO262:$AO$262) -> 10.285317 | AQ261: =ABS(AG261*Z261-AP261)<=0.000000001*MAX(ABS(AG261*Z261),ABS(AP261),scale_money) -> TRUE | AR261: =IF(A261<>rem_m,L261=0,L261=M260-J261-K261) -> TRUE | AS261: =IF(A261>prem_rem_m,AND(R261=0,S261=0,F261=0,G261=0,K261=0),R261=M260*premium) -> TRUE | AT261: =AND(C261>=18,C261<=120,OR(B261-B260=0,B261-B260=1)) -> TRUE | AU261: =-(N262-O262)+v_m*(E262*(sum_assured+Q262)+P262+(1-E262)*(1-G262)*AH262) -> 45.474393 | AV261: =ABS(AH261-AU261)<=0.000000001*MAX(ABS(AH261),ABS(AU261),scale_pp) -> TRUE | AW261: =AND(AI261>=0,AI261>=AG261) -> TRUE | AX261: =AND(U261=J261*sum_assured,R261=M260*N261,T261=M260*P261) -> TRUE
A262: 210 | B262: =MIN(INT((dur_m+A262-1)/12),dur_y_last) -> 19 | C262: =age_at_entry+B262 -> 57 | D262: =INDEX(mort_table,MATCH(C262,mort_age,0),MATCH(sex,mort_sex,0)) -> 0.0042711581 | E262: =IF(A262<=rem_m,1-(1-D262)^(1/12),0) -> 0.00035662852 | F262: =IF(A262<=prem_rem_m,INDEX(lapse_table,MATCH(MIN(B262,5),lapse_key,0)),0) -> 0.04 | G262: =1-(1-F262)^(1/12) -> 0.0033960532 | H262: =INDEX(comm_table,MATCH(MIN(B262,1),comm_key,0)) -> 0.02 | I262: =(1+e_m)^A262 -> 1.6774571 | J262: =M261*E262 -> 0.00015970953 | K262: =(M261-J262)*G262 -> 0.0015203176 | L262: =IF(A262=rem_m,M261-J262-K262,0) -> 0.4461516 | M262: =M261-J262-K262-L262 -> 0 | N262: =IF(A262<=prem_rem_m,premium,0) -> 52.96 | O262: =N262*H262 -> 1.0592 | P262: =maint_base*I262 -> 8.3872857 | Q262: =claim_exp_base*I262 -> 419.36428 | R262: =M261*N262 -> 23.717163 | S262: =R262*H262 -> 0.47434326 | T262: =M261*P262 -> 3.7560918 | U262: =J262*sum_assured -> 39.927383 | V262: =J262*Q262 -> 0.066976473 | W262: =R262-S262-T262-U262-V262 -> -20.507631 | X262: =U262+V262+T262-(R262-S262)*(1+i_m) -> 20.43154 | Y262: =v_m -> 0.99673694 | Z262: =v_m^A262 -> 0.50340388 | AA262: =(R262-S262)*Z261-(T262+U262+V262)*Z262 -> -10.285317 | AB262: =R262*Z261 -> 11.978398 | AC262: =S262*Z261 -> 0.23956796 | AD262: =T262*Z262 -> 1.8908312 | AE262: =U262*Z262 -> 20.099599 | AF262: =V262*Z262 -> 0.033716217 | AG262: 0 | AH262: =IF(M262>0,AG262/M262,0) -> 0 | AI262: =IF(AG262>0,AG262,0) -> 0 | AK262: =AND(M262>=0,M262<=M261) -> TRUE | AL262: =AND(D262>=0,D262<=1,E262>=0,E262<=1,F262>=0,F262<=1,G262>=0,G262<=1,J262+K262+L262<=M261+0.000000001*scale_count) -> TRUE | AM262: =(AG261+R262-S262)*(1+i_m)-T262-U262-V262 -> -8.9650509e-15 | AN262: =ABS(AM262-AG262)<=0.000000001*MAX(ABS(AM262),ABS(AG262),scale_money) -> TRUE | AO262: =(U262+V262+T262)*Z262-(R262-S262)*Z261 -> 10.285317 | AR262: =IF(A262<>rem_m,L262=0,L262=M261-J262-K262) -> TRUE | AS262: =IF(A262>prem_rem_m,AND(R262=0,S262=0,F262=0,G262=0,K262=0),R262=M261*premium) -> TRUE | AT262: =AND(C262>=18,C262<=120,OR(B262-B261=0,B262-B261=1)) -> TRUE | AW262: =AND(AI262>=0,AI262>=AG262) -> TRUE | AX262: =AND(U262=J262*sum_assured,R262=M261*N262,T262=M261*P262) -> TRUE
A264: Scalars (section 11.2): the derived constants, the PV sums over t = 1 .. rem_m in ascending t, the time-0 state variables and maturities(rem_m)
A265: age_at_entry | B265: =age_at_entry -> 38 | C265: 5 | D265: Int (years)
A266: dur_m | B266: =dur_m -> 30 | C266: 4.3 | D266: Int (months)
A267: term_m | B267: =term_m -> 240 | C267: 4.3 | D267: Int (months)
A268: rem_m | B268: =rem_m -> 210 | C268: 4.3 | D268: Int (months)
A269: prem_term_m | B269: =prem_term_m -> 240 | C269: 4.3 | D269: Int (months)
A270: prem_rem_m | B270: =prem_rem_m -> 210 | C270: 4.3 | D270: Int (months)
A271: dur_y_last | B271: =dur_y_last -> 19 | C271: 4.3 | D271: Int (years)
A272: pv_premiums | B272: =SUM($AB$53:$AB$262) -> 5662.0561 | C272: 9.3 | D272: Money
A273: pv_commission | B273: =SUM($AC$53:$AC$262) -> 113.24112 | C273: 9.3 | D273: Money
A274: pv_maint_expense | B274: =SUM($AD$53:$AD$262) -> 656.93011 | C274: 9.3 | D274: Money
A275: pv_death_outgo | B275: =SUM($AE$53:$AE$262) -> 4232.3759 | C275: 9.3 | D275: Money
A276: pv_claim_expense | B276: =SUM($AF$53:$AF$262) -> 5.5602988 | C276: 9.3 | D276: Money
A277: pv_net_cf | B277: =B272-B273-B274-B275-B276 -> 653.94869 | C277: 9.3 | D277: Money
A278: reserve_0 | B278: =$AG$52 -> -653.94869 | C278: 10.2 | D278: Money: reserve(0)
A279: reserve_pp_0 | B279: =$AH$52 -> -653.94869 | C279: 10.4 | D279: Money per policy: reserve_pp(0)
A280: reserve_floored_0 | B280: =$AI$52 -> 0 | C280: 10.5 | D280: Money: reserve_floored(0)
A281: maturities_n | B281: =$L$262 -> 0.4461516 | C281: 7.3 | D281: Count: maturities(rem_m), the survivors to the end of the term
A283: Check cells (section 12): the section 1 scales and two helper sums, then one <id>_ok per (sheet) invariant, TRUE when every row cell and scalar cell of that invariant is TRUE
A284: scale_money | B284: =sum_assured*pols_if_init -> 250000 | D284: Money (in-force) scale of section 1: sum_assured * pols_if_init
A285: scale_pp | B285: =sum_assured -> 250000 | D285: Money per policy scale of section 1: sum_assured
A286: scale_count | B286: =pols_if_init -> 1 | D286: Count scale of section 1: pols_if_init
A287: exits_sum | B287: =SUMPRODUCT($J$53:$J$262+$K$53:$K$262+$L$53:$L$262) -> 1 | D287: helper (P8): sum over t = 1 .. rem_m of deaths + lapses + maturities
A288: pv_net_cf_t_sum | B288: =SUM($AA$53:$AA$262) -> 653.94869 | D288: helper (P9): sum over t = 1 .. rem_m of pv_net_cf_t
A290: H1_ok | B290: =AND($AK$52:$AK$262) -> TRUE | D290: every H1 row cell (t = 0 .. rem_m)
A291: H2_ok | B291: =AND($AL$53:$AL$262) -> TRUE | D291: every H2 row cell (t = 1 .. rem_m)
A292: H3_ok | B292: =AND($AG$262=0,$M$262=0) -> TRUE | D292: reserve(rem_m) = 0 and pols_if(rem_m) = 0, exactly
A293: H4_ok | B293: =AND($AN$53:$AN$262) -> TRUE | D293: every H4 row cell (t = 1 .. rem_m)
A294: H5a_ok | B294: =ABS(reserve_0-(-pv_net_cf))<=0.000000001*MAX(ABS(reserve_0),ABS(pv_net_cf),scale_money) -> TRUE | D294: reserve(0) equals -pv_net_cf within tolerance (scale_money)
A295: H5b_ok | B295: =AND($AQ$52:$AQ$261) -> TRUE | D295: every H5b row cell (t = 0 .. rem_m - 1)
A296: P1_ok | B296: =AND($AR$53:$AR$262) -> TRUE | D296: every P1 row cell (t = 1 .. rem_m)
A297: P2_ok | B297: =AND($AS$53:$AS$262) -> TRUE | D297: every P2 row cell (t = 1 .. rem_m)
A298: P3_ok | B298: =SUMPRODUCT(--($N$53:$N$262<>0))=prem_rem_m -> TRUE | D298: the number of months with premium_pp <> 0 equals prem_rem_m
A299: P4_ok | B299: =AND($AT$53:$AT$262) -> TRUE | D299: every P4 row cell (t = 1 .. rem_m)
A300: P5_ok | B300: =AND($AV$52:$AV$261) -> TRUE | D300: every P5 row cell (t = 0 .. rem_m - 1)
A301: P6_ok | B301: =AND($AW$52:$AW$262) -> TRUE | D301: every P6 row cell (t = 0 .. rem_m)
A302: P8_ok | B302: =ABS(exits_sum-scale_count)<=0.000000001*MAX(ABS(exits_sum),ABS(scale_count),scale_count) -> TRUE | D302: exits_sum equals pols_if_init within tolerance (scale_count)
A303: P9_ok | B303: =ABS(pv_net_cf-pv_net_cf_t_sum)<=0.000000001*MAX(ABS(pv_net_cf),ABS(pv_net_cf_t_sum),scale_money) -> TRUE | D303: pv_net_cf equals pv_net_cf_t_sum within tolerance (scale_money)
...

Sheet P02
A1: Inputs (section 3.1, from section 13) and the run-level valuation_date (3.3), typed
A2: valuation_date | B2: 46388 | C2: 3.3 | D2: Date, first of a month (run-level input)
A3: policy_id | B3: P02 | C3: 3.1 | D3: string
A4: sex | B4: F | C4: 3.1 | D4: string, M or F
A5: birth_date | B5: 33544 | C5: 3.1 | D5: Date
A6: entry_date | B6: 46388 | C6: 3.1 | D6: Date
A7: maturity_date | B7: 55519 | C7: 3.1 | D7: Date
A8: prem_term_y | B8: 25 | C8: 3.1 | D8: Int (years)
A9: sum_assured | B9: 400000 | C9: 3.1 | D9: Money per policy
A10: premium | B10: 51.64 | C10: 3.1 | D10: Money per policy, monthly, in advance
A11: pols_if_init | B11: 1 | C11: 3.1 | D11: Count
A13: Derived constants (sections 3.2, 4.3 and 5), by formula
A14: age_at_entry | B14: =YEAR(entry_date)-YEAR(birth_date)-IF(OR(MONTH(entry_date)<MONTH(birth_date),AND(MONTH(entry_date)=MONTH(birth_date),DAY(entry_date)<DAY(birth_date))),1,0) -> 35 | C14: 5 | D14: Int (years)
A15: dur_m | B15: =12*(YEAR(valuation_date)-YEAR(entry_date))+(MONTH(valuation_date)-MONTH(entry_date))-IF(DAY(valuation_date)<DAY(entry_date),1,0) -> 0 | C15: 4.3 | D15: Int (months)
A16: term_m | B16: =12*(YEAR(maturity_date)-YEAR(entry_date))+(MONTH(maturity_date)-MONTH(entry_date))-IF(DAY(maturity_date)<DAY(entry_date),1,0) -> 300 | C16: 4.3 | D16: Int (months)
A17: rem_m | B17: =term_m-dur_m -> 300 | C17: 4.3 | D17: Int (months)
A18: prem_term_m | B18: =12*prem_term_y -> 300 | C18: 4.3 | D18: Int (months)
A19: prem_rem_m | B19: =MAX(prem_term_m-dur_m,0) -> 300 | C19: 4.3 | D19: Int (months)
A20: dur_y_last | B20: =INT((term_m-1)/12) -> 24 | C20: 4.3 | D20: Int (years)
A22: Basis constants (section 6), each in one cell
A23: i | B23: 0.04 | C23: 6 | D23: Rate[Annual]
A24: e | B24: 0.03 | C24: 6 | D24: Rate[Annual]
A25: i_m | B25: =(1+i)^(1/12)-1 -> 0.0032737398 | C25: 6 | D25: Rate[Monthly]
A26: v_m | B26: =(1+i)^(-1/12) -> 0.99673694 | C26: 6 | D26: factor
A27: e_m | B27: =(1+e)^(1/12)-1 -> 0.0024662698 | C27: 6 | D27: Rate[Monthly]
A28: A_M | B28: 0.0002 | C28: 6.1 | D28: Gompertz-Makeham A, sex M
A29: A_F | B29: 0.00015 | C29: 6.1 | D29: Gompertz-Makeham A, sex F
A30: B_M | B30: 1.7e-05 | C30: 6.1 | D30: Gompertz-Makeham B, sex M
A31: B_F | B31: 1.1e-05 | C31: 6.1 | D31: Gompertz-Makeham B, sex F
A32: c | B32: 1.1 | C32: 6.1 | D32: Gompertz-Makeham c (both sexes); defined name gm_c
A33: maint_base | B33: 5 | C33: 6.5 | D33: Money per policy, per month, time-0 prices
A34: claim_exp_base | B34: 250 | C34: 6.5 | D34: Money per policy (per death), time-0 prices
A36: Lapse table (section 6.2): key k = min(dur_y, 5)
A37: k | B37: lapse_table | D37: Prob, annual
A38: 0 | B38: 0.15
A39: 1 | B39: 0.1
A40: 2 | B40: 0.08
A41: 3 | B41: 0.06
A42: 4 | B42: 0.05
A43: 5 | B43: 0.04
A45: Commission table (section 6.6): key k = min(dur_y, 1)
A46: k | B46: comm_table | D46: Fraction
A47: 0 | B47: 0.2
A48: 1 | B48: 0.02
A50: Monthly block (sections 7.1 and 11.1): rows t = 0 .. rem_m, one column per quantity in the 7.1 order; the row-level check cells of section 12 follow the blank column
A51: t | B51: dur_y | C51: age | D51: q_ann | E51: q_m | F51: w_ann | G51: w_m | H51: comm_rate | I51: infl | J51: deaths | K51: lapses | L51: maturities | M51: pols_if | N51: premium_pp | O51: commission_pp | P51: maint_pp | Q51: claim_exp_pp | R51: premium_income | S51: commission | T51: maint_expense | U51: death_outgo | V51: claim_expense | W51: net_cf | X51: net_outgo | Y51: v | Z51: disc | AA51: pv_net_cf_t | AB51: pv_premiums_t | AC51: pv_commission_t | AD51: pv_maint_expense_t | AE51: pv_death_outgo_t | AF51: pv_claim_expense_t | AG51: reserve | AH51: reserve_pp | AI51: reserve_floored | AK51: H1 | AL51: H2 | AM51: H4_lhs | AN51: H4 | AO51: H5b_term | AP51: H5b_sum | AQ51: H5b | AR51: P1 | AS51: P2 | AT51: P4 | AU51: P5_rhs | AV51: P5 | AW51: P6 | AX51: P10
A52: 0 | I52: 1 | M52: =pols_if_init -> 1 | Z52: 1 | AG52: =(AG53+X53)*Y53 -> -1024.1131 | AH52: =IF(M52>0,AG52/M52,0) -> -1024.1131 | AI52: =IF(AG52>0,AG52,0) -> 0 | AK52: =M52>=0 -> TRUE | AP52: =SUM(AO53:$AO$352) -> -1024.1131 | AQ52: =ABS(AG52*Z52-AP52)<=0.000000001*MAX(ABS(AG52*Z52),ABS(AP52),scale_money) -> TRUE | AU52: =-(N53-O53)+v_m*(E53*(sum_assured+Q53)+P53+(1-E53)*(1-G53)*AH53) -> -1024.1131 | AV52: =ABS(AH52-AU52)<=0.000000001*MAX(ABS(AH52),ABS(AU52),scale_pp) -> TRUE | AW52: =AND(AI52>=0,AI52>=AG52) -> TRUE
A53: 1 | B53: =MIN(INT((dur_m+A53-1)/12),dur_y_last) -> 0 | C53: =age_at_entry+B53 -> 35 | D53: =INDEX(mort_table,MATCH(C53,mort_age,0),MATCH(sex,mort_sex,0)) -> 0.00047422518 | E53: =IF(A53<=rem_m,1-(1-D53)^(1/12),0) -> 3.9527357e-05 | F53: =IF(A53<=prem_rem_m,INDEX(lapse_table,MATCH(MIN(B53,5),lapse_key,0)),0) -> 0.15 | G53: =1-(1-F53)^(1/12) -> 0.013451947 | H53: =INDEX(comm_table,MATCH(MIN(B53,1),comm_key,0)) -> 0.2 | I53: =(1+e_m)^A53 -> 1.0024663 | J53: =M52*E53 -> 3.9527357e-05 | K53: =(M52-J53)*G53 -> 0.013451415 | L53: =IF(A53=rem_m,M52-J53-K53,0) -> 0 | M53: =M52-J53-K53-L53 -> 0.98650906 | N53: =IF(A53<=prem_rem_m,premium,0) -> 51.64 | O53: =N53*H53 -> 10.328 | P53: =maint_base*I53 -> 5.0123313 | Q53: =claim_exp_base*I53 -> 250.61657 | R53: =M52*N53 -> 51.64 | S53: =R53*H53 -> 10.328 | T53: =M52*P53 -> 5.0123313 | U53: =J53*sum_assured -> 15.810943 | V53: =J53*Q53 -> 0.0099062105 | W53: =R53-S53-T53-U53-V53 -> 20.47882 | X53: =U53+V53+T53-(R53-S53)*(1+i_m) -> -20.614064 | Y53: =v_m -> 0.99673694 | Z53: =v_m^A53 -> 0.99673694 | AA53: =(R53-S53)*Z52-(T53+U53+V53)*Z53 -> 20.5468 | AB53: =R53*Z52 -> 51.64 | AC53: =S53*Z52 -> 10.328 | AD53: =T53*Z53 -> 4.9959758 | AE53: =U53*Z53 -> 15.759351 | AF53: =V53*Z53 -> 0.009873886 | AG53: =(AG54+X54)*Y54 -> -1006.8517 | AH53: =IF(M53>0,AG53/M53,0) -> -1020.6209 | AI53: =IF(AG53>0,AG53,0) -> 0 | AK53: =AND(M53>=0,M53<=M52) -> TRUE | AL53: =AND(D53>=0,D53<=1,E53>=0,E53<=1,F53>=0,F53<=1,G53>=0,G53<=1,J53+K53+L53<=M52+0.000000001*scale_count) -> TRUE | AM53: =(AG52+R53-S53)*(1+i_m)-T53-U53-V53 -> -1006.8517 | AN53: =ABS(AM53-AG53)<=0.000000001*MAX(ABS(AM53),ABS(AG53),scale_money) -> TRUE | AO53: =(U53+V53+T53)*Z53-(R53-S53)*Z52 -> -20.5468 | AP53: =SUM(AO54:$AO$352) -> -1003.5663 | AQ53: =ABS(AG53*Z53-AP53)<=0.000000001*MAX(ABS(AG53*Z53),ABS(AP53),scale_money) -> TRUE | AR53: =IF(A53<>rem_m,L53=0,L53=M52-J53-K53) -> TRUE | AS53: =IF(A53>prem_rem_m,AND(R53=0,S53=0,F53=0,G53=0,K53=0),R53=M52*premium) -> TRUE | AT53: =AND(C53>=18,C53<=120) -> TRUE | AU53: =-(N54-O54)+v_m*(E54*(sum_assured+Q54)+P54+(1-E54)*(1-G54)*AH54) -> -1020.6209 | AV53: =ABS(AH53-AU53)<=0.000000001*MAX(ABS(AH53),ABS(AU53),scale_pp) -> TRUE | AW53: =AND(AI53>=0,AI53>=AG53) -> TRUE | AX53: =AND(U53=J53*sum_assured,R53=M52*N53,T53=M52*P53) -> TRUE
A54: 2 | B54: =MIN(INT((dur_m+A54-1)/12),dur_y_last) -> 0 | C54: =age_at_entry+B54 -> 35 | D54: =INDEX(mort_table,MATCH(C54,mort_age,0),MATCH(sex,mort_sex,0)) -> 0.00047422518 | E54: =IF(A54<=rem_m,1-(1-D54)^(1/12),0) -> 3.9527357e-05 | F54: =IF(A54<=prem_rem_m,INDEX(lapse_table,MATCH(MIN(B54,5),lapse_key,0)),0) -> 0.15 | G54: =1-(1-F54)^(1/12) -> 0.013451947 | H54: =INDEX(comm_table,MATCH(MIN(B54,1),comm_key,0)) -> 0.2 | I54: =(1+e_m)^A54 -> 1.0049386 | J54: =M53*E54 -> 3.8994096e-05 | K54: =(M53-J54)*G54 -> 0.013269943 | L54: =IF(A54=rem_m,M53-J54-K54,0) -> 0 | M54: =M53-J54-K54-L54 -> 0.97320012 | N54: =IF(A54<=prem_rem_m,premium,0) -> 51.64 | O54: =N54*H54 -> 10.328 | P54: =maint_base*I54 -> 5.0246931 | Q54: =claim_exp_base*I54 -> 251.23466 | R54: =M53*N54 -> 50.943328 | S54: =R54*H54 -> 10.188666 | T54: =M53*P54 -> 4.9569053 | U54: =J54*sum_assured -> 15.597638 | V54: =J54*Q54 -> 0.0097966682 | W54: =R54-S54-T54-U54-V54 -> 20.190322 | X54: =U54+V54+T54-(R54-S54)*(1+i_m) -> -20.323742 | Y54: =v_m -> 0.99673694 | Z54: =v_m^A54 -> 0.99348453 | AA54: =(R54-S54)*Z53-(T54+U54+V54)*Z54 -> 20.191323 | AB54: =R54*Z53 -> 50.777097 | AC54: =S54*Z53 -> 10.155419 | AD54: =T54*Z54 -> 4.9246087 | AE54: =U54*Z54 -> 15.496012 | AF54: =V54*Z54 -> 0.0097328383 | AG54: =(AG55+X55)*Y55 -> -989.82414 | AH54: =IF(M54>0,AG54/M54,0) -> -1017.0818 | AI54: =IF(AG54>0,AG54,0) -> 0 | AK54: =AND(M54>=0,M54<=M53) -> TRUE | AL54: =AND(D54>=0,D54<=1,E54>=0,E54<=1,F54>=0,F54<=1,G54>=0,G54<=1,J54+K54+L54<=M53+0.000000001*scale_count) -> TRUE | AM54: =(AG53+R54-S54)*(1+i_m)-T54-U54-V54 -> -989.82414 | AN54: =ABS(AM54-AG54)<=0.000000001*MAX(ABS(AM54),ABS(AG54),scale_money) -> TRUE | AO54: =(U54+V54+T54)*Z54-(R54-S54)*Z53 -> -20.191323 | AP54: =SUM(AO55:$AO$352) -> -983.37498 | AQ54: =ABS(AG54*Z54-AP54)<=0.000000001*MAX(ABS(AG54*Z54),ABS(AP54),scale_money) -> TRUE | AR54: =IF(A54<>rem_m,L54=0,L54=M53-J54-K54) -> TRUE | AS54: =IF(A54>prem_rem_m,AND(R54=0,S54=0,F54=0,G54=0,K54=0),R54=M53*premium) -> TRUE | AT54: =AND(C54>=18,C54<=120,OR(B54-B53=0,B54-B53=1)) -> TRUE | AU54: =-(N55-O55)+v_m*(E55*(sum_assured+Q55)+P55+(1-E55)*(1-G55)*AH55) -> -1017.0818 | AV54: =ABS(AH54-AU54)<=0.000000001*MAX(ABS(AH54),ABS(AU54),scale_pp) -> TRUE | AW54: =AND(AI54>=0,AI54>=AG54) -> TRUE | AX54: =AND(U54=J54*sum_assured,R54=M53*N54,T54=M53*P54) -> TRUE
A55: 3 | B55: =MIN(INT((dur_m+A55-1)/12),dur_y_last) -> 0 | C55: =age_at_entry+B55 -> 35 | D55: =INDEX(mort_table,MATCH(C55,mort_age,0),MATCH(sex,mort_sex,0)) -> 0.00047422518 | E55: =IF(A55<=rem_m,1-(1-D55)^(1/12),0) -> 3.9527357e-05 | F55: =IF(A55<=prem_rem_m,INDEX(lapse_table,MATCH(MIN(B55,5),lapse_key,0)),0) -> 0.15 | G55: =1-(1-F55)^(1/12) -> 0.013451947 | H55: =INDEX(comm_table,MATCH(MIN(B55,1),comm_key,0)) -> 0.2 | I55: =(1+e_m)^A55 -> 1.0074171 | J55: =M54*E55 -> 3.8468029e-05 | K55: =(M54-J55)*G55 -> 0.013090919 | L55: =IF(A55=rem_m,M54-J55-K55,0) -> 0 | M55: =M54-J55-K55-L55 -> 0.96007073 | N55: =IF(A55<=prem_rem_m,premium,0) -> 51.64 | O55: =N55*H55 -> 10.328 | P55: =maint_base*I55 -> 5.0370854 | Q55: =claim_exp_base*I55 -> 251.85427 | R55: =M54*N55 -> 50.256054 | S55: =R55*H55 -> 10.051211 | T55: =M54*P55 -> 4.9020921 | U55: =J55*sum_assured -> 15.387211 | V55: =J55*Q55 -> 0.0096883372 | W55: =R55-S55-T55-U55-V55 -> 19.905852 | X55: =U55+V55+T55-(R55-S55)*(1+i_m) -> -20.037472 | Y55: =v_m -> 0.99673694 | Z55: =v_m^A55 -> 0.99024274 | AA55: =(R55-S55)*Z54-(T55+U55+V55)*Z55 -> 19.841961 | AB55: =R55*Z54 -> 49.928613 | AC55: =S55*Z54 -> 9.9857225 | AD55: =T55*Z55 -> 4.8542611 | AE55: =U55*Z55 -> 15.237074 | AF55: =V55*Z55 -> 0.0095938055 | AG55: =(AG56+X56)*Y56 -> -973.0271 | AH55: =IF(M55>0,AG55/M55,0) -> -1013.4952 | AI55: =IF(AG55>0,AG55,0) -> 0 | AK55: =AND(M55>=0,M55<=M54) -> TRUE | AL55: =AND(D55>=0,D55<=1,E55>=0,E55<=1,F55>=0,F55<=1,G55>=0,G55<=1,J55+K55+L55<=M54+0.000000001*scale_count) -> TRUE | AM55: =(AG54+R55-S55)*(1+i_m)-T55-U55-V55 -> -973.0271 | AN55: =ABS(AM55-AG55)<=0.000000001*MAX(ABS(AM55),ABS(AG55),scale_money) -> TRUE | AO55: =(U55+V55+T55)*Z55-(R55-S55)*Z54 -> -19.841961 | AP55: =SUM(AO56:$AO$352) -> -963.53302 | AQ55: =ABS(AG55*Z55-AP55)<=0.000000001*MAX(ABS(AG55*Z55),ABS(AP55),scale_money) -> TRUE | AR55: =IF(A55<>rem_m,L55=0,L55=M54-J55-K55) -> TRUE | AS55: =IF(A55>prem_rem_m,AND(R55=0,S55=0,F55=0,G55=0,K55=0),R55=M54*premium) -> TRUE | AT55: =AND(C55>=18,C55<=120,OR(B55-B54=0,B55-B54=1)) -> TRUE | AU55: =-(N56-O56)+v_m*(E56*(sum_assured+Q56)+P56+(1-E56)*(1-G56)*AH56) -> -1013.4952 | AV55: =ABS(AH55-AU55)<=0.000000001*MAX(ABS(AH55),ABS(AU55),scale_pp) -> TRUE | AW55: =AND(AI55>=0,AI55>=AG55) -> TRUE | AX55: =AND(U55=J55*sum_assured,R55=M54*N55,T55=M54*P55) -> TRUE
A56: 4 | B56: =MIN(INT((dur_m+A56-1)/12),dur_y_last) -> 0 | C56: =age_at_entry+B56 -> 35 | D56: =INDEX(mort_table,MATCH(C56,mort_age,0),MATCH(sex,mort_sex,0)) -> 0.00047422518 | E56: =IF(A56<=rem_m,1-(1-D56)^(1/12),0) -> 3.9527357e-05 | F56: =IF(A56<=prem_rem_m,INDEX(lapse_table,MATCH(MIN(B56,5),lapse_key,0)),0) -> 0.15 | G56: =1-(1-F56)^(1/12) -> 0.013451947 | H56: =INDEX(comm_table,MATCH(MIN(B56,1),comm_key,0)) -> 0.2 | I56: =(1+e_m)^A56 -> 1.0099016 | J56: =M55*E56 -> 3.7949059e-05 | K56: =(M55-J56)*G56 -> 0.01291431 | L56: =IF(A56=rem_m,M55-J56-K56,0) -> 0 | M56: =M55-J56-K56-L56 -> 0.94711847 | N56: =IF(A56<=prem_rem_m,premium,0) -> 51.64 | O56: =N56*H56 -> 10.328 | P56: =maint_base*I56 -> 5.0495082 | Q56: =claim_exp_base*I56 -> 252.47541 | R56: =M55*N56 -> 49.578053 | S56: =R56*H56 -> 9.9156105 | T56: =M55*P56 -> 4.847885 | U56: =J56*sum_assured -> 15.179623 | V56: =J56*Q56 -> 0.0095812041 | W56: =R56-S56-T56-U56-V56 -> 19.625352 | X56: =U56+V56+T56-(R56-S56)*(1+i_m) -> -19.755197 | Y56: =v_m -> 0.99673694 | Z56: =v_m^A56 -> 0.98701152 | AA56: =(R56-S56)*Z55-(T56+U56+V56)*Z56 -> 19.498607 | AB56: =R56*Z55 -> 49.094307 | AC56: =S56*Z55 -> 9.8188613 | AD56: =T56*Z56 -> 4.7849183 | AE56: =U56*Z56 -> 14.982463 | AF56: =V56*Z56 -> 0.0094567588 | AG56: =(AG57+X57)*Y57 -> -956.45734 | AH56: =IF(M56>0,AG56/M56,0) -> -1009.8603 | AI56: =IF(AG56>0,AG56,0) -> 0 | AK56: =AND(M56>=0,M56<=M55) -> TRUE | AL56: =AND(D56>=0,D56<=1,E56>=0,E56<=1,F56>=0,F56<=1,G56>=0,G56<=1,J56+K56+L56<=M55+0.000000001*scale_count) -> TRUE | AM56: =(AG55+R56-S56)*(1+i_m)-T56-U56-V56 -> -956.45734 | AN56: =ABS(AM56-AG56)<=0.000000001*MAX(ABS(AM56),ABS(AG56),scale_money) -> TRUE | AO56: =(U56+V56+T56)*Z56-(R56-S56)*Z55 -> -19.498607 | AP56: =SUM(AO57:$AO$352) -> -944.03441 | AQ56: =ABS(AG56*Z56-AP56)<=0.000000001*MAX(ABS(AG56*Z56),ABS(AP56),scale_money) -> TRUE | AR56: =IF(A56<>rem_m,L56=0,L56=M55-J56-K56) -> TRUE | AS56: =IF(A56>prem_rem_m,AND(R56=0,S56=0,F56=0,G56=0,K56=0),R56=M55*premium) -> TRUE | AT56: =AND(C56>=18,C56<=120,OR(B56-B55=0,B56-B55=1)) -> TRUE | AU56: =-(N57-O57)+v_m*(E57*(sum_assured+Q57)+P57+(1-E57)*(1-G57)*AH57) -> -1009.8603 | AV56: =ABS(AH56-AU56)<=0.000000001*MAX(ABS(AH56),ABS(AU56),scale_pp) -> TRUE | AW56: =AND(AI56>=0,AI56>=AG56) -> TRUE | AX56: =AND(U56=J56*sum_assured,R56=M55*N56,T56=M55*P56) -> TRUE
A57: 5 | B57: =MIN(INT((dur_m+A57-1)/12),dur_y_last) -> 0 | C57: =age_at_entry+B57 -> 35 | D57: =INDEX(mort_table,MATCH(C57,mort_age,0),MATCH(sex,mort_sex,0)) -> 0.00047422518 | E57: =IF(A57<=rem_m,1-(1-D57)^(1/12),0) -> 3.9527357e-05 | F57: =IF(A57<=prem_rem_m,INDEX(lapse_table,MATCH(MIN(B57,5),lapse_key,0)),0) -> 0.15 | G57: =1-(1-F57)^(1/12) -> 0.013451947 | H57: =INDEX(comm_table,MATCH(MIN(B57,1),comm_key,0)) -> 0.2 | I57: =(1+e_m)^A57 -> 1.0123923 | J57: =M56*E57 -> 3.743709e-05 | K57: =(M56-J57)*G57 -> 0.012740084 | L57: =IF(A57=rem_m,M56-J57-K57,0) -> 0 | M57: =M56-J57-K57-L57 -> 0.93434095 | N57: =IF(A57<=prem_rem_m,premium,0) -> 51.64 | O57: =N57*H57 -> 10.328 | P57: =maint_base*I57 -> 5.0619616 | Q57: =claim_exp_base*I57 -> 253.09808 | R57: =M56*N57 -> 48.909198 | S57: =R57*H57 -> 9.7818396 | T57: =M56*P57 -> 4.7942774 | U57: =J57*sum_assured -> 14.974836 | V57: =J57*Q57 -> 0.0094752556 | W57: =R57-S57-T57-U57-V57 -> 19.34877 | X57: =U57+V57+T57-(R57-S57)*(1+i_m) -> -19.476863 | Y57: =v_m -> 0.99673694 | Z57: =v_m^A57 -> 0.98379084 | AA57: =(R57-S57)*Z56-(T57+U57+V57)*Z57 -> 19.161159 | AB57: =R57*Z56 -> 48.273942 | AC57: =S57*Z56 -> 9.6547883 | AD57: =T57*Z57 -> 4.7165662 | AE57: =U57*Z57 -> 14.732107 | AF57: =V57*Z57 -> 0.0093216697 | AG57: =(AG58+X58)*Y58 -> -940.11167 | AH57: =IF(M57>0,AG57/M57,0) -> -1006.1762 | AI57: =IF(AG57>0,AG57,0) -> 0 | AK57: =AND(M57>=0,M57<=M56) -> TRUE | AL57: =AND(D57>=0,D57<=1,E57>=0,E57<=1,F57>=0,F57<=1,G57>=0,G57<=1,J57+K57+L57<=M56+0.000000001*scale_count) -> TRUE | AM57: =(AG56+R57-S57)*(1+i_m)-T57-U57-V57 -> -940.11167 | AN57: =ABS(AM57-AG57)<=0.000000001*MAX(ABS(AM57),ABS(AG57),scale_money) -> TRUE | AO57: =(U57+V57+T57)*Z57-(R57-S57)*Z56 -> -19.161159 | AP57: =SUM(AO58:$AO$352) -> -924.87325 | AQ57: =ABS(AG57*Z57-AP57)<=0.000000001*MAX(ABS(AG57*Z57),ABS(AP57),scale_money) -> TRUE | AR57: =IF(A57<>rem_m,L57=0,L57=M56-J57-K57) -> TRUE | AS57: =IF(A57>prem_rem_m,AND(R57=0,S57=0,F57=0,G57=0,K57=0),R57=M56*premium) -> TRUE | AT57: =AND(C57>=18,C57<=120,OR(B57-B56=0,B57-B56=1)) -> TRUE | AU57: =-(N58-O58)+v_m*(E58*(sum_assured+Q58)+P58+(1-E58)*(1-G58)*AH58) -> -1006.1762 | AV57: =ABS(AH57-AU57)<=0.000000001*MAX(ABS(AH57),ABS(AU57),scale_pp) -> TRUE | AW57: =AND(AI57>=0,AI57>=AG57) -> TRUE | AX57: =AND(U57=J57*sum_assured,R57=M56*N57,T57=M56*P57) -> TRUE
A58: 6 | B58: =MIN(INT((dur_m+A58-1)/12),dur_y_last) -> 0 | C58: =age_at_entry+B58 -> 35 | D58: =INDEX(mort_table,MATCH(C58,mort_age,0),MATCH(sex,mort_sex,0)) -> 0.00047422518 | E58: =IF(A58<=rem_m,1-(1-D58)^(1/12),0) -> 3.9527357e-05 | F58: =IF(A58<=prem_rem_m,INDEX(lapse_table,MATCH(MIN(B58,5),lapse_key,0)),0) -> 0.15 | G58: =1-(1-F58)^(1/12) -> 0.013451947 | H58: =INDEX(comm_table,MATCH(MIN(B58,1),comm_key,0)) -> 0.2 | I58: =(1+e_m)^A58 -> 1.0148892 | J58: =M57*E58 -> 3.6932028e-05 | K58: =(M57-J58)*G58 -> 0.012568208 | L58: =IF(A58=rem_m,M57-J58-K58,0) -> 0 | M58: =M57-J58-K58-L58 -> 0.92173581 | N58: =IF(A58<=prem_rem_m,premium,0) -> 51.64 | O58: =N58*H58 -> 10.328 | P58: =maint_base*I58 -> 5.0744458 | Q58: =claim_exp_base*I58 -> 253.72229 | R58: =M57*N58 -> 48.249367 | S58: =R58*H58 -> 9.6498734 | T58: =M57*P58 -> 4.7412625 | U58: =J58*sum_assured -> 14.772811 | V58: =J58*Q58 -> 0.0093704788 | W58: =R58-S58-T58-U58-V58 -> 19.076049 | X58: =U58+V58+T58-(R58-S58)*(1+i_m) -> -19.202414 | Y58: =v_m -> 0.99673694 | Z58: =v_m^A58 -> 0.98058068 | AA58: =(R58-S58)*Z57-(T58+U58+V58)*Z58 -> 18.829516 | AB58: =R58*Z57 -> 47.467285 | AC58: =S58*Z57 -> 9.493457 | AD58: =T58*Z58 -> 4.6491904 | AE58: =U58*Z58 -> 14.485933 | AF58: =V58*Z58 -> 0.0091885104 | AG58: =(AG59+X59)*Y59 -> -923.98694 | AH58: =IF(M58>0,AG58/M58,0) -> -1002.4423 | AI58: =IF(AG58>0,AG58,0) -> 0 | AK58: =AND(M58>=0,M58<=M57) -> TRUE | AL58: =AND(D58>=0,D58<=1,E58>=0,E58<=1,F58>=0,F58<=1,G58>=0,G58<=1,J58+K58+L58<=M57+0.000000001*scale_count) -> TRUE | AM58: =(AG57+R58-S58)*(1+i_m)-T58-U58-V58 -> -923.98694 | AN58: =ABS(AM58-AG58)<=0.000000001*MAX(ABS(AM58),ABS(AG58),scale_money) -> TRUE | AO58: =(U58+V58+T58)*Z58-(R58-S58)*Z57 -> -18.829516 | AP58: =SUM(AO59:$AO$352) -> -906.04373 | AQ58: =ABS(AG58*Z58-AP58)<=0.000000001*MAX(ABS(AG58*Z58),ABS(AP58),scale_money) -> TRUE | AR58: =IF(A58<>rem_m,L58=0,L58=M57-J58-K58) -> TRUE | AS58: =IF(A58>prem_rem_m,AND(R58=0,S58=0,F58=0,G58=0,K58=0),R58=M57*premium) -> TRUE | AT58: =AND(C58>=18,C58<=120,OR(B58-B57=0,B58-B57=1)) -> TRUE | AU58: =-(N59-O59)+v_m*(E59*(sum_assured+Q59)+P59+(1-E59)*(1-G59)*AH59) -> -1002.4423 | AV58: =ABS(AH58-AU58)<=0.000000001*MAX(ABS(AH58),ABS(AU58),scale_pp) -> TRUE | AW58: =AND(AI58>=0,AI58>=AG58) -> TRUE | AX58: =AND(U58=J58*sum_assured,R58=M57*N58,T58=M57*P58) -> TRUE
A59: 7 | B59: =MIN(INT((dur_m+A59-1)/12),dur_y_last) -> 0 | C59: =age_at_entry+B59 -> 35 | D59: =INDEX(mort_table,MATCH(C59,mort_age,0),MATCH(sex,mort_sex,0)) -> 0.00047422518 | E59: =IF(A59<=rem_m,1-(1-D59)^(1/12),0) -> 3.9527357e-05 | F59: =IF(A59<=prem_rem_m,INDEX(lapse_table,MATCH(MIN(B59,5),lapse_key,0)),0) -> 0.15 | G59: =1-(1-F59)^(1/12) -> 0.013451947 | H59: =INDEX(comm_table,MATCH(MIN(B59,1),comm_key,0)) -> 0.2 | I59: =(1+e_m)^A59 -> 1.0173921 | J59: =M58*E59 -> 3.6433781e-05 | K59: =(M58-J59)*G59 -> 0.012398651 | L59: =IF(A59=rem_m,M58-J59-K59,0) -> 0 | M59: =M58-J59-K59-L59 -> 0.90930073 | N59: =IF(A59<=prem_rem_m,premium,0) -> 51.64 | O59: =N59*H59 -> 10.328 | P59: =maint_base*I59 -> 5.0869607 | Q59: =claim_exp_base*I59 -> 254.34804 | R59: =M58*N59 -> 47.598437 | S59: =R59*H59 -> 9.5196875 | T59: =M58*P59 -> 4.6888339 | U59: =J59*sum_assured -> 14.573512 | V59: =J59*Q59 -> 0.0092668605 | W59: =R59-S59-T59-U59-V59 -> 18.807137 | X59: =U59+V59+T59-(R59-S59)*(1+i_m) -> -18.931797 | Y59: =v_m -> 0.99673694 | Z59: =v_m^A59 -> 0.97738098 | AA59: =(R59-S59)*Z58-(T59+U59+V59)*Z59 -> 18.503578 | AB59: =R59*Z58 -> 46.674108 | AC59: =S59*Z58 -> 9.3348216 | AD59: =T59*Z59 -> 4.5827771 | AE59: =U59*Z59 -> 14.243874 | AF59: =V59*Z59 -> 0.0090572533 | AG59: =(AG60+X60)*Y60 -> -908.08003 | AH59: =IF(M59>0,AG59/M59,0) -> -998.65754 | AI59: =IF(AG59>0,AG59,0) -> 0 | AK59: =AND(M59>=0,M59<=M58) -> TRUE | AL59: =AND(D59>=0,D59<=1,E59>=0,E59<=1,F59>=0,F59<=1,G59>=0,G59<=1,J59+K59+L59<=M58+0.000000001*scale_count) -> TRUE | AM59: =(AG58+R59-S59)*(1+i_m)-T59-U59-V59 -> -908.08003 | AN59: =ABS(AM59-AG59)<=0.000000001*MAX(ABS(AM59),ABS(AG59),scale_money) -> TRUE | AO59: =(U59+V59+T59)*Z59-(R59-S59)*Z58 -> -18.503578 | AP59: =SUM(AO60:$AO$352) -> -887.54016 | AQ59: =ABS(AG59*Z59-AP59)<=0.000000001*MAX(ABS(AG59*Z59),ABS(AP59),scale_money) -> TRUE | AR59: =IF(A59<>rem_m,L59=0,L59=M58-J59-K59) -> TRUE | AS59: =IF(A59>prem_rem_m,AND(R59=0,S59=0,F59=0,G59=0,K59=0),R59=M58*premium) -> TRUE | AT59: =AND(C59>=18,C59<=120,OR(B59-B58=0,B59-B58=1)) -> TRUE | AU59: =-(N60-O60)+v_m*(E60*(sum_assured+Q60)+P60+(1-E60)*(1-G60)*AH60) -> -998.65754 | AV59: =ABS(AH59-AU59)<=0.000000001*MAX(ABS(AH59),ABS(AU59),scale_pp) -> TRUE | AW59: =AND(AI59>=0,AI59>=AG59) -> TRUE | AX59: =AND(U59=J59*sum_assured,R59=M58*N59,T59=M58*P59) -> TRUE
A60: 8 | B60: =MIN(INT((dur_m+A60-1)/12),dur_y_last) -> 0 | C60: =age_at_entry+B60 -> 35 | D60: =INDEX(mort_table,MATCH(C60,mort_age,0),MATCH(sex,mort_sex,0)) -> 0.00047422518 | E60: =IF(A60<=rem_m,1-(1-D60)^(1/12),0) -> 3.9527357e-05 | F60: =IF(A60<=prem_rem_m,INDEX(lapse_table,MATCH(MIN(B60,5),lapse_key,0)),0) -> 0.15 | G60: =1-(1-F60)^(1/12) -> 0.013451947 | H60: =INDEX(comm_table,MATCH(MIN(B60,1),comm_key,0)) -> 0.2 | I60: =(1+e_m)^A60 -> 1.0199013 | J60: =M59*E60 -> 3.5942254e-05 | K60: =(M59-J60)*G60 -> 0.012231382 | L60: =IF(A60=rem_m,M59-J60-K60,0) -> 0 | M60: =M59-J60-K60-L60 -> 0.8970334 | N60: =IF(A60<=prem_rem_m,premium,0) -> 51.64 | O60: =N60*H60 -> 10.328 | P60: =maint_base*I60 -> 5.0995066 | Q60: =claim_exp_base*I60 -> 254.97533 | R60: =M59*N60 -> 46.95629 | S60: =R60*H60 -> 9.3912579 | T60: =M59*P60 -> 4.636985 | U60: =J60*sum_assured -> 14.376902 | V60: =J60*Q60 -> 0.0091643881 | W60: =R60-S60-T60-U60-V60 -> 18.54198 | X60: =U60+V60+T60-(R60-S60)*(1+i_m) -> -18.664959 | Y60: =v_m -> 0.99673694 | Z60: =v_m^A60 -> 0.97419173 | AA60: =(R60-S60)*Z59-(T60+U60+V60)*Z60 -> 18.183248 | AB60: =R60*Z59 -> 45.894185 | AC60: =S60*Z59 -> 9.1788369 | AD60: =T60*Z60 -> 4.5173125 | AE60: =U60*Z60 -> 14.005859 | AF60: =V60*Z60 -> 0.0089278711 | AG60: =(AG61+X61)*Y61 -> -892.38789 | AH60: =IF(M60>0,AG60/M60,0) -> -994.82125 | AI60: =IF(AG60>0,AG60,0) -> 0 | AK60: =AND(M60>=0,M60<=M59) -> TRUE | AL60: =AND(D60>=0,D60<=1,E60>=0,E60<=1,F60>=0,F60<=1,G60>=0,G60<=1,J60+K60+L60<=M59+0.000000001*scale_count) -> TRUE | AM60: =(AG59+R60-S60)*(1+i_m)-T60-U60-V60 -> -892.38789 | AN60: =ABS(AM60-AG60)<=0.000000001*MAX(ABS(AM60),ABS(AG60),scale_money) -> TRUE | AO60: =(U60+V60+T60)*Z60-(R60-S60)*Z59 -> -18.183248 | AP60: =SUM(AO61:$AO$352) -> -869.35691 | AQ60: =ABS(AG60*Z60-AP60)<=0.000000001*MAX(ABS(AG60*Z60),ABS(AP60),scale_money) -> TRUE | AR60: =IF(A60<>rem_m,L60=0,L60=M59-J60-K60) -> TRUE | AS60: =IF(A60>prem_rem_m,AND(R60=0,S60=0,F60=0,G60=0,K60=0),R60=M59*premium) -> TRUE | AT60: =AND(C60>=18,C60<=120,OR(B60-B59=0,B60-B59=1)) -> TRUE | AU60: =-(N61-O61)+v_m*(E61*(sum_assured+Q61)+P61+(1-E61)*(1-G61)*AH61) -> -994.82125 | AV60: =ABS(AH60-AU60)<=0.000000001*MAX(ABS(AH60),ABS(AU60),scale_pp) -> TRUE | AW60: =AND(AI60>=0,AI60>=AG60) -> TRUE | AX60: =AND(U60=J60*sum_assured,R60=M59*N60,T60=M59*P60) -> TRUE
A61: 9 | B61: =MIN(INT((dur_m+A61-1)/12),dur_y_last) -> 0 | C61: =age_at_entry+B61 -> 35 | D61: =INDEX(mort_table,MATCH(C61,mort_age,0),MATCH(sex,mort_sex,0)) -> 0.00047422518 | E61: =IF(A61<=rem_m,1-(1-D61)^(1/12),0) -> 3.9527357e-05 | F61: =IF(A61<=prem_rem_m,INDEX(lapse_table,MATCH(MIN(B61,5),lapse_key,0)),0) -> 0.15 | G61: =1-(1-F61)^(1/12) -> 0.013451947 | H61: =INDEX(comm_table,MATCH(MIN(B61,1),comm_key,0)) -> 0.2 | I61: =(1+e_m)^A61 -> 1.0224167 | J61: =M60*E61 -> 3.545736e-05 | K61: =(M60-J61)*G61 -> 0.012066369 | L61: =IF(A61=rem_m,M60-J61-K61,0) -> 0 | M61: =M60-J61-K61-L61 -> 0.88493158 | N61: =IF(A61<=prem_rem_m,premium,0) -> 51.64 | O61: =N61*H61 -> 10.328 | P61: =maint_base*I61 -> 5.1120833 | Q61: =claim_exp_base*I61 -> 255.60417 | R61: =M60*N61 -> 46.322805 | S61: =R61*H61 -> 9.264561 | T61: =M60*P61 -> 4.5857095 | U61: =J61*sum_assured -> 14.182944 | V61: =J61*Q61 -> 0.0090630488 | W61: =R61-S61-T61-U61-V61 -> 18.280528 | X61: =U61+V61+T61-(R61-S61)*(1+i_m) -> -18.401847 | Y61: =v_m -> 0.99673694 | Z61: =v_m^A61 -> 0.97101289 | AA61: =(R61-S61)*Z60-(T61+U61+V61)*Z61 -> 17.86843 | AB61: =R61*Z60 -> 45.127294 | AC61: =S61*Z60 -> 9.0254587 | AD61: =T61*Z61 -> 4.452783 | AE61: =U61*Z61 -> 13.771821 | AF61: =V61*Z61 -> 0.0088003372 | AG61: =(AG62+X62)*Y62 -> -876.90749 | AH61: =IF(M61>0,AG61/M61,0) -> -990.93253 | AI61: =IF(AG61>0,AG61,0) -> 0 | AK61: =AND(M61>=0,M61<=M60) -> TRUE | AL61: =AND(D61>=0,D61<=1,E61>=0,E61<=1,F61>=0,F61<=1,G61>=0,G61<=1,J61+K61+L61<=M60+0.000000001*scale_count) -> TRUE | AM61: =(AG60+R61-S61)*(1+i_m)-T61-U61-V61 -> -876.90749 | AN61: =ABS(AM61-AG61)<=0.000000001*MAX(ABS(AM61),ABS(AG61),scale_money) -> TRUE | AO61: =(U61+V61+T61)*Z61-(R61-S61)*Z60 -> -17.86843 | AP61: =SUM(AO62:$AO$352) -> -851.48848 | AQ61: =ABS(AG61*Z61-AP61)<=0.000000001*MAX(ABS(AG61*Z61),ABS(AP61),scale_money) -> TRUE | AR61: =IF(A61<>rem_m,L61=0,L61=M60-J61-K61) -> TRUE | AS61: =IF(A61>prem_rem_m,AND(R61=0,S61=0,F61=0,G61=0,K61=0),R61=M60*premium) -> TRUE | AT61: =AND(C61>=18,C61<=120,OR(B61-B60=0,B61-B60=1)) -> TRUE | AU61: =-(N62-O62)+v_m*(E62*(sum_assured+Q62)+P62+(1-E62)*(1-G62)*AH62) -> -990.93253 | AV61: =ABS(AH61-AU61)<=0.000000001*MAX(ABS(AH61),ABS(AU61),scale_pp) -> TRUE | AW61: =AND(AI61>=0,AI61>=AG61) -> TRUE | AX61: =AND(U61=J61*sum_assured,R61=M60*N61,T61=M60*P61) -> TRUE
A62: 10 | B62: =MIN(INT((dur_m+A62-1)/12),dur_y_last) -> 0 | C62: =age_at_entry+B62 -> 35 | D62: =INDEX(mort_table,MATCH(C62,mort_age,0),MATCH(sex,mort_sex,0)) -> 0.00047422518 | E62: =IF(A62<=rem_m,1-(1-D62)^(1/12),0) -> 3.9527357e-05 | F62: =IF(A62<=prem_rem_m,INDEX(lapse_table,MATCH(MIN(B62,5),lapse_key,0)),0) -> 0.15 | G62: =1-(1-F62)^(1/12) -> 0.013451947 | H62: =INDEX(comm_table,MATCH(MIN(B62,1),comm_key,0)) -> 0.2 | I62: =(1+e_m)^A62 -> 1.0249382 | J62: =M61*E62 -> 3.4979006e-05 | K62: =(M61-J62)*G62 -> 0.011903582 | L62: =IF(A62=rem_m,M61-J62-K62,0) -> 0 | M62: =M61-J62-K62-L62 -> 0.87299302 | N62: =IF(A62<=prem_rem_m,premium,0) -> 51.64 | O62: =N62*H62 -> 10.328 | P62: =maint_base*I62 -> 5.1246911 | Q62: =claim_exp_base*I62 -> 256.23455 | R62: =M61*N62 -> 45.697867 | S62: =R62*H62 -> 9.1395733 | T62: =M61*P62 -> 4.535001 | U62: =J62*sum_assured -> 13.991603 | V62: =J62*Q62 -> 0.0089628301 | W62: =R62-S62-T62-U62-V62 -> 18.022727 | X62: =U62+V62+T62-(R62-S62)*(1+i_m) -> -18.142409 | Y62: =v_m -> 0.99673694 | Z62: =v_m^A62 -> 0.96784442 | AA62: =(R62-S62)*Z61-(T62+U62+V62)*Z62 -> 17.55903 | AB62: =R62*Z61 -> 44.373218 | AC62: =S62*Z61 -> 8.8746435 | AD62: =T62*Z62 -> 4.3891754 | AE62: =U62*Z62 -> 13.541694 | AF62: =V62*Z62 -> 0.0086746251 | AG62: =(AG63+X63)*Y63 -> -861.63585 | AH62: =IF(M62>0,AG62/M62,0) -> -986.99054 | AI62: =IF(AG62>0,AG62,0) -> 0 | AK62: =AND(M62>=0,M62<=M61) -> TRUE | AL62: =AND(D62>=0,D62<=1,E62>=0,E62<=1,F62>=0,F62<=1,G62>=0,G62<=1,J62+K62+L62<=M61+0.000000001*scale_count) -> TRUE | AM62: =(AG61+R62-S62)*(1+i_m)-T62-U62-V62 -> -861.63585 | AN62: =ABS(AM62-AG62)<=0.000000001*MAX(ABS(AM62),ABS(AG62),scale_money) -> TRUE | AO62: =(U62+V62+T62)*Z62-(R62-S62)*Z61 -> -17.55903 | AP62: =SUM(AO63:$AO$352) -> -833.92945 | AQ62: =ABS(AG62*Z62-AP62)<=0.000000001*MAX(ABS(AG62*Z62),ABS(AP62),scale_money) -> TRUE | AR62: =IF(A62<>rem_m,L62=0,L62=M61-J62-K62) -> TRUE | AS62: =IF(A62>prem_rem_m,AND(R62=0,S62=0,F62=0,G62=0,K62=0),R62=M61*premium) -> TRUE | AT62: =AND(C62>=18,C62<=120,OR(B62-B61=0,B62-B61=1)) -> TRUE | AU62: =-(N63-O63)+v_m*(E63*(sum_assured+Q63)+P63+(1-E63)*(1-G63)*AH63) -> -986.99054 | AV62: =ABS(AH62-AU62)<=0.000000001*MAX(ABS(AH62),ABS(AU62),scale_pp) -> TRUE | AW62: =AND(AI62>=0,AI62>=AG62) -> TRUE | AX62: =AND(U62=J62*sum_assured,R62=M61*N62,T62=M61*P62) -> TRUE
A63: 11 | B63: =MIN(INT((dur_m+A63-1)/12),dur_y_last) -> 0 | C63: =age_at_entry+B63 -> 35 | D63: =INDEX(mort_table,MATCH(C63,mort_age,0),MATCH(sex,mort_sex,0)) -> 0.00047422518 | E63: =IF(A63<=rem_m,1-(1-D63)^(1/12),0) -> 3.9527357e-05 | F63: =IF(A63<=prem_rem_m,INDEX(lapse_table,MATCH(MIN(B63,5),lapse_key,0)),0) -> 0.15 | G63: =1-(1-F63)^(1/12) -> 0.013451947 | H63: =INDEX(comm_table,MATCH(MIN(B63,1),comm_key,0)) -> 0.2 | I63: =(1+e_m)^A63 -> 1.027466 | J63: =M62*E63 -> 3.4507107e-05 | K63: =(M62-J63)*G63 -> 0.011742992 | L63: =IF(A63=rem_m,M62-J63-K63,0) -> 0 | M63: =M62-J63-K63-L63 -> 0.86121552 | N63: =IF(A63<=prem_rem_m,premium,0) -> 51.64 | O63: =N63*H63 -> 10.328 | P63: =maint_base*I63 -> 5.13733 | Q63: =claim_exp_base*I63 -> 256.8665 | R63: =M62*N63 -> 45.081359 | S63: =R63*H63 -> 9.0162719 | T63: =M62*P63 -> 4.4848532 | U63: =J63*sum_assured -> 13.802843 | V63: =J63*Q63 -> 0.0088637196 | W63: =R63-S63-T63-U63-V63 -> 17.768528 | X63: =U63+V63+T63-(R63-S63)*(1+i_m) -> -17.886596 | Y63: =v_m -> 0.99673694 | Z63: =v_m^A63 -> 0.96468629 | AA63: =(R63-S63)*Z62-(T63+U63+V63)*Z63 -> 17.254954 | AB63: =R63*Z62 -> 43.631742 | AC63: =S63*Z62 -> 8.7263484 | AD63: =T63*Z63 -> 4.3264764 | AE63: =U63*Z63 -> 13.315413 | AF63: =V63*Z63 -> 0.0085507088 | AG63: =(AG64+X64)*Y64 -> -846.57002 | AH63: =IF(M63>0,AG63/M63,0) -> -982.99439 | AI63: =IF(AG63>0,AG63,0) -> 0 | AK63: =AND(M63>=0,M63<=M62) -> TRUE | AL63: =AND(D63>=0,D63<=1,E63>=0,E63<=1,F63>=0,F63<=1,G63>=0,G63<=1,J63+K63+L63<=M62+0.000000001*scale_count) -> TRUE | AM63: =(AG62+R63-S63)*(1+i_m)-T63-U63-V63 -> -846.57002 | AN63: =ABS(AM63-AG63)<=0.000000001*MAX(ABS(AM63),ABS(AG63),scale_money) -> TRUE | AO63: =(U63+V63+T63)*Z63-(R63-S63)*Z62 -> -17.254954 | AP63: =SUM(AO64:$AO$352) -> -816.67449 | AQ63: =ABS(AG63*Z63-AP63)<=0.000000001*MAX(ABS(AG63*Z63),ABS(AP63),scale_money) -> TRUE | AR63: =IF(A63<>rem_m,L63=0,L63=M62-J63-K63) -> TRUE | AS63: =IF(A63>prem_rem_m,AND(R63=0,S63=0,F63=0,G63=0,K63=0),R63=M62*premium) -> TRUE | AT63: =AND(C63>=18,C63<=120,OR(B63-B62=0,B63-B62=1)) -> TRUE | AU63: =-(N64-O64)+v_m*(E64*(sum_assured+Q64)+P64+(1-E64)*(1-G64)*AH64) -> -982.99439 | AV63: =ABS(AH63-AU63)<=0.000000001*MAX(ABS(AH63),ABS(AU63),scale_pp) -> TRUE | AW63: =AND(AI63>=0,AI63>=AG63) -> TRUE | AX63: =AND(U63=J63*sum_assured,R63=M62*N63,T63=M62*P63) -> TRUE
A64: 12 | B64: =MIN(INT((dur_m+A64-1)/12),dur_y_last) -> 0 | C64: =age_at_entry+B64 -> 35 | D64: =INDEX(mort_table,MATCH(C64,mort_age,0),MATCH(sex,mort_sex,0)) -> 0.00047422518 | E64: =IF(A64<=rem_m,1-(1-D64)^(1/12),0) -> 3.9527357e-05 | F64: =IF(A64<=prem_rem_m,INDEX(lapse_table,MATCH(MIN(B64,5),lapse_key,0)),0) -> 0.15 | G64: =1-(1-F64)^(1/12) -> 0.013451947 | H64: =INDEX(comm_table,MATCH(MIN(B64,1),comm_key,0)) -> 0.2 | I64: =(1+e_m)^A64 -> 1.03 | J64: =M63*E64 -> 3.4041573e-05 | K64: =(M63-J64)*G64 -> 0.011584568 | L64: =IF(A64=rem_m,M63-J64-K64,0) -> 0 | M64: =M63-J64-K64-L64 -> 0.84959691 | N64: =IF(A64<=prem_rem_m,premium,0) -> 51.64 | O64: =N64*H64 -> 10.328 | P64: =maint_base*I64 -> 5.15 | Q64: =claim_exp_base*I64 -> 257.5 | R64: =M63*N64 -> 44.473169 | S64: =R64*H64 -> 8.8946339 | T64: =M63*P64 -> 4.4352599 | U64: =J64*sum_assured -> 13.616629 | V64: =J64*Q64 -> 0.0087657051 | W64: =R64-S64-T64-U64-V64 -> 17.517881 | X64: =U64+V64+T64-(R64-S64)*(1+i_m) -> -17.634355 | Y64: =v_m -> 0.99673694 | Z64: =v_m^A64 -> 0.96153846 | AA64: =(R64-S64)*Z63-(T64+U64+V64)*Z64 -> 16.956111 | AB64: =R64*Z63 -> 42.902657 | AC64: =S64*Z63 -> 8.5805313 | AD64: =T64*Z64 -> 4.264673 | AE64: =U64*Z64 -> 13.092913 | AF64: =V64*Z64 -> 0.0084285626 | AG64: =(AG65+X65)*Y65 -> -831.70712 | AH64: =IF(M64>0,AG64/M64,0) -> -978.9432 | AI64: =IF(AG64>0,AG64,0) -> 0 | AK64: =AND(M64>=0,M64<=M63) -> TRUE | AL64: =AND(D64>=0,D64<=1,E64>=0,E64<=1,F64>=0,F64<=1,G64>=0,G64<=1,J64+K64+L64<=M63+0.000000001*scale_count) -> TRUE | AM64: =(AG63+R64-S64)*(1+i_m)-T64-U64-V64 -> -831.70712 | AN64: =ABS(AM64-AG64)<=0.000000001*MAX(ABS(AM64),ABS(AG64),scale_money) -> TRUE | AO64: =(U64+V64+T64)*Z64-(R64-S64)*Z63 -> -16.956111 | AP64: =SUM(AO65:$AO$352) -> -799.71838 | AQ64: =ABS(AG64*Z64-AP64)<=0.000000001*MAX(ABS(AG64*Z64),ABS(AP64),scale_money) -> TRUE | AR64: =IF(A64<>rem_m,L64=0,L64=M63-J64-K64) -> TRUE | AS64: =IF(A64>prem_rem_m,AND(R64=0,S64=0,F64=0,G64=0,K64=0),R64=M63*premium) -> TRUE | AT64: =AND(C64>=18,C64<=120,OR(B64-B63=0,B64-B63=1)) -> TRUE | AU64: =-(N65-O65)+v_m*(E65*(sum_assured+Q65)+P65+(1-E65)*(1-G65)*AH65) -> -978.9432 | AV64: =ABS(AH64-AU64)<=0.000000001*MAX(ABS(AH64),ABS(AU64),scale_pp) -> TRUE | AW64: =AND(AI64>=0,AI64>=AG64) -> TRUE | AX64: =AND(U64=J64*sum_assured,R64=M63*N64,T64=M63*P64) -> TRUE
A65: 13 | B65: =MIN(INT((dur_m+A65-1)/12),dur_y_last) -> 1 | C65: =age_at_entry+B65 -> 36 | D65: =INDEX(mort_table,MATCH(C65,mort_age,0),MATCH(sex,mort_sex,0)) -> 0.00050664304 | E65: =IF(A65<=rem_m,1-(1-D65)^(1/12),0) -> 4.223006e-05 | F65: =IF(A65<=prem_rem_m,INDEX(lapse_table,MATCH(MIN(B65,5),lapse_key,0)),0) -> 0.1 | G65: =1-(1-F65)^(1/12) -> 0.008741611 | H65: =INDEX(comm_table,MATCH(MIN(B65,1),comm_key,0)) -> 0.02 | I65: =(1+e_m)^A65 -> 1.0325403 | J65: =M64*E65 -> 3.5878529e-05 | K65: =(M64-J65)*G65 -> 0.007426532 | L65: =IF(A65=rem_m,M64-J65-K65,0) -> 0 | M65: =M64-J65-K65-L65 -> 0.8421345 | N65: =IF(A65<=prem_rem_m,premium,0) -> 51.64 | O65: =N65*H65 -> 1.0328 | P65: =maint_base*I65 -> 5.1627013 | Q65: =claim_exp_base*I65 -> 258.13506 | R65: =M64*N65 -> 43.873184 | S65: =R65*H65 -> 0.87746369 | T65: =M64*P65 -> 4.3862151 | U65: =J65*sum_assured -> 14.351411 | V65: =J65*Q65 -> 0.0092615063 | W65: =R65-S65-T65-U65-V65 -> 24.248833 | X65: =U65+V65+T65-(R65-S65)*(1+i_m) -> -24.389589 | Y65: =v_m -> 0.99673694 | Z65: =v_m^A65 -> 0.95840091 | AA65: =(R65-S65)*Z64-(T65+U65+V65)*Z65 -> 23.375005 | AB65: =R65*Z64 -> 42.185754 | AC65: =S65*Z64 -> 0.84371508 | AD65: =T65*Z65 -> 4.2037525 | AE65: =U65*Z65 -> 13.754406 | AF65: =V65*Z65 -> 0.008876236 | AG65: =(AG66+X66)*Y66 -> -810.04032 | AH65: =IF(M65>0,AG65/M65,0) -> -961.88949 | AI65: =IF(AG65>0,AG65,0) -> 0 | AK65: =AND(M65>=0,M65<=M64) -> TRUE | AL65: =AND(D65>=0,D65<=1,E65>=0,E65<=1,F65>=0,F65<=1,G65>=0,G65<=1,J65+K65+L65<=M64+0.000000001*scale_count) -> TRUE | AM65: =(AG64+R65-S65)*(1+i_m)-T65-U65-V65 -> -810.04032 | AN65: =ABS(AM65-AG65)<=0.000000001*MAX(ABS(AM65),ABS(AG65),scale_money) -> TRUE | AO65: =(U65+V65+T65)*Z65-(R65-S65)*Z64 -> -23.375005 | AP65: =SUM(AO66:$AO$352) -> -776.34338 | AQ65: =ABS(AG65*Z65-AP65)<=0.000000001*MAX(ABS(AG65*Z65),ABS(AP65),scale_money) -> TRUE | AR65: =IF(A65<>rem_m,L65=0,L65=M64-J65-K65) -> TRUE | AS65: =IF(A65>prem_rem_m,AND(R65=0,S65=0,F65=0,G65=0,K65=0),R65=M64*premium) -> TRUE | AT65: =AND(C65>=18,C65<=120,OR(B65-B64=0,B65-B64=1)) -> TRUE | AU65: =-(N66-O66)+v_m*(E66*(sum_assured+Q66)+P66+(1-E66)*(1-G66)*AH66) -> -961.88949 | AV65: =ABS(AH65-AU65)<=0.000000001*MAX(ABS(AH65),ABS(AU65),scale_pp) -> TRUE | AW65: =AND(AI65>=0,AI65>=AG65) -> TRUE | AX65: =AND(U65=J65*sum_assured,R65=M64*N65,T65=M64*P65) -> TRUE
... A351: 299 | B351: =MIN(INT((dur_m+A351-1)/12),dur_y_last) -> 24 | C351: =age_at_entry+B351 -> 59 | D351: =INDEX(mort_table,MATCH(C351,mort_age,0),MATCH(sex,mort_sex,0)) -> 0.0033390522 | E351: =IF(A351<=rem_m,1-(1-D351)^(1/12),0) -> 0.0002786811 | F351: =IF(A351<=prem_rem_m,INDEX(lapse_table,MATCH(MIN(B351,5),lapse_key,0)),0) -> 0.04 | G351: =1-(1-F351)^(1/12) -> 0.0033960532 | H351: =INDEX(comm_table,MATCH(MIN(B351,1),comm_key,0)) -> 0.02 | I351: =(1+e_m)^A351 -> 2.0886268 | J351: =M350*E351 -> 7.5257225e-05 | K351: =(M350-J351)*G351 -> 0.00091684122 | L351: =IF(A351=rem_m,M350-J351-K351,0) -> 0 | M351: =M350-J351-K351-L351 -> 0.26905573 | N351: =IF(A351<=prem_rem_m,premium,0) -> 51.64 | O351: =N351*H351 -> 1.0328 | P351: =maint_base*I351 -> 10.443134 | Q351: =claim_exp_base*I351 -> 522.1567 | R351: =M350*N351 -> 13.94527 | S351: =R351*H351 -> 0.2789054 | T351: =M350*P351 -> 2.8201457 | U351: =J351*sum_assured -> 30.10289 | V351: =J351*Q351 -> 0.039296065 | W351: =R351-S351-T351-U351-V351 -> -19.295967 | X351: =U351+V351+T351-(R351-S351)*(1+i_m) -> 19.251227 | Y351: =v_m -> 0.99673694 | Z351: =v_m^A351 -> 0.37634484 | AA351: =(R351-S351)*Z350-(T351+U351+V351)*Z351 -> -7.2451 | AB351: =R351*Z350 -> 5.2654117 | AC351: =S351*Z350 -> 0.10530823 | AD351: =T351*Z351 -> 1.0613473 | AE351: =U351*Z351 -> 11.329067 | AF351: =V351*Z351 -> 0.014788871 | AG351: =(AG352+X352)*Y352 -> 19.124919 | AH351: =IF(M351>0,AG351/M351,0) -> 71.081625 | AI351: =IF(AG351>0,AG351,0) -> 19.124919 | AK351: =AND(M351>=0,M351<=M350) -> TRUE | AL351: =AND(D351>=0,D351<=1,E351>=0,E351<=1,F351>=0,F351<=1,G351>=0,G351<=1,J351+K351+L351<=M350+0.000000001*scale_count) -> TRUE | AM351: =(AG350+R351-S351)*(1+i_m)-T351-U351-V351 -> 19.124919 | AN351: =ABS(AM351-AG351)<=0.000000001*MAX(ABS(AM351),ABS(AG351),scale_money) -> TRUE | AO351: =(U351+V351+T351)*Z351-(R351-S351)*Z350 -> 7.2451 | AP351: =SUM(AO352:$AO$352) -> 7.1975644 | AQ351: =ABS(AG351*Z351-AP351)<=0.000000001*MAX(ABS(AG351*Z351),ABS(AP351),scale_money) -> TRUE | AR351: =IF(A351<>rem_m,L351=0,L351=M350-J351-K351) -> TRUE | AS351: =IF(A351>prem_rem_m,AND(R351=0,S351=0,F351=0,G351=0,K351=0),R351=M350*premium) -> TRUE | AT351: =AND(C351>=18,C351<=120,OR(B351-B350=0,B351-B350=1)) -> TRUE | AU351: =-(N352-O352)+v_m*(E352*(sum_assured+Q352)+P352+(1-E352)*(1-G352)*AH352) -> 71.081625 | AV351: =ABS(AH351-AU351)<=0.000000001*MAX(ABS(AH351),ABS(AU351),scale_pp) -> TRUE | AW351: =AND(AI351>=0,AI351>=AG351) -> TRUE | AX351: =AND(U351=J351*sum_assured,R351=M350*N351,T351=M350*P351) -> TRUE
A352: 300 | B352: =MIN(INT((dur_m+A352-1)/12),dur_y_last) -> 24 | C352: =age_at_entry+B352 -> 59 | D352: =INDEX(mort_table,MATCH(C352,mort_age,0),MATCH(sex,mort_sex,0)) -> 0.0033390522 | E352: =IF(A352<=rem_m,1-(1-D352)^(1/12),0) -> 0.0002786811 | F352: =IF(A352<=prem_rem_m,INDEX(lapse_table,MATCH(MIN(B352,5),lapse_key,0)),0) -> 0.04 | G352: =1-(1-F352)^(1/12) -> 0.0033960532 | H352: =INDEX(comm_table,MATCH(MIN(B352,1),comm_key,0)) -> 0.02 | I352: =(1+e_m)^A352 -> 2.0937779 | J352: =M351*E352 -> 7.4980746e-05 | K352: =(M351-J352)*G352 -> 0.00091347294 | L352: =IF(A352=rem_m,M351-J352-K352,0) -> 0.26806728 | M352: =M351-J352-K352-L352 -> 0 | N352: =IF(A352<=prem_rem_m,premium,0) -> 51.64 | O352: =N352*H352 -> 1.0328 | P352: =maint_base*I352 -> 10.46889 | Q352: =claim_exp_base*I352 -> 523.44448 | R352: =M351*N352 -> 13.894038 | S352: =R352*H352 -> 0.27788076 | T352: =M351*P352 -> 2.8167148 | U352: =J352*sum_assured -> 29.992298 | V352: =J352*Q352 -> 0.039248258 | W352: =R352-S352-T352-U352-V352 -> -19.232104 | X352: =U352+V352+T352-(R352-S352)*(1+i_m) -> 19.187529 | Y352: =v_m -> 0.99673694 | Z352: =v_m^A352 -> 0.3751168 | AA352: =(R352-S352)*Z351-(T352+U352+V352)*Z352 -> -7.1975644 | AB352: =R352*Z351 -> 5.2289494 | AC352: =S352*Z351 -> 0.10457899 | AD352: =T352*Z352 -> 1.056597 | AE352: =U352*Z352 -> 11.250615 | AF352: =V352*Z352 -> 0.014722681 | AG352: 0 | AH352: =IF(M352>0,AG352/M352,0) -> 0 | AI352: =IF(AG352>0,AG352,0) -> 0 | AK352: =AND(M352>=0,M352<=M351) -> TRUE | AL352: =AND(D352>=0,D352<=1,E352>=0,E352<=1,F352>=0,F352<=1,G352>=0,G352<=1,J352+K352+L352<=M351+0.000000001*scale_count) -> TRUE | AM352: =(AG351+R352-S352)*(1+i_m)-T352-U352-V352 -> -3.3514858e-15 | AN352: =ABS(AM352-AG352)<=0.000000001*MAX(ABS(AM352),ABS(AG352),scale_money) -> TRUE | AO352: =(U352+V352+T352)*Z352-(R352-S352)*Z351 -> 7.1975644 | AR352: =IF(A352<>rem_m,L352=0,L352=M351-J352-K352) -> TRUE | AS352: =IF(A352>prem_rem_m,AND(R352=0,S352=0,F352=0,G352=0,K352=0),R352=M351*premium) -> TRUE | AT352: =AND(C352>=18,C352<=120,OR(B352-B351=0,B352-B351=1)) -> TRUE | AW352: =AND(AI352>=0,AI352>=AG352) -> TRUE | AX352: =AND(U352=J352*sum_assured,R352=M351*N352,T352=M351*P352) -> TRUE
A354: Scalars (section 11.2): the derived constants, the PV sums over t = 1 .. rem_m in ascending t, the time-0 state variables and maturities(rem_m)
A355: age_at_entry | B355: =age_at_entry -> 35 | C355: 5 | D355: Int (years)
A356: dur_m | B356: =dur_m -> 0 | C356: 4.3 | D356: Int (months)
A357: term_m | B357: =term_m -> 300 | C357: 4.3 | D357: Int (months)
A358: rem_m | B358: =rem_m -> 300 | C358: 4.3 | D358: Int (months)
A359: prem_term_m | B359: =prem_term_m -> 300 | C359: 4.3 | D359: Int (months)
A360: prem_rem_m | B360: =prem_rem_m -> 300 | C360: 4.3 | D360: Int (months)
A361: dur_y_last | B361: =dur_y_last -> 24 | C361: 4.3 | D361: Int (years)
A362: pv_premiums | B362: =SUM($AB$53:$AB$352) -> 5327.8947 | C362: 9.3 | D362: Money
A363: pv_commission | B363: =SUM($AC$53:$AC$352) -> 208.39909 | C363: 9.3 | D363: Money
A364: pv_maint_expense | B364: =SUM($AD$53:$AD$352) -> 670.58943 | C364: 9.3 | D364: Money
A365: pv_death_outgo | B365: =SUM($AE$53:$AE$352) -> 3421.6369 | C365: 9.3 | D365: Money
A366: pv_claim_expense | B366: =SUM($AF$53:$AF$352) -> 3.1562144 | C366: 9.3 | D366: Money
A367: pv_net_cf | B367: =B362-B363-B364-B365-B366 -> 1024.1131 | C367: 9.3 | D367: Money
A368: reserve_0 | B368: =$AG$52 -> -1024.1131 | C368: 10.2 | D368: Money: reserve(0)
A369: reserve_pp_0 | B369: =$AH$52 -> -1024.1131 | C369: 10.4 | D369: Money per policy: reserve_pp(0)
A370: reserve_floored_0 | B370: =$AI$52 -> 0 | C370: 10.5 | D370: Money: reserve_floored(0)
A371: maturities_n | B371: =$L$352 -> 0.26806728 | C371: 7.3 | D371: Count: maturities(rem_m), the survivors to the end of the term
A373: Check cells (section 12): the section 1 scales and two helper sums, then one <id>_ok per (sheet) invariant, TRUE when every row cell and scalar cell of that invariant is TRUE
A374: scale_money | B374: =sum_assured*pols_if_init -> 400000 | D374: Money (in-force) scale of section 1: sum_assured * pols_if_init
A375: scale_pp | B375: =sum_assured -> 400000 | D375: Money per policy scale of section 1: sum_assured
A376: scale_count | B376: =pols_if_init -> 1 | D376: Count scale of section 1: pols_if_init
A377: exits_sum | B377: =SUMPRODUCT($J$53:$J$352+$K$53:$K$352+$L$53:$L$352) -> 1 | D377: helper (P8): sum over t = 1 .. rem_m of deaths + lapses + maturities
A378: pv_net_cf_t_sum | B378: =SUM($AA$53:$AA$352) -> 1024.1131 | D378: helper (P9): sum over t = 1 .. rem_m of pv_net_cf_t
A380: H1_ok | B380: =AND($AK$52:$AK$352) -> TRUE | D380: every H1 row cell (t = 0 .. rem_m)
A381: H2_ok | B381: =AND($AL$53:$AL$352) -> TRUE | D381: every H2 row cell (t = 1 .. rem_m)
A382: H3_ok | B382: =AND($AG$352=0,$M$352=0) -> TRUE | D382: reserve(rem_m) = 0 and pols_if(rem_m) = 0, exactly
A383: H4_ok | B383: =AND($AN$53:$AN$352) -> TRUE | D383: every H4 row cell (t = 1 .. rem_m)
A384: H5a_ok | B384: =ABS(reserve_0-(-pv_net_cf))<=0.000000001*MAX(ABS(reserve_0),ABS(pv_net_cf),scale_money) -> TRUE | D384: reserve(0) equals -pv_net_cf within tolerance (scale_money)
A385: H5b_ok | B385: =AND($AQ$52:$AQ$351) -> TRUE | D385: every H5b row cell (t = 0 .. rem_m - 1)
A386: P1_ok | B386: =AND($AR$53:$AR$352) -> TRUE | D386: every P1 row cell (t = 1 .. rem_m)
A387: P2_ok | B387: =AND($AS$53:$AS$352) -> TRUE | D387: every P2 row cell (t = 1 .. rem_m)
A388: P3_ok | B388: =SUMPRODUCT(--($N$53:$N$352<>0))=prem_rem_m -> TRUE | D388: the number of months with premium_pp <> 0 equals prem_rem_m
A389: P4_ok | B389: =AND($AT$53:$AT$352) -> TRUE | D389: every P4 row cell (t = 1 .. rem_m)
A390: P5_ok | B390: =AND($AV$52:$AV$351) -> TRUE | D390: every P5 row cell (t = 0 .. rem_m - 1)
A391: P6_ok | B391: =AND($AW$52:$AW$352) -> TRUE | D391: every P6 row cell (t = 0 .. rem_m)
A392: P8_ok | B392: =ABS(exits_sum-scale_count)<=0.000000001*MAX(ABS(exits_sum),ABS(scale_count),scale_count) -> TRUE | D392: exits_sum equals pols_if_init within tolerance (scale_count)
A393: P9_ok | B393: =ABS(pv_net_cf-pv_net_cf_t_sum)<=0.000000001*MAX(ABS(pv_net_cf),ABS(pv_net_cf_t_sum),scale_money) -> TRUE | D393: pv_net_cf equals pv_net_cf_t_sum within tolerance (scale_money)
...

Sheet P03
A1: Inputs (section 3.1, from section 13) and the run-level valuation_date (3.3), typed
A2: valuation_date | B2: 46388 | C2: 3.3 | D2: Date, first of a month (run-level input)
A3: policy_id | B3: P03 | C3: 3.1 | D3: string
A4: sex | B4: M | C4: 3.1 | D4: string, M or F
A5: birth_date | B5: 24247 | C5: 3.1 | D5: Date
A6: entry_date | B6: 39097 | C6: 3.1 | D6: Date
A7: maturity_date | B7: 46402 | C7: 3.1 | D7: Date
A8: prem_term_y | B8: 20 | C8: 3.1 | D8: Int (years)
A9: sum_assured | B9: 150000 | C9: 3.1 | D9: Money per policy
A10: premium | B10: 39.99 | C10: 3.1 | D10: Money per policy, monthly, in advance
A11: pols_if_init | B11: 1 | C11: 3.1 | D11: Count
A13: Derived constants (sections 3.2, 4.3 and 5), by formula
A14: age_at_entry | B14: =YEAR(entry_date)-YEAR(birth_date)-IF(OR(MONTH(entry_date)<MONTH(birth_date),AND(MONTH(entry_date)=MONTH(birth_date),DAY(entry_date)<DAY(birth_date))),1,0) -> 40 | C14: 5 | D14: Int (years)
A15: dur_m | B15: =12*(YEAR(valuation_date)-YEAR(entry_date))+(MONTH(valuation_date)-MONTH(entry_date))-IF(DAY(valuation_date)<DAY(entry_date),1,0) -> 239 | C15: 4.3 | D15: Int (months)
A16: term_m | B16: =12*(YEAR(maturity_date)-YEAR(entry_date))+(MONTH(maturity_date)-MONTH(entry_date))-IF(DAY(maturity_date)<DAY(entry_date),1,0) -> 240 | C16: 4.3 | D16: Int (months)
A17: rem_m | B17: =term_m-dur_m -> 1 | C17: 4.3 | D17: Int (months)
A18: prem_term_m | B18: =12*prem_term_y -> 240 | C18: 4.3 | D18: Int (months)
A19: prem_rem_m | B19: =MAX(prem_term_m-dur_m,0) -> 1 | C19: 4.3 | D19: Int (months)
A20: dur_y_last | B20: =INT((term_m-1)/12) -> 19 | C20: 4.3 | D20: Int (years)
A22: Basis constants (section 6), each in one cell
A23: i | B23: 0.04 | C23: 6 | D23: Rate[Annual]
A24: e | B24: 0.03 | C24: 6 | D24: Rate[Annual]
A25: i_m | B25: =(1+i)^(1/12)-1 -> 0.0032737398 | C25: 6 | D25: Rate[Monthly]
A26: v_m | B26: =(1+i)^(-1/12) -> 0.99673694 | C26: 6 | D26: factor
A27: e_m | B27: =(1+e)^(1/12)-1 -> 0.0024662698 | C27: 6 | D27: Rate[Monthly]
A28: A_M | B28: 0.0002 | C28: 6.1 | D28: Gompertz-Makeham A, sex M
A29: A_F | B29: 0.00015 | C29: 6.1 | D29: Gompertz-Makeham A, sex F
A30: B_M | B30: 1.7e-05 | C30: 6.1 | D30: Gompertz-Makeham B, sex M
A31: B_F | B31: 1.1e-05 | C31: 6.1 | D31: Gompertz-Makeham B, sex F
A32: c | B32: 1.1 | C32: 6.1 | D32: Gompertz-Makeham c (both sexes); defined name gm_c
A33: maint_base | B33: 5 | C33: 6.5 | D33: Money per policy, per month, time-0 prices
A34: claim_exp_base | B34: 250 | C34: 6.5 | D34: Money per policy (per death), time-0 prices
A36: Lapse table (section 6.2): key k = min(dur_y, 5)
A37: k | B37: lapse_table | D37: Prob, annual
A38: 0 | B38: 0.15
A39: 1 | B39: 0.1
A40: 2 | B40: 0.08
A41: 3 | B41: 0.06
A42: 4 | B42: 0.05
A43: 5 | B43: 0.04
A45: Commission table (section 6.6): key k = min(dur_y, 1)
A46: k | B46: comm_table | D46: Fraction
A47: 0 | B47: 0.2
A48: 1 | B48: 0.02
A50: Monthly block (sections 7.1 and 11.1): rows t = 0 .. rem_m, one column per quantity in the 7.1 order; the row-level check cells of section 12 follow the blank column
A51: t | B51: dur_y | C51: age | D51: q_ann | E51: q_m | F51: w_ann | G51: w_m | H51: comm_rate | I51: infl | J51: deaths | K51: lapses | L51: maturities | M51: pols_if | N51: premium_pp | O51: commission_pp | P51: maint_pp | Q51: claim_exp_pp | R51: premium_income | S51: commission | T51: maint_expense | U51: death_outgo | V51: claim_expense | W51: net_cf | X51: net_outgo | Y51: v | Z51: disc | AA51: pv_net_cf_t | AB51: pv_premiums_t | AC51: pv_commission_t | AD51: pv_maint_expense_t | AE51: pv_death_outgo_t | AF51: pv_claim_expense_t | AG51: reserve | AH51: reserve_pp | AI51: reserve_floored | AK51: H1 | AL51: H2 | AM51: H4_lhs | AN51: H4 | AO51: H5b_term | AP51: H5b_sum | AQ51: H5b | AR51: P1 | AS51: P2 | AT51: P4 | AU51: P5_rhs | AV51: P5 | AW51: P6 | AX51: P10
A52: 0 | I52: 1 | M52: =pols_if_init -> 1 | Z52: 1 | AG52: =(AG53+X53)*Y53 -> 29.904078 | AH52: =IF(M52>0,AG52/M52,0) -> 29.904078 | AI52: =IF(AG52>0,AG52,0) -> 29.904078 | AK52: =M52>=0 -> TRUE | AP52: =SUM(AO53:$AO$53) -> 29.904078 | AQ52: =ABS(AG52*Z52-AP52)<=0.000000001*MAX(ABS(AG52*Z52),ABS(AP52),scale_money) -> TRUE | AU52: =-(N53-O53)+v_m*(E53*(sum_assured+Q53)+P53+(1-E53)*(1-G53)*AH53) -> 29.904078 | AV52: =ABS(AH52-AU52)<=0.000000001*MAX(ABS(AH52),ABS(AU52),scale_pp) -> TRUE | AW52: =AND(AI52>=0,AI52>=AG52) -> TRUE
A53: 1 | B53: =MIN(INT((dur_m+A53-1)/12),dur_y_last) -> 19 | C53: =age_at_entry+B53 -> 59 | D53: =INDEX(mort_table,MATCH(C53,mort_age,0),MATCH(sex,mort_sex,0)) -> 0.005123997 | E53: =IF(A53<=rem_m,1-(1-D53)^(1/12),0) -> 0.00042800586 | F53: =IF(A53<=prem_rem_m,INDEX(lapse_table,MATCH(MIN(B53,5),lapse_key,0)),0) -> 0.04 | G53: =1-(1-F53)^(1/12) -> 0.0033960532 | H53: =INDEX(comm_table,MATCH(MIN(B53,1),comm_key,0)) -> 0.02 | I53: =(1+e_m)^A53 -> 1.0024663 | J53: =M52*E53 -> 0.00042800586 | K53: =(M52-J53)*G53 -> 0.0033945997 | L53: =IF(A53=rem_m,M52-J53-K53,0) -> 0.99617739 | M53: =M52-J53-K53-L53 -> 0 | N53: =IF(A53<=prem_rem_m,premium,0) -> 39.99 | O53: =N53*H53 -> 0.7998 | P53: =maint_base*I53 -> 5.0123313 | Q53: =claim_exp_base*I53 -> 250.61657 | R53: =M52*N53 -> 39.99 | S53: =R53*H53 -> 0.7998 | T53: =M52*P53 -> 5.0123313 | U53: =J53*sum_assured -> 64.200878 | V53: =J53*Q53 -> 0.10726536 | W53: =R53-S53-T53-U53-V53 -> -30.130275 | X53: =U53+V53+T53-(R53-S53)*(1+i_m) -> 30.001977 | Y53: =v_m -> 0.99673694 | Z53: =v_m^A53 -> 0.99673694 | AA53: =(R53-S53)*Z52-(T53+U53+V53)*Z53 -> -29.904078 | AB53: =R53*Z52 -> 39.99 | AC53: =S53*Z52 -> 0.7998 | AD53: =T53*Z53 -> 4.9959758 | AE53: =U53*Z53 -> 63.991387 | AF53: =V53*Z53 -> 0.10691535 | AG53: 0 | AH53: =IF(M53>0,AG53/M53,0) -> 0 | AI53: =IF(AG53>0,AG53,0) -> 0 | AK53: =AND(M53>=0,M53<=M52) -> TRUE | AL53: =AND(D53>=0,D53<=1,E53>=0,E53<=1,F53>=0,F53<=1,G53>=0,G53<=1,J53+K53+L53<=M52+0.000000001*scale_count) -> TRUE | AM53: =(AG52+R53-S53)*(1+i_m)-T53-U53-V53 -> -1.2490009e-16 | AN53: =ABS(AM53-AG53)<=0.000000001*MAX(ABS(AM53),ABS(AG53),scale_money) -> TRUE | AO53: =(U53+V53+T53)*Z53-(R53-S53)*Z52 -> 29.904078 | AR53: =IF(A53<>rem_m,L53=0,L53=M52-J53-K53) -> TRUE | AS53: =IF(A53>prem_rem_m,AND(R53=0,S53=0,F53=0,G53=0,K53=0),R53=M52*premium) -> TRUE | AT53: =AND(C53>=18,C53<=120) -> TRUE | AW53: =AND(AI53>=0,AI53>=AG53) -> TRUE | AX53: =AND(U53=J53*sum_assured,R53=M52*N53,T53=M52*P53) -> TRUE
A55: Scalars (section 11.2): the derived constants, the PV sums over t = 1 .. rem_m in ascending t, the time-0 state variables and maturities(rem_m)
A56: age_at_entry | B56: =age_at_entry -> 40 | C56: 5 | D56: Int (years)
A57: dur_m | B57: =dur_m -> 239 | C57: 4.3 | D57: Int (months)
A58: term_m | B58: =term_m -> 240 | C58: 4.3 | D58: Int (months)
A59: rem_m | B59: =rem_m -> 1 | C59: 4.3 | D59: Int (months)
A60: prem_term_m | B60: =prem_term_m -> 240 | C60: 4.3 | D60: Int (months)
A61: prem_rem_m | B61: =prem_rem_m -> 1 | C61: 4.3 | D61: Int (months)
A62: dur_y_last | B62: =dur_y_last -> 19 | C62: 4.3 | D62: Int (years)
A63: pv_premiums | B63: =SUM($AB$53:$AB$53) -> 39.99 | C63: 9.3 | D63: Money
A64: pv_commission | B64: =SUM($AC$53:$AC$53) -> 0.7998 | C64: 9.3 | D64: Money
A65: pv_maint_expense | B65: =SUM($AD$53:$AD$53) -> 4.9959758 | C65: 9.3 | D65: Money
A66: pv_death_outgo | B66: =SUM($AE$53:$AE$53) -> 63.991387 | C66: 9.3 | D66: Money
A67: pv_claim_expense | B67: =SUM($AF$53:$AF$53) -> 0.10691535 | C67: 9.3 | D67: Money
A68: pv_net_cf | B68: =B63-B64-B65-B66-B67 -> -29.904078 | C68: 9.3 | D68: Money
A69: reserve_0 | B69: =$AG$52 -> 29.904078 | C69: 10.2 | D69: Money: reserve(0)
A70: reserve_pp_0 | B70: =$AH$52 -> 29.904078 | C70: 10.4 | D70: Money per policy: reserve_pp(0)
A71: reserve_floored_0 | B71: =$AI$52 -> 29.904078 | C71: 10.5 | D71: Money: reserve_floored(0)
A72: maturities_n | B72: =$L$53 -> 0.99617739 | C72: 7.3 | D72: Count: maturities(rem_m), the survivors to the end of the term
A74: Check cells (section 12): the section 1 scales and two helper sums, then one <id>_ok per (sheet) invariant, TRUE when every row cell and scalar cell of that invariant is TRUE
A75: scale_money | B75: =sum_assured*pols_if_init -> 150000 | D75: Money (in-force) scale of section 1: sum_assured * pols_if_init
A76: scale_pp | B76: =sum_assured -> 150000 | D76: Money per policy scale of section 1: sum_assured
A77: scale_count | B77: =pols_if_init -> 1 | D77: Count scale of section 1: pols_if_init
A78: exits_sum | B78: =SUMPRODUCT($J$53:$J$53+$K$53:$K$53+$L$53:$L$53) -> 1 | D78: helper (P8): sum over t = 1 .. rem_m of deaths + lapses + maturities
A79: pv_net_cf_t_sum | B79: =SUM($AA$53:$AA$53) -> -29.904078 | D79: helper (P9): sum over t = 1 .. rem_m of pv_net_cf_t
A81: H1_ok | B81: =AND($AK$52:$AK$53) -> TRUE | D81: every H1 row cell (t = 0 .. rem_m)
A82: H2_ok | B82: =AND($AL$53:$AL$53) -> TRUE | D82: every H2 row cell (t = 1 .. rem_m)
A83: H3_ok | B83: =AND($AG$53=0,$M$53=0) -> TRUE | D83: reserve(rem_m) = 0 and pols_if(rem_m) = 0, exactly
A84: H4_ok | B84: =AND($AN$53:$AN$53) -> TRUE | D84: every H4 row cell (t = 1 .. rem_m)
A85: H5a_ok | B85: =ABS(reserve_0-(-pv_net_cf))<=0.000000001*MAX(ABS(reserve_0),ABS(pv_net_cf),scale_money) -> TRUE | D85: reserve(0) equals -pv_net_cf within tolerance (scale_money)
A86: H5b_ok | B86: =AND($AQ$52:$AQ$52) -> TRUE | D86: every H5b row cell (t = 0 .. rem_m - 1)
A87: P1_ok | B87: =AND($AR$53:$AR$53) -> TRUE | D87: every P1 row cell (t = 1 .. rem_m)
A88: P2_ok | B88: =AND($AS$53:$AS$53) -> TRUE | D88: every P2 row cell (t = 1 .. rem_m)
A89: P3_ok | B89: =SUMPRODUCT(--($N$53:$N$53<>0))=prem_rem_m -> TRUE | D89: the number of months with premium_pp <> 0 equals prem_rem_m
A90: P4_ok | B90: =AND($AT$53:$AT$53) -> TRUE | D90: every P4 row cell (t = 1 .. rem_m)
A91: P5_ok | B91: =AND($AV$52:$AV$52) -> TRUE | D91: every P5 row cell (t = 0 .. rem_m - 1)
A92: P6_ok | B92: =AND($AW$52:$AW$53) -> TRUE | D92: every P6 row cell (t = 0 .. rem_m)
A93: P8_ok | B93: =ABS(exits_sum-scale_count)<=0.000000001*MAX(ABS(exits_sum),ABS(scale_count),scale_count) -> TRUE | D93: exits_sum equals pols_if_init within tolerance (scale_count)
A94: P9_ok | B94: =ABS(pv_net_cf-pv_net_cf_t_sum)<=0.000000001*MAX(ABS(pv_net_cf),ABS(pv_net_cf_t_sum),scale_money) -> TRUE | D94: pv_net_cf equals pv_net_cf_t_sum within tolerance (scale_money)
A95: P10_ok | B95: =AND($AX$53:$AX$53) -> TRUE | D95: every P10 row cell (t = 1 .. rem_m)
A96: rows_ok | B96: =MAX($A$52:$A$53)=rem_m -> TRUE | D96: layout: the last t of the monthly block equals the formula-derived rem_m
A97: ok | B97: =AND($B$81:$B$96) -> TRUE | D97: every cell above

Sheet P04
A1: Inputs (section 3.1, from section 13) and the run-level valuation_date (3.3), typed
A2: valuation_date | B2: 46388 | C2: 3.3 | D2: Date, first of a month (run-level input)
A3: policy_id | B3: P04 | C3: 3.1 | D3: string
A4: sex | B4: F | C4: 3.1 | D4: string, M or F
A5: birth_date | B5: 27981 | C5: 3.1 | D5: Date
A6: entry_date | B6: 42083 | C6: 3.1 | D6: Date
A7: maturity_date | B7: 53041 | C7: 3.1 | D7: Date
A8: prem_term_y | B8: 20 | C8: 3.1 | D8: Int (years)
A9: sum_assured | B9: 300000 | C9: 3.1 | D9: Money per policy
A10: premium | B10: 68.98 | C10: 3.1 | D10: Money per policy, monthly, in advance
A11: pols_if_init | B11: 1 | C11: 3.1 | D11: Count
A13: Derived constants (sections 3.2, 4.3 and 5), by formula
A14: age_at_entry | B14: =YEAR(entry_date)-YEAR(birth_date)-IF(OR(MONTH(entry_date)<MONTH(birth_date),AND(MONTH(entry_date)=MONTH(birth_date),DAY(entry_date)<DAY(birth_date))),1,0) -> 38 | C14: 5 | D14: Int (years)
A15: dur_m | B15: =12*(YEAR(valuation_date)-YEAR(entry_date))+(MONTH(valuation_date)-MONTH(entry_date))-IF(DAY(valuation_date)<DAY(entry_date),1,0) -> 141 | C15: 4.3 | D15: Int (months)
A16: term_m | B16: =12*(YEAR(maturity_date)-YEAR(entry_date))+(MONTH(maturity_date)-MONTH(entry_date))-IF(DAY(maturity_date)<DAY(entry_date),1,0) -> 360 | C16: 4.3 | D16: Int (months)
A17: rem_m | B17: =term_m-dur_m -> 219 | C17: 4.3 | D17: Int (months)
A18: prem_term_m | B18: =12*prem_term_y -> 240 | C18: 4.3 | D18: Int (months)
A19: prem_rem_m | B19: =MAX(prem_term_m-dur_m,0) -> 99 | C19: 4.3 | D19: Int (months)
A20: dur_y_last | B20: =INT((term_m-1)/12) -> 29 | C20: 4.3 | D20: Int (years)
A22: Basis constants (section 6), each in one cell
A23: i | B23: 0.04 | C23: 6 | D23: Rate[Annual]
A24: e | B24: 0.03 | C24: 6 | D24: Rate[Annual]
A25: i_m | B25: =(1+i)^(1/12)-1 -> 0.0032737398 | C25: 6 | D25: Rate[Monthly]
A26: v_m | B26: =(1+i)^(-1/12) -> 0.99673694 | C26: 6 | D26: factor
A27: e_m | B27: =(1+e)^(1/12)-1 -> 0.0024662698 | C27: 6 | D27: Rate[Monthly]
A28: A_M | B28: 0.0002 | C28: 6.1 | D28: Gompertz-Makeham A, sex M
A29: A_F | B29: 0.00015 | C29: 6.1 | D29: Gompertz-Makeham A, sex F
A30: B_M | B30: 1.7e-05 | C30: 6.1 | D30: Gompertz-Makeham B, sex M
A31: B_F | B31: 1.1e-05 | C31: 6.1 | D31: Gompertz-Makeham B, sex F
A32: c | B32: 1.1 | C32: 6.1 | D32: Gompertz-Makeham c (both sexes); defined name gm_c
A33: maint_base | B33: 5 | C33: 6.5 | D33: Money per policy, per month, time-0 prices
A34: claim_exp_base | B34: 250 | C34: 6.5 | D34: Money per policy (per death), time-0 prices
A36: Lapse table (section 6.2): key k = min(dur_y, 5)
A37: k | B37: lapse_table | D37: Prob, annual
A38: 0 | B38: 0.15
A39: 1 | B39: 0.1
A40: 2 | B40: 0.08
A41: 3 | B41: 0.06
A42: 4 | B42: 0.05
A43: 5 | B43: 0.04
A45: Commission table (section 6.6): key k = min(dur_y, 1)
A46: k | B46: comm_table | D46: Fraction
A47: 0 | B47: 0.2
A48: 1 | B48: 0.02
A50: Monthly block (sections 7.1 and 11.1): rows t = 0 .. rem_m, one column per quantity in the 7.1 order; the row-level check cells of section 12 follow the blank column
A51: t | B51: dur_y | C51: age | D51: q_ann | E51: q_m | F51: w_ann | G51: w_m | H51: comm_rate | I51: infl | J51: deaths | K51: lapses | L51: maturities | M51: pols_if | N51: premium_pp | O51: commission_pp | P51: maint_pp | Q51: claim_exp_pp | R51: premium_income | S51: commission | T51: maint_expense | U51: death_outgo | V51: claim_expense | W51: net_cf | X51: net_outgo | Y51: v | Z51: disc | AA51: pv_net_cf_t | AB51: pv_premiums_t | AC51: pv_commission_t | AD51: pv_maint_expense_t | AE51: pv_death_outgo_t | AF51: pv_claim_expense_t | AG51: reserve | AH51: reserve_pp | AI51: reserve_floored | AK51: H1 | AL51: H2 | AM51: H4_lhs | AN51: H4 | AO51: H5b_term | AP51: H5b_sum | AQ51: H5b | AR51: P1 | AS51: P2 | AT51: P4 | AU51: P5_rhs | AV51: P5 | AW51: P6 | AX51: P10
A52: 0 | I52: 1 | M52: =pols_if_init -> 1 | Z52: 1 | AG52: =(AG53+X53)*Y53 -> 5172.5656 | AH52: =IF(M52>0,AG52/M52,0) -> 5172.5656 | AI52: =IF(AG52>0,AG52,0) -> 5172.5656 | AK52: =M52>=0 -> TRUE | AP52: =SUM(AO53:$AO$271) -> 5172.5656 | AQ52: =ABS(AG52*Z52-AP52)<=0.000000001*MAX(ABS(AG52*Z52),ABS(AP52),scale_money) -> TRUE | AU52: =-(N53-O53)+v_m*(E53*(sum_assured+Q53)+P53+(1-E53)*(1-G53)*AH53) -> 5172.5656 | AV52: =ABS(AH52-AU52)<=0.000000001*MAX(ABS(AH52),ABS(AU52),scale_pp) -> TRUE | AW52: =AND(AI52>=0,AI52>=AG52) -> TRUE
A53: 1 | B53: =MIN(INT((dur_m+A53-1)/12),dur_y_last) -> 11 | C53: =age_at_entry+B53 -> 49 | D53: =INDEX(mort_table,MATCH(C53,mort_age,0),MATCH(sex,mort_sex,0)) -> 0.0013807176 | E53: =IF(A53<=rem_m,1-(1-D53)^(1/12),0) -> 0.00011513268 | F53: =IF(A53<=prem_rem_m,INDEX(lapse_table,MATCH(MIN(B53,5),lapse_key,0)),0) -> 0.04 | G53: =1-(1-F53)^(1/12) -> 0.0033960532 | H53: =INDEX(comm_table,MATCH(MIN(B53,1),comm_key,0)) -> 0.02 | I53: =(1+e_m)^A53 -> 1.0024663 | J53: =M52*E53 -> 0.00011513268 | K53: =(M52-J53)*G53 -> 0.0033956622 | L53: =IF(A53=rem_m,M52-J53-K53,0) -> 0 | M53: =M52-J53-K53-L53 -> 0.99648921 | N53: =IF(A53<=prem_rem_m,premium,0) -> 68.98 | O53: =N53*H53 -> 1.3796 | P53: =maint_base*I53 -> 5.0123313 | Q53: =claim_exp_base*I53 -> 250.61657 | R53: =M52*N53 -> 68.98 | S53: =R53*H53 -> 1.3796 | T53: =M52*P53 -> 5.0123313 | U53: =J53*sum_assured -> 34.539804 | V53: =J53*Q53 -> 0.028854157 | W53: =R53-S53-T53-U53-V53 -> 28.01941 | X53: =U53+V53+T53-(R53-S53)*(1+i_m) -> -28.240716 | Y53: =v_m -> 0.99673694 | Z53: =v_m^A53 -> 0.99673694 | AA53: =(R53-S53)*Z52-(T53+U53+V53)*Z53 -> 28.148565 | AB53: =R53*Z52 -> 68.98 | AC53: =S53*Z52 -> 1.3796 | AD53: =T53*Z53 -> 4.9959758 | AE53: =U53*Z53 -> 34.427099 | AF53: =V53*Z53 -> 0.028760005 | AG53: =(AG54+X54)*Y54 -> 5217.74 | AH53: =IF(M53>0,AG53/M53,0) -> 5236.1229 | AI53: =IF(AG53>0,AG53,0) -> 5217.74 | AK53: =AND(M53>=0,M53<=M52) -> TRUE | AL53: =AND(D53>=0,D53<=1,E53>=0,E53<=1,F53>=0,F53<=1,G53>=0,G53<=1,J53+K53+L53<=M52+0.000000001*scale_count) -> TRUE | AM53: =(AG52+R53-S53)*(1+i_m)-T53-U53-V53 -> 5217.74 | AN53: =ABS(AM53-AG53)<=0.000000001*MAX(ABS(AM53),ABS(AG53),scale_money) -> TRUE | AO53: =(U53+V53+T53)*Z53-(R53-S53)*Z52 -> -28.148565 | AP53: =SUM(AO54:$AO$271) -> 5200.7142 | AQ53: =ABS(AG53*Z53-AP53)<=0.000000001*MAX(ABS(AG53*Z53),ABS(AP53),scale_money) -> TRUE | AR53: =IF(A53<>rem_m,L53=0,L53=M52-J53-K53) -> TRUE | AS53: =IF(A53>prem_rem_m,AND(R53=0,S53=0,F53=0,G53=0,K53=0),R53=M52*premium) -> TRUE | AT53: =AND(C53>=18,C53<=120) -> TRUE | AU53: =-(N54-O54)+v_m*(E54*(sum_assured+Q54)+P54+(1-E54)*(1-G54)*AH54) -> 5236.1229 | AV53: =ABS(AH53-AU53)<=0.000000001*MAX(ABS(AH53),ABS(AU53),scale_pp) -> TRUE | AW53: =AND(AI53>=0,AI53>=AG53) -> TRUE | AX53: =AND(U53=J53*sum_assured,R53=M52*N53,T53=M52*P53) -> TRUE
A54: 2 | B54: =MIN(INT((dur_m+A54-1)/12),dur_y_last) -> 11 | C54: =age_at_entry+B54 -> 49 | D54: =INDEX(mort_table,MATCH(C54,mort_age,0),MATCH(sex,mort_sex,0)) -> 0.0013807176 | E54: =IF(A54<=rem_m,1-(1-D54)^(1/12),0) -> 0.00011513268 | F54: =IF(A54<=prem_rem_m,INDEX(lapse_table,MATCH(MIN(B54,5),lapse_key,0)),0) -> 0.04 | G54: =1-(1-F54)^(1/12) -> 0.0033960532 | H54: =INDEX(comm_table,MATCH(MIN(B54,1),comm_key,0)) -> 0.02 | I54: =(1+e_m)^A54 -> 1.0049386 | J54: =M53*E54 -> 0.00011472847 | K54: =(M53-J54)*G54 -> 0.0033837407 | L54: =IF(A54=rem_m,M53-J54-K54,0) -> 0 | M54: =M53-J54-K54-L54 -> 0.99299074 | N54: =IF(A54<=prem_rem_m,premium,0) -> 68.98 | O54: =N54*H54 -> 1.3796 | P54: =maint_base*I54 -> 5.0246931 | Q54: =claim_exp_base*I54 -> 251.23466 | R54: =M53*N54 -> 68.737825 | S54: =R54*H54 -> 1.3747565 | T54: =M53*P54 -> 5.0070524 | U54: =J54*sum_assured -> 34.418542 | V54: =J54*Q54 -> 0.028823769 | W54: =R54-S54-T54-U54-V54 -> 27.90865 | X54: =U54+V54+T54-(R54-S54)*(1+i_m) -> -28.12918 | Y54: =v_m -> 0.99673694 | Z54: =v_m^A54 -> 0.99348453 | AA54: =(R54-S54)*Z53-(T54+U54+V54)*Z54 -> 27.945905 | AB54: =R54*Z53 -> 68.51353 | AC54: =S54*Z53 -> 1.3702706 | AD54: =T54*Z54 -> 4.9744292 | AE54: =U54*Z54 -> 34.194289 | AF54: =V54*Z54 -> 0.028635968 | AG54: =(AG55+X55)*Y55 -> 5262.9507 | AH54: =IF(M54>0,AG54/M54,0) -> 5300.1005 | AI54: =IF(AG54>0,AG54,0) -> 5262.9507 | AK54: =AND(M54>=0,M54<=M53) -> TRUE | AL54: =AND(D54>=0,D54<=1,E54>=0,E54<=1,F54>=0,F54<=1,G54>=0,G54<=1,J54+K54+L54<=M53+0.000000001*scale_count) -> TRUE | AM54: =(AG53+R54-S54)*(1+i_m)-T54-U54-V54 -> 5262.9507 | AN54: =ABS(AM54-AG54)<=0.000000001*MAX(ABS(AM54),ABS(AG54),scale_money) -> TRUE | AO54: =(U54+V54+T54)*Z54-(R54-S54)*Z53 -> -27.945905 | AP54: =SUM(AO55:$AO$271) -> 5228.6601 | AQ54: =ABS(AG54*Z54-AP54)<=0.000000001*MAX(ABS(AG54*Z54),ABS(AP54),scale_money) -> TRUE | AR54: =IF(A54<>rem_m,L54=0,L54=M53-J54-K54) -> TRUE | AS54: =IF(A54>prem_rem_m,AND(R54=0,S54=0,F54=0,G54=0,K54=0),R54=M53*premium) -> TRUE | AT54: =AND(C54>=18,C54<=120,OR(B54-B53=0,B54-B53=1)) -> TRUE | AU54: =-(N55-O55)+v_m*(E55*(sum_assured+Q55)+P55+(1-E55)*(1-G55)*AH55) -> 5300.1005 | AV54: =ABS(AH54-AU54)<=0.000000001*MAX(ABS(AH54),ABS(AU54),scale_pp) -> TRUE | AW54: =AND(AI54>=0,AI54>=AG54) -> TRUE | AX54: =AND(U54=J54*sum_assured,R54=M53*N54,T54=M53*P54) -> TRUE
A55: 3 | B55: =MIN(INT((dur_m+A55-1)/12),dur_y_last) -> 11 | C55: =age_at_entry+B55 -> 49 | D55: =INDEX(mort_table,MATCH(C55,mort_age,0),MATCH(sex,mort_sex,0)) -> 0.0013807176 | E55: =IF(A55<=rem_m,1-(1-D55)^(1/12),0) -> 0.00011513268 | F55: =IF(A55<=prem_rem_m,INDEX(lapse_table,MATCH(MIN(B55,5),lapse_key,0)),0) -> 0.04 | G55: =1-(1-F55)^(1/12) -> 0.0033960532 | H55: =INDEX(comm_table,MATCH(MIN(B55,1),comm_key,0)) -> 0.02 | I55: =(1+e_m)^A55 -> 1.0074171 | J55: =M54*E55 -> 0.00011432569 | K55: =(M54-J55)*G55 -> 0.0033718611 | L55: =IF(A55=rem_m,M54-J55-K55,0) -> 0 | M55: =M54-J55-K55-L55 -> 0.98950455 | N55: =IF(A55<=prem_rem_m,premium,0) -> 68.98 | O55: =N55*H55 -> 1.3796 | P55: =maint_base*I55 -> 5.0370854 | Q55: =claim_exp_base*I55 -> 251.85427 | R55: =M54*N55 -> 68.496501 | S55: =R55*H55 -> 1.36993 | T55: =M54*P55 -> 5.0017791 | U55: =J55*sum_assured -> 34.297706 | V55: =J55*Q55 -> 0.028793412 | W55: =R55-S55-T55-U55-V55 -> 27.798293 | X55: =U55+V55+T55-(R55-S55)*(1+i_m) -> -28.018048 | Y55: =v_m -> 0.99673694 | Z55: =v_m^A55 -> 0.99024274 | AA55: =(R55-S55)*Z54-(T55+U55+V55)*Z55 -> 27.744668 | AB55: =R55*Z54 -> 68.050214 | AC55: =S55*Z54 -> 1.3610043 | AD55: =T55*Z55 -> 4.9529754 | AE55: =U55*Z55 -> 33.963054 | AF55: =V55*Z55 -> 0.028512467 | AG55: =(AG56+X56)*Y56 -> 5308.1983 | AH55: =IF(M55>0,AG55/M55,0) -> 5364.5011 | AI55: =IF(AG55>0,AG55,0) -> 5308.1983 | AK55: =AND(M55>=0,M55<=M54) -> TRUE | AL55: =AND(D55>=0,D55<=1,E55>=0,E55<=1,F55>=0,F55<=1,G55>=0,G55<=1,J55+K55+L55<=M54+0.000000001*scale_count) -> TRUE | AM55: =(AG54+R55-S55)*(1+i_m)-T55-U55-V55 -> 5308.1983 | AN55: =ABS(AM55-AG55)<=0.000000001*MAX(ABS(AM55),ABS(AG55),scale_money) -> TRUE | AO55: =(U55+V55+T55)*Z55-(R55-S55)*Z54 -> -27.744668 | AP55: =SUM(AO56:$AO$271) -> 5256.4048 | AQ55: =ABS(AG55*Z55-AP55)<=0.000000001*MAX(ABS(AG55*Z55),ABS(AP55),scale_money) -> TRUE | AR55: =IF(A55<>rem_m,L55=0,L55=M54-J55-K55) -> TRUE | AS55: =IF(A55>prem_rem_m,AND(R55=0,S55=0,F55=0,G55=0,K55=0),R55=M54*premium) -> TRUE | AT55: =AND(C55>=18,C55<=120,OR(B55-B54=0,B55-B54=1)) -> TRUE | AU55: =-(N56-O56)+v_m*(E56*(sum_assured+Q56)+P56+(1-E56)*(1-G56)*AH56) -> 5364.5011 | AV55: =ABS(AH55-AU55)<=0.000000001*MAX(ABS(AH55),ABS(AU55),scale_pp) -> TRUE | AW55: =AND(AI55>=0,AI55>=AG55) -> TRUE | AX55: =AND(U55=J55*sum_assured,R55=M54*N55,T55=M54*P55) -> TRUE
A56: 4 | B56: =MIN(INT((dur_m+A56-1)/12),dur_y_last) -> 12 | C56: =age_at_entry+B56 -> 50 | D56: =INDEX(mort_table,MATCH(C56,mort_age,0),MATCH(sex,mort_sex,0)) -> 0.0015037072 | E56: =IF(A56<=rem_m,1-(1-D56)^(1/12),0) -> 0.00012539538 | F56: =IF(A56<=prem_rem_m,INDEX(lapse_table,MATCH(MIN(B56,5),lapse_key,0)),0) -> 0.04 | G56: =1-(1-F56)^(1/12) -> 0.0033960532 | H56: =INDEX(comm_table,MATCH(MIN(B56,1),comm_key,0)) -> 0.02 | I56: =(1+e_m)^A56 -> 1.0099016 | J56: =M55*E56 -> 0.0001240793 | K56: =(M55-J56)*G56 -> 0.0033599887 | L56: =IF(A56=rem_m,M55-J56-K56,0) -> 0 | M56: =M55-J56-K56-L56 -> 0.98602048 | N56: =IF(A56<=prem_rem_m,premium,0) -> 68.98 | O56: =N56*H56 -> 1.3796 | P56: =maint_base*I56 -> 5.0495082 | Q56: =claim_exp_base*I56 -> 252.47541 | R56: =M55*N56 -> 68.256024 | S56: =R56*H56 -> 1.3651205 | T56: =M55*P56 -> 4.9965113 | U56: =J56*sum_assured -> 37.223789 | V56: =J56*Q56 -> 0.031326971 | W56: =R56-S56-T56-U56-V56 -> 24.639276 | X56: =U56+V56+T56-(R56-S56)*(1+i_m) -> -24.858259 | Y56: =v_m -> 0.99673694 | Z56: =v_m^A56 -> 0.98701152 | AA56: =(R56-S56)*Z55-(T56+U56+V56)*Z56 -> 24.535388 | AB56: =R56*Z55 -> 67.590032 | AC56: =S56*Z55 -> 1.3518006 | AD56: =T56*Z56 -> 4.9316142 | AE56: =U56*Z56 -> 36.740309 | AF56: =V56*Z56 -> 0.030920081 | AG56: =(AG57+X57)*Y57 -> 5350.4342 | AH56: =IF(M56>0,AG56/M56,0) -> 5426.2911 | AI56: =IF(AG56>0,AG56,0) -> 5350.4342 | AK56: =AND(M56>=0,M56<=M55) -> TRUE | AL56: =AND(D56>=0,D56<=1,E56>=0,E56<=1,F56>=0,F56<=1,G56>=0,G56<=1,J56+K56+L56<=M55+0.000000001*scale_count) -> TRUE | AM56: =(AG55+R56-S56)*(1+i_m)-T56-U56-V56 -> 5350.4342 | AN56: =ABS(AM56-AG56)<=0.000000001*MAX(ABS(AM56),ABS(AG56),scale_money) -> TRUE | AO56: =(U56+V56+T56)*Z56-(R56-S56)*Z55 -> -24.535388 | AP56: =SUM(AO57:$AO$271) -> 5280.9402 | AQ56: =ABS(AG56*Z56-AP56)<=0.000000001*MAX(ABS(AG56*Z56),ABS(AP56),scale_money) -> TRUE | AR56: =IF(A56<>rem_m,L56=0,L56=M55-J56-K56) -> TRUE | AS56: =IF(A56>prem_rem_m,AND(R56=0,S56=0,F56=0,G56=0,K56=0),R56=M55*premium) -> TRUE | AT56: =AND(C56>=18,C56<=120,OR(B56-B55=0,B56-B55=1)) -> TRUE | AU56: =-(N57-O57)+v_m*(E57*(sum_assured+Q57)+P57+(1-E57)*(1-G57)*AH57) -> 5426.2911 | AV56: =ABS(AH56-AU56)<=0.000000001*MAX(ABS(AH56),ABS(AU56),scale_pp) -> TRUE | AW56: =AND(AI56>=0,AI56>=AG56) -> TRUE | AX56: =AND(U56=J56*sum_assured,R56=M55*N56,T56=M55*P56) -> TRUE
A57: 5 | B57: =MIN(INT((dur_m+A57-1)/12),dur_y_last) -> 12 | C57: =age_at_entry+B57 -> 50 | D57: =INDEX(mort_table,MATCH(C57,mort_age,0),MATCH(sex,mort_sex,0)) -> 0.0015037072 | E57: =IF(A57<=rem_m,1-(1-D57)^(1/12),0) -> 0.00012539538 | F57: =IF(A57<=prem_rem_m,INDEX(lapse_table,MATCH(MIN(B57,5),lapse_key,0)),0) -> 0.04 | G57: =1-(1-F57)^(1/12) -> 0.0033960532 | H57: =INDEX(comm_table,MATCH(MIN(B57,1),comm_key,0)) -> 0.02 | I57: =(1+e_m)^A57 -> 1.0123923 | J57: =M56*E57 -> 0.00012364241 | K57: =(M56-J57)*G57 -> 0.0033481581 | L57: =IF(A57=rem_m,M56-J57-K57,0) -> 0 | M57: =M56-J57-K57-L57 -> 0.98254868 | N57: =IF(A57<=prem_rem_m,premium,0) -> 68.98 | O57: =N57*H57 -> 1.3796 | P57: =maint_base*I57 -> 5.0619616 | Q57: =claim_exp_base*I57 -> 253.09808 | R57: =M56*N57 -> 68.015693 | S57: =R57*H57 -> 1.3603139 | T57: =M56*P57 -> 4.9911978 | U57: =J57*sum_assured -> 37.092723 | V57: =J57*Q57 -> 0.031293657 | W57: =R57-S57-T57-U57-V57 -> 24.540164 | X57: =U57+V57+T57-(R57-S57)*(1+i_m) -> -24.758376 | Y57: =v_m -> 0.99673694 | Z57: =v_m^A57 -> 0.98379084 | AA57: =(R57-S57)*Z56-(T57+U57+V57)*Z57 -> 24.357064 | AB57: =R57*Z56 -> 67.132272 | AC57: =S57*Z56 -> 1.3426454 | AD57: =T57*Z57 -> 4.9102947 | AE57: =U57*Z57 -> 36.491481 | AF57: =V57*Z57 -> 0.030786413 | AG57: =(AG58+X58)*Y58 -> 5392.7085 | AH57: =IF(M57>0,AG57/M57,0) -> 5488.4899 | AI57: =IF(AG57>0,AG57,0) -> 5392.7085 | AK57: =AND(M57>=0,M57<=M56) -> TRUE | AL57: =AND(D57>=0,D57<=1,E57>=0,E57<=1,F57>=0,F57<=1,G57>=0,G57<=1,J57+K57+L57<=M56+0.000000001*scale_count) -> TRUE | AM57: =(AG56+R57-S57)*(1+i_m)-T57-U57-V57 -> 5392.7085 | AN57: =ABS(AM57-AG57)<=0.000000001*MAX(ABS(AM57),ABS(AG57),scale_money) -> TRUE | AO57: =(U57+V57+T57)*Z57-(R57-S57)*Z56 -> -24.357064 | AP57: =SUM(AO58:$AO$271) -> 5305.2972 | AQ57: =ABS(AG57*Z57-AP57)<=0.000000001*MAX(ABS(AG57*Z57),ABS(AP57),scale_money) -> TRUE | AR57: =IF(A57<>rem_m,L57=0,L57=M56-J57-K57) -> TRUE | AS57: =IF(A57>prem_rem_m,AND(R57=0,S57=0,F57=0,G57=0,K57=0),R57=M56*premium) -> TRUE | AT57: =AND(C57>=18,C57<=120,OR(B57-B56=0,B57-B56=1)) -> TRUE | AU57: =-(N58-O58)+v_m*(E58*(sum_assured+Q58)+P58+(1-E58)*(1-G58)*AH58) -> 5488.4899 | AV57: =ABS(AH57-AU57)<=0.000000001*MAX(ABS(AH57),ABS(AU57),scale_pp) -> TRUE | AW57: =AND(AI57>=0,AI57>=AG57) -> TRUE | AX57: =AND(U57=J57*sum_assured,R57=M56*N57,T57=M56*P57) -> TRUE
A58: 6 | B58: =MIN(INT((dur_m+A58-1)/12),dur_y_last) -> 12 | C58: =age_at_entry+B58 -> 50 | D58: =INDEX(mort_table,MATCH(C58,mort_age,0),MATCH(sex,mort_sex,0)) -> 0.0015037072 | E58: =IF(A58<=rem_m,1-(1-D58)^(1/12),0) -> 0.00012539538 | F58: =IF(A58<=prem_rem_m,INDEX(lapse_table,MATCH(MIN(B58,5),lapse_key,0)),0) -> 0.04 | G58: =1-(1-F58)^(1/12) -> 0.0033960532 | H58: =INDEX(comm_table,MATCH(MIN(B58,1),comm_key,0)) -> 0.02 | I58: =(1+e_m)^A58 -> 1.0148892 | J58: =M57*E58 -> 0.00012320706 | K58: =(M57-J58)*G58 -> 0.0033363692 | L58: =IF(A58=rem_m,M57-J58-K58,0) -> 0 | M58: =M57-J58-K58-L58 -> 0.9790891 | N58: =IF(A58<=prem_rem_m,premium,0) -> 68.98 | O58: =N58*H58 -> 1.3796 | P58: =maint_base*I58 -> 5.0744458 | Q58: =claim_exp_base*I58 -> 253.72229 | R58: =M57*N58 -> 67.776208 | S58: =R58*H58 -> 1.3555242 | T58: =M57*P58 -> 4.98589 | U58: =J58*sum_assured -> 36.962119 | V58: =J58*Q58 -> 0.031260378 | W58: =R58-S58-T58-U58-V58 -> 24.441414 | X58: =U58+V58+T58-(R58-S58)*(1+i_m) -> -24.658858 | Y58: =v_m -> 0.99673694 | Z58: =v_m^A58 -> 0.98058068 | AA58: =(R58-S58)*Z57-(T58+U58+V58)*Z58 -> 24.18 | AB58: =R58*Z57 -> 66.677613 | AC58: =S58*Z57 -> 1.3335523 | AD58: =T58*Z58 -> 4.8890674 | AE58: =U58*Z58 -> 36.24434 | AF58: =V58*Z58 -> 0.030653323 | AG58: =(AG59+X59)*Y59 -> 5435.0217 | AH58: =IF(M58>0,AG58/M58,0) -> 5551.1001 | AI58: =IF(AG58>0,AG58,0) -> 5435.0217 | AK58: =AND(M58>=0,M58<=M57) -> TRUE | AL58: =AND(D58>=0,D58<=1,E58>=0,E58<=1,F58>=0,F58<=1,G58>=0,G58<=1,J58+K58+L58<=M57+0.000000001*scale_count) -> TRUE | AM58: =(AG57+R58-S58)*(1+i_m)-T58-U58-V58 -> 5435.0217 | AN58: =ABS(AM58-AG58)<=0.000000001*MAX(ABS(AM58),ABS(AG58),scale_money) -> TRUE | AO58: =(U58+V58+T58)*Z58-(R58-S58)*Z57 -> -24.18 | AP58: =SUM(AO59:$AO$271) -> 5329.4772 | AQ58: =ABS(AG58*Z58-AP58)<=0.000000001*MAX(ABS(AG58*Z58),ABS(AP58),scale_money) -> TRUE | AR58: =IF(A58<>rem_m,L58=0,L58=M57-J58-K58) -> TRUE | AS58: =IF(A58>prem_rem_m,AND(R58=0,S58=0,F58=0,G58=0,K58=0),R58=M57*premium) -> TRUE | AT58: =AND(C58>=18,C58<=120,OR(B58-B57=0,B58-B57=1)) -> TRUE | AU58: =-(N59-O59)+v_m*(E59*(sum_assured+Q59)+P59+(1-E59)*(1-G59)*AH59) -> 5551.1001 | AV58: =ABS(AH58-AU58)<=0.000000001*MAX(ABS(AH58),ABS(AU58),scale_pp) -> TRUE | AW58: =AND(AI58>=0,AI58>=AG58) -> TRUE | AX58: =AND(U58=J58*sum_assured,R58=M57*N58,T58=M57*P58) -> TRUE
A59: 7 | B59: =MIN(INT((dur_m+A59-1)/12),dur_y_last) -> 12 | C59: =age_at_entry+B59 -> 50 | D59: =INDEX(mort_table,MATCH(C59,mort_age,0),MATCH(sex,mort_sex,0)) -> 0.0015037072 | E59: =IF(A59<=rem_m,1-(1-D59)^(1/12),0) -> 0.00012539538 | F59: =IF(A59<=prem_rem_m,INDEX(lapse_table,MATCH(MIN(B59,5),lapse_key,0)),0) -> 0.04 | G59: =1-(1-F59)^(1/12) -> 0.0033960532 | H59: =INDEX(comm_table,MATCH(MIN(B59,1),comm_key,0)) -> 0.02 | I59: =(1+e_m)^A59 -> 1.0173921 | J59: =M58*E59 -> 0.00012277325 | K59: =(M58-J59)*G59 -> 0.0033246217 | L59: =IF(A59=rem_m,M58-J59-K59,0) -> 0 | M59: =M58-J59-K59-L59 -> 0.97564171 | N59: =IF(A59<=prem_rem_m,premium,0) -> 68.98 | O59: =N59*H59 -> 1.3796 | P59: =maint_base*I59 -> 5.0869607 | Q59: =claim_exp_base*I59 -> 254.34804 | R59: =M58*N59 -> 67.537566 | S59: =R59*H59 -> 1.3507513 | T59: =M58*P59 -> 4.9805878 | U59: =J59*sum_assured -> 36.831975 | V59: =J59*Q59 -> 0.031227135 | W59: =R59-S59-T59-U59-V59 -> 24.343026 | X59: =U59+V59+T59-(R59-S59)*(1+i_m) -> -24.559704 | Y59: =v_m -> 0.99673694 | Z59: =v_m^A59 -> 0.97738098 | AA59: =(R59-S59)*Z58-(T59+U59+V59)*Z59 -> 24.004188 | AB59: =R59*Z58 -> 66.226033 | AC59: =S59*Z58 -> 1.3245207 | AD59: =T59*Z59 -> 4.8679318 | AE59: =U59*Z59 -> 35.998872 | AF59: =V59*Z59 -> 0.030520808 | AG59: =(AG60+X60)*Y60 -> 5477.3742 | AH59: =IF(M59>0,AG59/M59,0) -> 5614.1247 | AI59: =IF(AG59>0,AG59,0) -> 5477.3742 | AK59: =AND(M59>=0,M59<=M58) -> TRUE | AL59: =AND(D59>=0,D59<=1,E59>=0,E59<=1,F59>=0,F59<=1,G59>=0,G59<=1,J59+K59+L59<=M58+0.000000001*scale_count) -> TRUE | AM59: =(AG58+R59-S59)*(1+i_m)-T59-U59-V59 -> 5477.3742 | AN59: =ABS(AM59-AG59)<=0.000000001*MAX(ABS(AM59),ABS(AG59),scale_money) -> TRUE | AO59: =(U59+V59+T59)*Z59-(R59-S59)*Z58 -> -24.004188 | AP59: =SUM(AO60:$AO$271) -> 5353.4814 | AQ59: =ABS(AG59*Z59-AP59)<=0.000000001*MAX(ABS(AG59*Z59),ABS(AP59),scale_money) -> TRUE | AR59: =IF(A59<>rem_m,L59=0,L59=M58-J59-K59) -> TRUE | AS59: =IF(A59>prem_rem_m,AND(R59=0,S59=0,F59=0,G59=0,K59=0),R59=M58*premium) -> TRUE | AT59: =AND(C59>=18,C59<=120,OR(B59-B58=0,B59-B58=1)) -> TRUE | AU59: =-(N60-O60)+v_m*(E60*(sum_assured+Q60)+P60+(1-E60)*(1-G60)*AH60) -> 5614.1247 | AV59: =ABS(AH59-AU59)<=0.000000001*MAX(ABS(AH59),ABS(AU59),scale_pp) -> TRUE | AW59: =AND(AI59>=0,AI59>=AG59) -> TRUE | AX59: =AND(U59=J59*sum_assured,R59=M58*N59,T59=M58*P59) -> TRUE
A60: 8 | B60: =MIN(INT((dur_m+A60-1)/12),dur_y_last) -> 12 | C60: =age_at_entry+B60 -> 50 | D60: =INDEX(mort_table,MATCH(C60,mort_age,0),MATCH(sex,mort_sex,0)) -> 0.0015037072 | E60: =IF(A60<=rem_m,1-(1-D60)^(1/12),0) -> 0.00012539538 | F60: =IF(A60<=prem_rem_m,INDEX(lapse_table,MATCH(MIN(B60,5),lapse_key,0)),0) -> 0.04 | G60: =1-(1-F60)^(1/12) -> 0.0033960532 | H60: =INDEX(comm_table,MATCH(MIN(B60,1),comm_key,0)) -> 0.02 | I60: =(1+e_m)^A60 -> 1.0199013 | J60: =M59*E60 -> 0.00012234096 | K60: =(M59-J60)*G60 -> 0.0033129157 | L60: =IF(A60=rem_m,M59-J60-K60,0) -> 0 | M60: =M59-J60-K60-L60 -> 0.97220645 | N60: =IF(A60<=prem_rem_m,premium,0) -> 68.98 | O60: =N60*H60 -> 1.3796 | P60: =maint_base*I60 -> 5.0995066 | Q60: =claim_exp_base*I60 -> 254.97533 | R60: =M59*N60 -> 67.299765 | S60: =R60*H60 -> 1.3459953 | T60: =M59*P60 -> 4.9752913 | U60: =J60*sum_assured -> 36.702288 | V60: =J60*Q60 -> 0.031193927 | W60: =R60-S60-T60-U60-V60 -> 24.244996 | X60: =U60+V60+T60-(R60-S60)*(1+i_m) -> -24.460912 | Y60: =v_m -> 0.99673694 | Z60: =v_m^A60 -> 0.97419173 | AA60: =(R60-S60)*Z59-(T60+U60+V60)*Z60 -> 23.829618 | AB60: =R60*Z59 -> 65.777511 | AC60: =S60*Z59 -> 1.3155502 | AD60: =T60*Z60 -> 4.8468877 | AE60: =U60*Z60 -> 35.755066 | AF60: =V60*Z60 -> 0.030388865 | AG60: =(AG61+X61)*Y61 -> 5519.7666 | AH60: =IF(M60>0,AG60/M60,0) -> 5677.5663 | AI60: =IF(AG60>0,AG60,0) -> 5519.7666 | AK60: =AND(M60>=0,M60<=M59) -> TRUE | AL60: =AND(D60>=0,D60<=1,E60>=0,E60<=1,F60>=0,F60<=1,G60>=0,G60<=1,J60+K60+L60<=M59+0.000000001*scale_count) -> TRUE | AM60: =(AG59+R60-S60)*(1+i_m)-T60-U60-V60 -> 5519.7666 | AN60: =ABS(AM60-AG60)<=0.000000001*MAX(ABS(AM60),ABS(AG60),scale_money) -> TRUE | AO60: =(U60+V60+T60)*Z60-(R60-S60)*Z59 -> -23.829618 | AP60: =SUM(AO61:$AO$271) -> 5377.311 | AQ60: =ABS(AG60*Z60-AP60)<=0.000000001*MAX(ABS(AG60*Z60),ABS(AP60),scale_money) -> TRUE | AR60: =IF(A60<>rem_m,L60=0,L60=M59-J60-K60) -> TRUE | AS60: =IF(A60>prem_rem_m,AND(R60=0,S60=0,F60=0,G60=0,K60=0),R60=M59*premium) -> TRUE | AT60: =AND(C60>=18,C60<=120,OR(B60-B59=0,B60-B59=1)) -> TRUE | AU60: =-(N61-O61)+v_m*(E61*(sum_assured+Q61)+P61+(1-E61)*(1-G61)*AH61) -> 5677.5663 | AV60: =ABS(AH60-AU60)<=0.000000001*MAX(ABS(AH60),ABS(AU60),scale_pp) -> TRUE | AW60: =AND(AI60>=0,AI60>=AG60) -> TRUE | AX60: =AND(U60=J60*sum_assured,R60=M59*N60,T60=M59*P60) -> TRUE
A61: 9 | B61: =MIN(INT((dur_m+A61-1)/12),dur_y_last) -> 12 | C61: =age_at_entry+B61 -> 50 | D61: =INDEX(mort_table,MATCH(C61,mort_age,0),MATCH(sex,mort_sex,0)) -> 0.0015037072 | E61: =IF(A61<=rem_m,1-(1-D61)^(1/12),0) -> 0.00012539538 | F61: =IF(A61<=prem_rem_m,INDEX(lapse_table,MATCH(MIN(B61,5),lapse_key,0)),0) -> 0.04 | G61: =1-(1-F61)^(1/12) -> 0.0033960532 | H61: =INDEX(comm_table,MATCH(MIN(B61,1),comm_key,0)) -> 0.02 | I61: =(1+e_m)^A61 -> 1.0224167 | J61: =M60*E61 -> 0.0001219102 | K61: =(M60-J61)*G61 -> 0.0033012508 | L61: =IF(A61=rem_m,M60-J61-K61,0) -> 0 | M61: =M60-J61-K61-L61 -> 0.96878329 | N61: =IF(A61<=prem_rem_m,premium,0) -> 68.98 | O61: =N61*H61 -> 1.3796 | P61: =maint_base*I61 -> 5.1120833 | Q61: =claim_exp_base*I61 -> 255.60417 | R61: =M60*N61 -> 67.062801 | S61: =R61*H61 -> 1.341256 | T61: =M60*P61 -> 4.9700004 | U61: =J61*sum_assured -> 36.573059 | V61: =J61*Q61 -> 0.031160754 | W61: =R61-S61-T61-U61-V61 -> 24.147325 | X61: =U61+V61+T61-(R61-S61)*(1+i_m) -> -24.36248 | Y61: =v_m -> 0.99673694 | Z61: =v_m^A61 -> 0.97101289 | AA61: =(R61-S61)*Z60-(T61+U61+V61)*Z61 -> 23.656283 | AB61: =R61*Z60 -> 65.332027 | AC61: =S61*Z60 -> 1.3066405 | AD61: =T61*Z61 -> 4.8259344 | AE61: =U61*Z61 -> 35.512911 | AF61: =V61*Z61 -> 0.030257494 | AG61: =(AG62+X62)*Y62 -> 5562.1994 | AH61: =IF(M61>0,AG61/M61,0) -> 5741.4279 | AI61: =IF(AG61>0,AG61,0) -> 5562.1994 | AK61: =AND(M61>=0,M61<=M60) -> TRUE | AL61: =AND(D61>=0,D61<=1,E61>=0,E61<=1,F61>=0,F61<=1,G61>=0,G61<=1,J61+K61+L61<=M60+0.000000001*scale_count) -> TRUE | AM61: =(AG60+R61-S61)*(1+i_m)-T61-U61-V61 -> 5562.1994 | AN61: =ABS(AM61-AG61)<=0.000000001*MAX(ABS(AM61),ABS(AG61),scale_money) -> TRUE | AO61: =(U61+V61+T61)*Z61-(R61-S61)*Z60 -> -23.656283 | AP61: =SUM(AO62:$AO$271) -> 5400.9673 | AQ61: =ABS(AG61*Z61-AP61)<=0.000000001*MAX(ABS(AG61*Z61),ABS(AP61),scale_money) -> TRUE | AR61: =IF(A61<>rem_m,L61=0,L61=M60-J61-K61) -> TRUE | AS61: =IF(A61>prem_rem_m,AND(R61=0,S61=0,F61=0,G61=0,K61=0),R61=M60*premium) -> TRUE | AT61: =AND(C61>=18,C61<=120,OR(B61-B60=0,B61-B60=1)) -> TRUE | AU61: =-(N62-O62)+v_m*(E62*(sum_assured+Q62)+P62+(1-E62)*(1-G62)*AH62) -> 5741.4279 | AV61: =ABS(AH61-AU61)<=0.000000001*MAX(ABS(AH61),ABS(AU61),scale_pp) -> TRUE | AW61: =AND(AI61>=0,AI61>=AG61) -> TRUE | AX61: =AND(U61=J61*sum_assured,R61=M60*N61,T61=M60*P61) -> TRUE
A62: 10 | B62: =MIN(INT((dur_m+A62-1)/12),dur_y_last) -> 12 | C62: =age_at_entry+B62 -> 50 | D62: =INDEX(mort_table,MATCH(C62,mort_age,0),MATCH(sex,mort_sex,0)) -> 0.0015037072 | E62: =IF(A62<=rem_m,1-(1-D62)^(1/12),0) -> 0.00012539538 | F62: =IF(A62<=prem_rem_m,INDEX(lapse_table,MATCH(MIN(B62,5),lapse_key,0)),0) -> 0.04 | G62: =1-(1-F62)^(1/12) -> 0.0033960532 | H62: =INDEX(comm_table,MATCH(MIN(B62,1),comm_key,0)) -> 0.02 | I62: =(1+e_m)^A62 -> 1.0249382 | J62: =M61*E62 -> 0.00012148095 | K62: =(M61-J62)*G62 -> 0.003289627 | L62: =IF(A62=rem_m,M61-J62-K62,0) -> 0 | M62: =M61-J62-K62-L62 -> 0.96537218 | N62: =IF(A62<=prem_rem_m,premium,0) -> 68.98 | O62: =N62*H62 -> 1.3796 | P62: =maint_base*I62 -> 5.1246911 | Q62: =claim_exp_base*I62 -> 256.23455 | R62: =M61*N62 -> 66.826671 | S62: =R62*H62 -> 1.3365334 | T62: =M61*P62 -> 4.9647151 | U62: =J62*sum_assured -> 36.444284 | V62: =J62*Q62 -> 0.031127616 | W62: =R62-S62-T62-U62-V62 -> 24.050011 | X62: =U62+V62+T62-(R62-S62)*(1+i_m) -> -24.264409 | Y62: =v_m -> 0.99673694 | Z62: =v_m^A62 -> 0.96784442 | AA62: =(R62-S62)*Z61-(T62+U62+V62)*Z62 -> 23.484173 | AB62: =R62*Z61 -> 64.889559 | AC62: =S62*Z61 -> 1.2977912 | AD62: =T62*Z62 -> 4.8050718 | AE62: =U62*Z62 -> 35.272397 | AF62: =V62*Z62 -> 0.03012669 | AG62: =(AG63+X63)*Y63 -> 5604.673 | AH62: =IF(M62>0,AG62/M62,0) -> 5805.7121 | AI62: =IF(AG62>0,AG62,0) -> 5604.673 | AK62: =AND(M62>=0,M62<=M61) -> TRUE | AL62: =AND(D62>=0,D62<=1,E62>=0,E62<=1,F62>=0,F62<=1,G62>=0,G62<=1,J62+K62+L62<=M61+0.000000001*scale_count) -> TRUE | AM62: =(AG61+R62-S62)*(1+i_m)-T62-U62-V62 -> 5604.673 | AN62: =ABS(AM62-AG62)<=0.000000001*MAX(ABS(AM62),ABS(AG62),scale_money) -> TRUE | AO62: =(U62+V62+T62)*Z62-(R62-S62)*Z61 -> -23.484173 | AP62: =SUM(AO63:$AO$271) -> 5424.4515 | AQ62: =ABS(AG62*Z62-AP62)<=0.000000001*MAX(ABS(AG62*Z62),ABS(AP62),scale_money) -> TRUE | AR62: =IF(A62<>rem_m,L62=0,L62=M61-J62-K62) -> TRUE | AS62: =IF(A62>prem_rem_m,AND(R62=0,S62=0,F62=0,G62=0,K62=0),R62=M61*premium) -> TRUE | AT62: =AND(C62>=18,C62<=120,OR(B62-B61=0,B62-B61=1)) -> TRUE | AU62: =-(N63-O63)+v_m*(E63*(sum_assured+Q63)+P63+(1-E63)*(1-G63)*AH63) -> 5805.7121 | AV62: =ABS(AH62-AU62)<=0.000000001*MAX(ABS(AH62),ABS(AU62),scale_pp) -> TRUE | AW62: =AND(AI62>=0,AI62>=AG62) -> TRUE | AX62: =AND(U62=J62*sum_assured,R62=M61*N62,T62=M61*P62) -> TRUE
A63: 11 | B63: =MIN(INT((dur_m+A63-1)/12),dur_y_last) -> 12 | C63: =age_at_entry+B63 -> 50 | D63: =INDEX(mort_table,MATCH(C63,mort_age,0),MATCH(sex,mort_sex,0)) -> 0.0015037072 | E63: =IF(A63<=rem_m,1-(1-D63)^(1/12),0) -> 0.00012539538 | F63: =IF(A63<=prem_rem_m,INDEX(lapse_table,MATCH(MIN(B63,5),lapse_key,0)),0) -> 0.04 | G63: =1-(1-F63)^(1/12) -> 0.0033960532 | H63: =INDEX(comm_table,MATCH(MIN(B63,1),comm_key,0)) -> 0.02 | I63: =(1+e_m)^A63 -> 1.027466 | J63: =M62*E63 -> 0.00012105321 | K63: =(M62-J63)*G63 -> 0.0032780442 | L63: =IF(A63=rem_m,M62-J63-K63,0) -> 0 | M63: =M62-J63-K63-L63 -> 0.96197309 | N63: =IF(A63<=prem_rem_m,premium,0) -> 68.98 | O63: =N63*H63 -> 1.3796 | P63: =maint_base*I63 -> 5.13733 | Q63: =claim_exp_base*I63 -> 256.8665 | R63: =M62*N63 -> 66.591373 | S63: =R63*H63 -> 1.3318275 | T63: =M62*P63 -> 4.9594354 | U63: =J63*sum_assured -> 36.315963 | V63: =J63*Q63 -> 0.031094514 | W63: =R63-S63-T63-U63-V63 -> 23.953053 | X63: =U63+V63+T63-(R63-S63)*(1+i_m) -> -24.166696 | Y63: =v_m -> 0.99673694 | Z63: =v_m^A63 -> 0.96468629 | AA63: =(R63-S63)*Z62-(T63+U63+V63)*Z63 -> 23.31328 | AB63: =R63*Z62 -> 64.450089 | AC63: =S63*Z62 -> 1.2890018 | AD63: =T63*Z63 -> 4.7842994 | AE63: =U63*Z63 -> 35.033512 | AF63: =V63*Z63 -> 0.029996451 | AG63: =(AG64+X64)*Y64 -> 5647.1879 | AH63: =IF(M63>0,AG63/M63,0) -> 5870.422 | AI63: =IF(AG63>0,AG63,0) -> 5647.1879 | AK63: =AND(M63>=0,M63<=M62) -> TRUE | AL63: =AND(D63>=0,D63<=1,E63>=0,E63<=1,F63>=0,F63<=1,G63>=0,G63<=1,J63+K63+L63<=M62+0.000000001*scale_count) -> TRUE | AM63: =(AG62+R63-S63)*(1+i_m)-T63-U63-V63 -> 5647.1879 | AN63: =ABS(AM63-AG63)<=0.000000001*MAX(ABS(AM63),ABS(AG63),scale_money) -> TRUE | AO63: =(U63+V63+T63)*Z63-(R63-S63)*Z62 -> -23.31328 | AP63: =SUM(AO64:$AO$271) -> 5447.7648 | AQ63: =ABS(AG63*Z63-AP63)<=0.000000001*MAX(ABS(AG63*Z63),ABS(AP63),scale_money) -> TRUE | AR63: =IF(A63<>rem_m,L63=0,L63=M62-J63-K63) -> TRUE | AS63: =IF(A63>prem_rem_m,AND(R63=0,S63=0,F63=0,G63=0,K63=0),R63=M62*premium) -> TRUE | AT63: =AND(C63>=18,C63<=120,OR(B63-B62=0,B63-B62=1)) -> TRUE | AU63: =-(N64-O64)+v_m*(E64*(sum_assured+Q64)+P64+(1-E64)*(1-G64)*AH64) -> 5870.422 | AV63: =ABS(AH63-AU63)<=0.000000001*MAX(ABS(AH63),ABS(AU63),scale_pp) -> TRUE | AW63: =AND(AI63>=0,AI63>=AG63) -> TRUE | AX63: =AND(U63=J63*sum_assured,R63=M62*N63,T63=M62*P63) -> TRUE
A64: 12 | B64: =MIN(INT((dur_m+A64-1)/12),dur_y_last) -> 12 | C64: =age_at_entry+B64 -> 50 | D64: =INDEX(mort_table,MATCH(C64,mort_age,0),MATCH(sex,mort_sex,0)) -> 0.0015037072 | E64: =IF(A64<=rem_m,1-(1-D64)^(1/12),0) -> 0.00012539538 | F64: =IF(A64<=prem_rem_m,INDEX(lapse_table,MATCH(MIN(B64,5),lapse_key,0)),0) -> 0.04 | G64: =1-(1-F64)^(1/12) -> 0.0033960532 | H64: =INDEX(comm_table,MATCH(MIN(B64,1),comm_key,0)) -> 0.02 | I64: =(1+e_m)^A64 -> 1.03 | J64: =M63*E64 -> 0.00012062698 | K64: =(M63-J64)*G64 -> 0.0032665021 | L64: =IF(A64=rem_m,M63-J64-K64,0) -> 0 | M64: =M63-J64-K64-L64 -> 0.95858596 | N64: =IF(A64<=prem_rem_m,premium,0) -> 68.98 | O64: =N64*H64 -> 1.3796 | P64: =maint_base*I64 -> 5.15 | Q64: =claim_exp_base*I64 -> 257.5 | R64: =M63*N64 -> 66.356903 | S64: =R64*H64 -> 1.3271381 | T64: =M63*P64 -> 4.9541614 | U64: =J64*sum_assured -> 36.188094 | V64: =J64*Q64 -> 0.031061447 | W64: =R64-S64-T64-U64-V64 -> 23.856449 | X64: =U64+V64+T64-(R64-S64)*(1+i_m) -> -24.069339 | Y64: =v_m -> 0.99673694 | Z64: =v_m^A64 -> 0.96153846 | AA64: =(R64-S64)*Z63-(T64+U64+V64)*Z64 -> 23.143596 | AB64: =R64*Z63 -> 64.013595 | AC64: =S64*Z63 -> 1.2802719 | AD64: =T64*Z64 -> 4.7636167 | AE64: =U64*Z64 -> 34.796244 | AF64: =V64*Z64 -> 0.029866776 | AG64: =(AG65+X65)*Y65 -> 5689.7447 | AH64: =IF(M64>0,AG64/M64,0) -> 5935.5602 | AI64: =IF(AG64>0,AG64,0) -> 5689.7447 | AK64: =AND(M64>=0,M64<=M63) -> TRUE | AL64: =AND(D64>=0,D64<=1,E64>=0,E64<=1,F64>=0,F64<=1,G64>=0,G64<=1,J64+K64+L64<=M63+0.000000001*scale_count) -> TRUE | AM64: =(AG63+R64-S64)*(1+i_m)-T64-U64-V64 -> 5689.7447 | AN64: =ABS(AM64-AG64)<=0.000000001*MAX(ABS(AM64),ABS(AG64),scale_money) -> TRUE | AO64: =(U64+V64+T64)*Z64-(R64-S64)*Z63 -> -23.143596 | AP64: =SUM(AO65:$AO$271) -> 5470.9084 | AQ64: =ABS(AG64*Z64-AP64)<=0.000000001*MAX(ABS(AG64*Z64),ABS(AP64),scale_money) -> TRUE | AR64: =IF(A64<>rem_m,L64=0,L64=M63-J64-K64) -> TRUE | AS64: =IF(A64>prem_rem_m,AND(R64=0,S64=0,F64=0,G64=0,K64=0),R64=M63*premium) -> TRUE | AT64: =AND(C64>=18,C64<=120,OR(B64-B63=0,B64-B63=1)) -> TRUE | AU64: =-(N65-O65)+v_m*(E65*(sum_assured+Q65)+P65+(1-E65)*(1-G65)*AH65) -> 5935.5602 | AV64: =ABS(AH64-AU64)<=0.000000001*MAX(ABS(AH64),ABS(AU64),scale_pp) -> TRUE | AW64: =AND(AI64>=0,AI64>=AG64) -> TRUE | AX64: =AND(U64=J64*sum_assured,R64=M63*N64,T64=M63*P64) -> TRUE
A65: 13 | B65: =MIN(INT((dur_m+A65-1)/12),dur_y_last) -> 12 | C65: =age_at_entry+B65 -> 50 | D65: =INDEX(mort_table,MATCH(C65,mort_age,0),MATCH(sex,mort_sex,0)) -> 0.0015037072 | E65: =IF(A65<=rem_m,1-(1-D65)^(1/12),0) -> 0.00012539538 | F65: =IF(A65<=prem_rem_m,INDEX(lapse_table,MATCH(MIN(B65,5),lapse_key,0)),0) -> 0.04 | G65: =1-(1-F65)^(1/12) -> 0.0033960532 | H65: =INDEX(comm_table,MATCH(MIN(B65,1),comm_key,0)) -> 0.02 | I65: =(1+e_m)^A65 -> 1.0325403 | J65: =M64*E65 -> 0.00012020225 | K65: =(M64-J65)*G65 -> 0.0032550007 | L65: =IF(A65=rem_m,M64-J65-K65,0) -> 0 | M65: =M64-J65-K65-L65 -> 0.95521075 | N65: =IF(A65<=prem_rem_m,premium,0) -> 68.98 | O65: =N65*H65 -> 1.3796 | P65: =maint_base*I65 -> 5.1627013 | Q65: =claim_exp_base*I65 -> 258.13506 | R65: =M64*N65 -> 66.123259 | S65: =R65*H65 -> 1.3224652 | T65: =M64*P65 -> 4.948893 | U65: =J65*sum_assured -> 36.060675 | V65: =J65*Q65 -> 0.031028415 | W65: =R65-S65-T65-U65-V65 -> 23.760198 | X65: =U65+V65+T65-(R65-S65)*(1+i_m) -> -23.972339 | Y65: =v_m -> 0.99673694 | Z65: =v_m^A65 -> 0.95840091 | AA65: =(R65-S65)*Z64-(T65+U65+V65)*Z65 -> 22.975112 | AB65: =R65*Z64 -> 63.580057 | AC65: =S65*Z64 -> 1.2716011 | AD65: =T65*Z65 -> 4.7430235 | AE65: =U65*Z65 -> 34.560583 | AF65: =V65*Z65 -> 0.029737661 | AG65: =(AG66+X66)*Y66 -> 5732.3438 | AH65: =IF(M65>0,AG65/M65,0) -> 6001.1299 | AI65: =IF(AG65>0,AG65,0) -> 5732.3438 | AK65: =AND(M65>=0,M65<=M64) -> TRUE | AL65: =AND(D65>=0,D65<=1,E65>=0,E65<=1,F65>=0,F65<=1,G65>=0,G65<=1,J65+K65+L65<=M64+0.000000001*scale_count) -> TRUE | AM65: =(AG64+R65-S65)*(1+i_m)-T65-U65-V65 -> 5732.3438 | AN65: =ABS(AM65-AG65)<=0.000000001*MAX(ABS(AM65),ABS(AG65),scale_money) -> TRUE | AO65: =(U65+V65+T65)*Z65-(R65-S65)*Z64 -> -22.975112 | AP65: =SUM(AO66:$AO$271) -> 5493.8835 | AQ65: =ABS(AG65*Z65-AP65)<=0.000000001*MAX(ABS(AG65*Z65),ABS(AP65),scale_money) -> TRUE | AR65: =IF(A65<>rem_m,L65=0,L65=M64-J65-K65) -> TRUE | AS65: =IF(A65>prem_rem_m,AND(R65=0,S65=0,F65=0,G65=0,K65=0),R65=M64*premium) -> TRUE | AT65: =AND(C65>=18,C65<=120,OR(B65-B64=0,B65-B64=1)) -> TRUE | AU65: =-(N66-O66)+v_m*(E66*(sum_assured+Q66)+P66+(1-E66)*(1-G66)*AH66) -> 6001.1299 | AV65: =ABS(AH65-AU65)<=0.000000001*MAX(ABS(AH65),ABS(AU65),scale_pp) -> TRUE | AW65: =AND(AI65>=0,AI65>=AG65) -> TRUE | AX65: =AND(U65=J65*sum_assured,R65=M64*N65,T65=M64*P65) -> TRUE
... A270: 218 | B270: =MIN(INT((dur_m+A270-1)/12),dur_y_last) -> 29 | C270: =age_at_entry+B270 -> 67 | D270: =INDEX(mort_table,MATCH(C270,mort_age,0),MATCH(sex,mort_sex,0)) -> 0.006973564 | E270: =IF(A270<=rem_m,1-(1-D270)^(1/12),0) -> 0.00058299607 | F270: =IF(A270<=prem_rem_m,INDEX(lapse_table,MATCH(MIN(B270,5),lapse_key,0)),0) -> 0 | G270: =1-(1-F270)^(1/12) -> 0 | H270: =INDEX(comm_table,MATCH(MIN(B270,1),comm_key,0)) -> 0.02 | I270: =(1+e_m)^A270 -> 1.7108407 | J270: =M269*E270 -> 0.00039062201 | K270: =(M269-J270)*G270 -> 0 | L270: =IF(A270=rem_m,M269-J270-K270,0) -> 0 | M270: =M269-J270-K270-L270 -> 0.6696345 | N270: =IF(A270<=prem_rem_m,premium,0) -> 0 | O270: =N270*H270 -> 0 | P270: =maint_base*I270 -> 8.5542037 | Q270: =claim_exp_base*I270 -> 427.71018 | R270: =M269*N270 -> 0 | S270: =R270*H270 -> 0 | T270: =M269*P270 -> 5.7315313 | U270: =J270*sum_assured -> 117.1866 | V270: =J270*Q270 -> 0.16707301 | W270: =R270-S270-T270-U270-V270 -> -123.08521 | X270: =U270+V270+T270-(R270-S270)*(1+i_m) -> 123.08521 | Y270: =v_m -> 0.99673694 | Z270: =v_m^A270 -> 0.4904119 | AA270: =(R270-S270)*Z269-(T270+U270+V270)*Z270 -> -60.362451 | AB270: =R270*Z269 -> 0 | AC270: =S270*Z269 -> 0 | AD270: =T270*Z270 -> 2.8108112 | AE270: =U270*Z270 -> 57.469705 | AF270: =V270*Z270 -> 0.081934594 | AG270: =(AG271+X271)*Y271 -> 122.62654 | AH270: =IF(M270>0,AG270/M270,0) -> 183.12459 | AI270: =IF(AG270>0,AG270,0) -> 122.62654 | AK270: =AND(M270>=0,M270<=M269) -> TRUE | AL270: =AND(D270>=0,D270<=1,E270>=0,E270<=1,F270>=0,F270<=1,G270>=0,G270<=1,J270+K270+L270<=M269+0.000000001*scale_count) -> TRUE | AM270: =(AG269+R270-S270)*(1+i_m)-T270-U270-V270 -> 122.62654 | AN270: =ABS(AM270-AG270)<=0.000000001*MAX(ABS(AM270),ABS(AG270),scale_money) -> TRUE | AO270: =(U270+V270+T270)*Z270-(R270-S270)*Z269 -> 60.362451 | AP270: =SUM(AO271:$AO$271) -> 60.137515 | AQ270: =ABS(AG270*Z270-AP270)<=0.000000001*MAX(ABS(AG270*Z270),ABS(AP270),scale_money) -> TRUE | AR270: =IF(A270<>rem_m,L270=0,L270=M269-J270-K270) -> TRUE | AS270: =IF(A270>prem_rem_m,AND(R270=0,S270=0,F270=0,G270=0,K270=0),R270=M269*premium) -> TRUE | AT270: =AND(C270>=18,C270<=120,OR(B270-B269=0,B270-B269=1)) -> TRUE | AU270: =-(N271-O271)+v_m*(E271*(sum_assured+Q271)+P271+(1-E271)*(1-G271)*AH271) -> 183.12459 | AV270: =ABS(AH270-AU270)<=0.000000001*MAX(ABS(AH270),ABS(AU270),scale_pp) -> TRUE | AW270: =AND(AI270>=0,AI270>=AG270) -> TRUE | AX270: =AND(U270=J270*sum_assured,R270=M269*N270,T270=M269*P270) -> TRUE
A271: 219 | B271: =MIN(INT((dur_m+A271-1)/12),dur_y_last) -> 29 | C271: =age_at_entry+B271 -> 67 | D271: =INDEX(mort_table,MATCH(C271,mort_age,0),MATCH(sex,mort_sex,0)) -> 0.006973564 | E271: =IF(A271<=rem_m,1-(1-D271)^(1/12),0) -> 0.00058299607 | F271: =IF(A271<=prem_rem_m,INDEX(lapse_table,MATCH(MIN(B271,5),lapse_key,0)),0) -> 0 | G271: =1-(1-F271)^(1/12) -> 0 | H271: =INDEX(comm_table,MATCH(MIN(B271,1),comm_key,0)) -> 0.02 | I271: =(1+e_m)^A271 -> 1.7150601 | J271: =M270*E271 -> 0.00039039428 | K271: =(M270-J271)*G271 -> 0 | L271: =IF(A271=rem_m,M270-J271-K271,0) -> 0.6692441 | M271: =M270-J271-K271-L271 -> 0 | N271: =IF(A271<=prem_rem_m,premium,0) -> 0 | O271: =N271*H271 -> 0 | P271: =maint_base*I271 -> 8.5753006 | Q271: =claim_exp_base*I271 -> 428.76503 | R271: =M270*N271 -> 0 | S271: =R271*H271 -> 0 | T271: =M270*P271 -> 5.7423172 | U271: =J271*sum_assured -> 117.11828 | V271: =J271*Q271 -> 0.16738742 | W271: =R271-S271-T271-U271-V271 -> -123.02799 | X271: =U271+V271+T271-(R271-S271)*(1+i_m) -> 123.02799 | Y271: =v_m -> 0.99673694 | Z271: =v_m^A271 -> 0.48881166 | AA271: =(R271-S271)*Z270-(T271+U271+V271)*Z271 -> -60.137515 | AB271: =R271*Z270 -> 0 | AC271: =S271*Z270 -> 0 | AD271: =T271*Z271 -> 2.8069116 | AE271: =U271*Z271 -> 57.248783 | AF271: =V271*Z271 -> 0.081820921 | AG271: 0 | AH271: =IF(M271>0,AG271/M271,0) -> 0 | AI271: =IF(AG271>0,AG271,0) -> 0 | AK271: =AND(M271>=0,M271<=M270) -> TRUE | AL271: =AND(D271>=0,D271<=1,E271>=0,E271<=1,F271>=0,F271<=1,G271>=0,G271<=1,J271+K271+L271<=M270+0.000000001*scale_count) -> TRUE | AM271: =(AG270+R271-S271)*(1+i_m)-T271-U271-V271 -> -2.1094237e-15 | AN271: =ABS(AM271-AG271)<=0.000000001*MAX(ABS(AM271),ABS(AG271),scale_money) -> TRUE | AO271: =(U271+V271+T271)*Z271-(R271-S271)*Z270 -> 60.137515 | AR271: =IF(A271<>rem_m,L271=0,L271=M270-J271-K271) -> TRUE | AS271: =IF(A271>prem_rem_m,AND(R271=0,S271=0,F271=0,G271=0,K271=0),R271=M270*premium) -> TRUE | AT271: =AND(C271>=18,C271<=120,OR(B271-B270=0,B271-B270=1)) -> TRUE | AW271: =AND(AI271>=0,AI271>=AG271) -> TRUE | AX271: =AND(U271=J271*sum_assured,R271=M270*N271,T271=M270*P271) -> TRUE
A273: Scalars (section 11.2): the derived constants, the PV sums over t = 1 .. rem_m in ascending t, the time-0 state variables and maturities(rem_m)
A274: age_at_entry | B274: =age_at_entry -> 38 | C274: 5 | D274: Int (years)
A275: dur_m | B275: =dur_m -> 141 | C275: 4.3 | D275: Int (months)
A276: term_m | B276: =term_m -> 360 | C276: 4.3 | D276: Int (months)
A277: rem_m | B277: =rem_m -> 219 | C277: 4.3 | D277: Int (months)
A278: prem_term_m | B278: =prem_term_m -> 240 | C278: 4.3 | D278: Int (months)
A279: prem_rem_m | B279: =prem_rem_m -> 99 | C279: 4.3 | D279: Int (months)
A280: dur_y_last | B280: =dur_y_last -> 29 | C280: 4.3 | D280: Int (years)
A281: pv_premiums | B281: =SUM($AB$53:$AB$271) -> 4982.5837 | C281: 9.3 | D281: Money
A282: pv_commission | B282: =SUM($AC$53:$AC$271) -> 99.651673 | C282: 9.3 | D282: Money
A283: pv_maint_expense | B283: =SUM($AD$53:$AD$271) -> 765.99821 | C283: 9.3 | D283: Money
A284: pv_death_outgo | B284: =SUM($AE$53:$AE$271) -> 9278.9681 | C284: 9.3 | D284: Money
A285: pv_claim_expense | B285: =SUM($AF$53:$AF$271) -> 10.531314 | C285: 9.3 | D285: Money
A286: pv_net_cf | B286: =B281-B282-B283-B284-B285 -> -5172.5656 | C286: 9.3 | D286: Money
A287: reserve_0 | B287: =$AG$52 -> 5172.5656 | C287: 10.2 | D287: Money: reserve(0)
A288: reserve_pp_0 | B288: =$AH$52 -> 5172.5656 | C288: 10.4 | D288: Money per policy: reserve_pp(0)
A289: reserve_floored_0 | B289: =$AI$52 -> 5172.5656 | C289: 10.5 | D289: Money: reserve_floored(0)
A290: maturities_n | B290: =$L$271 -> 0.6692441 | C290: 7.3 | D290: Count: maturities(rem_m), the survivors to the end of the term
A292: Check cells (section 12): the section 1 scales and two helper sums, then one <id>_ok per (sheet) invariant, TRUE when every row cell and scalar cell of that invariant is TRUE
A293: scale_money | B293: =sum_assured*pols_if_init -> 300000 | D293: Money (in-force) scale of section 1: sum_assured * pols_if_init
A294: scale_pp | B294: =sum_assured -> 300000 | D294: Money per policy scale of section 1: sum_assured
A295: scale_count | B295: =pols_if_init -> 1 | D295: Count scale of section 1: pols_if_init
A296: exits_sum | B296: =SUMPRODUCT($J$53:$J$271+$K$53:$K$271+$L$53:$L$271) -> 1 | D296: helper (P8): sum over t = 1 .. rem_m of deaths + lapses + maturities
A297: pv_net_cf_t_sum | B297: =SUM($AA$53:$AA$271) -> -5172.5656 | D297: helper (P9): sum over t = 1 .. rem_m of pv_net_cf_t
A299: H1_ok | B299: =AND($AK$52:$AK$271) -> TRUE | D299: every H1 row cell (t = 0 .. rem_m)
A300: H2_ok | B300: =AND($AL$53:$AL$271) -> TRUE | D300: every H2 row cell (t = 1 .. rem_m)
A301: H3_ok | B301: =AND($AG$271=0,$M$271=0) -> TRUE | D301: reserve(rem_m) = 0 and pols_if(rem_m) = 0, exactly
A302: H4_ok | B302: =AND($AN$53:$AN$271) -> TRUE | D302: every H4 row cell (t = 1 .. rem_m)
A303: H5a_ok | B303: =ABS(reserve_0-(-pv_net_cf))<=0.000000001*MAX(ABS(reserve_0),ABS(pv_net_cf),scale_money) -> TRUE | D303: reserve(0) equals -pv_net_cf within tolerance (scale_money)
A304: H5b_ok | B304: =AND($AQ$52:$AQ$270) -> TRUE | D304: every H5b row cell (t = 0 .. rem_m - 1)
A305: P1_ok | B305: =AND($AR$53:$AR$271) -> TRUE | D305: every P1 row cell (t = 1 .. rem_m)
A306: P2_ok | B306: =AND($AS$53:$AS$271) -> TRUE | D306: every P2 row cell (t = 1 .. rem_m)
A307: P3_ok | B307: =SUMPRODUCT(--($N$53:$N$271<>0))=prem_rem_m -> TRUE | D307: the number of months with premium_pp <> 0 equals prem_rem_m
A308: P4_ok | B308: =AND($AT$53:$AT$271) -> TRUE | D308: every P4 row cell (t = 1 .. rem_m)
A309: P5_ok | B309: =AND($AV$52:$AV$270) -> TRUE | D309: every P5 row cell (t = 0 .. rem_m - 1)
A310: P6_ok | B310: =AND($AW$52:$AW$271) -> TRUE | D310: every P6 row cell (t = 0 .. rem_m)
A311: P8_ok | B311: =ABS(exits_sum-scale_count)<=0.000000001*MAX(ABS(exits_sum),ABS(scale_count),scale_count) -> TRUE | D311: exits_sum equals pols_if_init within tolerance (scale_count)
A312: P9_ok | B312: =ABS(pv_net_cf-pv_net_cf_t_sum)<=0.000000001*MAX(ABS(pv_net_cf),ABS(pv_net_cf_t_sum),scale_money) -> TRUE | D312: pv_net_cf equals pv_net_cf_t_sum within tolerance (scale_money)
...

Sheet P05
A1: Inputs (section 3.1, from section 13) and the run-level valuation_date (3.3), typed
A2: valuation_date | B2: 46388 | C2: 3.3 | D2: Date, first of a month (run-level input)
A3: policy_id | B3: P05 | C3: 3.1 | D3: string
A4: sex | B4: M | C4: 3.1 | D4: string, M or F
A5: birth_date | B5: 27502 | C5: 3.1 | D5: Date
A6: entry_date | B6: 43141 | C6: 3.1 | D6: Date
A7: maturity_date | B7: 46793 | C7: 3.1 | D7: Date
A8: prem_term_y | B8: 9 | C8: 3.1 | D8: Int (years)
A9: sum_assured | B9: 200000 | C9: 3.1 | D9: Money per policy
A10: premium | B10: 46.4 | C10: 3.1 | D10: Money per policy, monthly, in advance
A11: pols_if_init | B11: 1 | C11: 3.1 | D11: Count
A13: Derived constants (sections 3.2, 4.3 and 5), by formula
A14: age_at_entry | B14: =YEAR(entry_date)-YEAR(birth_date)-IF(OR(MONTH(entry_date)<MONTH(birth_date),AND(MONTH(entry_date)=MONTH(birth_date),DAY(entry_date)<DAY(birth_date))),1,0) -> 42 | C14: 5 | D14: Int (years)
A15: dur_m | B15: =12*(YEAR(valuation_date)-YEAR(entry_date))+(MONTH(valuation_date)-MONTH(entry_date))-IF(DAY(valuation_date)<DAY(entry_date),1,0) -> 106 | C15: 4.3 | D15: Int (months)
A16: term_m | B16: =12*(YEAR(maturity_date)-YEAR(entry_date))+(MONTH(maturity_date)-MONTH(entry_date))-IF(DAY(maturity_date)<DAY(entry_date),1,0) -> 120 | C16: 4.3 | D16: Int (months)
A17: rem_m | B17: =term_m-dur_m -> 14 | C17: 4.3 | D17: Int (months)
A18: prem_term_m | B18: =12*prem_term_y -> 108 | C18: 4.3 | D18: Int (months)
A19: prem_rem_m | B19: =MAX(prem_term_m-dur_m,0) -> 2 | C19: 4.3 | D19: Int (months)
A20: dur_y_last | B20: =INT((term_m-1)/12) -> 9 | C20: 4.3 | D20: Int (years)
A22: Basis constants (section 6), each in one cell
A23: i | B23: 0.04 | C23: 6 | D23: Rate[Annual]
A24: e | B24: 0.03 | C24: 6 | D24: Rate[Annual]
A25: i_m | B25: =(1+i)^(1/12)-1 -> 0.0032737398 | C25: 6 | D25: Rate[Monthly]
A26: v_m | B26: =(1+i)^(-1/12) -> 0.99673694 | C26: 6 | D26: factor
A27: e_m | B27: =(1+e)^(1/12)-1 -> 0.0024662698 | C27: 6 | D27: Rate[Monthly]
A28: A_M | B28: 0.0002 | C28: 6.1 | D28: Gompertz-Makeham A, sex M
A29: A_F | B29: 0.00015 | C29: 6.1 | D29: Gompertz-Makeham A, sex F
A30: B_M | B30: 1.7e-05 | C30: 6.1 | D30: Gompertz-Makeham B, sex M
A31: B_F | B31: 1.1e-05 | C31: 6.1 | D31: Gompertz-Makeham B, sex F
A32: c | B32: 1.1 | C32: 6.1 | D32: Gompertz-Makeham c (both sexes); defined name gm_c
A33: maint_base | B33: 5 | C33: 6.5 | D33: Money per policy, per month, time-0 prices
A34: claim_exp_base | B34: 250 | C34: 6.5 | D34: Money per policy (per death), time-0 prices
A36: Lapse table (section 6.2): key k = min(dur_y, 5)
A37: k | B37: lapse_table | D37: Prob, annual
A38: 0 | B38: 0.15
A39: 1 | B39: 0.1
A40: 2 | B40: 0.08
A41: 3 | B41: 0.06
A42: 4 | B42: 0.05
A43: 5 | B43: 0.04
A45: Commission table (section 6.6): key k = min(dur_y, 1)
A46: k | B46: comm_table | D46: Fraction
A47: 0 | B47: 0.2
A48: 1 | B48: 0.02
A50: Monthly block (sections 7.1 and 11.1): rows t = 0 .. rem_m, one column per quantity in the 7.1 order; the row-level check cells of section 12 follow the blank column
A51: t | B51: dur_y | C51: age | D51: q_ann | E51: q_m | F51: w_ann | G51: w_m | H51: comm_rate | I51: infl | J51: deaths | K51: lapses | L51: maturities | M51: pols_if | N51: premium_pp | O51: commission_pp | P51: maint_pp | Q51: claim_exp_pp | R51: premium_income | S51: commission | T51: maint_expense | U51: death_outgo | V51: claim_expense | W51: net_cf | X51: net_outgo | Y51: v | Z51: disc | AA51: pv_net_cf_t | AB51: pv_premiums_t | AC51: pv_commission_t | AD51: pv_maint_expense_t | AE51: pv_death_outgo_t | AF51: pv_claim_expense_t | AG51: reserve | AH51: reserve_pp | AI51: reserve_floored | AK51: H1 | AL51: H2 | AM51: H4_lhs | AN51: H4 | AO51: H5b_term | AP51: H5b_sum | AQ51: H5b | AR51: P1 | AS51: P2 | AT51: P4 | AU51: P5_rhs | AV51: P5 | AW51: P6 | AX51: P10
A52: 0 | I52: 1 | M52: =pols_if_init -> 1 | Z52: 1 | AG52: =(AG53+X53)*Y53 -> 537.96087 | AH52: =IF(M52>0,AG52/M52,0) -> 537.96087 | AI52: =IF(AG52>0,AG52,0) -> 537.96087 | AK52: =M52>=0 -> TRUE | AP52: =SUM(AO53:$AO$66) -> 537.96087 | AQ52: =ABS(AG52*Z52-AP52)<=0.000000001*MAX(ABS(AG52*Z52),ABS(AP52),scale_money) -> TRUE | AU52: =-(N53-O53)+v_m*(E53*(sum_assured+Q53)+P53+(1-E53)*(1-G53)*AH53) -> 537.96087 | AV52: =ABS(AH52-AU52)<=0.000000001*MAX(ABS(AH52),ABS(AU52),scale_pp) -> TRUE | AW52: =AND(AI52>=0,AI52>=AG52) -> TRUE
A53: 1 | B53: =MIN(INT((dur_m+A53-1)/12),dur_y_last) -> 8 | C53: =age_at_entry+B53 -> 50 | D53: =INDEX(mort_table,MATCH(C53,mort_age,0),MATCH(sex,mort_sex,0)) -> 0.0022912131 | E53: =IF(A53<=rem_m,1-(1-D53)^(1/12),0) -> 0.00019113522 | F53: =IF(A53<=prem_rem_m,INDEX(lapse_table,MATCH(MIN(B53,5),lapse_key,0)),0) -> 0.04 | G53: =1-(1-F53)^(1/12) -> 0.0033960532 | H53: =INDEX(comm_table,MATCH(MIN(B53,1),comm_key,0)) -> 0.02 | I53: =(1+e_m)^A53 -> 1.0024663 | J53: =M52*E53 -> 0.00019113522 | K53: =(M52-J53)*G53 -> 0.0033954041 | L53: =IF(A53=rem_m,M52-J53-K53,0) -> 0 | M53: =M52-J53-K53-L53 -> 0.99641346 | N53: =IF(A53<=prem_rem_m,premium,0) -> 46.4 | O53: =N53*H53 -> 0.928 | P53: =maint_base*I53 -> 5.0123313 | Q53: =claim_exp_base*I53 -> 250.61657 | R53: =M52*N53 -> 46.4 | S53: =R53*H53 -> 0.928 | T53: =M52*P53 -> 5.0123313 | U53: =J53*sum_assured -> 38.227045 | V53: =J53*Q53 -> 0.047901654 | W53: =R53-S53-T53-U53-V53 -> 2.1847221 | X53: =U53+V53+T53-(R53-S53)*(1+i_m) -> -2.3335856 | Y53: =v_m -> 0.99673694 | Z53: =v_m^A53 -> 0.99673694 | AA53: =(R53-S53)*Z52-(T53+U53+V53)*Z53 -> 2.3259709 | AB53: =R53*Z52 -> 46.4 | AC53: =S53*Z52 -> 0.928 | AD53: =T53*Z53 -> 4.9959758 | AE53: =U53*Z53 -> 38.102308 | AF53: =V53*Z53 -> 0.047745348 | AG53: =(AG54+X54)*Y54 -> 542.0556 | AH53: =IF(M53>0,AG53/M53,0) -> 544.0067 | AI53: =IF(AG53>0,AG53,0) -> 542.0556 | AK53: =AND(M53>=0,M53<=M52) -> TRUE | AL53: =AND(D53>=0,D53<=1,E53>=0,E53<=1,F53>=0,F53<=1,G53>=0,G53<=1,J53+K53+L53<=M52+0.000000001*scale_count) -> TRUE | AM53: =(AG52+R53-S53)*(1+i_m)-T53-U53-V53 -> 542.0556 | AN53: =ABS(AM53-AG53)<=0.000000001*MAX(ABS(AM53),ABS(AG53),scale_money) -> TRUE | AO53: =(U53+V53+T53)*Z53-(R53-S53)*Z52 -> -2.3259709 | AP53: =SUM(AO54:$AO$66) -> 540.28684 | AQ53: =ABS(AG53*Z53-AP53)<=0.000000001*MAX(ABS(AG53*Z53),ABS(AP53),scale_money) -> TRUE | AR53: =IF(A53<>rem_m,L53=0,L53=M52-J53-K53) -> TRUE | AS53: =IF(A53>prem_rem_m,AND(R53=0,S53=0,F53=0,G53=0,K53=0),R53=M52*premium) -> TRUE | AT53: =AND(C53>=18,C53<=120) -> TRUE | AU53: =-(N54-O54)+v_m*(E54*(sum_assured+Q54)+P54+(1-E54)*(1-G54)*AH54) -> 544.0067 | AV53: =ABS(AH53-AU53)<=0.000000001*MAX(ABS(AH53),ABS(AU53),scale_pp) -> TRUE | AW53: =AND(AI53>=0,AI53>=AG53) -> TRUE | AX53: =AND(U53=J53*sum_assured,R53=M52*N53,T53=M52*P53) -> TRUE
A54: 2 | B54: =MIN(INT((dur_m+A54-1)/12),dur_y_last) -> 8 | C54: =age_at_entry+B54 -> 50 | D54: =INDEX(mort_table,MATCH(C54,mort_age,0),MATCH(sex,mort_sex,0)) -> 0.0022912131 | E54: =IF(A54<=rem_m,1-(1-D54)^(1/12),0) -> 0.00019113522 | F54: =IF(A54<=prem_rem_m,INDEX(lapse_table,MATCH(MIN(B54,5),lapse_key,0)),0) -> 0.04 | G54: =1-(1-F54)^(1/12) -> 0.0033960532 | H54: =INDEX(comm_table,MATCH(MIN(B54,1),comm_key,0)) -> 0.02 | I54: =(1+e_m)^A54 -> 1.0049386 | J54: =M53*E54 -> 0.00019044971 | K54: =(M53-J54)*G54 -> 0.0033832263 | L54: =IF(A54=rem_m,M53-J54-K54,0) -> 0 | M54: =M53-J54-K54-L54 -> 0.99283978 | N54: =IF(A54<=prem_rem_m,premium,0) -> 46.4 | O54: =N54*H54 -> 0.928 | P54: =maint_base*I54 -> 5.0246931 | Q54: =claim_exp_base*I54 -> 251.23466 | R54: =M53*N54 -> 46.233585 | S54: =R54*H54 -> 0.92467169 | T54: =M53*P54 -> 5.0066719 | U54: =J54*sum_assured -> 38.089942 | V54: =J54*Q54 -> 0.047847567 | W54: =R54-S54-T54-U54-V54 -> 2.1644513 | X54: =U54+V54+T54-(R54-S54)*(1+i_m) -> -2.3127809 | Y54: =v_m -> 0.99673694 | Z54: =v_m^A54 -> 0.99348453 | AA54: =(R54-S54)*Z53-(T54+U54+V54)*Z54 -> 2.2977121 | AB54: =R54*Z53 -> 46.082722 | AC54: =S54*Z53 -> 0.92165443 | AD54: =T54*Z54 -> 4.974051 | AE54: =U54*Z54 -> 37.841768 | AF54: =V54*Z54 -> 0.047535818 | AG54: =(AG55+X55)*Y55 -> 546.14293 | AH54: =IF(M54>0,AG54/M54,0) -> 550.08163 | AI54: =IF(AG54>0,AG54,0) -> 546.14293 | AK54: =AND(M54>=0,M54<=M53) -> TRUE | AL54: =AND(D54>=0,D54<=1,E54>=0,E54<=1,F54>=0,F54<=1,G54>=0,G54<=1,J54+K54+L54<=M53+0.000000001*scale_count) -> TRUE | AM54: =(AG53+R54-S54)*(1+i_m)-T54-U54-V54 -> 546.14293 | AN54: =ABS(AM54-AG54)<=0.000000001*MAX(ABS(AM54),ABS(AG54),scale_money) -> TRUE | AO54: =(U54+V54+T54)*Z54-(R54-S54)*Z53 -> -2.2977121 | AP54: =SUM(AO55:$AO$66) -> 542.58455 | AQ54: =ABS(AG54*Z54-AP54)<=0.000000001*MAX(ABS(AG54*Z54),ABS(AP54),scale_money) -> TRUE | AR54: =IF(A54<>rem_m,L54=0,L54=M53-J54-K54) -> TRUE | AS54: =IF(A54>prem_rem_m,AND(R54=0,S54=0,F54=0,G54=0,K54=0),R54=M53*premium) -> TRUE | AT54: =AND(C54>=18,C54<=120,OR(B54-B53=0,B54-B53=1)) -> TRUE | AU54: =-(N55-O55)+v_m*(E55*(sum_assured+Q55)+P55+(1-E55)*(1-G55)*AH55) -> 550.08163 | AV54: =ABS(AH54-AU54)<=0.000000001*MAX(ABS(AH54),ABS(AU54),scale_pp) -> TRUE | AW54: =AND(AI54>=0,AI54>=AG54) -> TRUE | AX54: =AND(U54=J54*sum_assured,R54=M53*N54,T54=M53*P54) -> TRUE
A55: 3 | B55: =MIN(INT((dur_m+A55-1)/12),dur_y_last) -> 9 | C55: =age_at_entry+B55 -> 51 | D55: =INDEX(mort_table,MATCH(C55,mort_age,0),MATCH(sex,mort_sex,0)) -> 0.0025000957 | E55: =IF(A55<=rem_m,1-(1-D55)^(1/12),0) -> 0.00020858042 | F55: =IF(A55<=prem_rem_m,INDEX(lapse_table,MATCH(MIN(B55,5),lapse_key,0)),0) -> 0 | G55: =1-(1-F55)^(1/12) -> 0 | H55: =INDEX(comm_table,MATCH(MIN(B55,1),comm_key,0)) -> 0.02 | I55: =(1+e_m)^A55 -> 1.0074171 | J55: =M54*E55 -> 0.00020708694 | K55: =(M54-J55)*G55 -> 0 | L55: =IF(A55=rem_m,M54-J55-K55,0) -> 0 | M55: =M54-J55-K55-L55 -> 0.9926327 | N55: =IF(A55<=prem_rem_m,premium,0) -> 0 | O55: =N55*H55 -> 0 | P55: =maint_base*I55 -> 5.0370854 | Q55: =claim_exp_base*I55 -> 251.85427 | R55: =M54*N55 -> 0 | S55: =R55*H55 -> 0 | T55: =M54*P55 -> 5.0010187 | U55: =J55*sum_assured -> 41.417388 | V55: =J55*Q55 -> 0.05215573 | W55: =R55-S55-T55-U55-V55 -> -46.470562 | X55: =U55+V55+T55-(R55-S55)*(1+i_m) -> 46.470562 | Y55: =v_m -> 0.99673694 | Z55: =v_m^A55 -> 0.99024274 | AA55: =(R55-S55)*Z54-(T55+U55+V55)*Z55 -> -46.017137 | AB55: =R55*Z54 -> 0 | AC55: =S55*Z54 -> 0 | AD55: =T55*Z55 -> 4.9522225 | AE55: =U55*Z55 -> 41.013267 | AF55: =V55*Z55 -> 0.051646832 | AG55: =(AG56+X56)*Y56 -> 501.46029 | AH55: =IF(M55>0,AG55/M55,0) -> 505.18212 | AI55: =IF(AG55>0,AG55,0) -> 501.46029 | AK55: =AND(M55>=0,M55<=M54) -> TRUE | AL55: =AND(D55>=0,D55<=1,E55>=0,E55<=1,F55>=0,F55<=1,G55>=0,G55<=1,J55+K55+L55<=M54+0.000000001*scale_count) -> TRUE | AM55: =(AG54+R55-S55)*(1+i_m)-T55-U55-V55 -> 501.46029 | AN55: =ABS(AM55-AG55)<=0.000000001*MAX(ABS(AM55),ABS(AG55),scale_money) -> TRUE | AO55: =(U55+V55+T55)*Z55-(R55-S55)*Z54 -> 46.017137 | AP55: =SUM(AO56:$AO$66) -> 496.56741 | AQ55: =ABS(AG55*Z55-AP55)<=0.000000001*MAX(ABS(AG55*Z55),ABS(AP55),scale_money) -> TRUE | AR55: =IF(A55<>rem_m,L55=0,L55=M54-J55-K55) -> TRUE | AS55: =IF(A55>prem_rem_m,AND(R55=0,S55=0,F55=0,G55=0,K55=0),R55=M54*premium) -> TRUE | AT55: =AND(C55>=18,C55<=120,OR(B55-B54=0,B55-B54=1)) -> TRUE | AU55: =-(N56-O56)+v_m*(E56*(sum_assured+Q56)+P56+(1-E56)*(1-G56)*AH56) -> 505.18212 | AV55: =ABS(AH55-AU55)<=0.000000001*MAX(ABS(AH55),ABS(AU55),scale_pp) -> TRUE | AW55: =AND(AI55>=0,AI55>=AG55) -> TRUE | AX55: =AND(U55=J55*sum_assured,R55=M54*N55,T55=M54*P55) -> TRUE
A56: 4 | B56: =MIN(INT((dur_m+A56-1)/12),dur_y_last) -> 9 | C56: =age_at_entry+B56 -> 51 | D56: =INDEX(mort_table,MATCH(C56,mort_age,0),MATCH(sex,mort_sex,0)) -> 0.0025000957 | E56: =IF(A56<=rem_m,1-(1-D56)^(1/12),0) -> 0.00020858042 | F56: =IF(A56<=prem_rem_m,INDEX(lapse_table,MATCH(MIN(B56,5),lapse_key,0)),0) -> 0 | G56: =1-(1-F56)^(1/12) -> 0 | H56: =INDEX(comm_table,MATCH(MIN(B56,1),comm_key,0)) -> 0.02 | I56: =(1+e_m)^A56 -> 1.0099016 | J56: =M55*E56 -> 0.00020704375 | K56: =(M55-J56)*G56 -> 0 | L56: =IF(A56=rem_m,M55-J56-K56,0) -> 0 | M56: =M55-J56-K56-L56 -> 0.99242565 | N56: =IF(A56<=prem_rem_m,premium,0) -> 0 | O56: =N56*H56 -> 0 | P56: =maint_base*I56 -> 5.0495082 | Q56: =claim_exp_base*I56 -> 252.47541 | R56: =M55*N56 -> 0 | S56: =R56*H56 -> 0 | T56: =M55*P56 -> 5.0123069 | U56: =J56*sum_assured -> 41.408749 | V56: =J56*Q56 -> 0.052273454 | W56: =R56-S56-T56-U56-V56 -> -46.473329 | X56: =U56+V56+T56-(R56-S56)*(1+i_m) -> 46.473329 | Y56: =v_m -> 0.99673694 | Z56: =v_m^A56 -> 0.98701152 | AA56: =(R56-S56)*Z55-(T56+U56+V56)*Z56 -> -45.869711 | AB56: =R56*Z55 -> 0 | AC56: =S56*Z55 -> 0 | AD56: =T56*Z56 -> 4.9472047 | AE56: =U56*Z56 -> 40.870912 | AF56: =V56*Z56 -> 0.051594501 | AG56: =(AG57+X57)*Y57 -> 456.62861 | AH56: =IF(M56>0,AG56/M56,0) -> 460.11367 | AI56: =IF(AG56>0,AG56,0) -> 456.62861 | AK56: =AND(M56>=0,M56<=M55) -> TRUE | AL56: =AND(D56>=0,D56<=1,E56>=0,E56<=1,F56>=0,F56<=1,G56>=0,G56<=1,J56+K56+L56<=M55+0.000000001*scale_count) -> TRUE | AM56: =(AG55+R56-S56)*(1+i_m)-T56-U56-V56 -> 456.62861 | AN56: =ABS(AM56-AG56)<=0.000000001*MAX(ABS(AM56),ABS(AG56),scale_money) -> TRUE | AO56: =(U56+V56+T56)*Z56-(R56-S56)*Z55 -> 45.869711 | AP56: =SUM(AO57:$AO$66) -> 450.6977 | AQ56: =ABS(AG56*Z56-AP56)<=0.000000001*MAX(ABS(AG56*Z56),ABS(AP56),scale_money) -> TRUE | AR56: =IF(A56<>rem_m,L56=0,L56=M55-J56-K56) -> TRUE | AS56: =IF(A56>prem_rem_m,AND(R56=0,S56=0,F56=0,G56=0,K56=0),R56=M55*premium) -> TRUE | AT56: =AND(C56>=18,C56<=120,OR(B56-B55=0,B56-B55=1)) -> TRUE | AU56: =-(N57-O57)+v_m*(E57*(sum_assured+Q57)+P57+(1-E57)*(1-G57)*AH57) -> 460.11367 | AV56: =ABS(AH56-AU56)<=0.000000001*MAX(ABS(AH56),ABS(AU56),scale_pp) -> TRUE | AW56: =AND(AI56>=0,AI56>=AG56) -> TRUE | AX56: =AND(U56=J56*sum_assured,R56=M55*N56,T56=M55*P56) -> TRUE
A57: 5 | B57: =MIN(INT((dur_m+A57-1)/12),dur_y_last) -> 9 | C57: =age_at_entry+B57 -> 51 | D57: =INDEX(mort_table,MATCH(C57,mort_age,0),MATCH(sex,mort_sex,0)) -> 0.0025000957 | E57: =IF(A57<=rem_m,1-(1-D57)^(1/12),0) -> 0.00020858042 | F57: =IF(A57<=prem_rem_m,INDEX(lapse_table,MATCH(MIN(B57,5),lapse_key,0)),0) -> 0 | G57: =1-(1-F57)^(1/12) -> 0 | H57: =INDEX(comm_table,MATCH(MIN(B57,1),comm_key,0)) -> 0.02 | I57: =(1+e_m)^A57 -> 1.0123923 | J57: =M56*E57 -> 0.00020700056 | K57: =(M56-J57)*G57 -> 0 | L57: =IF(A57=rem_m,M56-J57-K57,0) -> 0 | M57: =M56-J57-K57-L57 -> 0.99221865 | N57: =IF(A57<=prem_rem_m,premium,0) -> 0 | O57: =N57*H57 -> 0 | P57: =maint_base*I57 -> 5.0619616 | Q57: =claim_exp_base*I57 -> 253.09808 | R57: =M56*N57 -> 0 | S57: =R57*H57 -> 0 | T57: =M56*P57 -> 5.0236206 | U57: =J57*sum_assured -> 41.400112 | V57: =J57*Q57 -> 0.052391444 | W57: =R57-S57-T57-U57-V57 -> -46.476124 | X57: =U57+V57+T57-(R57-S57)*(1+i_m) -> 46.476124 | Y57: =v_m -> 0.99673694 | Z57: =v_m^A57 -> 0.98379084 | AA57: =(R57-S57)*Z56-(T57+U57+V57)*Z57 -> -45.722785 | AB57: =R57*Z56 -> 0 | AC57: =S57*Z56 -> 0 | AD57: =T57*Z57 -> 4.9421919 | AE57: =U57*Z57 -> 40.729051 | AF57: =V57*Z57 -> 0.051542223 | AG57: =(AG58+X58)*Y58 -> 411.64737 | AH57: =IF(M57>0,AG57/M57,0) -> 414.87566 | AI57: =IF(AG57>0,AG57,0) -> 411.64737 | AK57: =AND(M57>=0,M57<=M56) -> TRUE | AL57: =AND(D57>=0,D57<=1,E57>=0,E57<=1,F57>=0,F57<=1,G57>=0,G57<=1,J57+K57+L57<=M56+0.000000001*scale_count) -> TRUE | AM57: =(AG56+R57-S57)*(1+i_m)-T57-U57-V57 -> 411.64737 | AN57: =ABS(AM57-AG57)<=0.000000001*MAX(ABS(AM57),ABS(AG57),scale_money) -> TRUE | AO57: =(U57+V57+T57)*Z57-(R57-S57)*Z56 -> 45.722785 | AP57: =SUM(AO58:$AO$66) -> 404.97492 | AQ57: =ABS(AG57*Z57-AP57)<=0.000000001*MAX(ABS(AG57*Z57),ABS(AP57),scale_money) -> TRUE | AR57: =IF(A57<>rem_m,L57=0,L57=M56-J57-K57) -> TRUE | AS57: =IF(A57>prem_rem_m,AND(R57=0,S57=0,F57=0,G57=0,K57=0),R57=M56*premium) -> TRUE | AT57: =AND(C57>=18,C57<=120,OR(B57-B56=0,B57-B56=1)) -> TRUE | AU57: =-(N58-O58)+v_m*(E58*(sum_assured+Q58)+P58+(1-E58)*(1-G58)*AH58) -> 414.87566 | AV57: =ABS(AH57-AU57)<=0.000000001*MAX(ABS(AH57),ABS(AU57),scale_pp) -> TRUE | AW57: =AND(AI57>=0,AI57>=AG57) -> TRUE | AX57: =AND(U57=J57*sum_assured,R57=M56*N57,T57=M56*P57) -> TRUE
A58: 6 | B58: =MIN(INT((dur_m+A58-1)/12),dur_y_last) -> 9 | C58: =age_at_entry+B58 -> 51 | D58: =INDEX(mort_table,MATCH(C58,mort_age,0),MATCH(sex,mort_sex,0)) -> 0.0025000957 | E58: =IF(A58<=rem_m,1-(1-D58)^(1/12),0) -> 0.00020858042 | F58: =IF(A58<=prem_rem_m,INDEX(lapse_table,MATCH(MIN(B58,5),lapse_key,0)),0) -> 0 | G58: =1-(1-F58)^(1/12) -> 0 | H58: =INDEX(comm_table,MATCH(MIN(B58,1),comm_key,0)) -> 0.02 | I58: =(1+e_m)^A58 -> 1.0148892 | J58: =M57*E58 -> 0.00020695738 | K58: =(M57-J58)*G58 -> 0 | L58: =IF(A58=rem_m,M57-J58-K58,0) -> 0 | M58: =M57-J58-K58-L58 -> 0.9920117 | N58: =IF(A58<=prem_rem_m,premium,0) -> 0 | O58: =N58*H58 -> 0 | P58: =maint_base*I58 -> 5.0744458 | Q58: =claim_exp_base*I58 -> 253.72229 | R58: =M57*N58 -> 0 | S58: =R58*H58 -> 0 | T58: =M57*P58 -> 5.0349598 | U58: =J58*sum_assured -> 41.391477 | V58: =J58*Q58 -> 0.052509701 | W58: =R58-S58-T58-U58-V58 -> -46.478946 | X58: =U58+V58+T58-(R58-S58)*(1+i_m) -> 46.478946 | Y58: =v_m -> 0.99673694 | Z58: =v_m^A58 -> 0.98058068 | AA58: =(R58-S58)*Z57-(T58+U58+V58)*Z58 -> -45.576356 | AB58: =R58*Z57 -> 0 | AC58: =S58*Z57 -> 0 | AD58: =T58*Z58 -> 4.9371842 | AE58: =U58*Z58 -> 40.587682 | AF58: =V58*Z58 -> 0.051489998 | AG58: =(AG59+X59)*Y59 -> 366.51605 | AH58: =IF(M58>0,AG58/M58,0) -> 369.46747 | AI58: =IF(AG58>0,AG58,0) -> 366.51605 | AK58: =AND(M58>=0,M58<=M57) -> TRUE | AL58: =AND(D58>=0,D58<=1,E58>=0,E58<=1,F58>=0,F58<=1,G58>=0,G58<=1,J58+K58+L58<=M57+0.000000001*scale_count) -> TRUE | AM58: =(AG57+R58-S58)*(1+i_m)-T58-U58-V58 -> 366.51605 | AN58: =ABS(AM58-AG58)<=0.000000001*MAX(ABS(AM58),ABS(AG58),scale_money) -> TRUE | AO58: =(U58+V58+T58)*Z58-(R58-S58)*Z57 -> 45.576356 | AP58: =SUM(AO59:$AO$66) -> 359.39856 | AQ58: =ABS(AG58*Z58-AP58)<=0.000000001*MAX(ABS(AG58*Z58),ABS(AP58),scale_money) -> TRUE | AR58: =IF(A58<>rem_m,L58=0,L58=M57-J58-K58) -> TRUE | AS58: =IF(A58>prem_rem_m,AND(R58=0,S58=0,F58=0,G58=0,K58=0),R58=M57*premium) -> TRUE | AT58: =AND(C58>=18,C58<=120,OR(B58-B57=0,B58-B57=1)) -> TRUE | AU58: =-(N59-O59)+v_m*(E59*(sum_assured+Q59)+P59+(1-E59)*(1-G59)*AH59) -> 369.46747 | AV58: =ABS(AH58-AU58)<=0.000000001*MAX(ABS(AH58),ABS(AU58),scale_pp) -> TRUE | AW58: =AND(AI58>=0,AI58>=AG58) -> TRUE | AX58: =AND(U58=J58*sum_assured,R58=M57*N58,T58=M57*P58) -> TRUE
A59: 7 | B59: =MIN(INT((dur_m+A59-1)/12),dur_y_last) -> 9 | C59: =age_at_entry+B59 -> 51 | D59: =INDEX(mort_table,MATCH(C59,mort_age,0),MATCH(sex,mort_sex,0)) -> 0.0025000957 | E59: =IF(A59<=rem_m,1-(1-D59)^(1/12),0) -> 0.00020858042 | F59: =IF(A59<=prem_rem_m,INDEX(lapse_table,MATCH(MIN(B59,5),lapse_key,0)),0) -> 0 | G59: =1-(1-F59)^(1/12) -> 0 | H59: =INDEX(comm_table,MATCH(MIN(B59,1),comm_key,0)) -> 0.02 | I59: =(1+e_m)^A59 -> 1.0173921 | J59: =M58*E59 -> 0.00020691422 | K59: =(M58-J59)*G59 -> 0 | L59: =IF(A59=rem_m,M58-J59-K59,0) -> 0 | M59: =M58-J59-K59-L59 -> 0.99180478 | N59: =IF(A59<=prem_rem_m,premium,0) -> 0 | O59: =N59*H59 -> 0 | P59: =maint_base*I59 -> 5.0869607 | Q59: =claim_exp_base*I59 -> 254.34804 | R59: =M58*N59 -> 0 | S59: =R59*H59 -> 0 | T59: =M58*P59 -> 5.0463245 | U59: =J59*sum_assured -> 41.382843 | V59: =J59*Q59 -> 0.052628225 | W59: =R59-S59-T59-U59-V59 -> -46.481796 | X59: =U59+V59+T59-(R59-S59)*(1+i_m) -> 46.481796 | Y59: =v_m -> 0.99673694 | Z59: =v_m^A59 -> 0.97738098 | AA59: =(R59-S59)*Z58-(T59+U59+V59)*Z59 -> -45.430424 | AB59: =R59*Z58 -> 0 | AC59: =S59*Z58 -> 0 | AD59: =T59*Z59 -> 4.9321817 | AE59: =U59*Z59 -> 40.446804 | AF59: =V59*Z59 -> 0.051437826 | AG59: =(AG60+X60)*Y60 -> 321.23414 | AH59: =IF(M59>0,AG59/M59,0) -> 323.88847 | AI59: =IF(AG59>0,AG59,0) -> 321.23414 | AK59: =AND(M59>=0,M59<=M58) -> TRUE | AL59: =AND(D59>=0,D59<=1,E59>=0,E59<=1,F59>=0,F59<=1,G59>=0,G59<=1,J59+K59+L59<=M58+0.000000001*scale_count) -> TRUE | AM59: =(AG58+R59-S59)*(1+i_m)-T59-U59-V59 -> 321.23414 | AN59: =ABS(AM59-AG59)<=0.000000001*MAX(ABS(AM59),ABS(AG59),scale_money) -> TRUE | AO59: =(U59+V59+T59)*Z59-(R59-S59)*Z58 -> 45.430424 | AP59: =SUM(AO60:$AO$66) -> 313.96814 | AQ59: =ABS(AG59*Z59-AP59)<=0.000000001*MAX(ABS(AG59*Z59),ABS(AP59),scale_money) -> TRUE | AR59: =IF(A59<>rem_m,L59=0,L59=M58-J59-K59) -> TRUE | AS59: =IF(A59>prem_rem_m,AND(R59=0,S59=0,F59=0,G59=0,K59=0),R59=M58*premium) -> TRUE | AT59: =AND(C59>=18,C59<=120,OR(B59-B58=0,B59-B58=1)) -> TRUE | AU59: =-(N60-O60)+v_m*(E60*(sum_assured+Q60)+P60+(1-E60)*(1-G60)*AH60) -> 323.88847 | AV59: =ABS(AH59-AU59)<=0.000000001*MAX(ABS(AH59),ABS(AU59),scale_pp) -> TRUE | AW59: =AND(AI59>=0,AI59>=AG59) -> TRUE | AX59: =AND(U59=J59*sum_assured,R59=M58*N59,T59=M58*P59) -> TRUE
A60: 8 | B60: =MIN(INT((dur_m+A60-1)/12),dur_y_last) -> 9 | C60: =age_at_entry+B60 -> 51 | D60: =INDEX(mort_table,MATCH(C60,mort_age,0),MATCH(sex,mort_sex,0)) -> 0.0025000957 | E60: =IF(A60<=rem_m,1-(1-D60)^(1/12),0) -> 0.00020858042 | F60: =IF(A60<=prem_rem_m,INDEX(lapse_table,MATCH(MIN(B60,5),lapse_key,0)),0) -> 0 | G60: =1-(1-F60)^(1/12) -> 0 | H60: =INDEX(comm_table,MATCH(MIN(B60,1),comm_key,0)) -> 0.02 | I60: =(1+e_m)^A60 -> 1.0199013 | J60: =M59*E60 -> 0.00020687106 | K60: =(M59-J60)*G60 -> 0 | L60: =IF(A60=rem_m,M59-J60-K60,0) -> 0 | M60: =M59-J60-K60-L60 -> 0.99159791 | N60: =IF(A60<=prem_rem_m,premium,0) -> 0 | O60: =N60*H60 -> 0 | P60: =maint_base*I60 -> 5.0995066 | Q60: =claim_exp_base*I60 -> 254.97533 | R60: =M59*N60 -> 0 | S60: =R60*H60 -> 0 | T60: =M59*P60 -> 5.057715 | U60: =J60*sum_assured -> 41.374212 | V60: =J60*Q60 -> 0.052747016 | W60: =R60-S60-T60-U60-V60 -> -46.484674 | X60: =U60+V60+T60-(R60-S60)*(1+i_m) -> 46.484674 | Y60: =v_m -> 0.99673694 | Z60: =v_m^A60 -> 0.97419173 | AA60: =(R60-S60)*Z59-(T60+U60+V60)*Z60 -> -45.284985 | AB60: =R60*Z59 -> 0 | AC60: =S60*Z59 -> 0 | AD60: =T60*Z60 -> 4.9271841 | AE60: =U60*Z60 -> 40.306415 | AF60: =V60*Z60 -> 0.051385707 | AG60: =(AG61+X61)*Y61 -> 275.8011 | AH60: =IF(M60>0,AG60/M60,0) -> 278.13804 | AI60: =IF(AG60>0,AG60,0) -> 275.8011 | AK60: =AND(M60>=0,M60<=M59) -> TRUE | AL60: =AND(D60>=0,D60<=1,E60>=0,E60<=1,F60>=0,F60<=1,G60>=0,G60<=1,J60+K60+L60<=M59+0.000000001*scale_count) -> TRUE | AM60: =(AG59+R60-S60)*(1+i_m)-T60-U60-V60 -> 275.8011 | AN60: =ABS(AM60-AG60)<=0.000000001*MAX(ABS(AM60),ABS(AG60),scale_money) -> TRUE | AO60: =(U60+V60+T60)*Z60-(R60-S60)*Z59 -> 45.284985 | AP60: =SUM(AO61:$AO$66) -> 268.68315 | AQ60: =ABS(AG60*Z60-AP60)<=0.000000001*MAX(ABS(AG60*Z60),ABS(AP60),scale_money) -> TRUE | AR60: =IF(A60<>rem_m,L60=0,L60=M59-J60-K60) -> TRUE | AS60: =IF(A60>prem_rem_m,AND(R60=0,S60=0,F60=0,G60=0,K60=0),R60=M59*premium) -> TRUE | AT60: =AND(C60>=18,C60<=120,OR(B60-B59=0,B60-B59=1)) -> TRUE | AU60: =-(N61-O61)+v_m*(E61*(sum_assured+Q61)+P61+(1-E61)*(1-G61)*AH61) -> 278.13804 | AV60: =ABS(AH60-AU60)<=0.000000001*MAX(ABS(AH60),ABS(AU60),scale_pp) -> TRUE | AW60: =AND(AI60>=0,AI60>=AG60) -> TRUE | AX60: =AND(U60=J60*sum_assured,R60=M59*N60,T60=M59*P60) -> TRUE
A61: 9 | B61: =MIN(INT((dur_m+A61-1)/12),dur_y_last) -> 9 | C61: =age_at_entry+B61 -> 51 | D61: =INDEX(mort_table,MATCH(C61,mort_age,0),MATCH(sex,mort_sex,0)) -> 0.0025000957 | E61: =IF(A61<=rem_m,1-(1-D61)^(1/12),0) -> 0.00020858042 | F61: =IF(A61<=prem_rem_m,INDEX(lapse_table,MATCH(MIN(B61,5),lapse_key,0)),0) -> 0 | G61: =1-(1-F61)^(1/12) -> 0 | H61: =INDEX(comm_table,MATCH(MIN(B61,1),comm_key,0)) -> 0.02 | I61: =(1+e_m)^A61 -> 1.0224167 | J61: =M60*E61 -> 0.00020682791 | K61: =(M60-J61)*G61 -> 0 | L61: =IF(A61=rem_m,M60-J61-K61,0) -> 0 | M61: =M60-J61-K61-L61 -> 0.99139108 | N61: =IF(A61<=prem_rem_m,premium,0) -> 0 | O61: =N61*H61 -> 0 | P61: =maint_base*I61 -> 5.1120833 | Q61: =claim_exp_base*I61 -> 255.60417 | R61: =M60*N61 -> 0 | S61: =R61*H61 -> 0 | T61: =M60*P61 -> 5.0691311 | U61: =J61*sum_assured -> 41.365582 | V61: =J61*Q61 -> 0.052866075 | W61: =R61-S61-T61-U61-V61 -> -46.487579 | X61: =U61+V61+T61-(R61-S61)*(1+i_m) -> 46.487579 | Y61: =v_m -> 0.99673694 | Z61: =v_m^A61 -> 0.97101289 | AA61: =(R61-S61)*Z60-(T61+U61+V61)*Z61 -> -45.140038 | AB61: =R61*Z60 -> 0 | AC61: =S61*Z60 -> 0 | AD61: =T61*Z61 -> 4.9221917 | AE61: =U61*Z61 -> 40.166513 | AF61: =V61*Z61 -> 0.05133364 | AG61: =(AG62+X62)*Y62 -> 230.21642 | AH61: =IF(M61>0,AG61/M61,0) -> 232.21555 | AI61: =IF(AG61>0,AG61,0) -> 230.21642 | AK61: =AND(M61>=0,M61<=M60) -> TRUE | AL61: =AND(D61>=0,D61<=1,E61>=0,E61<=1,F61>=0,F61<=1,G61>=0,G61<=1,J61+K61+L61<=M60+0.000000001*scale_count) -> TRUE | AM61: =(AG60+R61-S61)*(1+i_m)-T61-U61-V61 -> 230.21642 | AN61: =ABS(AM61-AG61)<=0.000000001*MAX(ABS(AM61),ABS(AG61),scale_money) -> TRUE | AO61: =(U61+V61+T61)*Z61-(R61-S61)*Z60 -> 45.140038 | AP61: =SUM(AO62:$AO$66) -> 223.54311 | AQ61: =ABS(AG61*Z61-AP61)<=0.000000001*MAX(ABS(AG61*Z61),ABS(AP61),scale_money) -> TRUE | AR61: =IF(A61<>rem_m,L61=0,L61=M60-J61-K61) -> TRUE | AS61: =IF(A61>prem_rem_m,AND(R61=0,S61=0,F61=0,G61=0,K61=0),R61=M60*premium) -> TRUE | AT61: =AND(C61>=18,C61<=120,OR(B61-B60=0,B61-B60=1)) -> TRUE | AU61: =-(N62-O62)+v_m*(E62*(sum_assured+Q62)+P62+(1-E62)*(1-G62)*AH62) -> 232.21555 | AV61: =ABS(AH61-AU61)<=0.000000001*MAX(ABS(AH61),ABS(AU61),scale_pp) -> TRUE | AW61: =AND(AI61>=0,AI61>=AG61) -> TRUE | AX61: =AND(U61=J61*sum_assured,R61=M60*N61,T61=M60*P61) -> TRUE
A62: 10 | B62: =MIN(INT((dur_m+A62-1)/12),dur_y_last) -> 9 | C62: =age_at_entry+B62 -> 51 | D62: =INDEX(mort_table,MATCH(C62,mort_age,0),MATCH(sex,mort_sex,0)) -> 0.0025000957 | E62: =IF(A62<=rem_m,1-(1-D62)^(1/12),0) -> 0.00020858042 | F62: =IF(A62<=prem_rem_m,INDEX(lapse_table,MATCH(MIN(B62,5),lapse_key,0)),0) -> 0 | G62: =1-(1-F62)^(1/12) -> 0 | H62: =INDEX(comm_table,MATCH(MIN(B62,1),comm_key,0)) -> 0.02 | I62: =(1+e_m)^A62 -> 1.0249382 | J62: =M61*E62 -> 0.00020678477 | K62: =(M61-J62)*G62 -> 0 | L62: =IF(A62=rem_m,M61-J62-K62,0) -> 0 | M62: =M61-J62-K62-L62 -> 0.9911843 | N62: =IF(A62<=prem_rem_m,premium,0) -> 0 | O62: =N62*H62 -> 0 | P62: =maint_base*I62 -> 5.1246911 | Q62: =claim_exp_base*I62 -> 256.23455 | R62: =M61*N62 -> 0 | S62: =R62*H62 -> 0 | T62: =M61*P62 -> 5.080573 | U62: =J62*sum_assured -> 41.356954 | V62: =J62*Q62 -> 0.052985403 | W62: =R62-S62-T62-U62-V62 -> -46.490512 | X62: =U62+V62+T62-(R62-S62)*(1+i_m) -> 46.490512 | Y62: =v_m -> 0.99673694 | Z62: =v_m^A62 -> 0.96784442 | AA62: =(R62-S62)*Z61-(T62+U62+V62)*Z62 -> -44.995583 | AB62: =R62*Z61 -> 0 | AC62: =S62*Z61 -> 0 | AD62: =T62*Z62 -> 4.9172043 | AE62: =U62*Z62 -> 40.027097 | AF62: =V62*Z62 -> 0.051281627 | AG62: =(AG63+X63)*Y63 -> 184.47958 | AH62: =IF(M62>0,AG62/M62,0) -> 186.12036 | AI62: =IF(AG62>0,AG62,0) -> 184.47958 | AK62: =AND(M62>=0,M62<=M61) -> TRUE | AL62: =AND(D62>=0,D62<=1,E62>=0,E62<=1,F62>=0,F62<=1,G62>=0,G62<=1,J62+K62+L62<=M61+0.000000001*scale_count) -> TRUE | AM62: =(AG61+R62-S62)*(1+i_m)-T62-U62-V62 -> 184.47958 | AN62: =ABS(AM62-AG62)<=0.000000001*MAX(ABS(AM62),ABS(AG62),scale_money) -> TRUE | AO62: =(U62+V62+T62)*Z62-(R62-S62)*Z61 -> 44.995583 | AP62: =SUM(AO63:$AO$66) -> 178.54753 | AQ62: =ABS(AG62*Z62-AP62)<=0.000000001*MAX(ABS(AG62*Z62),ABS(AP62),scale_money) -> TRUE | AR62: =IF(A62<>rem_m,L62=0,L62=M61-J62-K62) -> TRUE | AS62: =IF(A62>prem_rem_m,AND(R62=0,S62=0,F62=0,G62=0,K62=0),R62=M61*premium) -> TRUE | AT62: =AND(C62>=18,C62<=120,OR(B62-B61=0,B62-B61=1)) -> TRUE | AU62: =-(N63-O63)+v_m*(E63*(sum_assured+Q63)+P63+(1-E63)*(1-G63)*AH63) -> 186.12036 | AV62: =ABS(AH62-AU62)<=0.000000001*MAX(ABS(AH62),ABS(AU62),scale_pp) -> TRUE | AW62: =AND(AI62>=0,AI62>=AG62) -> TRUE | AX62: =AND(U62=J62*sum_assured,R62=M61*N62,T62=M61*P62) -> TRUE
A63: 11 | B63: =MIN(INT((dur_m+A63-1)/12),dur_y_last) -> 9 | C63: =age_at_entry+B63 -> 51 | D63: =INDEX(mort_table,MATCH(C63,mort_age,0),MATCH(sex,mort_sex,0)) -> 0.0025000957 | E63: =IF(A63<=rem_m,1-(1-D63)^(1/12),0) -> 0.00020858042 | F63: =IF(A63<=prem_rem_m,INDEX(lapse_table,MATCH(MIN(B63,5),lapse_key,0)),0) -> 0 | G63: =1-(1-F63)^(1/12) -> 0 | H63: =INDEX(comm_table,MATCH(MIN(B63,1),comm_key,0)) -> 0.02 | I63: =(1+e_m)^A63 -> 1.027466 | J63: =M62*E63 -> 0.00020674164 | K63: =(M62-J63)*G63 -> 0 | L63: =IF(A63=rem_m,M62-J63-K63,0) -> 0 | M63: =M62-J63-K63-L63 -> 0.99097756 | N63: =IF(A63<=prem_rem_m,premium,0) -> 0 | O63: =N63*H63 -> 0 | P63: =maint_base*I63 -> 5.13733 | Q63: =claim_exp_base*I63 -> 256.8665 | R63: =M62*N63 -> 0 | S63: =R63*H63 -> 0 | T63: =M62*P63 -> 5.0920408 | U63: =J63*sum_assured -> 41.348327 | V63: =J63*Q63 -> 0.053105 | W63: =R63-S63-T63-U63-V63 -> -46.493473 | X63: =U63+V63+T63-(R63-S63)*(1+i_m) -> 46.493473 | Y63: =v_m -> 0.99673694 | Z63: =v_m^A63 -> 0.96468629 | AA63: =(R63-S63)*Z62-(T63+U63+V63)*Z63 -> -44.851616 | AB63: =R63*Z62 -> 0 | AC63: =S63*Z62 -> 0 | AD63: =T63*Z63 -> 4.9122219 | AE63: =U63*Z63 -> 39.888165 | AF63: =V63*Z63 -> 0.051229666 | AG63: =(AG64+X64)*Y64 -> 138.59004 | AH63: =IF(M63>0,AG63/M63,0) -> 139.85185 | AI63: =IF(AG63>0,AG63,0) -> 138.59004 | AK63: =AND(M63>=0,M63<=M62) -> TRUE | AL63: =AND(D63>=0,D63<=1,E63>=0,E63<=1,F63>=0,F63<=1,G63>=0,G63<=1,J63+K63+L63<=M62+0.000000001*scale_count) -> TRUE | AM63: =(AG62+R63-S63)*(1+i_m)-T63-U63-V63 -> 138.59004 | AN63: =ABS(AM63-AG63)<=0.000000001*MAX(ABS(AM63),ABS(AG63),scale_money) -> TRUE | AO63: =(U63+V63+T63)*Z63-(R63-S63)*Z62 -> 44.851616 | AP63: =SUM(AO64:$AO$66) -> 133.69591 | AQ63: =ABS(AG63*Z63-AP63)<=0.000000001*MAX(ABS(AG63*Z63),ABS(AP63),scale_money) -> TRUE | AR63: =IF(A63<>rem_m,L63=0,L63=M62-J63-K63) -> TRUE | AS63: =IF(A63>prem_rem_m,AND(R63=0,S63=0,F63=0,G63=0,K63=0),R63=M62*premium) -> TRUE | AT63: =AND(C63>=18,C63<=120,OR(B63-B62=0,B63-B62=1)) -> TRUE | AU63: =-(N64-O64)+v_m*(E64*(sum_assured+Q64)+P64+(1-E64)*(1-G64)*AH64) -> 139.85185 | AV63: =ABS(AH63-AU63)<=0.000000001*MAX(ABS(AH63),ABS(AU63),scale_pp) -> TRUE | AW63: =AND(AI63>=0,AI63>=AG63) -> TRUE | AX63: =AND(U63=J63*sum_assured,R63=M62*N63,T63=M62*P63) -> TRUE
A64: 12 | B64: =MIN(INT((dur_m+A64-1)/12),dur_y_last) -> 9 | C64: =age_at_entry+B64 -> 51 | D64: =INDEX(mort_table,MATCH(C64,mort_age,0),MATCH(sex,mort_sex,0)) -> 0.0025000957 | E64: =IF(A64<=rem_m,1-(1-D64)^(1/12),0) -> 0.00020858042 | F64: =IF(A64<=prem_rem_m,INDEX(lapse_table,MATCH(MIN(B64,5),lapse_key,0)),0) -> 0 | G64: =1-(1-F64)^(1/12) -> 0 | H64: =INDEX(comm_table,MATCH(MIN(B64,1),comm_key,0)) -> 0.02 | I64: =(1+e_m)^A64 -> 1.03 | J64: =M63*E64 -> 0.00020669852 | K64: =(M63-J64)*G64 -> 0 | L64: =IF(A64=rem_m,M63-J64-K64,0) -> 0 | M64: =M63-J64-K64-L64 -> 0.99077086 | N64: =IF(A64<=prem_rem_m,premium,0) -> 0 | O64: =N64*H64 -> 0 | P64: =maint_base*I64 -> 5.15 | Q64: =claim_exp_base*I64 -> 257.5 | R64: =M63*N64 -> 0 | S64: =R64*H64 -> 0 | T64: =M63*P64 -> 5.1035344 | U64: =J64*sum_assured -> 41.339703 | V64: =J64*Q64 -> 0.053224868 | W64: =R64-S64-T64-U64-V64 -> -46.496462 | X64: =U64+V64+T64-(R64-S64)*(1+i_m) -> 46.496462 | Y64: =v_m -> 0.99673694 | Z64: =v_m^A64 -> 0.96153846 | AA64: =(R64-S64)*Z63-(T64+U64+V64)*Z64 -> -44.708137 | AB64: =R64*Z63 -> 0 | AC64: =S64*Z63 -> 0 | AD64: =T64*Z64 -> 4.9072446 | AE64: =U64*Z64 -> 39.749714 | AF64: =V64*Z64 -> 0.051177757 | AG64: =(AG65+X65)*Y65 -> 92.547288 | AH64: =IF(M64>0,AG64/M64,0) -> 93.409376 | AI64: =IF(AG64>0,AG64,0) -> 92.547288 | AK64: =AND(M64>=0,M64<=M63) -> TRUE | AL64: =AND(D64>=0,D64<=1,E64>=0,E64<=1,F64>=0,F64<=1,G64>=0,G64<=1,J64+K64+L64<=M63+0.000000001*scale_count) -> TRUE | AM64: =(AG63+R64-S64)*(1+i_m)-T64-U64-V64 -> 92.547288 | AN64: =ABS(AM64-AG64)<=0.000000001*MAX(ABS(AM64),ABS(AG64),scale_money) -> TRUE | AO64: =(U64+V64+T64)*Z64-(R64-S64)*Z63 -> 44.708137 | AP64: =SUM(AO65:$AO$66) -> 88.987777 | AQ64: =ABS(AG64*Z64-AP64)<=0.000000001*MAX(ABS(AG64*Z64),ABS(AP64),scale_money) -> TRUE | AR64: =IF(A64<>rem_m,L64=0,L64=M63-J64-K64) -> TRUE | AS64: =IF(A64>prem_rem_m,AND(R64=0,S64=0,F64=0,G64=0,K64=0),R64=M63*premium) -> TRUE | AT64: =AND(C64>=18,C64<=120,OR(B64-B63=0,B64-B63=1)) -> TRUE | AU64: =-(N65-O65)+v_m*(E65*(sum_assured+Q65)+P65+(1-E65)*(1-G65)*AH65) -> 93.409376 | AV64: =ABS(AH64-AU64)<=0.000000001*MAX(ABS(AH64),ABS(AU64),scale_pp) -> TRUE | AW64: =AND(AI64>=0,AI64>=AG64) -> TRUE | AX64: =AND(U64=J64*sum_assured,R64=M63*N64,T64=M63*P64) -> TRUE
A65: 13 | B65: =MIN(INT((dur_m+A65-1)/12),dur_y_last) -> 9 | C65: =age_at_entry+B65 -> 51 | D65: =INDEX(mort_table,MATCH(C65,mort_age,0),MATCH(sex,mort_sex,0)) -> 0.0025000957 | E65: =IF(A65<=rem_m,1-(1-D65)^(1/12),0) -> 0.00020858042 | F65: =IF(A65<=prem_rem_m,INDEX(lapse_table,MATCH(MIN(B65,5),lapse_key,0)),0) -> 0 | G65: =1-(1-F65)^(1/12) -> 0 | H65: =INDEX(comm_table,MATCH(MIN(B65,1),comm_key,0)) -> 0.02 | I65: =(1+e_m)^A65 -> 1.0325403 | J65: =M64*E65 -> 0.0002066554 | K65: =(M64-J65)*G65 -> 0 | L65: =IF(A65=rem_m,M64-J65-K65,0) -> 0 | M65: =M64-J65-K65-L65 -> 0.9905642 | N65: =IF(A65<=prem_rem_m,premium,0) -> 0 | O65: =N65*H65 -> 0 | P65: =maint_base*I65 -> 5.1627013 | Q65: =claim_exp_base*I65 -> 258.13506 | R65: =M64*N65 -> 0 | S65: =R65*H65 -> 0 | T65: =M64*P65 -> 5.115054 | U65: =J65*sum_assured -> 41.33108 | V65: =J65*Q65 -> 0.053345005 | W65: =R65-S65-T65-U65-V65 -> -46.499479 | X65: =U65+V65+T65-(R65-S65)*(1+i_m) -> 46.499479 | Y65: =v_m -> 0.99673694 | Z65: =v_m^A65 -> 0.95840091 | AA65: =(R65-S65)*Z64-(T65+U65+V65)*Z65 -> -44.565143 | AB65: =R65*Z64 -> 0 | AC65: =S65*Z64 -> 0 | AD65: =T65*Z65 -> 4.9022724 | AE65: =U65*Z65 -> 39.611745 | AF65: =V65*Z65 -> 0.051125902 | AG65: =(AG66+X66)*Y66 -> 46.350784 | AH65: =IF(M65>0,AG65/M65,0) -> 46.792307 | AI65: =IF(AG65>0,AG65,0) -> 46.350784 | AK65: =AND(M65>=0,M65<=M64) -> TRUE | AL65: =AND(D65>=0,D65<=1,E65>=0,E65<=1,F65>=0,F65<=1,G65>=0,G65<=1,J65+K65+L65<=M64+0.000000001*scale_count) -> TRUE | AM65: =(AG64+R65-S65)*(1+i_m)-T65-U65-V65 -> 46.350784 | AN65: =ABS(AM65-AG65)<=0.000000001*MAX(ABS(AM65),ABS(AG65),scale_money) -> TRUE | AO65: =(U65+V65+T65)*Z65-(R65-S65)*Z64 -> 44.565143 | AP65: =SUM(AO66:$AO$66) -> 44.422633 | AQ65: =ABS(AG65*Z65-AP65)<=0.000000001*MAX(ABS(AG65*Z65),ABS(AP65),scale_money) -> TRUE | AR65: =IF(A65<>rem_m,L65=0,L65=M64-J65-K65) -> TRUE | AS65: =IF(A65>prem_rem_m,AND(R65=0,S65=0,F65=0,G65=0,K65=0),R65=M64*premium) -> TRUE | AT65: =AND(C65>=18,C65<=120,OR(B65-B64=0,B65-B64=1)) -> TRUE | AU65: =-(N66-O66)+v_m*(E66*(sum_assured+Q66)+P66+(1-E66)*(1-G66)*AH66) -> 46.792307 | AV65: =ABS(AH65-AU65)<=0.000000001*MAX(ABS(AH65),ABS(AU65),scale_pp) -> TRUE | AW65: =AND(AI65>=0,AI65>=AG65) -> TRUE | AX65: =AND(U65=J65*sum_assured,R65=M64*N65,T65=M64*P65) -> TRUE
A66: 14 | B66: =MIN(INT((dur_m+A66-1)/12),dur_y_last) -> 9 | C66: =age_at_entry+B66 -> 51 | D66: =INDEX(mort_table,MATCH(C66,mort_age,0),MATCH(sex,mort_sex,0)) -> 0.0025000957 | E66: =IF(A66<=rem_m,1-(1-D66)^(1/12),0) -> 0.00020858042 | F66: =IF(A66<=prem_rem_m,INDEX(lapse_table,MATCH(MIN(B66,5),lapse_key,0)),0) -> 0 | G66: =1-(1-F66)^(1/12) -> 0 | H66: =INDEX(comm_table,MATCH(MIN(B66,1),comm_key,0)) -> 0.02 | I66: =(1+e_m)^A66 -> 1.0350868 | J66: =M65*E66 -> 0.0002066123 | K66: =(M65-J66)*G66 -> 0 | L66: =IF(A66=rem_m,M65-J66-K66,0) -> 0.99035759 | M66: =M65-J66-K66-L66 -> 0 | N66: =IF(A66<=prem_rem_m,premium,0) -> 0 | O66: =N66*H66 -> 0 | P66: =maint_base*I66 -> 5.1754339 | Q66: =claim_exp_base*I66 -> 258.7717 | R66: =M65*N66 -> 0 | S66: =R66*H66 -> 0 | T66: =M65*P66 -> 5.1265996 | U66: =J66*sum_assured -> 41.322459 | V66: =J66*Q66 -> 0.053465414 | W66: =R66-S66-T66-U66-V66 -> -46.502524 | X66: =U66+V66+T66-(R66-S66)*(1+i_m) -> 46.502524 | Y66: =v_m -> 0.99673694 | Z66: =v_m^A66 -> 0.95527359 | AA66: =(R66-S66)*Z65-(T66+U66+V66)*Z66 -> -44.422633 | AB66: =R66*Z65 -> 0 | AC66: =S66*Z65 -> 0 | AD66: =T66*Z66 -> 4.8973052 | AE66: =U66*Z66 -> 39.474254 | AF66: =V66*Z66 -> 0.051074098 | AG66: 0 | AH66: =IF(M66>0,AG66/M66,0) -> 0 | AI66: =IF(AG66>0,AG66,0) -> 0 | AK66: =AND(M66>=0,M66<=M65) -> TRUE | AL66: =AND(D66>=0,D66<=1,E66>=0,E66<=1,F66>=0,F66<=1,G66>=0,G66<=1,J66+K66+L66<=M65+0.000000001*scale_count) -> TRUE | AM66: =(AG65+R66-S66)*(1+i_m)-T66-U66-V66 -> -2.7061686e-15 | AN66: =ABS(AM66-AG66)<=0.000000001*MAX(ABS(AM66),ABS(AG66),scale_money) -> TRUE | AO66: =(U66+V66+T66)*Z66-(R66-S66)*Z65 -> 44.422633 | AR66: =IF(A66<>rem_m,L66=0,L66=M65-J66-K66) -> TRUE | AS66: =IF(A66>prem_rem_m,AND(R66=0,S66=0,F66=0,G66=0,K66=0),R66=M65*premium) -> TRUE | AT66: =AND(C66>=18,C66<=120,OR(B66-B65=0,B66-B65=1)) -> TRUE | AW66: =AND(AI66>=0,AI66>=AG66) -> TRUE | AX66: =AND(U66=J66*sum_assured,R66=M65*N66,T66=M65*P66) -> TRUE
A68: Scalars (section 11.2): the derived constants, the PV sums over t = 1 .. rem_m in ascending t, the time-0 state variables and maturities(rem_m)
A69: age_at_entry | B69: =age_at_entry -> 42 | C69: 5 | D69: Int (years)
A70: dur_m | B70: =dur_m -> 106 | C70: 4.3 | D70: Int (months)
A71: term_m | B71: =term_m -> 120 | C71: 4.3 | D71: Int (months)
A72: rem_m | B72: =rem_m -> 14 | C72: 4.3 | D72: Int (months)
A73: prem_term_m | B73: =prem_term_m -> 108 | C73: 4.3 | D73: Int (months)
A74: prem_rem_m | B74: =prem_rem_m -> 2 | C74: 4.3 | D74: Int (months)
A75: dur_y_last | B75: =dur_y_last -> 9 | C75: 4.3 | D75: Int (years)
A76: pv_premiums | B76: =SUM($AB$53:$AB$66) -> 92.482722 | C76: 9.3 | D76: Money
A77: pv_commission | B77: =SUM($AC$53:$AC$66) -> 1.8496544 | C77: 9.3 | D77: Money
A78: pv_maint_expense | B78: =SUM($AD$53:$AD$66) -> 69.066636 | C78: 9.3 | D78: Money
A79: pv_death_outgo | B79: =SUM($AE$53:$AE$66) -> 558.8157 | C79: 9.3 | D79: Money
A80: pv_claim_expense | B80: =SUM($AF$53:$AF$66) -> 0.71160094 | C80: 9.3 | D80: Money
A81: pv_net_cf | B81: =B76-B77-B78-B79-B80 -> -537.96087 | C81: 9.3 | D81: Money
A82: reserve_0 | B82: =$AG$52 -> 537.96087 | C82: 10.2 | D82: Money: reserve(0)
A83: reserve_pp_0 | B83: =$AH$52 -> 537.96087 | C83: 10.4 | D83: Money per policy: reserve_pp(0)
A84: reserve_floored_0 | B84: =$AI$52 -> 537.96087 | C84: 10.5 | D84: Money: reserve_floored(0)
A85: maturities_n | B85: =$L$66 -> 0.99035759 | C85: 7.3 | D85: Count: maturities(rem_m), the survivors to the end of the term
A87: Check cells (section 12): the section 1 scales and two helper sums, then one <id>_ok per (sheet) invariant, TRUE when every row cell and scalar cell of that invariant is TRUE
A88: scale_money | B88: =sum_assured*pols_if_init -> 200000 | D88: Money (in-force) scale of section 1: sum_assured * pols_if_init
A89: scale_pp | B89: =sum_assured -> 200000 | D89: Money per policy scale of section 1: sum_assured
A90: scale_count | B90: =pols_if_init -> 1 | D90: Count scale of section 1: pols_if_init
A91: exits_sum | B91: =SUMPRODUCT($J$53:$J$66+$K$53:$K$66+$L$53:$L$66) -> 1 | D91: helper (P8): sum over t = 1 .. rem_m of deaths + lapses + maturities
A92: pv_net_cf_t_sum | B92: =SUM($AA$53:$AA$66) -> -537.96087 | D92: helper (P9): sum over t = 1 .. rem_m of pv_net_cf_t
A94: H1_ok | B94: =AND($AK$52:$AK$66) -> TRUE | D94: every H1 row cell (t = 0 .. rem_m)
A95: H2_ok | B95: =AND($AL$53:$AL$66) -> TRUE | D95: every H2 row cell (t = 1 .. rem_m)
A96: H3_ok | B96: =AND($AG$66=0,$M$66=0) -> TRUE | D96: reserve(rem_m) = 0 and pols_if(rem_m) = 0, exactly
A97: H4_ok | B97: =AND($AN$53:$AN$66) -> TRUE | D97: every H4 row cell (t = 1 .. rem_m)
A98: H5a_ok | B98: =ABS(reserve_0-(-pv_net_cf))<=0.000000001*MAX(ABS(reserve_0),ABS(pv_net_cf),scale_money) -> TRUE | D98: reserve(0) equals -pv_net_cf within tolerance (scale_money)
A99: H5b_ok | B99: =AND($AQ$52:$AQ$65) -> TRUE | D99: every H5b row cell (t = 0 .. rem_m - 1)
A100: P1_ok | B100: =AND($AR$53:$AR$66) -> TRUE | D100: every P1 row cell (t = 1 .. rem_m)
A101: P2_ok | B101: =AND($AS$53:$AS$66) -> TRUE | D101: every P2 row cell (t = 1 .. rem_m)
A102: P3_ok | B102: =SUMPRODUCT(--($N$53:$N$66<>0))=prem_rem_m -> TRUE | D102: the number of months with premium_pp <> 0 equals prem_rem_m
A103: P4_ok | B103: =AND($AT$53:$AT$66) -> TRUE | D103: every P4 row cell (t = 1 .. rem_m)
A104: P5_ok | B104: =AND($AV$52:$AV$65) -> TRUE | D104: every P5 row cell (t = 0 .. rem_m - 1)
A105: P6_ok | B105: =AND($AW$52:$AW$66) -> TRUE | D105: every P6 row cell (t = 0 .. rem_m)
A106: P8_ok | B106: =ABS(exits_sum-scale_count)<=0.000000001*MAX(ABS(exits_sum),ABS(scale_count),scale_count) -> TRUE | D106: exits_sum equals pols_if_init within tolerance (scale_count)
A107: P9_ok | B107: =ABS(pv_net_cf-pv_net_cf_t_sum)<=0.000000001*MAX(ABS(pv_net_cf),ABS(pv_net_cf_t_sum),scale_money) -> TRUE | D107: pv_net_cf equals pv_net_cf_t_sum within tolerance (scale_money)
A108: P10_ok | B108: =AND($AX$53:$AX$66) -> TRUE | D108: every P10 row cell (t = 1 .. rem_m)
...

Sheet P06
A1: Inputs (section 3.1, from section 13) and the run-level valuation_date (3.3), typed
A2: valuation_date | B2: 46388 | C2: 3.3 | D2: Date, first of a month (run-level input)
A3: policy_id | B3: P06 | C3: 3.1 | D3: string
A4: sex | B4: F | C4: 3.1 | D4: string, M or F
A5: birth_date | B5: 37680 | C5: 3.1 | D5: Date
A6: entry_date | B6: 46336 | C6: 3.1 | D6: Date
A7: maturity_date | B7: 49989 | C7: 3.1 | D7: Date
A8: prem_term_y | B8: 10 | C8: 3.1 | D8: Int (years)
A9: sum_assured | B9: 100000 | C9: 3.1 | D9: Money per policy
A10: premium | B10: 10.76 | C10: 3.1 | D10: Money per policy, monthly, in advance
A11: pols_if_init | B11: 1 | C11: 3.1 | D11: Count
A13: Derived constants (sections 3.2, 4.3 and 5), by formula
A14: age_at_entry | B14: =YEAR(entry_date)-YEAR(birth_date)-IF(OR(MONTH(entry_date)<MONTH(birth_date),AND(MONTH(entry_date)=MONTH(birth_date),DAY(entry_date)<DAY(birth_date))),1,0) -> 23 | C14: 5 | D14: Int (years)
A15: dur_m | B15: =12*(YEAR(valuation_date)-YEAR(entry_date))+(MONTH(valuation_date)-MONTH(entry_date))-IF(DAY(valuation_date)<DAY(entry_date),1,0) -> 1 | C15: 4.3 | D15: Int (months)
A16: term_m | B16: =12*(YEAR(maturity_date)-YEAR(entry_date))+(MONTH(maturity_date)-MONTH(entry_date))-IF(DAY(maturity_date)<DAY(entry_date),1,0) -> 120 | C16: 4.3 | D16: Int (months)
A17: rem_m | B17: =term_m-dur_m -> 119 | C17: 4.3 | D17: Int (months)
A18: prem_term_m | B18: =12*prem_term_y -> 120 | C18: 4.3 | D18: Int (months)
A19: prem_rem_m | B19: =MAX(prem_term_m-dur_m,0) -> 119 | C19: 4.3 | D19: Int (months)
A20: dur_y_last | B20: =INT((term_m-1)/12) -> 9 | C20: 4.3 | D20: Int (years)
A22: Basis constants (section 6), each in one cell
A23: i | B23: 0.04 | C23: 6 | D23: Rate[Annual]
A24: e | B24: 0.03 | C24: 6 | D24: Rate[Annual]
A25: i_m | B25: =(1+i)^(1/12)-1 -> 0.0032737398 | C25: 6 | D25: Rate[Monthly]
A26: v_m | B26: =(1+i)^(-1/12) -> 0.99673694 | C26: 6 | D26: factor
A27: e_m | B27: =(1+e)^(1/12)-1 -> 0.0024662698 | C27: 6 | D27: Rate[Monthly]
A28: A_M | B28: 0.0002 | C28: 6.1 | D28: Gompertz-Makeham A, sex M
A29: A_F | B29: 0.00015 | C29: 6.1 | D29: Gompertz-Makeham A, sex F
A30: B_M | B30: 1.7e-05 | C30: 6.1 | D30: Gompertz-Makeham B, sex M
A31: B_F | B31: 1.1e-05 | C31: 6.1 | D31: Gompertz-Makeham B, sex F
A32: c | B32: 1.1 | C32: 6.1 | D32: Gompertz-Makeham c (both sexes); defined name gm_c
A33: maint_base | B33: 5 | C33: 6.5 | D33: Money per policy, per month, time-0 prices
A34: claim_exp_base | B34: 250 | C34: 6.5 | D34: Money per policy (per death), time-0 prices
A36: Lapse table (section 6.2): key k = min(dur_y, 5)
A37: k | B37: lapse_table | D37: Prob, annual
A38: 0 | B38: 0.15
A39: 1 | B39: 0.1
A40: 2 | B40: 0.08
A41: 3 | B41: 0.06
A42: 4 | B42: 0.05
A43: 5 | B43: 0.04
A45: Commission table (section 6.6): key k = min(dur_y, 1)
A46: k | B46: comm_table | D46: Fraction
A47: 0 | B47: 0.2
A48: 1 | B48: 0.02
A50: Monthly block (sections 7.1 and 11.1): rows t = 0 .. rem_m, one column per quantity in the 7.1 order; the row-level check cells of section 12 follow the blank column
A51: t | B51: dur_y | C51: age | D51: q_ann | E51: q_m | F51: w_ann | G51: w_m | H51: comm_rate | I51: infl | J51: deaths | K51: lapses | L51: maturities | M51: pols_if | N51: premium_pp | O51: commission_pp | P51: maint_pp | Q51: claim_exp_pp | R51: premium_income | S51: commission | T51: maint_expense | U51: death_outgo | V51: claim_expense | W51: net_cf | X51: net_outgo | Y51: v | Z51: disc | AA51: pv_net_cf_t | AB51: pv_premiums_t | AC51: pv_commission_t | AD51: pv_maint_expense_t | AE51: pv_death_outgo_t | AF51: pv_claim_expense_t | AG51: reserve | AH51: reserve_pp | AI51: reserve_floored | AK51: H1 | AL51: H2 | AM51: H4_lhs | AN51: H4 | AO51: H5b_term | AP51: H5b_sum | AQ51: H5b | AR51: P1 | AS51: P2 | AT51: P4 | AU51: P5_rhs | AV51: P5 | AW51: P6 | AX51: P10
A52: 0 | I52: 1 | M52: =pols_if_init -> 1 | Z52: 1 | AG52: =(AG53+X53)*Y53 -> -139.7904 | AH52: =IF(M52>0,AG52/M52,0) -> -139.7904 | AI52: =IF(AG52>0,AG52,0) -> 0 | AK52: =M52>=0 -> TRUE | AP52: =SUM(AO53:$AO$171) -> -139.7904 | AQ52: =ABS(AG52*Z52-AP52)<=0.000000001*MAX(ABS(AG52*Z52),ABS(AP52),scale_money) -> TRUE | AU52: =-(N53-O53)+v_m*(E53*(sum_assured+Q53)+P53+(1-E53)*(1-G53)*AH53) -> -139.7904 | AV52: =ABS(AH52-AU52)<=0.000000001*MAX(ABS(AH52),ABS(AU52),scale_pp) -> TRUE | AW52: =AND(AI52>=0,AI52>=AG52) -> TRUE
A53: 1 | B53: =MIN(INT((dur_m+A53-1)/12),dur_y_last) -> 0 | C53: =age_at_entry+B53 -> 23 | D53: =INDEX(mort_table,MATCH(C53,mort_age,0),MATCH(sex,mort_sex,0)) -> 0.00025331188 | E53: =IF(A53<=rem_m,1-(1-D53)^(1/12),0) -> 2.1111775e-05 | F53: =IF(A53<=prem_rem_m,INDEX(lapse_table,MATCH(MIN(B53,5),lapse_key,0)),0) -> 0.15 | G53: =1-(1-F53)^(1/12) -> 0.013451947 | H53: =INDEX(comm_table,MATCH(MIN(B53,1),comm_key,0)) -> 0.2 | I53: =(1+e_m)^A53 -> 1.0024663 | J53: =M52*E53 -> 2.1111775e-05 | K53: =(M52-J53)*G53 -> 0.013451663 | L53: =IF(A53=rem_m,M52-J53-K53,0) -> 0 | M53: =M52-J53-K53-L53 -> 0.98652723 | N53: =IF(A53<=prem_rem_m,premium,0) -> 10.76 | O53: =N53*H53 -> 2.152 | P53: =maint_base*I53 -> 5.0123313 | Q53: =claim_exp_base*I53 -> 250.61657 | R53: =M52*N53 -> 10.76 | S53: =R53*H53 -> 2.152 | T53: =M52*P53 -> 5.0123313 | U53: =J53*sum_assured -> 2.1111775 | V53: =J53*Q53 -> 0.0052909606 | W53: =R53-S53-T53-U53-V53 -> 1.4792002 | X53: =U53+V53+T53-(R53-S53)*(1+i_m) -> -1.5073806 | Y53: =v_m -> 0.99673694 | Z53: =v_m^A53 -> 0.99673694 | AA53: =(R53-S53)*Z52-(T53+U53+V53)*Z53 -> 1.5024619 | AB53: =R53*Z52 -> 10.76 | AC53: =S53*Z52 -> 2.152 | AD53: =T53*Z53 -> 4.9959758 | AE53: =U53*Z53 -> 2.1042886 | AF53: =V53*Z53 -> 0.0052736959 | AG53: =(AG54+X54)*Y54 -> -138.74065 | AH53: =IF(M53>0,AG53/M53,0) -> -140.6354 | AI53: =IF(AG53>0,AG53,0) -> 0 | AK53: =AND(M53>=0,M53<=M52) -> TRUE | AL53: =AND(D53>=0,D53<=1,E53>=0,E53<=1,F53>=0,F53<=1,G53>=0,G53<=1,J53+K53+L53<=M52+0.000000001*scale_count) -> TRUE | AM53: =(AG52+R53-S53)*(1+i_m)-T53-U53-V53 -> -138.74065 | AN53: =ABS(AM53-AG53)<=0.000000001*MAX(ABS(AM53),ABS(AG53),scale_money) -> TRUE | AO53: =(U53+V53+T53)*Z53-(R53-S53)*Z52 -> -1.5024619 | AP53: =SUM(AO54:$AO$171) -> -138.28793 | AQ53: =ABS(AG53*Z53-AP53)<=0.000000001*MAX(ABS(AG53*Z53),ABS(AP53),scale_money) -> TRUE | AR53: =IF(A53<>rem_m,L53=0,L53=M52-J53-K53) -> TRUE | AS53: =IF(A53>prem_rem_m,AND(R53=0,S53=0,F53=0,G53=0,K53=0),R53=M52*premium) -> TRUE | AT53: =AND(C53>=18,C53<=120) -> TRUE | AU53: =-(N54-O54)+v_m*(E54*(sum_assured+Q54)+P54+(1-E54)*(1-G54)*AH54) -> -140.6354 | AV53: =ABS(AH53-AU53)<=0.000000001*MAX(ABS(AH53),ABS(AU53),scale_pp) -> TRUE | AW53: =AND(AI53>=0,AI53>=AG53) -> TRUE | AX53: =AND(U53=J53*sum_assured,R53=M52*N53,T53=M52*P53) -> TRUE
A54: 2 | B54: =MIN(INT((dur_m+A54-1)/12),dur_y_last) -> 0 | C54: =age_at_entry+B54 -> 23 | D54: =INDEX(mort_table,MATCH(C54,mort_age,0),MATCH(sex,mort_sex,0)) -> 0.00025331188 | E54: =IF(A54<=rem_m,1-(1-D54)^(1/12),0) -> 2.1111775e-05 | F54: =IF(A54<=prem_rem_m,INDEX(lapse_table,MATCH(MIN(B54,5),lapse_key,0)),0) -> 0.15 | G54: =1-(1-F54)^(1/12) -> 0.013451947 | H54: =INDEX(comm_table,MATCH(MIN(B54,1),comm_key,0)) -> 0.2 | I54: =(1+e_m)^A54 -> 1.0049386 | J54: =M53*E54 -> 2.0827341e-05 | K54: =(M53-J54)*G54 -> 0.013270432 | L54: =IF(A54=rem_m,M53-J54-K54,0) -> 0 | M54: =M53-J54-K54-L54 -> 0.97323597 | N54: =IF(A54<=prem_rem_m,premium,0) -> 10.76 | O54: =N54*H54 -> 2.152 | P54: =maint_base*I54 -> 5.0246931 | Q54: =claim_exp_base*I54 -> 251.23466 | R54: =M53*N54 -> 10.615033 | S54: =R54*H54 -> 2.1230066 | T54: =M53*P54 -> 4.9569966 | U54: =J54*sum_assured -> 2.0827341 | V54: =J54*Q54 -> 0.0052325498 | W54: =R54-S54-T54-U54-V54 -> 1.4470632 | X54: =U54+V54+T54-(R54-S54)*(1+i_m) -> -1.4748639 | Y54: =v_m -> 0.99673694 | Z54: =v_m^A54 -> 0.99348453 | AA54: =(R54-S54)*Z53-(T54+U54+V54)*Z54 -> 1.4652544 | AB54: =R54*Z53 -> 10.580395 | AC54: =S54*Z53 -> 2.1160791 | AD54: =T54*Z54 -> 4.9246994 | AE54: =U54*Z54 -> 2.0691641 | AF54: =V54*Z54 -> 0.0051984573 | AG54: =(AG55+X55)*Y55 -> -137.71999 | AH54: =IF(M54>0,AG54/M54,0) -> -141.5073 | AI54: =IF(AG54>0,AG54,0) -> 0 | AK54: =AND(M54>=0,M54<=M53) -> TRUE | AL54: =AND(D54>=0,D54<=1,E54>=0,E54<=1,F54>=0,F54<=1,G54>=0,G54<=1,J54+K54+L54<=M53+0.000000001*scale_count) -> TRUE | AM54: =(AG53+R54-S54)*(1+i_m)-T54-U54-V54 -> -137.71999 | AN54: =ABS(AM54-AG54)<=0.000000001*MAX(ABS(AM54),ABS(AG54),scale_money) -> TRUE | AO54: =(U54+V54+T54)*Z54-(R54-S54)*Z53 -> -1.4652544 | AP54: =SUM(AO55:$AO$171) -> -136.82268 | AQ54: =ABS(AG54*Z54-AP54)<=0.000000001*MAX(ABS(AG54*Z54),ABS(AP54),scale_money) -> TRUE | AR54: =IF(A54<>rem_m,L54=0,L54=M53-J54-K54) -> TRUE | AS54: =IF(A54>prem_rem_m,AND(R54=0,S54=0,F54=0,G54=0,K54=0),R54=M53*premium) -> TRUE | AT54: =AND(C54>=18,C54<=120,OR(B54-B53=0,B54-B53=1)) -> TRUE | AU54: =-(N55-O55)+v_m*(E55*(sum_assured+Q55)+P55+(1-E55)*(1-G55)*AH55) -> -141.5073 | AV54: =ABS(AH54-AU54)<=0.000000001*MAX(ABS(AH54),ABS(AU54),scale_pp) -> TRUE | AW54: =AND(AI54>=0,AI54>=AG54) -> TRUE | AX54: =AND(U54=J54*sum_assured,R54=M53*N54,T54=M53*P54) -> TRUE
