Workbook
Name all_ok: checks!$B$22
Name cif: inputs!$AH$4:$FC$104
Name cif_age: inputs!$AF$4:$AF$104
Name cif_year: inputs!$AH$1:$FC$1
Name cpi_rec_u: inputs!$X$2:$X$527
Name cpi_u: inputs!$AA$2:$AA$517
Name curve_t: inputs!$L$2:$L$503
Name d_L: inputs!$U$2:$U$503
Name I_act: inputs!$AB$2:$AB$517
Name I_cur: inputs!$AD$2:$AD$517
Name I_L: inputs!$AC$2:$AC$517
Name I_rec: inputs!$Y$2:$Y$527
Name j_L: inputs!$V$2:$V$503
Name mort_age: inputs!$F$2:$F$102
Name mort_v1_F: inputs!$H$2:$H$102
Name mort_v1_M: inputs!$G$2:$G$102
Name mort_v2_F: inputs!$J$2:$J$102
Name mort_v2_M: inputs!$I$2:$I$102
Name P_cur: inputs!$S$2:$S$503
Name P_L: inputs!$T$2:$T$503
Name P_rec: inputs!$P$2:$P$503

Sheet inputs
A1: input | B1: value | C1: note | F1: age | G1: mort_base_v1(M, x) | H1: mort_base_v1(F, x) | I1: mort_base_v2(M, x) | J1: mort_base_v2(F, x) | L1: t | M1: s = t / 12 | N1: z_rec(s) | O1: rf_df_rec(t) | P1: P_rec(t) | Q1: z_cur(s) | R1: rf_df_cur(t) | S1: P_cur(t) | T1: P_L(t) | U1: d_L(t) | V1: j_L(t) | X1: u (relative to V_rec) | Y1: I_rec(u) | AA1: u (relative to V) | AB1: I_act(u) | AC1: I_L(u) | AD1: I_cur(u) | AF1: age (rows) by year (columns) | AG1: g(x) | AH1: 2025 | AI1: 2026 | AJ1: 2027 | AK1: 2028 | AL1: 2029 | AM1: 2030 | AN1: 2031 | AO1: 2032 | AP1: 2033 | AQ1: 2034 | AR1: 2035 | AS1: 2036 | AT1: 2037 | AU1: 2038 | AV1: 2039 | AW1: 2040 | AX1: 2041 | AY1: 2042 | AZ1: 2043 | BA1: 2044 | BB1: 2045 | BC1: 2046 | BD1: 2047 | BE1: 2048 | BF1: 2049 | BG1: 2050 | BH1: 2051 | BI1: 2052 | BJ1: 2053 | BK1: 2054 | BL1: 2055 | BM1: 2056 | BN1: 2057 | BO1: 2058 | BP1: 2059 | BQ1: 2060 | BR1: 2061 | BS1: 2062 | BT1: 2063 | BU1: 2064 | BV1: 2065 | BW1: 2066 | BX1: 2067 | BY1: 2068 | BZ1: 2069 | CA1: 2070 | CB1: 2071 | CC1: 2072 | CD1: 2073 | CE1: 2074 | CF1: 2075 | CG1: 2076 | CH1: 2077 | CI1: 2078 | CJ1: 2079 | CK1: 2080 | CL1: 2081 | CM1: 2082 | CN1: 2083 | CO1: 2084 | CP1: 2085 | CQ1: 2086 | CR1: 2087 | CS1: 2088 | CT1: 2089 | CU1: 2090 | CV1: 2091 | CW1: 2092 | CX1: 2093 | CY1: 2094 | CZ1: 2095 | DA1: 2096 | DB1: 2097 | DC1: 2098 | DD1: 2099 | DE1: 2100 | DF1: 2101 | DG1: 2102 | DH1: 2103 | DI1: 2104 | DJ1: 2105 | DK1: 2106 | DL1: 2107 | DM1: 2108 | DN1: 2109 | DO1: 2110 | DP1: 2111 | DQ1: 2112 | DR1: 2113 | DS1: 2114 | DT1: 2115 | DU1: 2116 | DV1: 2117 | DW1: 2118 | DX1: 2119 | DY1: 2120 | DZ1: 2121 | EA1: 2122 | EB1: 2123 | EC1: 2124 | ED1: 2125 | EE1: 2126 | EF1: 2127 | EG1: 2128 | EH1: 2129 | EI1: 2130 | EJ1: 2131 | EK1: 2132 | EL1: 2133 | EM1: 2134 | EN1: 2135 | EO1: 2136 | EP1: 2137 | EQ1: 2138 | ER1: 2139 | ES1: 2140 | ET1: 2141 | EU1: 2142 | EV1: 2143 | EW1: 2144 | EX1: 2145 | EY1: 2146 | EZ1: 2147 | FA1: 2148 | FB1: 2149 | FC1: 2150
A2: 3.1 Run settings | F2: 20 | G2: =1-EXP(-inputs!$B$35-inputs!$B$36*inputs!$B$37^$F2*(inputs!$B$37-1)/LN(inputs!$B$37)) -> 0.00024963903 | H2: =1-EXP(-inputs!$B$35-inputs!$B$36*inputs!$B$37^($F2-4)*(inputs!$B$37-1)/LN(inputs!$B$37)) -> 0.0002385605 | I2: =0.96*G2 -> 0.00023965347 | J2: =0.96*H2 -> 0.00022901808 | L2: 0 | M2: =L2/12 -> 0 | N2: =0.04-0.015*EXP(-M2/10) -> 0.025 | O2: =EXP(-N2*M2) -> 1 | P2: =O2*EXP(-inputs!$B$27*L2/12) -> 1 | Q2: =0.045-0.015*EXP(-M2/10) -> 0.03 | R2: =EXP(-Q2*M2) -> 1 | S2: =R2*EXP(-inputs!$B$27*L2/12) -> 1 | T2: =INDEX(P_rec,MATCH(inputs!$B$13+L2,curve_t,0))/INDEX(P_rec,MATCH(inputs!$B$13,curve_t,0)) -> 1 | X2: -24 | Y2: =IF(X2<=0,100*1.04^(X2/12),100*1.025^(X2/12)) -> 92.455621 | AA2: -26 | AB2: =IF(AA2<=-13,100*1.04^((AA2+12)/12),100.1*1.032^((AA2+12)/12)) -> 95.527359 | AC2: =AB2 -> 95.527359 | AD2: =AB2 -> 95.527359 | AF2: h(y) = min(1, (y - 2026) / 20) | AI2: =MIN(1,(AI$1-2026)/20) -> 0 | AJ2: =MIN(1,(AJ$1-2026)/20) -> 0.05 | AK2: =MIN(1,(AK$1-2026)/20) -> 0.1 | AL2: =MIN(1,(AL$1-2026)/20) -> 0.15 | AM2: =MIN(1,(AM$1-2026)/20) -> 0.2 | AN2: =MIN(1,(AN$1-2026)/20) -> 0.25 | AO2: =MIN(1,(AO$1-2026)/20) -> 0.3 | AP2: =MIN(1,(AP$1-2026)/20) -> 0.35 | ... FC2: =MIN(1,(FC$1-2026)/20) -> 1
A3: variant | B3: O | F3: 21 | G3: =1-EXP(-inputs!$B$35-inputs!$B$36*inputs!$B$37^$F3*(inputs!$B$37-1)/LN(inputs!$B$37)) -> 0.00025331721 | H3: =1-EXP(-inputs!$B$35-inputs!$B$36*inputs!$B$37^($F3-4)*(inputs!$B$37-1)/LN(inputs!$B$37)) -> 0.00024086498 | I3: =0.96*G3 -> 0.00024318452 | J3: =0.96*H3 -> 0.00023123038 | L3: 1 | M3: =L3/12 -> 0.083333333 | N3: =0.04-0.015*EXP(-M3/10) -> 0.025124481 | O3: =EXP(-N3*M3) -> 0.99790848 | P3: =O3*EXP(-inputs!$B$27*L3/12) -> 0.99749277 | Q3: =0.045-0.015*EXP(-M3/10) -> 0.030124481 | R3: =EXP(-Q3*M3) -> 0.99749277 | S3: =R3*EXP(-inputs!$B$27*L3/12) -> 0.99707724 | T3: =INDEX(P_rec,MATCH(inputs!$B$13+L3,curve_t,0))/INDEX(P_rec,MATCH(inputs!$B$13,curve_t,0)) -> 0.99726278 | U3: =T3/T2 -> 0.99726278 | V3: =T2/T3-1 -> 0.0027447341 | X3: -23 | Y3: =IF(X3<=0,100*1.04^(X3/12),100*1.025^(X3/12)) -> 92.758297 | AA3: -25 | AB3: =IF(AA3<=-13,100*1.04^((AA3+12)/12),100.1*1.032^((AA3+12)/12)) -> 95.840091 | AC3: =AB3 -> 95.840091 | AD3: =AB3 -> 95.840091 | AF3: w(h) = 1 - 3 h^2 + 2 h^3 | AI3: =1-3*AI$2^2+2*AI$2^3 -> 1 | AJ3: =1-3*AJ$2^2+2*AJ$2^3 -> 0.99275 | AK3: =1-3*AK$2^2+2*AK$2^3 -> 0.972 | AL3: =1-3*AL$2^2+2*AL$2^3 -> 0.93925 | AM3: =1-3*AM$2^2+2*AM$2^3 -> 0.896 | AN3: =1-3*AN$2^2+2*AN$2^3 -> 0.84375 | AO3: =1-3*AO$2^2+2*AO$2^3 -> 0.784 | AP3: =1-3*AP$2^2+2*AP$2^3 -> 0.71825 | ... FC3: =1-3*FC$2^2+2*FC$2^3 -> 0
F4: 22 | G4: =1-EXP(-inputs!$B$35-inputs!$B$36*inputs!$B$37^$F4*(inputs!$B$37-1)/LN(inputs!$B$37)) -> 0.00025745146 | H4: =1-EXP(-inputs!$B$35-inputs!$B$36*inputs!$B$37^($F4-4)*(inputs!$B$37-1)/LN(inputs!$B$37)) -> 0.00024345521 | I4: =0.96*G4 -> 0.00024715341 | J4: =0.96*H4 -> 0.000233717 | L4: 2 | M4: =L4/12 -> 0.16666667 | N4: =0.04-0.015*EXP(-M4/10) -> 0.025247928 | O4: =EXP(-N4*M4) -> 0.99580085 | P4: =O4*EXP(-inputs!$B$27*L4/12) -> 0.99497136 | Q4: =0.045-0.015*EXP(-M4/10) -> 0.030247928 | R4: =EXP(-Q4*M4) -> 0.99497136 | S4: =R4*EXP(-inputs!$B$27*L4/12) -> 0.99414257 | T4: =INDEX(P_rec,MATCH(inputs!$B$13+L4,curve_t,0))/INDEX(P_rec,MATCH(inputs!$B$13,curve_t,0)) -> 0.99451547 | U4: =T4/T3 -> 0.99724515 | V4: =T3/T4-1 -> 0.0027624647 | X4: -22 | Y4: =IF(X4<=0,100*1.04^(X4/12),100*1.025^(X4/12)) -> 93.061963 | AA4: -24 | AB4: =IF(AA4<=-13,100*1.04^((AA4+12)/12),100.1*1.032^((AA4+12)/12)) -> 96.153846 | AC4: =AB4 -> 96.153846 | AD4: =AB4 -> 96.153846 | AF4: 20 | AG4: =IF($AF4<=85,1,IF($AF4<110,(110-$AF4)/25,0)) -> 1 | AH4: =1 -> 1 | AI4: =AH4*(1-$AG4*(0.01+0.01*AI$3)) -> 0.98 | AJ4: =AI4*(1-$AG4*(0.01+0.01*AJ$3)) -> 0.96047105 | AK4: =AJ4*(1-$AG4*(0.01+0.01*AK$3)) -> 0.94153056 | AL4: =AK4*(1-$AG4*(0.01+0.01*AL$3)) -> 0.92327193 | AM4: =AL4*(1-$AG4*(0.01+0.01*AM$3)) -> 0.90576669 | AN4: =AM4*(1-$AG4*(0.01+0.01*AN$3)) -> 0.88906662 | AO4: =AN4*(1-$AG4*(0.01+0.01*AO$3)) -> 0.87320567 | AP4: =AO4*(1-$AG4*(0.01+0.01*AP$3)) -> 0.85820182 | ... FC4: =FB4*(1-$AG4*(0.01+0.01*FC$3)) -> 0.25595353
F5: 23 | G5: =1-EXP(-inputs!$B$35-inputs!$B$36*inputs!$B$37^$F5*(inputs!$B$37-1)/LN(inputs!$B$37)) -> 0.00026209835 | H5: =1-EXP(-inputs!$B$35-inputs!$B$36*inputs!$B$37^($F5-4)*(inputs!$B$37-1)/LN(inputs!$B$37)) -> 0.00024636662 | I5: =0.96*G5 -> 0.00025161441 | J5: =0.96*H5 -> 0.00023651195 | L5: 3 | M5: =L5/12 -> 0.25 | N5: =0.04-0.015*EXP(-M5/10) -> 0.025370351 | O5: =EXP(-N5*M5) -> 0.99367748 | P5: =O5*EXP(-inputs!$B$27*L5/12) -> 0.99243616 | Q5: =0.045-0.015*EXP(-M5/10) -> 0.030370351 | R5: =EXP(-Q5*M5) -> 0.99243616 | S5: =R5*EXP(-inputs!$B$27*L5/12) -> 0.99119639 | T5: =INDEX(P_rec,MATCH(inputs!$B$13+L5,curve_t,0))/INDEX(P_rec,MATCH(inputs!$B$13,curve_t,0)) -> 0.99175841 | U5: =T5/T4 -> 0.99722774 | V5: =T4/T5-1 -> 0.002779971 | X5: -21 | Y5: =IF(X5<=0,100*1.04^(X5/12),100*1.025^(X5/12)) -> 93.366624 | AA5: -23 | AB5: =IF(AA5<=-13,100*1.04^((AA5+12)/12),100.1*1.032^((AA5+12)/12)) -> 96.468629 | AC5: =AB5 -> 96.468629 | AD5: =AB5 -> 96.468629 | AF5: 21 | AG5: =IF($AF5<=85,1,IF($AF5<110,(110-$AF5)/25,0)) -> 1 | AH5: =1 -> 1 | AI5: =AH5*(1-$AG5*(0.01+0.01*AI$3)) -> 0.98 | AJ5: =AI5*(1-$AG5*(0.01+0.01*AJ$3)) -> 0.96047105 | AK5: =AJ5*(1-$AG5*(0.01+0.01*AK$3)) -> 0.94153056 | AL5: =AK5*(1-$AG5*(0.01+0.01*AL$3)) -> 0.92327193 | AM5: =AL5*(1-$AG5*(0.01+0.01*AM$3)) -> 0.90576669 | AN5: =AM5*(1-$AG5*(0.01+0.01*AN$3)) -> 0.88906662 | AO5: =AN5*(1-$AG5*(0.01+0.01*AO$3)) -> 0.87320567 | AP5: =AO5*(1-$AG5*(0.01+0.01*AP$3)) -> 0.85820182 | ... FC5: =FB5*(1-$AG5*(0.01+0.01*FC$3)) -> 0.25595353
F6: 24 | G6: =1-EXP(-inputs!$B$35-inputs!$B$36*inputs!$B$37^$F6*(inputs!$B$37-1)/LN(inputs!$B$37)) -> 0.00026732142 | H6: =1-EXP(-inputs!$B$35-inputs!$B$36*inputs!$B$37^($F6-4)*(inputs!$B$37-1)/LN(inputs!$B$37)) -> 0.00024963903 | I6: =0.96*G6 -> 0.00025662856 | J6: =0.96*H6 -> 0.00023965347 | L6: 4 | M6: =L6/12 -> 0.33333333 | N6: =0.04-0.015*EXP(-M6/10) -> 0.025491758 | O6: =EXP(-N6*M6) -> 0.99153875 | P6: =O6*EXP(-inputs!$B$27*L6/12) -> 0.98988756 | Q6: =0.045-0.015*EXP(-M6/10) -> 0.030491758 | R6: =EXP(-Q6*M6) -> 0.98988756 | S6: =R6*EXP(-inputs!$B$27*L6/12) -> 0.98823912 | T6: =INDEX(P_rec,MATCH(inputs!$B$13+L6,curve_t,0))/INDEX(P_rec,MATCH(inputs!$B$13,curve_t,0)) -> 0.98899194 | U6: =T6/T5 -> 0.99721055 | V6: =T5/T6-1 -> 0.0027972556 | X6: -20 | Y6: =IF(X6<=0,100*1.04^(X6/12),100*1.025^(X6/12)) -> 93.672282 | AA6: -22 | AB6: =IF(AA6<=-13,100*1.04^((AA6+12)/12),100.1*1.032^((AA6+12)/12)) -> 96.784442 | AC6: =AB6 -> 96.784442 | AD6: =AB6 -> 96.784442 | AF6: 22 | AG6: =IF($AF6<=85,1,IF($AF6<110,(110-$AF6)/25,0)) -> 1 | AH6: =1 -> 1 | AI6: =AH6*(1-$AG6*(0.01+0.01*AI$3)) -> 0.98 | AJ6: =AI6*(1-$AG6*(0.01+0.01*AJ$3)) -> 0.96047105 | AK6: =AJ6*(1-$AG6*(0.01+0.01*AK$3)) -> 0.94153056 | AL6: =AK6*(1-$AG6*(0.01+0.01*AL$3)) -> 0.92327193 | AM6: =AL6*(1-$AG6*(0.01+0.01*AM$3)) -> 0.90576669 | AN6: =AM6*(1-$AG6*(0.01+0.01*AN$3)) -> 0.88906662 | AO6: =AN6*(1-$AG6*(0.01+0.01*AO$3)) -> 0.87320567 | AP6: =AO6*(1-$AG6*(0.01+0.01*AP$3)) -> 0.85820182 | ... FC6: =FB6*(1-$AG6*(0.01+0.01*FC$3)) -> 0.25595353
A7: valuation_date V | B7: 46387 | C7: the last day of a calendar month | F7: 25 | G7: =1-EXP(-inputs!$B$35-inputs!$B$36*inputs!$B$37^$F7*(inputs!$B$37-1)/LN(inputs!$B$37)) -> 0.00027319212 | H7: =1-EXP(-inputs!$B$35-inputs!$B$36*inputs!$B$37^($F7-4)*(inputs!$B$37-1)/LN(inputs!$B$37)) -> 0.00025331721 | I7: =0.96*G7 -> 0.00026226444 | J7: =0.96*H7 -> 0.00024318452 | L7: 5 | M7: =L7/12 -> 0.41666667 | N7: =0.04-0.015*EXP(-M7/10) -> 0.025612158 | O7: =EXP(-N7*M7) -> 0.98938501 | P7: =O7*EXP(-inputs!$B$27*L7/12) -> 0.98732594 | Q7: =0.045-0.015*EXP(-M7/10) -> 0.030612158 | R7: =EXP(-Q7*M7) -> 0.98732594 | S7: =R7*EXP(-inputs!$B$27*L7/12) -> 0.98527115 | T7: =INDEX(P_rec,MATCH(inputs!$B$13+L7,curve_t,0))/INDEX(P_rec,MATCH(inputs!$B$13,curve_t,0)) -> 0.98621641 | U7: =T7/T6 -> 0.99719358 | V7: =T6/T7-1 -> 0.0028143208 | X7: -19 | Y7: =IF(X7<=0,100*1.04^(X7/12),100*1.025^(X7/12)) -> 93.978941 | AA7: -21 | AB7: =IF(AA7<=-13,100*1.04^((AA7+12)/12),100.1*1.032^((AA7+12)/12)) -> 97.101289 | AC7: =AB7 -> 97.101289 | AD7: =AB7 -> 97.101289 | AF7: 23 | AG7: =IF($AF7<=85,1,IF($AF7<110,(110-$AF7)/25,0)) -> 1 | AH7: =1 -> 1 | AI7: =AH7*(1-$AG7*(0.01+0.01*AI$3)) -> 0.98 | AJ7: =AI7*(1-$AG7*(0.01+0.01*AJ$3)) -> 0.96047105 | AK7: =AJ7*(1-$AG7*(0.01+0.01*AK$3)) -> 0.94153056 | AL7: =AK7*(1-$AG7*(0.01+0.01*AL$3)) -> 0.92327193 | AM7: =AL7*(1-$AG7*(0.01+0.01*AM$3)) -> 0.90576669 | AN7: =AM7*(1-$AG7*(0.01+0.01*AN$3)) -> 0.88906662 | AO7: =AN7*(1-$AG7*(0.01+0.01*AO$3)) -> 0.87320567 | AP7: =AO7*(1-$AG7*(0.01+0.01*AP$3)) -> 0.85820182 | ... FC7: =FB7*(1-$AG7*(0.01+0.01*FC$3)) -> 0.25595353
A8: recognition_date V_rec | B8: 46022 | C8: a month-end | F8: 26 | G8: =1-EXP(-inputs!$B$35-inputs!$B$36*inputs!$B$37^$F8*(inputs!$B$37-1)/LN(inputs!$B$37)) -> 0.00027979075 | H8: =1-EXP(-inputs!$B$35-inputs!$B$36*inputs!$B$37^($F8-4)*(inputs!$B$37-1)/LN(inputs!$B$37)) -> 0.00025745146 | I8: =0.96*G8 -> 0.00026859912 | J8: =0.96*H8 -> 0.00024715341 | L8: 6 | M8: =L8/12 -> 0.5 | N8: =0.04-0.015*EXP(-M8/10) -> 0.025731559 | O8: =EXP(-N8*M8) -> 0.98721663 | P8: =O8*EXP(-inputs!$B$27*L8/12) -> 0.98475167 | Q8: =0.045-0.015*EXP(-M8/10) -> 0.030731559 | R8: =EXP(-Q8*M8) -> 0.98475167 | S8: =R8*EXP(-inputs!$B$27*L8/12) -> 0.98229287 | T8: =INDEX(P_rec,MATCH(inputs!$B$13+L8,curve_t,0))/INDEX(P_rec,MATCH(inputs!$B$13,curve_t,0)) -> 0.98343215 | U8: =T8/T7 -> 0.99717682 | V8: =T7/T8-1 -> 0.0028311691 | X8: -18 | Y8: =IF(X8<=0,100*1.04^(X8/12),100*1.025^(X8/12)) -> 94.286603 | AA8: -20 | AB8: =IF(AA8<=-13,100*1.04^((AA8+12)/12),100.1*1.032^((AA8+12)/12)) -> 97.419173 | AC8: =AB8 -> 97.419173 | AD8: =AB8 -> 97.419173 | AF8: 24 | AG8: =IF($AF8<=85,1,IF($AF8<110,(110-$AF8)/25,0)) -> 1 | AH8: =1 -> 1 | AI8: =AH8*(1-$AG8*(0.01+0.01*AI$3)) -> 0.98 | AJ8: =AI8*(1-$AG8*(0.01+0.01*AJ$3)) -> 0.96047105 | AK8: =AJ8*(1-$AG8*(0.01+0.01*AK$3)) -> 0.94153056 | AL8: =AK8*(1-$AG8*(0.01+0.01*AL$3)) -> 0.92327193 | AM8: =AL8*(1-$AG8*(0.01+0.01*AM$3)) -> 0.90576669 | AN8: =AM8*(1-$AG8*(0.01+0.01*AN$3)) -> 0.88906662 | AO8: =AN8*(1-$AG8*(0.01+0.01*AO$3)) -> 0.87320567 | AP8: =AO8*(1-$AG8*(0.01+0.01*AP$3)) -> 0.85820182 | ... FC8: =FB8*(1-$AG8*(0.01+0.01*FC$3)) -> 0.25595353
A9: prev_valuation_date V_prev | B9: 46022 | C9: a month-end; here equal to V_rec (C1) | F9: 27 | G9: =1-EXP(-inputs!$B$35-inputs!$B$36*inputs!$B$37^$F9*(inputs!$B$37-1)/LN(inputs!$B$37)) -> 0.00028720755 | H9: =1-EXP(-inputs!$B$35-inputs!$B$36*inputs!$B$37^($F9-4)*(inputs!$B$37-1)/LN(inputs!$B$37)) -> 0.00026209835 | I9: =0.96*G9 -> 0.00027571925 | J9: =0.96*H9 -> 0.00025161441 | L9: 7 | M9: =L9/12 -> 0.58333333 | N9: =0.04-0.015*EXP(-M9/10) -> 0.025849968 | O9: =EXP(-N9*M9) -> 0.98503397 | P9: =O9*EXP(-inputs!$B$27*L9/12) -> 0.98216514 | Q9: =0.045-0.015*EXP(-M9/10) -> 0.030849968 | R9: =EXP(-Q9*M9) -> 0.98216514 | S9: =R9*EXP(-inputs!$B$27*L9/12) -> 0.97930467 | T9: =INDEX(P_rec,MATCH(inputs!$B$13+L9,curve_t,0))/INDEX(P_rec,MATCH(inputs!$B$13,curve_t,0)) -> 0.98063948 | U9: =T9/T8 -> 0.99716028 | V9: =T8/T9-1 -> 0.002847803 | X9: -17 | Y9: =IF(X9<=0,100*1.04^(X9/12),100*1.025^(X9/12)) -> 94.595273 | AA9: -19 | AB9: =IF(AA9<=-13,100*1.04^((AA9+12)/12),100.1*1.032^((AA9+12)/12)) -> 97.738098 | AC9: =AB9 -> 97.738098 | AD9: =AB9 -> 97.738098 | AF9: 25 | AG9: =IF($AF9<=85,1,IF($AF9<110,(110-$AF9)/25,0)) -> 1 | AH9: =1 -> 1 | AI9: =AH9*(1-$AG9*(0.01+0.01*AI$3)) -> 0.98 | AJ9: =AI9*(1-$AG9*(0.01+0.01*AJ$3)) -> 0.96047105 | AK9: =AJ9*(1-$AG9*(0.01+0.01*AK$3)) -> 0.94153056 | AL9: =AK9*(1-$AG9*(0.01+0.01*AL$3)) -> 0.92327193 | AM9: =AL9*(1-$AG9*(0.01+0.01*AM$3)) -> 0.90576669 | AN9: =AM9*(1-$AG9*(0.01+0.01*AN$3)) -> 0.88906662 | AO9: =AN9*(1-$AG9*(0.01+0.01*AO$3)) -> 0.87320567 | AP9: =AO9*(1-$AG9*(0.01+0.01*AP$3)) -> 0.85820182 | ... FC9: =FB9*(1-$AG9*(0.01+0.01*FC$3)) -> 0.25595353
A10: m_V = mi(V) | B10: =12*YEAR(inputs!$B$7)+MONTH(inputs!$B$7)-1 -> 24323 | C10: mi(d) = 12 * year(d) + month(d) - 1 | F10: 28 | G10: =1-EXP(-inputs!$B$35-inputs!$B$36*inputs!$B$37^$F10*(inputs!$B$37-1)/LN(inputs!$B$37)) -> 0.00029554397 | H10: =1-EXP(-inputs!$B$35-inputs!$B$36*inputs!$B$37^($F10-4)*(inputs!$B$37-1)/LN(inputs!$B$37)) -> 0.00026732142 | I10: =0.96*G10 -> 0.00028372221 | J10: =0.96*H10 -> 0.00025662856 | L10: 8 | M10: =L10/12 -> 0.66666667 | N10: =0.04-0.015*EXP(-M10/10) -> 0.025967395 | O10: =EXP(-N10*M10) -> 0.98283739 | P10: =O10*EXP(-inputs!$B$27*L10/12) -> 0.97956672 | Q10: =0.045-0.015*EXP(-M10/10) -> 0.030967395 | R10: =EXP(-Q10*M10) -> 0.97956672 | S10: =R10*EXP(-inputs!$B$27*L10/12) -> 0.97630693 | T10: =INDEX(P_rec,MATCH(inputs!$B$13+L10,curve_t,0))/INDEX(P_rec,MATCH(inputs!$B$13,curve_t,0)) -> 0.97783873 | U10: =T10/T9 -> 0.99714396 | V10: =T9/T10-1 -> 0.0028642248 | X10: -16 | Y10: =IF(X10<=0,100*1.04^(X10/12),100*1.025^(X10/12)) -> 94.904954 | AA10: -18 | AB10: =IF(AA10<=-13,100*1.04^((AA10+12)/12),100.1*1.032^((AA10+12)/12)) -> 98.058068 | AC10: =AB10 -> 98.058068 | AD10: =AB10 -> 98.058068 | AF10: 26 | AG10: =IF($AF10<=85,1,IF($AF10<110,(110-$AF10)/25,0)) -> 1 | AH10: =1 -> 1 | AI10: =AH10*(1-$AG10*(0.01+0.01*AI$3)) -> 0.98 | AJ10: =AI10*(1-$AG10*(0.01+0.01*AJ$3)) -> 0.96047105 | AK10: =AJ10*(1-$AG10*(0.01+0.01*AK$3)) -> 0.94153056 | AL10: =AK10*(1-$AG10*(0.01+0.01*AL$3)) -> 0.92327193 | AM10: =AL10*(1-$AG10*(0.01+0.01*AM$3)) -> 0.90576669 | AN10: =AM10*(1-$AG10*(0.01+0.01*AN$3)) -> 0.88906662 | AO10: =AN10*(1-$AG10*(0.01+0.01*AO$3)) -> 0.87320567 | AP10: =AO10*(1-$AG10*(0.01+0.01*AP$3)) -> 0.85820182 | ... FC10: =FB10*(1-$AG10*(0.01+0.01*FC$3)) -> 0.25595353
A11: m_rec = mi(V_rec) | B11: =12*YEAR(inputs!$B$8)+MONTH(inputs!$B$8)-1 -> 24311 | F11: 29 | G11: =1-EXP(-inputs!$B$35-inputs!$B$36*inputs!$B$37^$F11*(inputs!$B$37-1)/LN(inputs!$B$37)) -> 0.00030491403 | H11: =1-EXP(-inputs!$B$35-inputs!$B$36*inputs!$B$37^($F11-4)*(inputs!$B$37-1)/LN(inputs!$B$37)) -> 0.00027319212 | I11: =0.96*G11 -> 0.00029271747 | J11: =0.96*H11 -> 0.00026226444 | L11: 9 | M11: =L11/12 -> 0.75 | N11: =0.04-0.015*EXP(-M11/10) -> 0.026083848 | O11: =EXP(-N11*M11) -> 0.98062723 | P11: =O11*EXP(-inputs!$B$27*L11/12) -> 0.97695676 | Q11: =0.045-0.015*EXP(-M11/10) -> 0.031083848 | R11: =EXP(-Q11*M11) -> 0.97695676 | S11: =R11*EXP(-inputs!$B$27*L11/12) -> 0.97330003 | T11: =INDEX(P_rec,MATCH(inputs!$B$13+L11,curve_t,0))/INDEX(P_rec,MATCH(inputs!$B$13,curve_t,0)) -> 0.97503022 | U11: =T11/T10 -> 0.99712784 | V11: =T10/T11-1 -> 0.0028804368 | X11: -15 | Y11: =IF(X11<=0,100*1.04^(X11/12),100*1.025^(X11/12)) -> 95.215648 | AA11: -17 | AB11: =IF(AA11<=-13,100*1.04^((AA11+12)/12),100.1*1.032^((AA11+12)/12)) -> 98.379084 | AC11: =AB11 -> 98.379084 | AD11: =AB11 -> 98.379084 | AF11: 27 | AG11: =IF($AF11<=85,1,IF($AF11<110,(110-$AF11)/25,0)) -> 1 | AH11: =1 -> 1 | AI11: =AH11*(1-$AG11*(0.01+0.01*AI$3)) -> 0.98 | AJ11: =AI11*(1-$AG11*(0.01+0.01*AJ$3)) -> 0.96047105 | AK11: =AJ11*(1-$AG11*(0.01+0.01*AK$3)) -> 0.94153056 | AL11: =AK11*(1-$AG11*(0.01+0.01*AL$3)) -> 0.92327193 | AM11: =AL11*(1-$AG11*(0.01+0.01*AM$3)) -> 0.90576669 | AN11: =AM11*(1-$AG11*(0.01+0.01*AN$3)) -> 0.88906662 | AO11: =AN11*(1-$AG11*(0.01+0.01*AO$3)) -> 0.87320567 | AP11: =AO11*(1-$AG11*(0.01+0.01*AP$3)) -> 0.85820182 | ... FC11: =FB11*(1-$AG11*(0.01+0.01*FC$3)) -> 0.25595353
A12: m_prev = mi(V_prev) | B12: =12*YEAR(inputs!$B$9)+MONTH(inputs!$B$9)-1 -> 24311 | F12: 30 | G12: =1-EXP(-inputs!$B$35-inputs!$B$36*inputs!$B$37^$F12*(inputs!$B$37-1)/LN(inputs!$B$37)) -> 0.00031544586 | H12: =1-EXP(-inputs!$B$35-inputs!$B$36*inputs!$B$37^($F12-4)*(inputs!$B$37-1)/LN(inputs!$B$37)) -> 0.00027979075 | I12: =0.96*G12 -> 0.00030282803 | J12: =0.96*H12 -> 0.00026859912 | L12: 10 | M12: =L12/12 -> 0.83333333 | N12: =0.04-0.015*EXP(-M12/10) -> 0.026199334 | O12: =EXP(-N12*M12) -> 0.97840383 | P12: =O12*EXP(-inputs!$B$27*L12/12) -> 0.97433563 | Q12: =0.045-0.015*EXP(-M12/10) -> 0.031199334 | R12: =EXP(-Q12*M12) -> 0.97433563 | S12: =R12*EXP(-inputs!$B$27*L12/12) -> 0.97028434 | T12: =INDEX(P_rec,MATCH(inputs!$B$13+L12,curve_t,0))/INDEX(P_rec,MATCH(inputs!$B$13,curve_t,0)) -> 0.97221426 | U12: =T12/T11 -> 0.99711192 | V12: =T11/T12-1 -> 0.0028964416 | X12: -14 | Y12: =IF(X12<=0,100*1.04^(X12/12),100*1.025^(X12/12)) -> 95.527359 | AA12: -16 | AB12: =IF(AA12<=-13,100*1.04^((AA12+12)/12),100.1*1.032^((AA12+12)/12)) -> 98.701152 | AC12: =AB12 -> 98.701152 | AD12: =AB12 -> 98.701152 | AF12: 28 | AG12: =IF($AF12<=85,1,IF($AF12<110,(110-$AF12)/25,0)) -> 1 | AH12: =1 -> 1 | AI12: =AH12*(1-$AG12*(0.01+0.01*AI$3)) -> 0.98 | AJ12: =AI12*(1-$AG12*(0.01+0.01*AJ$3)) -> 0.96047105 | AK12: =AJ12*(1-$AG12*(0.01+0.01*AK$3)) -> 0.94153056 | AL12: =AK12*(1-$AG12*(0.01+0.01*AL$3)) -> 0.92327193 | AM12: =AL12*(1-$AG12*(0.01+0.01*AM$3)) -> 0.90576669 | AN12: =AM12*(1-$AG12*(0.01+0.01*AN$3)) -> 0.88906662 | AO12: =AN12*(1-$AG12*(0.01+0.01*AO$3)) -> 0.87320567 | AP12: =AO12*(1-$AG12*(0.01+0.01*AP$3)) -> 0.85820182 | ... FC12: =FB12*(1-$AG12*(0.01+0.01*FC$3)) -> 0.25595353
A13: tau0 = m_V - m_rec | B13: =inputs!$B$10-inputs!$B$11 -> 12 | C13: months from recognition to V | F13: 31 | G13: =1-EXP(-inputs!$B$35-inputs!$B$36*inputs!$B$37^$F13*(inputs!$B$37-1)/LN(inputs!$B$37)) -> 0.00032728352 | H13: =1-EXP(-inputs!$B$35-inputs!$B$36*inputs!$B$37^($F13-4)*(inputs!$B$37-1)/LN(inputs!$B$37)) -> 0.00028720755 | I13: =0.96*G13 -> 0.00031419218 | J13: =0.96*H13 -> 0.00027571925 | L13: 11 | M13: =L13/12 -> 0.91666667 | N13: =0.04-0.015*EXP(-M13/10) -> 0.026313861 | O13: =EXP(-N13*M13) -> 0.97616755 | P13: =O13*EXP(-inputs!$B$27*L13/12) -> 0.97170368 | Q13: =0.045-0.015*EXP(-M13/10) -> 0.031313861 | R13: =EXP(-Q13*M13) -> 0.97170368 | S13: =R13*EXP(-inputs!$B$27*L13/12) -> 0.96726023 | T13: =INDEX(P_rec,MATCH(inputs!$B$13+L13,curve_t,0))/INDEX(P_rec,MATCH(inputs!$B$13,curve_t,0)) -> 0.96939116 | U13: =T13/T12 -> 0.99709622 | V13: =T12/T13-1 -> 0.0029122412 | X13: -13 | Y13: =IF(X13<=0,100*1.04^(X13/12),100*1.025^(X13/12)) -> 95.840091 | AA13: -15 | AB13: =IF(AA13<=-13,100*1.04^((AA13+12)/12),100.1*1.032^((AA13+12)/12)) -> 99.024274 | AC13: =AB13 -> 99.024274 | AD13: =AB13 -> 99.024274 | AF13: 29 | AG13: =IF($AF13<=85,1,IF($AF13<110,(110-$AF13)/25,0)) -> 1 | AH13: =1 -> 1 | AI13: =AH13*(1-$AG13*(0.01+0.01*AI$3)) -> 0.98 | AJ13: =AI13*(1-$AG13*(0.01+0.01*AJ$3)) -> 0.96047105 | AK13: =AJ13*(1-$AG13*(0.01+0.01*AK$3)) -> 0.94153056 | AL13: =AK13*(1-$AG13*(0.01+0.01*AL$3)) -> 0.92327193 | AM13: =AL13*(1-$AG13*(0.01+0.01*AM$3)) -> 0.90576669 | AN13: =AM13*(1-$AG13*(0.01+0.01*AN$3)) -> 0.88906662 | AO13: =AN13*(1-$AG13*(0.01+0.01*AO$3)) -> 0.87320567 | AP13: =AO13*(1-$AG13*(0.01+0.01*AP$3)) -> 0.85820182 | ... FC13: =FB13*(1-$AG13*(0.01+0.01*FC$3)) -> 0.25595353
A14: tau = m_V - m_prev | B14: =inputs!$B$10-inputs!$B$12 -> 12 | C14: the reporting period in months | F14: 32 | G14: =1-EXP(-inputs!$B$35-inputs!$B$36*inputs!$B$37^$F14*(inputs!$B$37-1)/LN(inputs!$B$37)) -> 0.00034058887 | H14: =1-EXP(-inputs!$B$35-inputs!$B$36*inputs!$B$37^($F14-4)*(inputs!$B$37-1)/LN(inputs!$B$37)) -> 0.00029554397 | I14: =0.96*G14 -> 0.00032696532 | J14: =0.96*H14 -> 0.00028372221 | L14: 12 | M14: =L14/12 -> 1 | N14: =0.04-0.015*EXP(-M14/10) -> 0.026427439 | O14: =EXP(-N14*M14) -> 0.97391871 | P14: =O14*EXP(-inputs!$B$27*L14/12) -> 0.96906127 | Q14: =0.045-0.015*EXP(-M14/10) -> 0.031427439 | R14: =EXP(-Q14*M14) -> 0.96906127 | S14: =R14*EXP(-inputs!$B$27*L14/12) -> 0.96422806 | T14: =INDEX(P_rec,MATCH(inputs!$B$13+L14,curve_t,0))/INDEX(P_rec,MATCH(inputs!$B$13,curve_t,0)) -> 0.96656122 | U14: =T14/T13 -> 0.99708071 | V14: =T13/T14-1 -> 0.0029278382 | X14: -12 | Y14: =IF(X14<=0,100*1.04^(X14/12),100*1.025^(X14/12)) -> 96.153846 | AA14: -14 | AB14: =IF(AA14<=-13,100*1.04^((AA14+12)/12),100.1*1.032^((AA14+12)/12)) -> 99.348453 | AC14: =AB14 -> 99.348453 | AD14: =AB14 -> 99.348453 | AF14: 30 | AG14: =IF($AF14<=85,1,IF($AF14<110,(110-$AF14)/25,0)) -> 1 | AH14: =1 -> 1 | AI14: =AH14*(1-$AG14*(0.01+0.01*AI$3)) -> 0.98 | AJ14: =AI14*(1-$AG14*(0.01+0.01*AJ$3)) -> 0.96047105 | AK14: =AJ14*(1-$AG14*(0.01+0.01*AK$3)) -> 0.94153056 | AL14: =AK14*(1-$AG14*(0.01+0.01*AL$3)) -> 0.92327193 | AM14: =AL14*(1-$AG14*(0.01+0.01*AM$3)) -> 0.90576669 | AN14: =AM14*(1-$AG14*(0.01+0.01*AN$3)) -> 0.88906662 | AO14: =AN14*(1-$AG14*(0.01+0.01*AO$3)) -> 0.87320567 | AP14: =AO14*(1-$AG14*(0.01+0.01*AP$3)) -> 0.85820182 | ... FC14: =FB14*(1-$AG14*(0.01+0.01*FC$3)) -> 0.25595353
A15: cpi_lag_m L | B15: 3 | C15: build-time constant of the CPI class | F15: 33 | G15: =1-EXP(-inputs!$B$35-inputs!$B$36*inputs!$B$37^$F15*(inputs!$B$37-1)/LN(inputs!$B$37)) -> 0.00035554388 | H15: =1-EXP(-inputs!$B$35-inputs!$B$36*inputs!$B$37^($F15-4)*(inputs!$B$37-1)/LN(inputs!$B$37)) -> 0.00030491403 | I15: =0.96*G15 -> 0.00034132212 | J15: =0.96*H15 -> 0.00029271747 | L15: 13 | M15: =L15/12 -> 1.0833333 | N15: =0.04-0.015*EXP(-M15/10) -> 0.026540073 | O15: =EXP(-N15*M15) -> 0.97165765 | P15: =O15*EXP(-inputs!$B$27*L15/12) -> 0.96640874 | Q15: =0.045-0.015*EXP(-M15/10) -> 0.031540073 | R15: =EXP(-Q15*M15) -> 0.96640874 | S15: =R15*EXP(-inputs!$B$27*L15/12) -> 0.96118817 | T15: =INDEX(P_rec,MATCH(inputs!$B$13+L15,curve_t,0))/INDEX(P_rec,MATCH(inputs!$B$13,curve_t,0)) -> 0.96372475 | U15: =T15/T14 -> 0.9970654 | V15: =T14/T15-1 -> 0.0029432346 | X15: -11 | Y15: =IF(X15<=0,100*1.04^(X15/12),100*1.025^(X15/12)) -> 96.468629 | AA15: -13 | AB15: =IF(AA15<=-13,100*1.04^((AA15+12)/12),100.1*1.032^((AA15+12)/12)) -> 99.673694 | AC15: =AB15 -> 99.673694 | AD15: =AB15 -> 99.673694 | AF15: 31 | AG15: =IF($AF15<=85,1,IF($AF15<110,(110-$AF15)/25,0)) -> 1 | AH15: =1 -> 1 | AI15: =AH15*(1-$AG15*(0.01+0.01*AI$3)) -> 0.98 | AJ15: =AI15*(1-$AG15*(0.01+0.01*AJ$3)) -> 0.96047105 | AK15: =AJ15*(1-$AG15*(0.01+0.01*AK$3)) -> 0.94153056 | AL15: =AK15*(1-$AG15*(0.01+0.01*AL$3)) -> 0.92327193 | AM15: =AL15*(1-$AG15*(0.01+0.01*AM$3)) -> 0.90576669 | AN15: =AM15*(1-$AG15*(0.01+0.01*AN$3)) -> 0.88906662 | AO15: =AN15*(1-$AG15*(0.01+0.01*AO$3)) -> 0.87320567 | AP15: =AO15*(1-$AG15*(0.01+0.01*AP$3)) -> 0.85820182 | ... FC15: =FB15*(1-$AG15*(0.01+0.01*FC$3)) -> 0.25595353
A16: include_inv_exp | B16: TRUE | F16: 34 | G16: =1-EXP(-inputs!$B$35-inputs!$B$36*inputs!$B$37^$F16*(inputs!$B$37-1)/LN(inputs!$B$37)) -> 0.00037235304 | H16: =1-EXP(-inputs!$B$35-inputs!$B$36*inputs!$B$37^($F16-4)*(inputs!$B$37-1)/LN(inputs!$B$37)) -> 0.00031544586 | I16: =0.96*G16 -> 0.00035745892 | J16: =0.96*H16 -> 0.00030282803 | L16: 14 | M16: =L16/12 -> 1.1666667 | N16: =0.04-0.015*EXP(-M16/10) -> 0.026651773 | O16: =EXP(-N16*M16) -> 0.9693847 | P16: =O16*EXP(-inputs!$B$27*L16/12) -> 0.96374642 | Q16: =0.045-0.015*EXP(-M16/10) -> 0.031651773 | R16: =EXP(-Q16*M16) -> 0.96374642 | S16: =R16*EXP(-inputs!$B$27*L16/12) -> 0.95814093 | T16: =INDEX(P_rec,MATCH(inputs!$B$13+L16,curve_t,0))/INDEX(P_rec,MATCH(inputs!$B$13,curve_t,0)) -> 0.96088205 | U16: =T16/T15 -> 0.99705029 | V16: =T15/T16-1 -> 0.0029584328 | X16: -10 | Y16: =IF(X16<=0,100*1.04^(X16/12),100*1.025^(X16/12)) -> 96.784442 | AA16: -12 | AB16: =IF(AA16<=-13,100*1.04^((AA16+12)/12),100.1*1.032^((AA16+12)/12)) -> 100.1 | AC16: =AB16 -> 100.1 | AD16: =AB16 -> 100.1 | AF16: 32 | AG16: =IF($AF16<=85,1,IF($AF16<110,(110-$AF16)/25,0)) -> 1 | AH16: =1 -> 1 | AI16: =AH16*(1-$AG16*(0.01+0.01*AI$3)) -> 0.98 | AJ16: =AI16*(1-$AG16*(0.01+0.01*AJ$3)) -> 0.96047105 | AK16: =AJ16*(1-$AG16*(0.01+0.01*AK$3)) -> 0.94153056 | AL16: =AK16*(1-$AG16*(0.01+0.01*AL$3)) -> 0.92327193 | AM16: =AL16*(1-$AG16*(0.01+0.01*AM$3)) -> 0.90576669 | AN16: =AM16*(1-$AG16*(0.01+0.01*AN$3)) -> 0.88906662 | AO16: =AN16*(1-$AG16*(0.01+0.01*AO$3)) -> 0.87320567 | AP16: =AO16*(1-$AG16*(0.01+0.01*AP$3)) -> 0.85820182 | ... FC16: =FB16*(1-$AG16*(0.01+0.01*FC$3)) -> 0.25595353
A17: discount_coverage_units | B17: TRUE | C17: the only form in the spec (C13) | F17: 35 | G17: =1-EXP(-inputs!$B$35-inputs!$B$36*inputs!$B$37^$F17*(inputs!$B$37-1)/LN(inputs!$B$37)) -> 0.0003912462 | H17: =1-EXP(-inputs!$B$35-inputs!$B$36*inputs!$B$37^($F17-4)*(inputs!$B$37-1)/LN(inputs!$B$37)) -> 0.00032728352 | I17: =0.96*G17 -> 0.00037559635 | J17: =0.96*H17 -> 0.00031419218 | L17: 15 | M17: =L17/12 -> 1.25 | N17: =0.04-0.015*EXP(-M17/10) -> 0.026762546 | O17: =EXP(-N17*M17) -> 0.96710019 | P17: =O17*EXP(-inputs!$B$27*L17/12) -> 0.96107466 | Q17: =0.045-0.015*EXP(-M17/10) -> 0.031762546 | R17: =EXP(-Q17*M17) -> 0.96107466 | S17: =R17*EXP(-inputs!$B$27*L17/12) -> 0.95508668 | T17: =INDEX(P_rec,MATCH(inputs!$B$13+L17,curve_t,0))/INDEX(P_rec,MATCH(inputs!$B$13,curve_t,0)) -> 0.9580334 | U17: =T17/T16 -> 0.99703538 | V17: =T16/T17-1 -> 0.0029734351 | X17: -9 | Y17: =IF(X17<=0,100*1.04^(X17/12),100*1.025^(X17/12)) -> 97.101289 | AA17: -11 | AB17: =IF(AA17<=-13,100*1.04^((AA17+12)/12),100.1*1.032^((AA17+12)/12)) -> 100.3631 | AC17: =AB17 -> 100.3631 | AD17: =AB17 -> 100.3631 | AF17: 33 | AG17: =IF($AF17<=85,1,IF($AF17<110,(110-$AF17)/25,0)) -> 1 | AH17: =1 -> 1 | AI17: =AH17*(1-$AG17*(0.01+0.01*AI$3)) -> 0.98 | AJ17: =AI17*(1-$AG17*(0.01+0.01*AJ$3)) -> 0.96047105 | AK17: =AJ17*(1-$AG17*(0.01+0.01*AK$3)) -> 0.94153056 | AL17: =AK17*(1-$AG17*(0.01+0.01*AL$3)) -> 0.92327193 | AM17: =AL17*(1-$AG17*(0.01+0.01*AM$3)) -> 0.90576669 | AN17: =AM17*(1-$AG17*(0.01+0.01*AN$3)) -> 0.88906662 | AO17: =AN17*(1-$AG17*(0.01+0.01*AO$3)) -> 0.87320567 | AP17: =AO17*(1-$AG17*(0.01+0.01*AP$3)) -> 0.85820182 | ... FC17: =FB17*(1-$AG17*(0.01+0.01*FC$3)) -> 0.25595353
A18: scenario count J | B18: 1 | C18: one scenario per run (G6) | F18: 36 | G18: =1-EXP(-inputs!$B$35-inputs!$B$36*inputs!$B$37^$F18*(inputs!$B$37-1)/LN(inputs!$B$37)) -> 0.00041248168 | H18: =1-EXP(-inputs!$B$35-inputs!$B$36*inputs!$B$37^($F18-4)*(inputs!$B$37-1)/LN(inputs!$B$37)) -> 0.00034058887 | I18: =0.96*G18 -> 0.00039598241 | J18: =0.96*H18 -> 0.00032696532 | L18: 16 | M18: =L18/12 -> 1.3333333 | N18: =0.04-0.015*EXP(-M18/10) -> 0.0268724 | O18: =EXP(-N18*M18) -> 0.96480442 | P18: =O18*EXP(-inputs!$B$27*L18/12) -> 0.95839379 | Q18: =0.045-0.015*EXP(-M18/10) -> 0.0318724 | R18: =EXP(-Q18*M18) -> 0.95839379 | S18: =R18*EXP(-inputs!$B$27*L18/12) -> 0.95202575 | T18: =INDEX(P_rec,MATCH(inputs!$B$13+L18,curve_t,0))/INDEX(P_rec,MATCH(inputs!$B$13,curve_t,0)) -> 0.95517909 | U18: =T18/T17 -> 0.99702066 | V18: =T17/T18-1 -> 0.0029882435 | X18: -8 | Y18: =IF(X18<=0,100*1.04^(X18/12),100*1.025^(X18/12)) -> 97.419173 | AA18: -10 | AB18: =IF(AA18<=-13,100*1.04^((AA18+12)/12),100.1*1.032^((AA18+12)/12)) -> 100.62688 | AC18: =AB18 -> 100.62688 | AD18: =AB18 -> 100.62688 | AF18: 34 | AG18: =IF($AF18<=85,1,IF($AF18<110,(110-$AF18)/25,0)) -> 1 | AH18: =1 -> 1 | AI18: =AH18*(1-$AG18*(0.01+0.01*AI$3)) -> 0.98 | AJ18: =AI18*(1-$AG18*(0.01+0.01*AJ$3)) -> 0.96047105 | AK18: =AJ18*(1-$AG18*(0.01+0.01*AK$3)) -> 0.94153056 | AL18: =AK18*(1-$AG18*(0.01+0.01*AL$3)) -> 0.92327193 | AM18: =AL18*(1-$AG18*(0.01+0.01*AM$3)) -> 0.90576669 | AN18: =AM18*(1-$AG18*(0.01+0.01*AN$3)) -> 0.88906662 | AO18: =AN18*(1-$AG18*(0.01+0.01*AO$3)) -> 0.87320567 | AP18: =AO18*(1-$AG18*(0.01+0.01*AP$3)) -> 0.85820182 | ... FC18: =FB18*(1-$AG18*(0.01+0.01*FC$3)) -> 0.25595353
A19: T (recognition run) = 12*120 + 1 - min a0 at V_rec | B19: =12*120+1-MIN(inputs!$B$68,inputs!$C$68) -> 501 | C19: the generator writes rows t = 0 .. 501 on the REC sheets | F19: 37 | G19: =1-EXP(-inputs!$B$35-inputs!$B$36*inputs!$B$37^$F19*(inputs!$B$37-1)/LN(inputs!$B$37)) -> 0.00043634983 | H19: =1-EXP(-inputs!$B$35-inputs!$B$36*inputs!$B$37^($F19-4)*(inputs!$B$37-1)/LN(inputs!$B$37)) -> 0.00035554388 | I19: =0.96*G19 -> 0.00041889583 | J19: =0.96*H19 -> 0.00034132212 | L19: 17 | M19: =L19/12 -> 1.4166667 | N19: =0.04-0.015*EXP(-M19/10) -> 0.026981342 | O19: =EXP(-N19*M19) -> 0.96249773 | P19: =O19*EXP(-inputs!$B$27*L19/12) -> 0.95570413 | Q19: =0.045-0.015*EXP(-M19/10) -> 0.031981342 | R19: =EXP(-Q19*M19) -> 0.95570413 | S19: =R19*EXP(-inputs!$B$27*L19/12) -> 0.94895848 | T19: =INDEX(P_rec,MATCH(inputs!$B$13+L19,curve_t,0))/INDEX(P_rec,MATCH(inputs!$B$13,curve_t,0)) -> 0.95231941 | U19: =T19/T18 -> 0.99700613 | V19: =T18/T19-1 -> 0.0030028603 | X19: -7 | Y19: =IF(X19<=0,100*1.04^(X19/12),100*1.025^(X19/12)) -> 97.738098 | AA19: -9 | AB19: =IF(AA19<=-13,100*1.04^((AA19+12)/12),100.1*1.032^((AA19+12)/12)) -> 100.89137 | AC19: =AB19 -> 100.89137 | AD19: =AB19 -> 100.89137 | AF19: 35 | AG19: =IF($AF19<=85,1,IF($AF19<110,(110-$AF19)/25,0)) -> 1 | AH19: =1 -> 1 | AI19: =AH19*(1-$AG19*(0.01+0.01*AI$3)) -> 0.98 | AJ19: =AI19*(1-$AG19*(0.01+0.01*AJ$3)) -> 0.96047105 | AK19: =AJ19*(1-$AG19*(0.01+0.01*AK$3)) -> 0.94153056 | AL19: =AK19*(1-$AG19*(0.01+0.01*AL$3)) -> 0.92327193 | AM19: =AL19*(1-$AG19*(0.01+0.01*AM$3)) -> 0.90576669 | AN19: =AM19*(1-$AG19*(0.01+0.01*AN$3)) -> 0.88906662 | AO19: =AN19*(1-$AG19*(0.01+0.01*AO$3)) -> 0.87320567 | AP19: =AO19*(1-$AG19*(0.01+0.01*AP$3)) -> 0.85820182 | ... FC19: =FB19*(1-$AG19*(0.01+0.01*FC$3)) -> 0.25595353
A20: T (runs at V) = 12*120 + 1 - min a0 at V | B20: =12*120+1-MIN(inputs!$B$69,inputs!$C$69) -> 489 | C20: the generator writes rows t = 0 .. 489 on the OLD, NEW and CUR sheets | F20: 38 | G20: =1-EXP(-inputs!$B$35-inputs!$B$36*inputs!$B$37^$F20*(inputs!$B$37-1)/LN(inputs!$B$37)) -> 0.00046317694 | H20: =1-EXP(-inputs!$B$35-inputs!$B$36*inputs!$B$37^($F20-4)*(inputs!$B$37-1)/LN(inputs!$B$37)) -> 0.00037235304 | I20: =0.96*G20 -> 0.00044464986 | J20: =0.96*H20 -> 0.00035745892 | L20: 18 | M20: =L20/12 -> 1.5 | N20: =0.04-0.015*EXP(-M20/10) -> 0.02708938 | O20: =EXP(-N20*M20) -> 0.96018042 | P20: =O20*EXP(-inputs!$B$27*L20/12) -> 0.95300601 | Q20: =0.045-0.015*EXP(-M20/10) -> 0.03208938 | R20: =EXP(-Q20*M20) -> 0.95300601 | S20: =R20*EXP(-inputs!$B$27*L20/12) -> 0.9458852 | T20: =INDEX(P_rec,MATCH(inputs!$B$13+L20,curve_t,0))/INDEX(P_rec,MATCH(inputs!$B$13,curve_t,0)) -> 0.94945463 | U20: =T20/T19 -> 0.99699179 | V20: =T19/T20-1 -> 0.0030172876 | X20: -6 | Y20: =IF(X20<=0,100*1.04^(X20/12),100*1.025^(X20/12)) -> 98.058068 | AA20: -8 | AB20: =IF(AA20<=-13,100*1.04^((AA20+12)/12),100.1*1.032^((AA20+12)/12)) -> 101.15654 | AC20: =AB20 -> 101.15654 | AD20: =AB20 -> 101.15654 | AF20: 36 | AG20: =IF($AF20<=85,1,IF($AF20<110,(110-$AF20)/25,0)) -> 1 | AH20: =1 -> 1 | AI20: =AH20*(1-$AG20*(0.01+0.01*AI$3)) -> 0.98 | AJ20: =AI20*(1-$AG20*(0.01+0.01*AJ$3)) -> 0.96047105 | AK20: =AJ20*(1-$AG20*(0.01+0.01*AK$3)) -> 0.94153056 | AL20: =AK20*(1-$AG20*(0.01+0.01*AL$3)) -> 0.92327193 | AM20: =AL20*(1-$AG20*(0.01+0.01*AM$3)) -> 0.90576669 | AN20: =AM20*(1-$AG20*(0.01+0.01*AN$3)) -> 0.88906662 | AO20: =AN20*(1-$AG20*(0.01+0.01*AO$3)) -> 0.87320567 | AP20: =AO20*(1-$AG20*(0.01+0.01*AP$3)) -> 0.85820182 | ... FC20: =FB20*(1-$AG20*(0.01+0.01*FC$3)) -> 0.25595353
F21: 39 | G21: =1-EXP(-inputs!$B$35-inputs!$B$36*inputs!$B$37^$F21*(inputs!$B$37-1)/LN(inputs!$B$37)) -> 0.00049332976 | H21: =1-EXP(-inputs!$B$35-inputs!$B$36*inputs!$B$37^($F21-4)*(inputs!$B$37-1)/LN(inputs!$B$37)) -> 0.0003912462 | I21: =0.96*G21 -> 0.00047359657 | J21: =0.96*H21 -> 0.00037559635 | L21: 19 | M21: =L21/12 -> 1.5833333 | N21: =0.04-0.015*EXP(-M21/10) -> 0.027196522 | O21: =EXP(-N21*M21) -> 0.95785281 | P21: =O21*EXP(-inputs!$B$27*L21/12) -> 0.95029974 | Q21: =0.045-0.015*EXP(-M21/10) -> 0.032196522 | R21: =EXP(-Q21*M21) -> 0.95029974 | S21: =R21*EXP(-inputs!$B$27*L21/12) -> 0.94280624 | T21: =INDEX(P_rec,MATCH(inputs!$B$13+L21,curve_t,0))/INDEX(P_rec,MATCH(inputs!$B$13,curve_t,0)) -> 0.94658503 | U21: =T21/T20 -> 0.99697763 | V21: =T20/T21-1 -> 0.0030315276 | X21: -5 | Y21: =IF(X21<=0,100*1.04^(X21/12),100*1.025^(X21/12)) -> 98.379084 | AA21: -7 | AB21: =IF(AA21<=-13,100*1.04^((AA21+12)/12),100.1*1.032^((AA21+12)/12)) -> 101.42242 | AC21: =AB21 -> 101.42242 | AD21: =AB21 -> 101.42242 | AF21: 37 | AG21: =IF($AF21<=85,1,IF($AF21<110,(110-$AF21)/25,0)) -> 1 | AH21: =1 -> 1 | AI21: =AH21*(1-$AG21*(0.01+0.01*AI$3)) -> 0.98 | AJ21: =AI21*(1-$AG21*(0.01+0.01*AJ$3)) -> 0.96047105 | AK21: =AJ21*(1-$AG21*(0.01+0.01*AK$3)) -> 0.94153056 | AL21: =AK21*(1-$AG21*(0.01+0.01*AL$3)) -> 0.92327193 | AM21: =AL21*(1-$AG21*(0.01+0.01*AM$3)) -> 0.90576669 | AN21: =AM21*(1-$AG21*(0.01+0.01*AN$3)) -> 0.88906662 | AO21: =AN21*(1-$AG21*(0.01+0.01*AO$3)) -> 0.87320567 | AP21: =AO21*(1-$AG21*(0.01+0.01*AP$3)) -> 0.85820182 | ... FC21: =FB21*(1-$AG21*(0.01+0.01*FC$3)) -> 0.25595353
A22: 3.5 Assumption tables: scalar tables and the constants derived from them | F22: 40 | G22: =1-EXP(-inputs!$B$35-inputs!$B$36*inputs!$B$37^$F22*(inputs!$B$37-1)/LN(inputs!$B$37)) -> 0.00052722044 | H22: =1-EXP(-inputs!$B$35-inputs!$B$36*inputs!$B$37^($F22-4)*(inputs!$B$37-1)/LN(inputs!$B$37)) -> 0.00041248168 | I22: =0.96*G22 -> 0.00050613163 | J22: =0.96*H22 -> 0.00039598241 | L22: 20 | M22: =L22/12 -> 1.6666667 | N22: =0.04-0.015*EXP(-M22/10) -> 0.027302774 | O22: =EXP(-N22*M22) -> 0.95551518 | P22: =O22*EXP(-inputs!$B$27*L22/12) -> 0.94758564 | Q22: =0.045-0.015*EXP(-M22/10) -> 0.032302774 | R22: =EXP(-Q22*M22) -> 0.94758564 | S22: =R22*EXP(-inputs!$B$27*L22/12) -> 0.93972191 | T22: =INDEX(P_rec,MATCH(inputs!$B$13+L22,curve_t,0))/INDEX(P_rec,MATCH(inputs!$B$13,curve_t,0)) -> 0.94371088 | U22: =T22/T21 -> 0.99696366 | V22: =T21/T22-1 -> 0.0030455824 | X22: -4 | Y22: =IF(X22<=0,100*1.04^(X22/12),100*1.025^(X22/12)) -> 98.701152 | AA22: -6 | AB22: =IF(AA22<=-13,100*1.04^((AA22+12)/12),100.1*1.032^((AA22+12)/12)) -> 101.68899 | AC22: =AB22 -> 101.68899 | AD22: =AB22 -> 101.68899 | AF22: 38 | AG22: =IF($AF22<=85,1,IF($AF22<110,(110-$AF22)/25,0)) -> 1 | AH22: =1 -> 1 | AI22: =AH22*(1-$AG22*(0.01+0.01*AI$3)) -> 0.98 | AJ22: =AI22*(1-$AG22*(0.01+0.01*AJ$3)) -> 0.96047105 | AK22: =AJ22*(1-$AG22*(0.01+0.01*AK$3)) -> 0.94153056 | AL22: =AK22*(1-$AG22*(0.01+0.01*AL$3)) -> 0.92327193 | AM22: =AL22*(1-$AG22*(0.01+0.01*AM$3)) -> 0.90576669 | AN22: =AM22*(1-$AG22*(0.01+0.01*AN$3)) -> 0.88906662 | AO22: =AN22*(1-$AG22*(0.01+0.01*AO$3)) -> 0.87320567 | AP22: =AO22*(1-$AG22*(0.01+0.01*AP$3)) -> 0.85820182 | ... FC22: =FB22*(1-$AG22*(0.01+0.01*FC$3)) -> 0.25595353
A23: expense v1: maint_pm (December 2025 prices) | B23: 5 | C23: version 1, priced at V_prev; used by REC as is, by OLD rebased | F23: 41 | G23: =1-EXP(-inputs!$B$35-inputs!$B$36*inputs!$B$37^$F23*(inputs!$B$37-1)/LN(inputs!$B$37)) -> 0.0005653122 | H23: =1-EXP(-inputs!$B$35-inputs!$B$36*inputs!$B$37^($F23-4)*(inputs!$B$37-1)/LN(inputs!$B$37)) -> 0.00043634983 | I23: =0.96*G23 -> 0.00054269971 | J23: =0.96*H23 -> 0.00041889583 | L23: 21 | M23: =L23/12 -> 1.75 | N23: =0.04-0.015*EXP(-M23/10) -> 0.027408145 | O23: =EXP(-N23*M23) -> 0.95316786 | P23: =O23*EXP(-inputs!$B$27*L23/12) -> 0.94486402 | Q23: =0.045-0.015*EXP(-M23/10) -> 0.032408145 | R23: =EXP(-Q23*M23) -> 0.94486402 | S23: =R23*EXP(-inputs!$B$27*L23/12) -> 0.93663253 | T23: =INDEX(P_rec,MATCH(inputs!$B$13+L23,curve_t,0))/INDEX(P_rec,MATCH(inputs!$B$13,curve_t,0)) -> 0.94083245 | U23: =T23/T22 -> 0.99694988 | V23: =T22/T23-1 -> 0.0030594541 | X23: -3 | Y23: =IF(X23<=0,100*1.04^(X23/12),100*1.025^(X23/12)) -> 99.024274 | AA23: -5 | AB23: =IF(AA23<=-13,100*1.04^((AA23+12)/12),100.1*1.032^((AA23+12)/12)) -> 101.95626 | AC23: =AB23 -> 101.95626 | AD23: =AB23 -> 101.95626 | AF23: 39 | AG23: =IF($AF23<=85,1,IF($AF23<110,(110-$AF23)/25,0)) -> 1 | AH23: =1 -> 1 | AI23: =AH23*(1-$AG23*(0.01+0.01*AI$3)) -> 0.98 | AJ23: =AI23*(1-$AG23*(0.01+0.01*AJ$3)) -> 0.96047105 | AK23: =AJ23*(1-$AG23*(0.01+0.01*AK$3)) -> 0.94153056 | AL23: =AK23*(1-$AG23*(0.01+0.01*AL$3)) -> 0.92327193 | AM23: =AL23*(1-$AG23*(0.01+0.01*AM$3)) -> 0.90576669 | AN23: =AM23*(1-$AG23*(0.01+0.01*AN$3)) -> 0.88906662 | AO23: =AN23*(1-$AG23*(0.01+0.01*AO$3)) -> 0.87320567 | AP23: =AO23*(1-$AG23*(0.01+0.01*AP$3)) -> 0.85820182 | ... FC23: =FB23*(1-$AG23*(0.01+0.01*FC$3)) -> 0.25595353
A24: expense v2: maint_pm (December 2026 prices) | B24: 5.3 | C24: version 2, priced at V; used by NEW and CUR | F24: 42 | G24: =1-EXP(-inputs!$B$35-inputs!$B$36*inputs!$B$37^$F24*(inputs!$B$37-1)/LN(inputs!$B$37)) -> 0.0006081256 | H24: =1-EXP(-inputs!$B$35-inputs!$B$36*inputs!$B$37^($F24-4)*(inputs!$B$37-1)/LN(inputs!$B$37)) -> 0.00046317694 | I24: =0.96*G24 -> 0.00058380057 | J24: =0.96*H24 -> 0.00044464986 | L24: 22 | M24: =L24/12 -> 1.8333333 | N24: =0.04-0.015*EXP(-M24/10) -> 0.027512641 | O24: =EXP(-N24*M24) -> 0.95081113 | P24: =O24*EXP(-inputs!$B$27*L24/12) -> 0.94213518 | Q24: =0.045-0.015*EXP(-M24/10) -> 0.032512641 | R24: =EXP(-Q24*M24) -> 0.94213518 | S24: =R24*EXP(-inputs!$B$27*L24/12) -> 0.93353841 | T24: =INDEX(P_rec,MATCH(inputs!$B$13+L24,curve_t,0))/INDEX(P_rec,MATCH(inputs!$B$13,curve_t,0)) -> 0.93794999 | U24: =T24/T23 -> 0.99693627 | V24: =T23/T24-1 -> 0.0030731446 | X24: -2 | Y24: =IF(X24<=0,100*1.04^(X24/12),100*1.025^(X24/12)) -> 99.348453 | AA24: -4 | AB24: =IF(AA24<=-13,100*1.04^((AA24+12)/12),100.1*1.032^((AA24+12)/12)) -> 102.22424 | AC24: =AB24 -> 102.22424 | AD24: =AB24 -> 102.22424 | AF24: 40 | AG24: =IF($AF24<=85,1,IF($AF24<110,(110-$AF24)/25,0)) -> 1 | AH24: =1 -> 1 | AI24: =AH24*(1-$AG24*(0.01+0.01*AI$3)) -> 0.98 | AJ24: =AI24*(1-$AG24*(0.01+0.01*AJ$3)) -> 0.96047105 | AK24: =AJ24*(1-$AG24*(0.01+0.01*AK$3)) -> 0.94153056 | AL24: =AK24*(1-$AG24*(0.01+0.01*AL$3)) -> 0.92327193 | AM24: =AL24*(1-$AG24*(0.01+0.01*AM$3)) -> 0.90576669 | AN24: =AM24*(1-$AG24*(0.01+0.01*AN$3)) -> 0.88906662 | AO24: =AN24*(1-$AG24*(0.01+0.01*AO$3)) -> 0.87320567 | AP24: =AO24*(1-$AG24*(0.01+0.01*AP$3)) -> 0.85820182 | ... FC24: =FB24*(1-$AG24*(0.01+0.01*FC$3)) -> 0.25595353
A25: maint_pm_old = maint_pm_v1 * I_act(0) / I_act(-tau) (5.4) | B25: =inputs!$B$23*INDEX(I_act,MATCH(0,cpi_u,0))/INDEX(I_act,MATCH(-inputs!$B$14,cpi_u,0)) -> 5.16 | C25: used by OLD (5.4, C8) | F25: 43 | G25: =1-EXP(-inputs!$B$35-inputs!$B$36*inputs!$B$37^$F25*(inputs!$B$37-1)/LN(inputs!$B$37)) -> 0.00065624567 | H25: =1-EXP(-inputs!$B$35-inputs!$B$36*inputs!$B$37^($F25-4)*(inputs!$B$37-1)/LN(inputs!$B$37)) -> 0.00049332976 | I25: =0.96*G25 -> 0.00062999584 | J25: =0.96*H25 -> 0.00047359657 | L25: 23 | M25: =L25/12 -> 1.9166667 | N25: =0.04-0.015*EXP(-M25/10) -> 0.02761627 | O25: =EXP(-N25*M25) -> 0.94844528 | P25: =O25*EXP(-inputs!$B$27*L25/12) -> 0.93939943 | Q25: =0.045-0.015*EXP(-M25/10) -> 0.03261627 | R25: =EXP(-Q25*M25) -> 0.93939943 | S25: =R25*EXP(-inputs!$B$27*L25/12) -> 0.93043985 | T25: =INDEX(P_rec,MATCH(inputs!$B$13+L25,curve_t,0))/INDEX(P_rec,MATCH(inputs!$B$13,curve_t,0)) -> 0.93506377 | U25: =T25/T24 -> 0.99692284 | V25: =T24/T25-1 -> 0.0030866562 | X25: -1 | Y25: =IF(X25<=0,100*1.04^(X25/12),100*1.025^(X25/12)) -> 99.673694 | AA25: -3 | AB25: =IF(AA25<=-13,100*1.04^((AA25+12)/12),100.1*1.032^((AA25+12)/12)) -> 102.49292 | AC25: =AB25 -> 102.49292 | AD25: =AB25 -> 102.49292 | AF25: 41 | AG25: =IF($AF25<=85,1,IF($AF25<110,(110-$AF25)/25,0)) -> 1 | AH25: =1 -> 1 | AI25: =AH25*(1-$AG25*(0.01+0.01*AI$3)) -> 0.98 | AJ25: =AI25*(1-$AG25*(0.01+0.01*AJ$3)) -> 0.96047105 | AK25: =AJ25*(1-$AG25*(0.01+0.01*AK$3)) -> 0.94153056 | AL25: =AK25*(1-$AG25*(0.01+0.01*AL$3)) -> 0.92327193 | AM25: =AL25*(1-$AG25*(0.01+0.01*AM$3)) -> 0.90576669 | AN25: =AM25*(1-$AG25*(0.01+0.01*AN$3)) -> 0.88906662 | AO25: =AN25*(1-$AG25*(0.01+0.01*AO$3)) -> 0.87320567 | AP25: =AO25*(1-$AG25*(0.01+0.01*AP$3)) -> 0.85820182 | ... FC25: =FB25*(1-$AG25*(0.01+0.01*FC$3)) -> 0.25595353
A26: inv_expense: ie_rate | B26: 0.0015 | C26: Rate[Annual, Effective]; not stressed | F26: 44 | G26: =1-EXP(-inputs!$B$35-inputs!$B$36*inputs!$B$37^$F26*(inputs!$B$37-1)/LN(inputs!$B$37)) -> 0.00071032986 | H26: =1-EXP(-inputs!$B$35-inputs!$B$36*inputs!$B$37^($F26-4)*(inputs!$B$37-1)/LN(inputs!$B$37)) -> 0.00052722044 | I26: =0.96*G26 -> 0.00068191667 | J26: =0.96*H26 -> 0.00050613163 | L26: 24 | M26: =L26/12 -> 2 | N26: =0.04-0.015*EXP(-M26/10) -> 0.027719039 | O26: =EXP(-N26*M26) -> 0.94607061 | P26: =O26*EXP(-inputs!$B$27*L26/12) -> 0.93665705 | Q26: =0.045-0.015*EXP(-M26/10) -> 0.032719039 | R26: =EXP(-Q26*M26) -> 0.93665705 | S26: =R26*EXP(-inputs!$B$27*L26/12) -> 0.92733715 | T26: =INDEX(P_rec,MATCH(inputs!$B$13+L26,curve_t,0))/INDEX(P_rec,MATCH(inputs!$B$13,curve_t,0)) -> 0.93217404 | U26: =T26/T25 -> 0.99690959 | V26: =T25/T26-1 -> 0.0030999908 | X26: 0 | Y26: =IF(X26<=0,100*1.04^(X26/12),100*1.025^(X26/12)) -> 100 | AA26: -2 | AB26: =IF(AA26<=-13,100*1.04^((AA26+12)/12),100.1*1.032^((AA26+12)/12)) -> 102.7623 | AC26: =AB26 -> 102.7623 | AD26: =AB26 -> 102.7623 | AF26: 42 | AG26: =IF($AF26<=85,1,IF($AF26<110,(110-$AF26)/25,0)) -> 1 | AH26: =1 -> 1 | AI26: =AH26*(1-$AG26*(0.01+0.01*AI$3)) -> 0.98 | AJ26: =AI26*(1-$AG26*(0.01+0.01*AJ$3)) -> 0.96047105 | AK26: =AJ26*(1-$AG26*(0.01+0.01*AK$3)) -> 0.94153056 | AL26: =AK26*(1-$AG26*(0.01+0.01*AL$3)) -> 0.92327193 | AM26: =AL26*(1-$AG26*(0.01+0.01*AM$3)) -> 0.90576669 | AN26: =AM26*(1-$AG26*(0.01+0.01*AN$3)) -> 0.88906662 | AO26: =AN26*(1-$AG26*(0.01+0.01*AO$3)) -> 0.87320567 | AP26: =AO26*(1-$AG26*(0.01+0.01*AP$3)) -> 0.85820182 | ... FC26: =FB26*(1-$AG26*(0.01+0.01*FC$3)) -> 0.25595353
A27: ilp | B27: 0.005 | C27: Rate[Annual, Continuous]; part of the locked-in basis | F27: 45 | G27: =1-EXP(-inputs!$B$35-inputs!$B$36*inputs!$B$37^$F27*(inputs!$B$37-1)/LN(inputs!$B$37)) -> 0.00077111701 | H27: =1-EXP(-inputs!$B$35-inputs!$B$36*inputs!$B$37^($F27-4)*(inputs!$B$37-1)/LN(inputs!$B$37)) -> 0.0005653122 | I27: =0.96*G27 -> 0.00074027233 | J27: =0.96*H27 -> 0.00054269971 | L27: 25 | M27: =L27/12 -> 2.0833333 | N27: =0.04-0.015*EXP(-M27/10) -> 0.027820955 | O27: =EXP(-N27*M27) -> 0.94368739 | P27: =O27*EXP(-inputs!$B$27*L27/12) -> 0.93390833 | Q27: =0.045-0.015*EXP(-M27/10) -> 0.032820955 | R27: =EXP(-Q27*M27) -> 0.93390833 | S27: =R27*EXP(-inputs!$B$27*L27/12) -> 0.92423061 | T27: =INDEX(P_rec,MATCH(inputs!$B$13+L27,curve_t,0))/INDEX(P_rec,MATCH(inputs!$B$13,curve_t,0)) -> 0.92928105 | U27: =T27/T26 -> 0.99689651 | V27: =T26/T27-1 -> 0.0031131503 | X27: 1 | Y27: =IF(X27<=0,100*1.04^(X27/12),100*1.025^(X27/12)) -> 100.20598 | AA27: -1 | AB27: =IF(AA27<=-13,100*1.04^((AA27+12)/12),100.1*1.032^((AA27+12)/12)) -> 103.0324 | AC27: =AB27 -> 103.0324 | AD27: =AB27 -> 103.0324 | AF27: 43 | AG27: =IF($AF27<=85,1,IF($AF27<110,(110-$AF27)/25,0)) -> 1 | AH27: =1 -> 1 | AI27: =AH27*(1-$AG27*(0.01+0.01*AI$3)) -> 0.98 | AJ27: =AI27*(1-$AG27*(0.01+0.01*AJ$3)) -> 0.96047105 | AK27: =AJ27*(1-$AG27*(0.01+0.01*AK$3)) -> 0.94153056 | AL27: =AK27*(1-$AG27*(0.01+0.01*AL$3)) -> 0.92327193 | AM27: =AL27*(1-$AG27*(0.01+0.01*AM$3)) -> 0.90576669 | AN27: =AM27*(1-$AG27*(0.01+0.01*AN$3)) -> 0.88906662 | AO27: =AN27*(1-$AG27*(0.01+0.01*AO$3)) -> 0.87320567 | AP27: =AO27*(1-$AG27*(0.01+0.01*AP$3)) -> 0.85820182 | ... FC27: =FB27*(1-$AG27*(0.01+0.01*FC$3)) -> 0.25595353
A28: ra_param: alpha | B28: 0.75 | F28: 46 | G28: =1-EXP(-inputs!$B$35-inputs!$B$36*inputs!$B$37^$F28*(inputs!$B$37-1)/LN(inputs!$B$37)) -> 0.00083943734 | H28: =1-EXP(-inputs!$B$35-inputs!$B$36*inputs!$B$37^($F28-4)*(inputs!$B$37-1)/LN(inputs!$B$37)) -> 0.0006081256 | I28: =0.96*G28 -> 0.00080585985 | J28: =0.96*H28 -> 0.00058380057 | L28: 26 | M28: =L28/12 -> 2.1666667 | N28: =0.04-0.015*EXP(-M28/10) -> 0.027922025 | O28: =EXP(-N28*M28) -> 0.94129591 | P28: =O28*EXP(-inputs!$B$27*L28/12) -> 0.93115358 | Q28: =0.045-0.015*EXP(-M28/10) -> 0.032922025 | R28: =EXP(-Q28*M28) -> 0.93115358 | S28: =R28*EXP(-inputs!$B$27*L28/12) -> 0.92112053 | T28: =INDEX(P_rec,MATCH(inputs!$B$13+L28,curve_t,0))/INDEX(P_rec,MATCH(inputs!$B$13,curve_t,0)) -> 0.92638504 | U28: =T28/T27 -> 0.99688361 | V28: =T27/T28-1 -> 0.0031261369 | X28: 2 | Y28: =IF(X28<=0,100*1.04^(X28/12),100*1.025^(X28/12)) -> 100.41239 | AA28: 0 | AB28: =IF(AA28<=-13,100*1.04^((AA28+12)/12),100.1*1.032^((AA28+12)/12)) -> 103.3032 | AC28: =AB28 -> 103.3032 | AD28: =AB28 -> 103.3032 | AF28: 44 | AG28: =IF($AF28<=85,1,IF($AF28<110,(110-$AF28)/25,0)) -> 1 | AH28: =1 -> 1 | AI28: =AH28*(1-$AG28*(0.01+0.01*AI$3)) -> 0.98 | AJ28: =AI28*(1-$AG28*(0.01+0.01*AJ$3)) -> 0.96047105 | AK28: =AJ28*(1-$AG28*(0.01+0.01*AK$3)) -> 0.94153056 | AL28: =AK28*(1-$AG28*(0.01+0.01*AL$3)) -> 0.92327193 | AM28: =AL28*(1-$AG28*(0.01+0.01*AM$3)) -> 0.90576669 | AN28: =AM28*(1-$AG28*(0.01+0.01*AN$3)) -> 0.88906662 | AO28: =AN28*(1-$AG28*(0.01+0.01*AO$3)) -> 0.87320567 | AP28: =AO28*(1-$AG28*(0.01+0.01*AP$3)) -> 0.85820182 | ... FC28: =FB28*(1-$AG28*(0.01+0.01*FC$3)) -> 0.25595353
A29: ra_param: z_alpha | B29: 0.67448975 | F29: 47 | G29: =1-EXP(-inputs!$B$35-inputs!$B$36*inputs!$B$37^$F29*(inputs!$B$37-1)/LN(inputs!$B$37)) -> 0.00091622382 | H29: =1-EXP(-inputs!$B$35-inputs!$B$36*inputs!$B$37^($F29-4)*(inputs!$B$37-1)/LN(inputs!$B$37)) -> 0.00065624567 | I29: =0.96*G29 -> 0.00087957486 | J29: =0.96*H29 -> 0.00062999584 | L29: 27 | M29: =L29/12 -> 2.25 | N29: =0.04-0.015*EXP(-M29/10) -> 0.028022257 | O29: =EXP(-N29*M29) -> 0.93889645 | P29: =O29*EXP(-inputs!$B$27*L29/12) -> 0.92839306 | Q29: =0.045-0.015*EXP(-M29/10) -> 0.033022257 | R29: =EXP(-Q29*M29) -> 0.92839306 | S29: =R29*EXP(-inputs!$B$27*L29/12) -> 0.91800717 | T29: =INDEX(P_rec,MATCH(inputs!$B$13+L29,curve_t,0))/INDEX(P_rec,MATCH(inputs!$B$13,curve_t,0)) -> 0.92348626 | U29: =T29/T28 -> 0.99687087 | V29: =T28/T29-1 -> 0.0031389524 | X29: 3 | Y29: =IF(X29<=0,100*1.04^(X29/12),100*1.025^(X29/12)) -> 100.61922 | AA29: 1 | AC29: =$AB$28*INDEX(I_rec,MATCH(inputs!$B$13+AA29,cpi_rec_u,0))/INDEX(I_rec,MATCH(inputs!$B$13,cpi_rec_u,0)) -> 103.51599 | AD29: =$AB$28*1.03^(AA29/12) -> 103.55797 | AF29: 45 | AG29: =IF($AF29<=85,1,IF($AF29<110,(110-$AF29)/25,0)) -> 1 | AH29: =1 -> 1 | AI29: =AH29*(1-$AG29*(0.01+0.01*AI$3)) -> 0.98 | AJ29: =AI29*(1-$AG29*(0.01+0.01*AJ$3)) -> 0.96047105 | AK29: =AJ29*(1-$AG29*(0.01+0.01*AK$3)) -> 0.94153056 | AL29: =AK29*(1-$AG29*(0.01+0.01*AL$3)) -> 0.92327193 | AM29: =AL29*(1-$AG29*(0.01+0.01*AM$3)) -> 0.90576669 | AN29: =AM29*(1-$AG29*(0.01+0.01*AN$3)) -> 0.88906662 | AO29: =AN29*(1-$AG29*(0.01+0.01*AO$3)) -> 0.87320567 | AP29: =AO29*(1-$AG29*(0.01+0.01*AP$3)) -> 0.85820182 | ... FC29: =FB29*(1-$AG29*(0.01+0.01*FC$3)) -> 0.25595353
A30: ra_param: sigma_l | B30: 0.1 | F30: 48 | G30: =1-EXP(-inputs!$B$35-inputs!$B$36*inputs!$B$37^$F30*(inputs!$B$37-1)/LN(inputs!$B$37)) -> 0.0010025248 | H30: =1-EXP(-inputs!$B$35-inputs!$B$36*inputs!$B$37^($F30-4)*(inputs!$B$37-1)/LN(inputs!$B$37)) -> 0.00071032986 | I30: =0.96*G30 -> 0.00096242378 | J30: =0.96*H30 -> 0.00068191667 | L30: 28 | M30: =L30/12 -> 2.3333333 | N30: =0.04-0.015*EXP(-M30/10) -> 0.028121657 | O30: =EXP(-N30*M30) -> 0.93648929 | P30: =O30*EXP(-inputs!$B$27*L30/12) -> 0.92562706 | Q30: =0.045-0.015*EXP(-M30/10) -> 0.033121657 | R30: =EXP(-Q30*M30) -> 0.92562706 | S30: =R30*EXP(-inputs!$B$27*L30/12) -> 0.91489083 | T30: =INDEX(P_rec,MATCH(inputs!$B$13+L30,curve_t,0))/INDEX(P_rec,MATCH(inputs!$B$13,curve_t,0)) -> 0.92058495 | U30: =T30/T29 -> 0.9968583 | V30: =T29/T30-1 -> 0.0031515988 | X30: 4 | Y30: =IF(X30<=0,100*1.04^(X30/12),100*1.025^(X30/12)) -> 100.82648 | AA30: 2 | AC30: =$AB$28*INDEX(I_rec,MATCH(inputs!$B$13+AA30,cpi_rec_u,0))/INDEX(I_rec,MATCH(inputs!$B$13,cpi_rec_u,0)) -> 103.72921 | AD30: =$AB$28*1.03^(AA30/12) -> 103.81338 | AF30: 46 | AG30: =IF($AF30<=85,1,IF($AF30<110,(110-$AF30)/25,0)) -> 1 | AH30: =1 -> 1 | AI30: =AH30*(1-$AG30*(0.01+0.01*AI$3)) -> 0.98 | AJ30: =AI30*(1-$AG30*(0.01+0.01*AJ$3)) -> 0.96047105 | AK30: =AJ30*(1-$AG30*(0.01+0.01*AK$3)) -> 0.94153056 | AL30: =AK30*(1-$AG30*(0.01+0.01*AL$3)) -> 0.92327193 | AM30: =AL30*(1-$AG30*(0.01+0.01*AM$3)) -> 0.90576669 | AN30: =AM30*(1-$AG30*(0.01+0.01*AN$3)) -> 0.88906662 | AO30: =AN30*(1-$AG30*(0.01+0.01*AO$3)) -> 0.87320567 | AP30: =AO30*(1-$AG30*(0.01+0.01*AP$3)) -> 0.85820182 | ... FC30: =FB30*(1-$AG30*(0.01+0.01*FC$3)) -> 0.25595353
A31: ra_param: sigma_e | B31: 0.1 | F31: 49 | G31: =1-EXP(-inputs!$B$35-inputs!$B$36*inputs!$B$37^$F31*(inputs!$B$37-1)/LN(inputs!$B$37)) -> 0.0010995182 | H31: =1-EXP(-inputs!$B$35-inputs!$B$36*inputs!$B$37^($F31-4)*(inputs!$B$37-1)/LN(inputs!$B$37)) -> 0.00077111701 | I31: =0.96*G31 -> 0.0010555374 | J31: =0.96*H31 -> 0.00074027233 | L31: 29 | M31: =L31/12 -> 2.4166667 | N31: =0.04-0.015*EXP(-M31/10) -> 0.028220231 | O31: =EXP(-N31*M31) -> 0.93407467 | P31: =O31*EXP(-inputs!$B$27*L31/12) -> 0.92285586 | Q31: =0.045-0.015*EXP(-M31/10) -> 0.033220231 | R31: =EXP(-Q31*M31) -> 0.92285586 | S31: =R31*EXP(-inputs!$B$27*L31/12) -> 0.91177178 | T31: =INDEX(P_rec,MATCH(inputs!$B$13+L31,curve_t,0))/INDEX(P_rec,MATCH(inputs!$B$13,curve_t,0)) -> 0.91768133 | U31: =T31/T30 -> 0.9968459 | V31: =T30/T31-1 -> 0.0031640781 | X31: 5 | Y31: =IF(X31<=0,100*1.04^(X31/12),100*1.025^(X31/12)) -> 101.03417 | AA31: 3 | AC31: =$AB$28*INDEX(I_rec,MATCH(inputs!$B$13+AA31,cpi_rec_u,0))/INDEX(I_rec,MATCH(inputs!$B$13,cpi_rec_u,0)) -> 103.94288 | AD31: =$AB$28*1.03^(AA31/12) -> 104.06941 | AF31: 47 | AG31: =IF($AF31<=85,1,IF($AF31<110,(110-$AF31)/25,0)) -> 1 | AH31: =1 -> 1 | AI31: =AH31*(1-$AG31*(0.01+0.01*AI$3)) -> 0.98 | AJ31: =AI31*(1-$AG31*(0.01+0.01*AJ$3)) -> 0.96047105 | AK31: =AJ31*(1-$AG31*(0.01+0.01*AK$3)) -> 0.94153056 | AL31: =AK31*(1-$AG31*(0.01+0.01*AL$3)) -> 0.92327193 | AM31: =AL31*(1-$AG31*(0.01+0.01*AM$3)) -> 0.90576669 | AN31: =AM31*(1-$AG31*(0.01+0.01*AN$3)) -> 0.88906662 | AO31: =AN31*(1-$AG31*(0.01+0.01*AO$3)) -> 0.87320567 | AP31: =AO31*(1-$AG31*(0.01+0.01*AP$3)) -> 0.85820182 | ... FC31: =FB31*(1-$AG31*(0.01+0.01*FC$3)) -> 0.25595353
A32: ie_m = (1 + ie_rate)^(1/12) - 1 (6.4) | B32: =(1+inputs!$B$26)^(1/12)-1 -> 0.00012491414 | F32: 50 | G32: =1-EXP(-inputs!$B$35-inputs!$B$36*inputs!$B$37^$F32*(inputs!$B$37-1)/LN(inputs!$B$37)) -> 0.0012085275 | H32: =1-EXP(-inputs!$B$35-inputs!$B$36*inputs!$B$37^($F32-4)*(inputs!$B$37-1)/LN(inputs!$B$37)) -> 0.00083943734 | I32: =0.96*G32 -> 0.0011601864 | J32: =0.96*H32 -> 0.00080585985 | L32: 30 | M32: =L32/12 -> 2.5 | N32: =0.04-0.015*EXP(-M32/10) -> 0.028317988 | O32: =EXP(-N32*M32) -> 0.93165289 | P32: =O32*EXP(-inputs!$B$27*L32/12) -> 0.92007971 | Q32: =0.045-0.015*EXP(-M32/10) -> 0.033317988 | R32: =EXP(-Q32*M32) -> 0.92007971 | S32: =R32*EXP(-inputs!$B$27*L32/12) -> 0.9086503 | T32: =INDEX(P_rec,MATCH(inputs!$B$13+L32,curve_t,0))/INDEX(P_rec,MATCH(inputs!$B$13,curve_t,0)) -> 0.91477565 | U32: =T32/T31 -> 0.99683367 | V32: =T31/T32-1 -> 0.003176392 | X32: 6 | Y32: =IF(X32<=0,100*1.04^(X32/12),100*1.025^(X32/12)) -> 101.24228 | AA32: 4 | AC32: =$AB$28*INDEX(I_rec,MATCH(inputs!$B$13+AA32,cpi_rec_u,0))/INDEX(I_rec,MATCH(inputs!$B$13,cpi_rec_u,0)) -> 104.15698 | AD32: =$AB$28*1.03^(AA32/12) -> 104.32607 | AF32: 48 | AG32: =IF($AF32<=85,1,IF($AF32<110,(110-$AF32)/25,0)) -> 1 | AH32: =1 -> 1 | AI32: =AH32*(1-$AG32*(0.01+0.01*AI$3)) -> 0.98 | AJ32: =AI32*(1-$AG32*(0.01+0.01*AJ$3)) -> 0.96047105 | AK32: =AJ32*(1-$AG32*(0.01+0.01*AK$3)) -> 0.94153056 | AL32: =AK32*(1-$AG32*(0.01+0.01*AL$3)) -> 0.92327193 | AM32: =AL32*(1-$AG32*(0.01+0.01*AM$3)) -> 0.90576669 | AN32: =AM32*(1-$AG32*(0.01+0.01*AN$3)) -> 0.88906662 | AO32: =AN32*(1-$AG32*(0.01+0.01*AO$3)) -> 0.87320567 | AP32: =AO32*(1-$AG32*(0.01+0.01*AP$3)) -> 0.85820182 | ... FC32: =FB32*(1-$AG32*(0.01+0.01*FC$3)) -> 0.25595353
A33: mort_mult = exp(-sigma_l * z_alpha - sigma_l * sigma_l / 2) (6.8) | B33: =EXP(-inputs!$B$30*inputs!$B$29-inputs!$B$30*inputs!$B$30/2) -> 0.9301132 | F33: 51 | G33: =1-EXP(-inputs!$B$35-inputs!$B$36*inputs!$B$37^$F33*(inputs!$B$37-1)/LN(inputs!$B$37)) -> 0.0013310397 | H33: =1-EXP(-inputs!$B$35-inputs!$B$36*inputs!$B$37^($F33-4)*(inputs!$B$37-1)/LN(inputs!$B$37)) -> 0.00091622382 | I33: =0.96*G33 -> 0.0012777981 | J33: =0.96*H33 -> 0.00087957486 | L33: 31 | M33: =L33/12 -> 2.5833333 | N33: =0.04-0.015*EXP(-M33/10) -> 0.028414934 | O33: =EXP(-N33*M33) -> 0.92922419 | P33: =O33*EXP(-inputs!$B$27*L33/12) -> 0.91729889 | Q33: =0.045-0.015*EXP(-M33/10) -> 0.033414934 | R33: =EXP(-Q33*M33) -> 0.91729889 | S33: =R33*EXP(-inputs!$B$27*L33/12) -> 0.90552664 | T33: =INDEX(P_rec,MATCH(inputs!$B$13+L33,curve_t,0))/INDEX(P_rec,MATCH(inputs!$B$13,curve_t,0)) -> 0.91186812 | U33: =T33/T32 -> 0.99682159 | V33: =T32/T33-1 -> 0.0031885425 | X33: 7 | Y33: =IF(X33<=0,100*1.04^(X33/12),100*1.025^(X33/12)) -> 101.45083 | AA33: 5 | AC33: =$AB$28*INDEX(I_rec,MATCH(inputs!$B$13+AA33,cpi_rec_u,0))/INDEX(I_rec,MATCH(inputs!$B$13,cpi_rec_u,0)) -> 104.37153 | AD33: =$AB$28*1.03^(AA33/12) -> 104.58337 | AF33: 49 | AG33: =IF($AF33<=85,1,IF($AF33<110,(110-$AF33)/25,0)) -> 1 | AH33: =1 -> 1 | AI33: =AH33*(1-$AG33*(0.01+0.01*AI$3)) -> 0.98 | AJ33: =AI33*(1-$AG33*(0.01+0.01*AJ$3)) -> 0.96047105 | AK33: =AJ33*(1-$AG33*(0.01+0.01*AK$3)) -> 0.94153056 | AL33: =AK33*(1-$AG33*(0.01+0.01*AL$3)) -> 0.92327193 | AM33: =AL33*(1-$AG33*(0.01+0.01*AM$3)) -> 0.90576669 | AN33: =AM33*(1-$AG33*(0.01+0.01*AN$3)) -> 0.88906662 | AO33: =AN33*(1-$AG33*(0.01+0.01*AO$3)) -> 0.87320567 | AP33: =AO33*(1-$AG33*(0.01+0.01*AP$3)) -> 0.85820182 | ... FC33: =FB33*(1-$AG33*(0.01+0.01*FC$3)) -> 0.25595353
A34: exp_mult = exp(sigma_e * z_alpha - sigma_e * sigma_e / 2) (6.8) | B34: =EXP(inputs!$B$31*inputs!$B$29-inputs!$B$31*inputs!$B$31/2) -> 1.0644401 | F34: 52 | G34: =1-EXP(-inputs!$B$35-inputs!$B$36*inputs!$B$37^$F34*(inputs!$B$37-1)/LN(inputs!$B$37)) -> 0.0014687256 | H34: =1-EXP(-inputs!$B$35-inputs!$B$36*inputs!$B$37^($F34-4)*(inputs!$B$37-1)/LN(inputs!$B$37)) -> 0.0010025248 | I34: =0.96*G34 -> 0.0014099766 | J34: =0.96*H34 -> 0.00096242378 | L34: 32 | M34: =L34/12 -> 2.6666667 | N34: =0.04-0.015*EXP(-M34/10) -> 0.028511075 | O34: =EXP(-N34*M34) -> 0.92678884 | P34: =O34*EXP(-inputs!$B$27*L34/12) -> 0.91451367 | Q34: =0.045-0.015*EXP(-M34/10) -> 0.033511075 | R34: =EXP(-Q34*M34) -> 0.91451367 | S34: =R34*EXP(-inputs!$B$27*L34/12) -> 0.90240108 | T34: =INDEX(P_rec,MATCH(inputs!$B$13+L34,curve_t,0))/INDEX(P_rec,MATCH(inputs!$B$13,curve_t,0)) -> 0.90895897 | U34: =T34/T33 -> 0.99680968 | V34: =T33/T34-1 -> 0.0032005315 | X34: 8 | Y34: =IF(X34<=0,100*1.04^(X34/12),100*1.025^(X34/12)) -> 101.6598 | AA34: 6 | AC34: =$AB$28*INDEX(I_rec,MATCH(inputs!$B$13+AA34,cpi_rec_u,0))/INDEX(I_rec,MATCH(inputs!$B$13,cpi_rec_u,0)) -> 104.58652 | AD34: =$AB$28*1.03^(AA34/12) -> 104.8413 | AF34: 50 | AG34: =IF($AF34<=85,1,IF($AF34<110,(110-$AF34)/25,0)) -> 1 | AH34: =1 -> 1 | AI34: =AH34*(1-$AG34*(0.01+0.01*AI$3)) -> 0.98 | AJ34: =AI34*(1-$AG34*(0.01+0.01*AJ$3)) -> 0.96047105 | AK34: =AJ34*(1-$AG34*(0.01+0.01*AK$3)) -> 0.94153056 | AL34: =AK34*(1-$AG34*(0.01+0.01*AL$3)) -> 0.92327193 | AM34: =AL34*(1-$AG34*(0.01+0.01*AM$3)) -> 0.90576669 | AN34: =AM34*(1-$AG34*(0.01+0.01*AN$3)) -> 0.88906662 | AO34: =AN34*(1-$AG34*(0.01+0.01*AO$3)) -> 0.87320567 | AP34: =AO34*(1-$AG34*(0.01+0.01*AP$3)) -> 0.85820182 | ... FC34: =FB34*(1-$AG34*(0.01+0.01*FC$3)) -> 0.25595353
A35: Makeham A (6.1) | B35: 0.00022 | F35: 53 | G35: =1-EXP(-inputs!$B$35-inputs!$B$36*inputs!$B$37^$F35*(inputs!$B$37-1)/LN(inputs!$B$37)) -> 0.0016234618 | H35: =1-EXP(-inputs!$B$35-inputs!$B$36*inputs!$B$37^($F35-4)*(inputs!$B$37-1)/LN(inputs!$B$37)) -> 0.0010995182 | I35: =0.96*G35 -> 0.0015585234 | J35: =0.96*H35 -> 0.0010555374 | L35: 33 | M35: =L35/12 -> 2.75 | N35: =0.04-0.015*EXP(-M35/10) -> 0.028606418 | O35: =EXP(-N35*M35) -> 0.92434708 | P35: =O35*EXP(-inputs!$B$27*L35/12) -> 0.91172429 | Q35: =0.045-0.015*EXP(-M35/10) -> 0.033606418 | R35: =EXP(-Q35*M35) -> 0.91172429 | S35: =R35*EXP(-inputs!$B$27*L35/12) -> 0.89927387 | T35: =INDEX(P_rec,MATCH(inputs!$B$13+L35,curve_t,0))/INDEX(P_rec,MATCH(inputs!$B$13,curve_t,0)) -> 0.90604841 | U35: =T35/T34 -> 0.99679793 | V35: =T34/T35-1 -> 0.0032123608 | X35: 9 | Y35: =IF(X35<=0,100*1.04^(X35/12),100*1.025^(X35/12)) -> 101.8692 | AA35: 7 | AC35: =$AB$28*INDEX(I_rec,MATCH(inputs!$B$13+AA35,cpi_rec_u,0))/INDEX(I_rec,MATCH(inputs!$B$13,cpi_rec_u,0)) -> 104.80195 | AD35: =$AB$28*1.03^(AA35/12) -> 105.09986 | AF35: 51 | AG35: =IF($AF35<=85,1,IF($AF35<110,(110-$AF35)/25,0)) -> 1 | AH35: =1 -> 1 | AI35: =AH35*(1-$AG35*(0.01+0.01*AI$3)) -> 0.98 | AJ35: =AI35*(1-$AG35*(0.01+0.01*AJ$3)) -> 0.96047105 | AK35: =AJ35*(1-$AG35*(0.01+0.01*AK$3)) -> 0.94153056 | AL35: =AK35*(1-$AG35*(0.01+0.01*AL$3)) -> 0.92327193 | AM35: =AL35*(1-$AG35*(0.01+0.01*AM$3)) -> 0.90576669 | AN35: =AM35*(1-$AG35*(0.01+0.01*AN$3)) -> 0.88906662 | AO35: =AN35*(1-$AG35*(0.01+0.01*AO$3)) -> 0.87320567 | AP35: =AO35*(1-$AG35*(0.01+0.01*AP$3)) -> 0.85820182 | ... FC35: =FB35*(1-$AG35*(0.01+0.01*FC$3)) -> 0.25595353
A36: Makeham B (6.1) | B36: 2.7e-06 | F36: 54 | G36: =1-EXP(-inputs!$B$35-inputs!$B$36*inputs!$B$37^$F36*(inputs!$B$37-1)/LN(inputs!$B$37)) -> 0.0017973567 | H36: =1-EXP(-inputs!$B$35-inputs!$B$36*inputs!$B$37^($F36-4)*(inputs!$B$37-1)/LN(inputs!$B$37)) -> 0.0012085275 | I36: =0.96*G36 -> 0.0017254625 | J36: =0.96*H36 -> 0.0011601864 | L36: 34 | M36: =L36/12 -> 2.8333333 | N36: =0.04-0.015*EXP(-M36/10) -> 0.02870097 | O36: =EXP(-N36*M36) -> 0.92189918 | P36: =O36*EXP(-inputs!$B$27*L36/12) -> 0.90893101 | Q36: =0.045-0.015*EXP(-M36/10) -> 0.03370097 | R36: =EXP(-Q36*M36) -> 0.90893101 | S36: =R36*EXP(-inputs!$B$27*L36/12) -> 0.89614527 | T36: =INDEX(P_rec,MATCH(inputs!$B$13+L36,curve_t,0))/INDEX(P_rec,MATCH(inputs!$B$13,curve_t,0)) -> 0.90313667 | U36: =T36/T35 -> 0.99678633 | V36: =T35/T36-1 -> 0.0032240322 | X36: 10 | Y36: =IF(X36<=0,100*1.04^(X36/12),100*1.025^(X36/12)) -> 102.07903 | AA36: 8 | AC36: =$AB$28*INDEX(I_rec,MATCH(inputs!$B$13+AA36,cpi_rec_u,0))/INDEX(I_rec,MATCH(inputs!$B$13,cpi_rec_u,0)) -> 105.01782 | AD36: =$AB$28*1.03^(AA36/12) -> 105.35907 | AF36: 52 | AG36: =IF($AF36<=85,1,IF($AF36<110,(110-$AF36)/25,0)) -> 1 | AH36: =1 -> 1 | AI36: =AH36*(1-$AG36*(0.01+0.01*AI$3)) -> 0.98 | AJ36: =AI36*(1-$AG36*(0.01+0.01*AJ$3)) -> 0.96047105 | AK36: =AJ36*(1-$AG36*(0.01+0.01*AK$3)) -> 0.94153056 | AL36: =AK36*(1-$AG36*(0.01+0.01*AL$3)) -> 0.92327193 | AM36: =AL36*(1-$AG36*(0.01+0.01*AM$3)) -> 0.90576669 | AN36: =AM36*(1-$AG36*(0.01+0.01*AN$3)) -> 0.88906662 | AO36: =AN36*(1-$AG36*(0.01+0.01*AO$3)) -> 0.87320567 | AP36: =AO36*(1-$AG36*(0.01+0.01*AP$3)) -> 0.85820182 | ... FC36: =FB36*(1-$AG36*(0.01+0.01*FC$3)) -> 0.25595353
A37: Makeham c (6.1) | B37: 1.124 | F37: 55 | G37: =1-EXP(-inputs!$B$35-inputs!$B$36*inputs!$B$37^$F37*(inputs!$B$37-1)/LN(inputs!$B$37)) -> 0.0019927785 | H37: =1-EXP(-inputs!$B$35-inputs!$B$36*inputs!$B$37^($F37-4)*(inputs!$B$37-1)/LN(inputs!$B$37)) -> 0.0013310397 | I37: =0.96*G37 -> 0.0019130673 | J37: =0.96*H37 -> 0.0012777981 | L37: 35 | M37: =L37/12 -> 2.9166667 | N37: =0.04-0.015*EXP(-M37/10) -> 0.028794737 | O37: =EXP(-N37*M37) -> 0.91944537 | P37: =O37*EXP(-inputs!$B$27*L37/12) -> 0.90613409 | Q37: =0.045-0.015*EXP(-M37/10) -> 0.033794737 | R37: =EXP(-Q37*M37) -> 0.90613409 | S37: =R37*EXP(-inputs!$B$27*L37/12) -> 0.89301552 | T37: =INDEX(P_rec,MATCH(inputs!$B$13+L37,curve_t,0))/INDEX(P_rec,MATCH(inputs!$B$13,curve_t,0)) -> 0.90022395 | U37: =T37/T36 -> 0.99677489 | V37: =T36/T37-1 -> 0.0032355475 | X37: 11 | Y37: =IF(X37<=0,100*1.04^(X37/12),100*1.025^(X37/12)) -> 102.2893 | AA37: 9 | AC37: =$AB$28*INDEX(I_rec,MATCH(inputs!$B$13+AA37,cpi_rec_u,0))/INDEX(I_rec,MATCH(inputs!$B$13,cpi_rec_u,0)) -> 105.23414 | AD37: =$AB$28*1.03^(AA37/12) -> 105.61891 | AF37: 53 | AG37: =IF($AF37<=85,1,IF($AF37<110,(110-$AF37)/25,0)) -> 1 | AH37: =1 -> 1 | AI37: =AH37*(1-$AG37*(0.01+0.01*AI$3)) -> 0.98 | AJ37: =AI37*(1-$AG37*(0.01+0.01*AJ$3)) -> 0.96047105 | AK37: =AJ37*(1-$AG37*(0.01+0.01*AK$3)) -> 0.94153056 | AL37: =AK37*(1-$AG37*(0.01+0.01*AL$3)) -> 0.92327193 | AM37: =AL37*(1-$AG37*(0.01+0.01*AM$3)) -> 0.90576669 | AN37: =AM37*(1-$AG37*(0.01+0.01*AN$3)) -> 0.88906662 | AO37: =AN37*(1-$AG37*(0.01+0.01*AO$3)) -> 0.87320567 | AP37: =AO37*(1-$AG37*(0.01+0.01*AP$3)) -> 0.85820182 | ... FC37: =FB37*(1-$AG37*(0.01+0.01*FC$3)) -> 0.25595353
F38: 56 | G38: =1-EXP(-inputs!$B$35-inputs!$B$36*inputs!$B$37^$F38*(inputs!$B$37-1)/LN(inputs!$B$37)) -> 0.0022123868 | H38: =1-EXP(-inputs!$B$35-inputs!$B$36*inputs!$B$37^($F38-4)*(inputs!$B$37-1)/LN(inputs!$B$37)) -> 0.0014687256 | I38: =0.96*G38 -> 0.0021238914 | J38: =0.96*H38 -> 0.0014099766 | L38: 36 | M38: =L38/12 -> 3 | N38: =0.04-0.015*EXP(-M38/10) -> 0.028887727 | O38: =EXP(-N38*M38) -> 0.9169859 | P38: =O38*EXP(-inputs!$B$27*L38/12) -> 0.90333376 | Q38: =0.045-0.015*EXP(-M38/10) -> 0.033887727 | R38: =EXP(-Q38*M38) -> 0.90333376 | S38: =R38*EXP(-inputs!$B$27*L38/12) -> 0.88988487 | T38: =INDEX(P_rec,MATCH(inputs!$B$13+L38,curve_t,0))/INDEX(P_rec,MATCH(inputs!$B$13,curve_t,0)) -> 0.89731047 | U38: =T38/T37 -> 0.9967636 | V38: =T37/T38-1 -> 0.0032469085 | X38: 12 | Y38: =IF(X38<=0,100*1.04^(X38/12),100*1.025^(X38/12)) -> 102.5 | AA38: 10 | AC38: =$AB$28*INDEX(I_rec,MATCH(inputs!$B$13+AA38,cpi_rec_u,0))/INDEX(I_rec,MATCH(inputs!$B$13,cpi_rec_u,0)) -> 105.45091 | AD38: =$AB$28*1.03^(AA38/12) -> 105.8794 | AF38: 54 | AG38: =IF($AF38<=85,1,IF($AF38<110,(110-$AF38)/25,0)) -> 1 | AH38: =1 -> 1 | AI38: =AH38*(1-$AG38*(0.01+0.01*AI$3)) -> 0.98 | AJ38: =AI38*(1-$AG38*(0.01+0.01*AJ$3)) -> 0.96047105 | AK38: =AJ38*(1-$AG38*(0.01+0.01*AK$3)) -> 0.94153056 | AL38: =AK38*(1-$AG38*(0.01+0.01*AL$3)) -> 0.92327193 | AM38: =AL38*(1-$AG38*(0.01+0.01*AM$3)) -> 0.90576669 | AN38: =AM38*(1-$AG38*(0.01+0.01*AN$3)) -> 0.88906662 | AO38: =AN38*(1-$AG38*(0.01+0.01*AO$3)) -> 0.87320567 | AP38: =AO38*(1-$AG38*(0.01+0.01*AP$3)) -> 0.85820182 | ... FC38: =FB38*(1-$AG38*(0.01+0.01*FC$3)) -> 0.25595353
A39: 3.3 Group inputs and 3.4 reads from the previous run (the REC sheets) | F39: 57 | G39: =1-EXP(-inputs!$B$35-inputs!$B$36*inputs!$B$37^$F39*(inputs!$B$37-1)/LN(inputs!$B$37)) -> 0.0024591689 | H39: =1-EXP(-inputs!$B$35-inputs!$B$36*inputs!$B$37^($F39-4)*(inputs!$B$37-1)/LN(inputs!$B$37)) -> 0.0016234618 | I39: =0.96*G39 -> 0.0023608022 | J39: =0.96*H39 -> 0.0015585234 | L39: 37 | M39: =L39/12 -> 3.0833333 | N39: =0.04-0.015*EXP(-M39/10) -> 0.028979944 | O39: =EXP(-N39*M39) -> 0.91452102 | P39: =O39*EXP(-inputs!$B$27*L39/12) -> 0.90053028 | Q39: =0.045-0.015*EXP(-M39/10) -> 0.033979944 | R39: =EXP(-Q39*M39) -> 0.90053028 | S39: =R39*EXP(-inputs!$B$27*L39/12) -> 0.88675357 | T39: =INDEX(P_rec,MATCH(inputs!$B$13+L39,curve_t,0))/INDEX(P_rec,MATCH(inputs!$B$13,curve_t,0)) -> 0.89439642 | U39: =T39/T38 -> 0.99675246 | V39: =T38/T39-1 -> 0.003258117 | X39: 13 | Y39: =IF(X39<=0,100*1.04^(X39/12),100*1.025^(X39/12)) -> 102.71113 | AA39: 11 | AC39: =$AB$28*INDEX(I_rec,MATCH(inputs!$B$13+AA39,cpi_rec_u,0))/INDEX(I_rec,MATCH(inputs!$B$13,cpi_rec_u,0)) -> 105.66812 | AD39: =$AB$28*1.03^(AA39/12) -> 106.14052 | AF39: 55 | AG39: =IF($AF39<=85,1,IF($AF39<110,(110-$AF39)/25,0)) -> 1 | AH39: =1 -> 1 | AI39: =AH39*(1-$AG39*(0.01+0.01*AI$3)) -> 0.98 | AJ39: =AI39*(1-$AG39*(0.01+0.01*AJ$3)) -> 0.96047105 | AK39: =AJ39*(1-$AG39*(0.01+0.01*AK$3)) -> 0.94153056 | AL39: =AK39*(1-$AG39*(0.01+0.01*AL$3)) -> 0.92327193 | AM39: =AL39*(1-$AG39*(0.01+0.01*AM$3)) -> 0.90576669 | AN39: =AM39*(1-$AG39*(0.01+0.01*AN$3)) -> 0.88906662 | AO39: =AN39*(1-$AG39*(0.01+0.01*AO$3)) -> 0.87320567 | AP39: =AO39*(1-$AG39*(0.01+0.01*AP$3)) -> 0.85820182 | ... FC39: =FB39*(1-$AG39*(0.01+0.01*FC$3)) -> 0.25595353
A40: portfolio | B40: =inputs!$B$64 -> IA | F40: 58 | G40: =1-EXP(-inputs!$B$35-inputs!$B$36*inputs!$B$37^$F40*(inputs!$B$37-1)/LN(inputs!$B$37)) -> 0.0027364792 | H40: =1-EXP(-inputs!$B$35-inputs!$B$36*inputs!$B$37^($F40-4)*(inputs!$B$37-1)/LN(inputs!$B$37)) -> 0.0017973567 | I40: =0.96*G40 -> 0.00262702 | J40: =0.96*H40 -> 0.0017254625 | L40: 38 | M40: =L40/12 -> 3.1666667 | N40: =0.04-0.015*EXP(-M40/10) -> 0.029071396 | O40: =EXP(-N40*M40) -> 0.91205095 | P40: =O40*EXP(-inputs!$B$27*L40/12) -> 0.89772387 | Q40: =0.045-0.015*EXP(-M40/10) -> 0.034071396 | R40: =EXP(-Q40*M40) -> 0.89772387 | S40: =R40*EXP(-inputs!$B$27*L40/12) -> 0.88362184 | T40: =INDEX(P_rec,MATCH(inputs!$B$13+L40,curve_t,0))/INDEX(P_rec,MATCH(inputs!$B$13,curve_t,0)) -> 0.89148201 | U40: =T40/T39 -> 0.99674148 | V40: =T39/T40-1 -> 0.0032691747 | X40: 14 | Y40: =IF(X40<=0,100*1.04^(X40/12),100*1.025^(X40/12)) -> 102.9227 | AA40: 12 | AC40: =$AB$28*INDEX(I_rec,MATCH(inputs!$B$13+AA40,cpi_rec_u,0))/INDEX(I_rec,MATCH(inputs!$B$13,cpi_rec_u,0)) -> 105.88578 | AD40: =$AB$28*1.03^(AA40/12) -> 106.4023 | AF40: 56 | AG40: =IF($AF40<=85,1,IF($AF40<110,(110-$AF40)/25,0)) -> 1 | AH40: =1 -> 1 | AI40: =AH40*(1-$AG40*(0.01+0.01*AI$3)) -> 0.98 | AJ40: =AI40*(1-$AG40*(0.01+0.01*AJ$3)) -> 0.96047105 | AK40: =AJ40*(1-$AG40*(0.01+0.01*AK$3)) -> 0.94153056 | AL40: =AK40*(1-$AG40*(0.01+0.01*AL$3)) -> 0.92327193 | AM40: =AL40*(1-$AG40*(0.01+0.01*AM$3)) -> 0.90576669 | AN40: =AM40*(1-$AG40*(0.01+0.01*AN$3)) -> 0.88906662 | AO40: =AN40*(1-$AG40*(0.01+0.01*AO$3)) -> 0.87320567 | AP40: =AO40*(1-$AG40*(0.01+0.01*AP$3)) -> 0.85820182 | ... FC40: =FB40*(1-$AG40*(0.01+0.01*FC$3)) -> 0.25595353
A41: cohort | B41: =inputs!$B$65 -> 2025 | F41: 59 | G41: =1-EXP(-inputs!$B$35-inputs!$B$36*inputs!$B$37^$F41*(inputs!$B$37-1)/LN(inputs!$B$37)) -> 0.0030480838 | H41: =1-EXP(-inputs!$B$35-inputs!$B$36*inputs!$B$37^($F41-4)*(inputs!$B$37-1)/LN(inputs!$B$37)) -> 0.0019927785 | I41: =0.96*G41 -> 0.0029261605 | J41: =0.96*H41 -> 0.0019130673 | L41: 39 | M41: =L41/12 -> 3.25 | N41: =0.04-0.015*EXP(-M41/10) -> 0.02916209 | O41: =EXP(-N41*M41) -> 0.90957594 | P41: =O41*EXP(-inputs!$B$27*L41/12) -> 0.89491477 | Q41: =0.045-0.015*EXP(-M41/10) -> 0.03416209 | R41: =EXP(-Q41*M41) -> 0.89491477 | S41: =R41*EXP(-inputs!$B$27*L41/12) -> 0.88048993 | T41: =INDEX(P_rec,MATCH(inputs!$B$13+L41,curve_t,0))/INDEX(P_rec,MATCH(inputs!$B$13,curve_t,0)) -> 0.88856743 | U41: =T41/T40 -> 0.99673064 | V41: =T40/T41-1 -> 0.0032800833 | X41: 15 | Y41: =IF(X41<=0,100*1.04^(X41/12),100*1.025^(X41/12)) -> 103.13471 | AA41: 13 | AC41: =$AB$28*INDEX(I_rec,MATCH(inputs!$B$13+AA41,cpi_rec_u,0))/INDEX(I_rec,MATCH(inputs!$B$13,cpi_rec_u,0)) -> 106.10389 | AD41: =$AB$28*1.03^(AA41/12) -> 106.66471 | AF41: 57 | AG41: =IF($AF41<=85,1,IF($AF41<110,(110-$AF41)/25,0)) -> 1 | AH41: =1 -> 1 | AI41: =AH41*(1-$AG41*(0.01+0.01*AI$3)) -> 0.98 | AJ41: =AI41*(1-$AG41*(0.01+0.01*AJ$3)) -> 0.96047105 | AK41: =AJ41*(1-$AG41*(0.01+0.01*AK$3)) -> 0.94153056 | AL41: =AK41*(1-$AG41*(0.01+0.01*AL$3)) -> 0.92327193 | AM41: =AL41*(1-$AG41*(0.01+0.01*AM$3)) -> 0.90576669 | AN41: =AM41*(1-$AG41*(0.01+0.01*AN$3)) -> 0.88906662 | AO41: =AN41*(1-$AG41*(0.01+0.01*AO$3)) -> 0.87320567 | AP41: =AO41*(1-$AG41*(0.01+0.01*AP$3)) -> 0.85820182 | ... FC41: =FB41*(1-$AG41*(0.01+0.01*FC$3)) -> 0.25595353
A42: profit_bucket | B42: =inputs!$B$66 -> ONEROUS | F42: 60 | G42: =1-EXP(-inputs!$B$35-inputs!$B$36*inputs!$B$37^$F42*(inputs!$B$37-1)/LN(inputs!$B$37)) -> 0.0033982113 | H42: =1-EXP(-inputs!$B$35-inputs!$B$36*inputs!$B$37^($F42-4)*(inputs!$B$37-1)/LN(inputs!$B$37)) -> 0.0022123868 | I42: =0.96*G42 -> 0.0032622828 | J42: =0.96*H42 -> 0.0021238914 | L42: 40 | M42: =L42/12 -> 3.3333333 | N42: =0.04-0.015*EXP(-M42/10) -> 0.02925203 | O42: =EXP(-N42*M42) -> 0.9070962 | P42: =O42*EXP(-inputs!$B$27*L42/12) -> 0.89210322 | Q42: =0.045-0.015*EXP(-M42/10) -> 0.03425203 | R42: =EXP(-Q42*M42) -> 0.89210322 | S42: =R42*EXP(-inputs!$B$27*L42/12) -> 0.87735805 | T42: =INDEX(P_rec,MATCH(inputs!$B$13+L42,curve_t,0))/INDEX(P_rec,MATCH(inputs!$B$13,curve_t,0)) -> 0.88565289 | U42: =T42/T41 -> 0.99671995 | V42: =T41/T42-1 -> 0.0032908446 | X42: 16 | Y42: =IF(X42<=0,100*1.04^(X42/12),100*1.025^(X42/12)) -> 103.34715 | AA42: 14 | AC42: =$AB$28*INDEX(I_rec,MATCH(inputs!$B$13+AA42,cpi_rec_u,0))/INDEX(I_rec,MATCH(inputs!$B$13,cpi_rec_u,0)) -> 106.32244 | AD42: =$AB$28*1.03^(AA42/12) -> 106.92778 | AF42: 58 | AG42: =IF($AF42<=85,1,IF($AF42<110,(110-$AF42)/25,0)) -> 1 | AH42: =1 -> 1 | AI42: =AH42*(1-$AG42*(0.01+0.01*AI$3)) -> 0.98 | AJ42: =AI42*(1-$AG42*(0.01+0.01*AJ$3)) -> 0.96047105 | AK42: =AJ42*(1-$AG42*(0.01+0.01*AK$3)) -> 0.94153056 | AL42: =AK42*(1-$AG42*(0.01+0.01*AL$3)) -> 0.92327193 | AM42: =AL42*(1-$AG42*(0.01+0.01*AM$3)) -> 0.90576669 | AN42: =AM42*(1-$AG42*(0.01+0.01*AN$3)) -> 0.88906662 | AO42: =AN42*(1-$AG42*(0.01+0.01*AO$3)) -> 0.87320567 | AP42: =AO42*(1-$AG42*(0.01+0.01*AP$3)) -> 0.85820182 | ... FC42: =FB42*(1-$AG42*(0.01+0.01*FC$3)) -> 0.25595353
A43: recognition_date | B43: =inputs!$B$8 -> 46022 | F43: 61 | G43: =1-EXP(-inputs!$B$35-inputs!$B$36*inputs!$B$37^$F43*(inputs!$B$37-1)/LN(inputs!$B$37)) -> 0.0037916077 | H43: =1-EXP(-inputs!$B$35-inputs!$B$36*inputs!$B$37^($F43-4)*(inputs!$B$37-1)/LN(inputs!$B$37)) -> 0.0024591689 | I43: =0.96*G43 -> 0.0036399434 | J43: =0.96*H43 -> 0.0023608022 | L43: 41 | M43: =L43/12 -> 3.4166667 | N43: =0.04-0.015*EXP(-M43/10) -> 0.029341225 | O43: =EXP(-N43*M43) -> 0.90461198 | P43: =O43*EXP(-inputs!$B$27*L43/12) -> 0.88928944 | Q43: =0.045-0.015*EXP(-M43/10) -> 0.034341225 | R43: =EXP(-Q43*M43) -> 0.88928944 | S43: =R43*EXP(-inputs!$B$27*L43/12) -> 0.87422644 | T43: =INDEX(P_rec,MATCH(inputs!$B$13+L43,curve_t,0))/INDEX(P_rec,MATCH(inputs!$B$13,curve_t,0)) -> 0.88273856 | U43: =T43/T42 -> 0.9967094 | V43: =T42/T43-1 -> 0.0033014603 | X43: 17 | Y43: =IF(X43<=0,100*1.04^(X43/12),100*1.025^(X43/12)) -> 103.56002 | AA43: 15 | AC43: =$AB$28*INDEX(I_rec,MATCH(inputs!$B$13+AA43,cpi_rec_u,0))/INDEX(I_rec,MATCH(inputs!$B$13,cpi_rec_u,0)) -> 106.54145 | AD43: =$AB$28*1.03^(AA43/12) -> 107.19149 | AF43: 59 | AG43: =IF($AF43<=85,1,IF($AF43<110,(110-$AF43)/25,0)) -> 1 | AH43: =1 -> 1 | AI43: =AH43*(1-$AG43*(0.01+0.01*AI$3)) -> 0.98 | AJ43: =AI43*(1-$AG43*(0.01+0.01*AJ$3)) -> 0.96047105 | AK43: =AJ43*(1-$AG43*(0.01+0.01*AK$3)) -> 0.94153056 | AL43: =AK43*(1-$AG43*(0.01+0.01*AL$3)) -> 0.92327193 | AM43: =AL43*(1-$AG43*(0.01+0.01*AM$3)) -> 0.90576669 | AN43: =AM43*(1-$AG43*(0.01+0.01*AN$3)) -> 0.88906662 | AO43: =AN43*(1-$AG43*(0.01+0.01*AO$3)) -> 0.87320567 | AP43: =AO43*(1-$AG43*(0.01+0.01*AP$3)) -> 0.85820182 | ... FC43: =FB43*(1-$AG43*(0.01+0.01*FC$3)) -> 0.25595353
A44: prev_valuation_date | B44: =inputs!$B$9 -> 46022 | F44: 62 | G44: =1-EXP(-inputs!$B$35-inputs!$B$36*inputs!$B$37^$F44*(inputs!$B$37-1)/LN(inputs!$B$37)) -> 0.0042336 | H44: =1-EXP(-inputs!$B$35-inputs!$B$36*inputs!$B$37^($F44-4)*(inputs!$B$37-1)/LN(inputs!$B$37)) -> 0.0027364792 | I44: =0.96*G44 -> 0.004064256 | J44: =0.96*H44 -> 0.00262702 | L44: 42 | M44: =L44/12 -> 3.5 | N44: =0.04-0.015*EXP(-M44/10) -> 0.029429679 | O44: =EXP(-N44*M44) -> 0.90212348 | P44: =O44*EXP(-inputs!$B$27*L44/12) -> 0.88647365 | Q44: =0.045-0.015*EXP(-M44/10) -> 0.034429679 | R44: =EXP(-Q44*M44) -> 0.88647365 | S44: =R44*EXP(-inputs!$B$27*L44/12) -> 0.87109532 | T44: =INDEX(P_rec,MATCH(inputs!$B$13+L44,curve_t,0))/INDEX(P_rec,MATCH(inputs!$B$13,curve_t,0)) -> 0.87982464 | U44: =T44/T43 -> 0.996699 | V44: =T43/T44-1 -> 0.0033119319 | X44: 18 | Y44: =IF(X44<=0,100*1.04^(X44/12),100*1.025^(X44/12)) -> 103.77334 | AA44: 16 | AC44: =$AB$28*INDEX(I_rec,MATCH(inputs!$B$13+AA44,cpi_rec_u,0))/INDEX(I_rec,MATCH(inputs!$B$13,cpi_rec_u,0)) -> 106.76091 | AD44: =$AB$28*1.03^(AA44/12) -> 107.45585 | AF44: 60 | AG44: =IF($AF44<=85,1,IF($AF44<110,(110-$AF44)/25,0)) -> 1 | AH44: =1 -> 1 | AI44: =AH44*(1-$AG44*(0.01+0.01*AI$3)) -> 0.98 | AJ44: =AI44*(1-$AG44*(0.01+0.01*AJ$3)) -> 0.96047105 | AK44: =AJ44*(1-$AG44*(0.01+0.01*AK$3)) -> 0.94153056 | AL44: =AK44*(1-$AG44*(0.01+0.01*AL$3)) -> 0.92327193 | AM44: =AL44*(1-$AG44*(0.01+0.01*AM$3)) -> 0.90576669 | AN44: =AM44*(1-$AG44*(0.01+0.01*AN$3)) -> 0.88906662 | AO44: =AN44*(1-$AG44*(0.01+0.01*AO$3)) -> 0.87320567 | AP44: =AO44*(1-$AG44*(0.01+0.01*AP$3)) -> 0.85820182 | ... FC44: =FB44*(1-$AG44*(0.01+0.01*FC$3)) -> 0.25595353
A45: csm_prev = CSM(0) of the REC run (group sheet) | B45: =group!$AJ$6 -> 0 | C45: read from the recognition run, not retyped (3.4) | F45: 63 | G45: =1-EXP(-inputs!$B$35-inputs!$B$36*inputs!$B$37^$F45*(inputs!$B$37-1)/LN(inputs!$B$37)) -> 0.0047301652 | H45: =1-EXP(-inputs!$B$35-inputs!$B$36*inputs!$B$37^($F45-4)*(inputs!$B$37-1)/LN(inputs!$B$37)) -> 0.0030480838 | I45: =0.96*G45 -> 0.0045409586 | J45: =0.96*H45 -> 0.0029261605 | L45: 43 | M45: =L45/12 -> 3.5833333 | N45: =0.04-0.015*EXP(-M45/10) -> 0.029517399 | O45: =EXP(-N45*M45) -> 0.89963093 | P45: =O45*EXP(-inputs!$B$27*L45/12) -> 0.88365608 | Q45: =0.045-0.015*EXP(-M45/10) -> 0.034517399 | R45: =EXP(-Q45*M45) -> 0.88365608 | S45: =R45*EXP(-inputs!$B$27*L45/12) -> 0.86796489 | T45: =INDEX(P_rec,MATCH(inputs!$B$13+L45,curve_t,0))/INDEX(P_rec,MATCH(inputs!$B$13,curve_t,0)) -> 0.87691131 | U45: =T45/T44 -> 0.99668874 | V45: =T44/T45-1 -> 0.0033222612 | X45: 19 | Y45: =IF(X45<=0,100*1.04^(X45/12),100*1.025^(X45/12)) -> 103.9871 | AA45: 17 | AC45: =$AB$28*INDEX(I_rec,MATCH(inputs!$B$13+AA45,cpi_rec_u,0))/INDEX(I_rec,MATCH(inputs!$B$13,cpi_rec_u,0)) -> 106.98082 | AD45: =$AB$28*1.03^(AA45/12) -> 107.72087 | AF45: 61 | AG45: =IF($AF45<=85,1,IF($AF45<110,(110-$AF45)/25,0)) -> 1 | AH45: =1 -> 1 | AI45: =AH45*(1-$AG45*(0.01+0.01*AI$3)) -> 0.98 | AJ45: =AI45*(1-$AG45*(0.01+0.01*AJ$3)) -> 0.96047105 | AK45: =AJ45*(1-$AG45*(0.01+0.01*AK$3)) -> 0.94153056 | AL45: =AK45*(1-$AG45*(0.01+0.01*AL$3)) -> 0.92327193 | AM45: =AL45*(1-$AG45*(0.01+0.01*AM$3)) -> 0.90576669 | AN45: =AM45*(1-$AG45*(0.01+0.01*AN$3)) -> 0.88906662 | AO45: =AN45*(1-$AG45*(0.01+0.01*AO$3)) -> 0.87320567 | AP45: =AO45*(1-$AG45*(0.01+0.01*AP$3)) -> 0.85820182 | ... FC45: =FB45*(1-$AG45*(0.01+0.01*FC$3)) -> 0.25595353
A46: lc_prev = LC(0) of the REC run (group sheet) | B46: =group!$AJ$7 -> 370593.24 | C46: read from the recognition run, not retyped (3.4) | F46: 64 | G46: =1-EXP(-inputs!$B$35-inputs!$B$36*inputs!$B$37^$F46*(inputs!$B$37-1)/LN(inputs!$B$37)) -> 0.0052880089 | H46: =1-EXP(-inputs!$B$35-inputs!$B$36*inputs!$B$37^($F46-4)*(inputs!$B$37-1)/LN(inputs!$B$37)) -> 0.0033982113 | I46: =0.96*G46 -> 0.0050764886 | J46: =0.96*H46 -> 0.0032622828 | L46: 44 | M46: =L46/12 -> 3.6666667 | N46: =0.04-0.015*EXP(-M46/10) -> 0.029604391 | O46: =EXP(-N46*M46) -> 0.89713455 | P46: =O46*EXP(-inputs!$B$27*L46/12) -> 0.88083693 | Q46: =0.045-0.015*EXP(-M46/10) -> 0.034604391 | R46: =EXP(-Q46*M46) -> 0.88083693 | S46: =R46*EXP(-inputs!$B$27*L46/12) -> 0.86483538 | T46: =INDEX(P_rec,MATCH(inputs!$B$13+L46,curve_t,0))/INDEX(P_rec,MATCH(inputs!$B$13,curve_t,0)) -> 0.87399876 | U46: =T46/T45 -> 0.99667862 | V46: =T45/T46-1 -> 0.0033324499 | X46: 20 | Y46: =IF(X46<=0,100*1.04^(X46/12),100*1.025^(X46/12)) -> 104.20129 | AA46: 18 | AC46: =$AB$28*INDEX(I_rec,MATCH(inputs!$B$13+AA46,cpi_rec_u,0))/INDEX(I_rec,MATCH(inputs!$B$13,cpi_rec_u,0)) -> 107.20118 | AD46: =$AB$28*1.03^(AA46/12) -> 107.98654 | AF46: 62 | AG46: =IF($AF46<=85,1,IF($AF46<110,(110-$AF46)/25,0)) -> 1 | AH46: =1 -> 1 | AI46: =AH46*(1-$AG46*(0.01+0.01*AI$3)) -> 0.98 | AJ46: =AI46*(1-$AG46*(0.01+0.01*AJ$3)) -> 0.96047105 | AK46: =AJ46*(1-$AG46*(0.01+0.01*AK$3)) -> 0.94153056 | AL46: =AK46*(1-$AG46*(0.01+0.01*AL$3)) -> 0.92327193 | AM46: =AL46*(1-$AG46*(0.01+0.01*AM$3)) -> 0.90576669 | AN46: =AM46*(1-$AG46*(0.01+0.01*AN$3)) -> 0.88906662 | AO46: =AN46*(1-$AG46*(0.01+0.01*AO$3)) -> 0.87320567 | AP46: =AO46*(1-$AG46*(0.01+0.01*AP$3)) -> 0.85820182 | ... FC46: =FB46*(1-$AG46*(0.01+0.01*FC$3)) -> 0.25595353
A47: cu_act (datum: payments actually made in the period) | B47: 1640400 | C47: section 13: the group input, a total | F47: 65 | G47: =1-EXP(-inputs!$B$35-inputs!$B$36*inputs!$B$37^$F47*(inputs!$B$37-1)/LN(inputs!$B$37)) -> 0.005914652 | H47: =1-EXP(-inputs!$B$35-inputs!$B$36*inputs!$B$37^($F47-4)*(inputs!$B$37-1)/LN(inputs!$B$37)) -> 0.0037916077 | I47: =0.96*G47 -> 0.0056780659 | J47: =0.96*H47 -> 0.0036399434 | L47: 45 | M47: =L47/12 -> 3.75 | N47: =0.04-0.015*EXP(-M47/10) -> 0.029690661 | O47: =EXP(-N47*M47) -> 0.89463454 | P47: =O47*EXP(-inputs!$B$27*L47/12) -> 0.87801643 | Q47: =0.045-0.015*EXP(-M47/10) -> 0.034690661 | R47: =EXP(-Q47*M47) -> 0.87801643 | S47: =R47*EXP(-inputs!$B$27*L47/12) -> 0.861707 | T47: =INDEX(P_rec,MATCH(inputs!$B$13+L47,curve_t,0))/INDEX(P_rec,MATCH(inputs!$B$13,curve_t,0)) -> 0.87108715 | U47: =T47/T46 -> 0.99666864 | V47: =T46/T47-1 -> 0.0033424994 | X47: 21 | Y47: =IF(X47<=0,100*1.04^(X47/12),100*1.025^(X47/12)) -> 104.41593 | AA47: 19 | AC47: =$AB$28*INDEX(I_rec,MATCH(inputs!$B$13+AA47,cpi_rec_u,0))/INDEX(I_rec,MATCH(inputs!$B$13,cpi_rec_u,0)) -> 107.422 | AD47: =$AB$28*1.03^(AA47/12) -> 108.25286 | AF47: 63 | AG47: =IF($AF47<=85,1,IF($AF47<110,(110-$AF47)/25,0)) -> 1 | AH47: =1 -> 1 | AI47: =AH47*(1-$AG47*(0.01+0.01*AI$3)) -> 0.98 | AJ47: =AI47*(1-$AG47*(0.01+0.01*AJ$3)) -> 0.96047105 | AK47: =AJ47*(1-$AG47*(0.01+0.01*AK$3)) -> 0.94153056 | AL47: =AK47*(1-$AG47*(0.01+0.01*AL$3)) -> 0.92327193 | AM47: =AL47*(1-$AG47*(0.01+0.01*AM$3)) -> 0.90576669 | AN47: =AM47*(1-$AG47*(0.01+0.01*AN$3)) -> 0.88906662 | AO47: =AN47*(1-$AG47*(0.01+0.01*AO$3)) -> 0.87320567 | AP47: =AO47*(1-$AG47*(0.01+0.01*AP$3)) -> 0.85820182 | ... FC47: =FB47*(1-$AG47*(0.01+0.01*FC$3)) -> 0.25595353
A48: prev_run_id | B48: REC-O | C48: the recognition run of this variant: the REC sheets | F48: 66 | G48: =1-EXP(-inputs!$B$35-inputs!$B$36*inputs!$B$37^$F48*(inputs!$B$37-1)/LN(inputs!$B$37)) -> 0.0066185277 | H48: =1-EXP(-inputs!$B$35-inputs!$B$36*inputs!$B$37^($F48-4)*(inputs!$B$37-1)/LN(inputs!$B$37)) -> 0.0042336 | I48: =0.96*G48 -> 0.0063537866 | J48: =0.96*H48 -> 0.004064256 | L48: 46 | M48: =L48/12 -> 3.8333333 | N48: =0.04-0.015*EXP(-M48/10) -> 0.029776215 | O48: =EXP(-N48*M48) -> 0.89213112 | P48: =O48*EXP(-inputs!$B$27*L48/12) -> 0.87519477 | Q48: =0.045-0.015*EXP(-M48/10) -> 0.034776215 | R48: =EXP(-Q48*M48) -> 0.87519477 | S48: =R48*EXP(-inputs!$B$27*L48/12) -> 0.85857994 | T48: =INDEX(P_rec,MATCH(inputs!$B$13+L48,curve_t,0))/INDEX(P_rec,MATCH(inputs!$B$13,curve_t,0)) -> 0.86817666 | U48: =T48/T47 -> 0.99665879 | V48: =T47/T48-1 -> 0.0033524115 | X48: 22 | Y48: =IF(X48<=0,100*1.04^(X48/12),100*1.025^(X48/12)) -> 104.63101 | AA48: 20 | AC48: =$AB$28*INDEX(I_rec,MATCH(inputs!$B$13+AA48,cpi_rec_u,0))/INDEX(I_rec,MATCH(inputs!$B$13,cpi_rec_u,0)) -> 107.64327 | AD48: =$AB$28*1.03^(AA48/12) -> 108.51984 | AF48: 64 | AG48: =IF($AF48<=85,1,IF($AF48<110,(110-$AF48)/25,0)) -> 1 | AH48: =1 -> 1 | AI48: =AH48*(1-$AG48*(0.01+0.01*AI$3)) -> 0.98 | AJ48: =AI48*(1-$AG48*(0.01+0.01*AJ$3)) -> 0.96047105 | AK48: =AJ48*(1-$AG48*(0.01+0.01*AK$3)) -> 0.94153056 | AL48: =AK48*(1-$AG48*(0.01+0.01*AL$3)) -> 0.92327193 | AM48: =AL48*(1-$AG48*(0.01+0.01*AM$3)) -> 0.90576669 | AN48: =AM48*(1-$AG48*(0.01+0.01*AN$3)) -> 0.88906662 | AO48: =AN48*(1-$AG48*(0.01+0.01*AO$3)) -> 0.87320567 | AP48: =AO48*(1-$AG48*(0.01+0.01*AP$3)) -> 0.85820182 | ... FC48: =FB48*(1-$AG48*(0.01+0.01*FC$3)) -> 0.25595353
A49: F_prev(0) = FCF_g^rec(0) | B49: =INDEX(group!$D$2:$D$503,MATCH(0,group!$A$2:$A$503,0)) -> 18529681 | C49: FCF_g^rec at month 0 (7.1) | F49: 67 | G49: =1-EXP(-inputs!$B$35-inputs!$B$36*inputs!$B$37^$F49*(inputs!$B$37-1)/LN(inputs!$B$37)) -> 0.007409089 | H49: =1-EXP(-inputs!$B$35-inputs!$B$36*inputs!$B$37^($F49-4)*(inputs!$B$37-1)/LN(inputs!$B$37)) -> 0.0047301652 | I49: =0.96*G49 -> 0.0071127254 | J49: =0.96*H49 -> 0.0045409586 | L49: 47 | M49: =L49/12 -> 3.9166667 | N49: =0.04-0.015*EXP(-M49/10) -> 0.029861059 | O49: =EXP(-N49*M49) -> 0.8896245 | P49: =O49*EXP(-inputs!$B$27*L49/12) -> 0.87237217 | Q49: =0.045-0.015*EXP(-M49/10) -> 0.034861059 | R49: =EXP(-Q49*M49) -> 0.87237217 | S49: =R49*EXP(-inputs!$B$27*L49/12) -> 0.85545441 | T49: =INDEX(P_rec,MATCH(inputs!$B$13+L49,curve_t,0))/INDEX(P_rec,MATCH(inputs!$B$13,curve_t,0)) -> 0.86526747 | U49: =T49/T48 -> 0.99664908 | V49: =T48/T49-1 -> 0.0033621878 | X49: 23 | Y49: =IF(X49<=0,100*1.04^(X49/12),100*1.025^(X49/12)) -> 104.84653 | AA49: 21 | AC49: =$AB$28*INDEX(I_rec,MATCH(inputs!$B$13+AA49,cpi_rec_u,0))/INDEX(I_rec,MATCH(inputs!$B$13,cpi_rec_u,0)) -> 107.865 | AD49: =$AB$28*1.03^(AA49/12) -> 108.78748 | AF49: 65 | AG49: =IF($AF49<=85,1,IF($AF49<110,(110-$AF49)/25,0)) -> 1 | AH49: =1 -> 1 | AI49: =AH49*(1-$AG49*(0.01+0.01*AI$3)) -> 0.98 | AJ49: =AI49*(1-$AG49*(0.01+0.01*AJ$3)) -> 0.96047105 | AK49: =AJ49*(1-$AG49*(0.01+0.01*AK$3)) -> 0.94153056 | AL49: =AK49*(1-$AG49*(0.01+0.01*AL$3)) -> 0.92327193 | AM49: =AL49*(1-$AG49*(0.01+0.01*AM$3)) -> 0.90576669 | AN49: =AM49*(1-$AG49*(0.01+0.01*AN$3)) -> 0.88906662 | AO49: =AN49*(1-$AG49*(0.01+0.01*AO$3)) -> 0.87320567 | AP49: =AO49*(1-$AG49*(0.01+0.01*AP$3)) -> 0.85820182 | ... FC49: =FB49*(1-$AG49*(0.01+0.01*FC$3)) -> 0.25595353
A50: F_prev(tau) = FCF_g^rec(tau) | B50: =INDEX(group!$D$2:$D$503,MATCH(inputs!$B$14,group!$A$2:$A$503,0)) -> 17362216 | C50: FCF_g^rec at month tau (7.1) | F50: 68 | G50: =1-EXP(-inputs!$B$35-inputs!$B$36*inputs!$B$37^$F50*(inputs!$B$37-1)/LN(inputs!$B$37)) -> 0.008296929 | H50: =1-EXP(-inputs!$B$35-inputs!$B$36*inputs!$B$37^($F50-4)*(inputs!$B$37-1)/LN(inputs!$B$37)) -> 0.0052880089 | I50: =0.96*G50 -> 0.0079650518 | J50: =0.96*H50 -> 0.0050764886 | L50: 48 | M50: =L50/12 -> 4 | N50: =0.04-0.015*EXP(-M50/10) -> 0.029945199 | O50: =EXP(-N50*M50) -> 0.88711487 | P50: =O50*EXP(-inputs!$B$27*L50/12) -> 0.86954882 | Q50: =0.045-0.015*EXP(-M50/10) -> 0.034945199 | R50: =EXP(-Q50*M50) -> 0.86954882 | S50: =R50*EXP(-inputs!$B$27*L50/12) -> 0.8523306 | T50: =INDEX(P_rec,MATCH(inputs!$B$13+L50,curve_t,0))/INDEX(P_rec,MATCH(inputs!$B$13,curve_t,0)) -> 0.86235974 | U50: =T50/T49 -> 0.9966395 | V50: =T49/T50-1 -> 0.0033718297 | X50: 24 | Y50: =IF(X50<=0,100*1.04^(X50/12),100*1.025^(X50/12)) -> 105.0625 | AA50: 22 | AC50: =$AB$28*INDEX(I_rec,MATCH(inputs!$B$13+AA50,cpi_rec_u,0))/INDEX(I_rec,MATCH(inputs!$B$13,cpi_rec_u,0)) -> 108.08718 | AD50: =$AB$28*1.03^(AA50/12) -> 109.05578 | AF50: 66 | AG50: =IF($AF50<=85,1,IF($AF50<110,(110-$AF50)/25,0)) -> 1 | AH50: =1 -> 1 | AI50: =AH50*(1-$AG50*(0.01+0.01*AI$3)) -> 0.98 | AJ50: =AI50*(1-$AG50*(0.01+0.01*AJ$3)) -> 0.96047105 | AK50: =AJ50*(1-$AG50*(0.01+0.01*AK$3)) -> 0.94153056 | AL50: =AK50*(1-$AG50*(0.01+0.01*AL$3)) -> 0.92327193 | AM50: =AL50*(1-$AG50*(0.01+0.01*AM$3)) -> 0.90576669 | AN50: =AM50*(1-$AG50*(0.01+0.01*AN$3)) -> 0.88906662 | AO50: =AN50*(1-$AG50*(0.01+0.01*AO$3)) -> 0.87320567 | AP50: =AO50*(1-$AG50*(0.01+0.01*AP$3)) -> 0.85820182 | ... FC50: =FB50*(1-$AG50*(0.01+0.01*FC$3)) -> 0.25595353
F51: 69 | G51: =1-EXP(-inputs!$B$35-inputs!$B$36*inputs!$B$37^$F51*(inputs!$B$37-1)/LN(inputs!$B$37)) -> 0.0092939131 | H51: =1-EXP(-inputs!$B$35-inputs!$B$36*inputs!$B$37^($F51-4)*(inputs!$B$37-1)/LN(inputs!$B$37)) -> 0.005914652 | I51: =0.96*G51 -> 0.0089221566 | J51: =0.96*H51 -> 0.0056780659 | L51: 49 | M51: =L51/12 -> 4.0833333 | N51: =0.04-0.015*EXP(-M51/10) -> 0.030028641 | O51: =EXP(-N51*M51) -> 0.88460244 | P51: =O51*EXP(-inputs!$B$27*L51/12) -> 0.86672493 | Q51: =0.045-0.015*EXP(-M51/10) -> 0.035028641 | R51: =EXP(-Q51*M51) -> 0.86672493 | S51: =R51*EXP(-inputs!$B$27*L51/12) -> 0.84920872 | T51: =INDEX(P_rec,MATCH(inputs!$B$13+L51,curve_t,0))/INDEX(P_rec,MATCH(inputs!$B$13,curve_t,0)) -> 0.85945364 | U51: =T51/T50 -> 0.99663006 | V51: =T50/T51-1 -> 0.0033813389 | X51: 25 | Y51: =IF(X51<=0,100*1.04^(X51/12),100*1.025^(X51/12)) -> 105.27891 | AA51: 23 | AC51: =$AB$28*INDEX(I_rec,MATCH(inputs!$B$13+AA51,cpi_rec_u,0))/INDEX(I_rec,MATCH(inputs!$B$13,cpi_rec_u,0)) -> 108.30982 | AD51: =$AB$28*1.03^(AA51/12) -> 109.32474 | AF51: 67 | AG51: =IF($AF51<=85,1,IF($AF51<110,(110-$AF51)/25,0)) -> 1 | AH51: =1 -> 1 | AI51: =AH51*(1-$AG51*(0.01+0.01*AI$3)) -> 0.98 | AJ51: =AI51*(1-$AG51*(0.01+0.01*AJ$3)) -> 0.96047105 | AK51: =AJ51*(1-$AG51*(0.01+0.01*AK$3)) -> 0.94153056 | AL51: =AK51*(1-$AG51*(0.01+0.01*AL$3)) -> 0.92327193 | AM51: =AL51*(1-$AG51*(0.01+0.01*AM$3)) -> 0.90576669 | AN51: =AM51*(1-$AG51*(0.01+0.01*AN$3)) -> 0.88906662 | AO51: =AN51*(1-$AG51*(0.01+0.01*AO$3)) -> 0.87320567 | AP51: =AO51*(1-$AG51*(0.01+0.01*AP$3)) -> 0.85820182 | ... FC51: =FB51*(1-$AG51*(0.01+0.01*FC$3)) -> 0.25595353
A52: 13 Model points, one column per policy (derived fields by formula) | B52: policy 21 | C52: policy 22 | F52: 70 | G52: =1-EXP(-inputs!$B$35-inputs!$B$36*inputs!$B$37^$F52*(inputs!$B$37-1)/LN(inputs!$B$37)) -> 0.010413327 | H52: =1-EXP(-inputs!$B$35-inputs!$B$36*inputs!$B$37^($F52-4)*(inputs!$B$37-1)/LN(inputs!$B$37)) -> 0.0066185277 | I52: =0.96*G52 -> 0.0099967939 | J52: =0.96*H52 -> 0.0063537866 | L52: 50 | M52: =L52/12 -> 4.1666667 | N52: =0.04-0.015*EXP(-M52/10) -> 0.030111391 | O52: =EXP(-N52*M52) -> 0.88208741 | P52: =O52*EXP(-inputs!$B$27*L52/12) -> 0.86390069 | Q52: =0.045-0.015*EXP(-M52/10) -> 0.035111391 | R52: =EXP(-Q52*M52) -> 0.86390069 | S52: =R52*EXP(-inputs!$B$27*L52/12) -> 0.84608894 | T52: =INDEX(P_rec,MATCH(inputs!$B$13+L52,curve_t,0))/INDEX(P_rec,MATCH(inputs!$B$13,curve_t,0)) -> 0.85654932 | U52: =T52/T51 -> 0.99662074 | V52: =T51/T52-1 -> 0.0033907168 | X52: 26 | Y52: =IF(X52<=0,100*1.04^(X52/12),100*1.025^(X52/12)) -> 105.49577 | AA52: 24 | AC52: =$AB$28*INDEX(I_rec,MATCH(inputs!$B$13+AA52,cpi_rec_u,0))/INDEX(I_rec,MATCH(inputs!$B$13,cpi_rec_u,0)) -> 108.53292 | AD52: =$AB$28*1.03^(AA52/12) -> 109.59436 | AF52: 68 | AG52: =IF($AF52<=85,1,IF($AF52<110,(110-$AF52)/25,0)) -> 1 | AH52: =1 -> 1 | AI52: =AH52*(1-$AG52*(0.01+0.01*AI$3)) -> 0.98 | AJ52: =AI52*(1-$AG52*(0.01+0.01*AJ$3)) -> 0.96047105 | AK52: =AJ52*(1-$AG52*(0.01+0.01*AK$3)) -> 0.94153056 | AL52: =AK52*(1-$AG52*(0.01+0.01*AL$3)) -> 0.92327193 | AM52: =AL52*(1-$AG52*(0.01+0.01*AM$3)) -> 0.90576669 | AN52: =AM52*(1-$AG52*(0.01+0.01*AN$3)) -> 0.88906662 | AO52: =AN52*(1-$AG52*(0.01+0.01*AO$3)) -> 0.87320567 | AP52: =AO52*(1-$AG52*(0.01+0.01*AP$3)) -> 0.85820182 | ... FC52: =FB52*(1-$AG52*(0.01+0.01*FC$3)) -> 0.25595353
A53: policy_id | B53: 21 | C53: 22 | F53: 71 | G53: =1-EXP(-inputs!$B$35-inputs!$B$36*inputs!$B$37^$F53*(inputs!$B$37-1)/LN(inputs!$B$37)) -> 0.011670038 | H53: =1-EXP(-inputs!$B$35-inputs!$B$36*inputs!$B$37^($F53-4)*(inputs!$B$37-1)/LN(inputs!$B$37)) -> 0.007409089 | I53: =0.96*G53 -> 0.011203237 | J53: =0.96*H53 -> 0.0071127254 | L53: 51 | M53: =L53/12 -> 4.25 | N53: =0.04-0.015*EXP(-M53/10) -> 0.030193453 | O53: =EXP(-N53*M53) -> 0.87956996 | P53: =O53*EXP(-inputs!$B$27*L53/12) -> 0.86107629 | Q53: =0.045-0.015*EXP(-M53/10) -> 0.035193453 | R53: =EXP(-Q53*M53) -> 0.86107629 | S53: =R53*EXP(-inputs!$B$27*L53/12) -> 0.84297146 | T53: =INDEX(P_rec,MATCH(inputs!$B$13+L53,curve_t,0))/INDEX(P_rec,MATCH(inputs!$B$13,curve_t,0)) -> 0.85364695 | U53: =T53/T52 -> 0.99661156 | V53: =T52/T53-1 -> 0.0033999651 | X53: 27 | Y53: =IF(X53<=0,100*1.04^(X53/12),100*1.025^(X53/12)) -> 105.71307 | AA53: 25 | AC53: =$AB$28*INDEX(I_rec,MATCH(inputs!$B$13+AA53,cpi_rec_u,0))/INDEX(I_rec,MATCH(inputs!$B$13,cpi_rec_u,0)) -> 108.75648 | AD53: =$AB$28*1.03^(AA53/12) -> 109.86465 | AF53: 69 | AG53: =IF($AF53<=85,1,IF($AF53<110,(110-$AF53)/25,0)) -> 1 | AH53: =1 -> 1 | AI53: =AH53*(1-$AG53*(0.01+0.01*AI$3)) -> 0.98 | AJ53: =AI53*(1-$AG53*(0.01+0.01*AJ$3)) -> 0.96047105 | AK53: =AJ53*(1-$AG53*(0.01+0.01*AK$3)) -> 0.94153056 | AL53: =AK53*(1-$AG53*(0.01+0.01*AL$3)) -> 0.92327193 | AM53: =AL53*(1-$AG53*(0.01+0.01*AM$3)) -> 0.90576669 | AN53: =AM53*(1-$AG53*(0.01+0.01*AN$3)) -> 0.88906662 | AO53: =AN53*(1-$AG53*(0.01+0.01*AO$3)) -> 0.87320567 | AP53: =AO53*(1-$AG53*(0.01+0.01*AP$3)) -> 0.85820182 | ... FC53: =FB53*(1-$AG53*(0.01+0.01*FC$3)) -> 0.25595353
A54: class | B54: level | C54: CPI | F54: 72 | G54: =1-EXP(-inputs!$B$35-inputs!$B$36*inputs!$B$37^$F54*(inputs!$B$37-1)/LN(inputs!$B$37)) -> 0.013080677 | H54: =1-EXP(-inputs!$B$35-inputs!$B$36*inputs!$B$37^($F54-4)*(inputs!$B$37-1)/LN(inputs!$B$37)) -> 0.008296929 | I54: =0.96*G54 -> 0.01255745 | J54: =0.96*H54 -> 0.0079650518 | L54: 52 | M54: =L54/12 -> 4.3333333 | N54: =0.04-0.015*EXP(-M54/10) -> 0.030274835 | O54: =EXP(-N54*M54) -> 0.87705028 | P54: =O54*EXP(-inputs!$B$27*L54/12) -> 0.85825191 | Q54: =0.045-0.015*EXP(-M54/10) -> 0.035274835 | R54: =EXP(-Q54*M54) -> 0.85825191 | S54: =R54*EXP(-inputs!$B$27*L54/12) -> 0.83985646 | T54: =INDEX(P_rec,MATCH(inputs!$B$13+L54,curve_t,0))/INDEX(P_rec,MATCH(inputs!$B$13,curve_t,0)) -> 0.85074668 | U54: =T54/T53 -> 0.9966025 | V54: =T53/T54-1 -> 0.0034090851 | X54: 28 | Y54: =IF(X54<=0,100*1.04^(X54/12),100*1.025^(X54/12)) -> 105.93082 | AA54: 26 | AC54: =$AB$28*INDEX(I_rec,MATCH(inputs!$B$13+AA54,cpi_rec_u,0))/INDEX(I_rec,MATCH(inputs!$B$13,cpi_rec_u,0)) -> 108.98051 | AD54: =$AB$28*1.03^(AA54/12) -> 110.13561 | AF54: 70 | AG54: =IF($AF54<=85,1,IF($AF54<110,(110-$AF54)/25,0)) -> 1 | AH54: =1 -> 1 | AI54: =AH54*(1-$AG54*(0.01+0.01*AI$3)) -> 0.98 | AJ54: =AI54*(1-$AG54*(0.01+0.01*AJ$3)) -> 0.96047105 | AK54: =AJ54*(1-$AG54*(0.01+0.01*AK$3)) -> 0.94153056 | AL54: =AK54*(1-$AG54*(0.01+0.01*AL$3)) -> 0.92327193 | AM54: =AL54*(1-$AG54*(0.01+0.01*AM$3)) -> 0.90576669 | AN54: =AM54*(1-$AG54*(0.01+0.01*AN$3)) -> 0.88906662 | AO54: =AN54*(1-$AG54*(0.01+0.01*AO$3)) -> 0.87320567 | AP54: =AO54*(1-$AG54*(0.01+0.01*AP$3)) -> 0.85820182 | ... FC54: =FB54*(1-$AG54*(0.01+0.01*FC$3)) -> 0.25595353
A55: sex | B55: M | C55: F | F55: 73 | G55: =1-EXP(-inputs!$B$35-inputs!$B$36*inputs!$B$37^$F55*(inputs!$B$37-1)/LN(inputs!$B$37)) -> 0.014663832 | H55: =1-EXP(-inputs!$B$35-inputs!$B$36*inputs!$B$37^($F55-4)*(inputs!$B$37-1)/LN(inputs!$B$37)) -> 0.0092939131 | I55: =0.96*G55 -> 0.014077278 | J55: =0.96*H55 -> 0.0089221566 | L55: 53 | M55: =L55/12 -> 4.4166667 | N55: =0.04-0.015*EXP(-M55/10) -> 0.030355541 | O55: =EXP(-N55*M55) -> 0.87452858 | P55: =O55*EXP(-inputs!$B$27*L55/12) -> 0.85542775 | Q55: =0.045-0.015*EXP(-M55/10) -> 0.035355541 | R55: =EXP(-Q55*M55) -> 0.85542775 | S55: =R55*EXP(-inputs!$B$27*L55/12) -> 0.83674411 | T55: =INDEX(P_rec,MATCH(inputs!$B$13+L55,curve_t,0))/INDEX(P_rec,MATCH(inputs!$B$13,curve_t,0)) -> 0.84784867 | U55: =T55/T54 -> 0.99659356 | V55: =T54/T55-1 -> 0.0034180785 | X55: 29 | Y55: =IF(X55<=0,100*1.04^(X55/12),100*1.025^(X55/12)) -> 106.14902 | AA55: 27 | AC55: =$AB$28*INDEX(I_rec,MATCH(inputs!$B$13+AA55,cpi_rec_u,0))/INDEX(I_rec,MATCH(inputs!$B$13,cpi_rec_u,0)) -> 109.20499 | AD55: =$AB$28*1.03^(AA55/12) -> 110.40723 | AF55: 71 | AG55: =IF($AF55<=85,1,IF($AF55<110,(110-$AF55)/25,0)) -> 1 | AH55: =1 -> 1 | AI55: =AH55*(1-$AG55*(0.01+0.01*AI$3)) -> 0.98 | AJ55: =AI55*(1-$AG55*(0.01+0.01*AJ$3)) -> 0.96047105 | AK55: =AJ55*(1-$AG55*(0.01+0.01*AK$3)) -> 0.94153056 | AL55: =AK55*(1-$AG55*(0.01+0.01*AL$3)) -> 0.92327193 | AM55: =AL55*(1-$AG55*(0.01+0.01*AM$3)) -> 0.90576669 | AN55: =AM55*(1-$AG55*(0.01+0.01*AN$3)) -> 0.88906662 | AO55: =AN55*(1-$AG55*(0.01+0.01*AO$3)) -> 0.87320567 | AP55: =AO55*(1-$AG55*(0.01+0.01*AP$3)) -> 0.85820182 | ... FC55: =FB55*(1-$AG55*(0.01+0.01*FC$3)) -> 0.25595353
A56: date_of_birth | B56: 17394 | C56: 16771 | F56: 74 | G56: =1-EXP(-inputs!$B$35-inputs!$B$36*inputs!$B$37^$F56*(inputs!$B$37-1)/LN(inputs!$B$37)) -> 0.016440266 | H56: =1-EXP(-inputs!$B$35-inputs!$B$36*inputs!$B$37^($F56-4)*(inputs!$B$37-1)/LN(inputs!$B$37)) -> 0.010413327 | I56: =0.96*G56 -> 0.015782655 | J56: =0.96*H56 -> 0.0099967939 | L56: 54 | M56: =L56/12 -> 4.5 | N56: =0.04-0.015*EXP(-M56/10) -> 0.030435578 | O56: =EXP(-N56*M56) -> 0.87200502 | P56: =O56*EXP(-inputs!$B$27*L56/12) -> 0.85260399 | Q56: =0.045-0.015*EXP(-M56/10) -> 0.035435578 | R56: =EXP(-Q56*M56) -> 0.85260399 | S56: =R56*EXP(-inputs!$B$27*L56/12) -> 0.8336346 | T56: =INDEX(P_rec,MATCH(inputs!$B$13+L56,curve_t,0))/INDEX(P_rec,MATCH(inputs!$B$13,curve_t,0)) -> 0.84495306 | U56: =T56/T55 -> 0.99658476 | V56: =T55/T56-1 -> 0.0034269466 | X56: 30 | Y56: =IF(X56<=0,100*1.04^(X56/12),100*1.025^(X56/12)) -> 106.36767 | AA56: 28 | AC56: =$AB$28*INDEX(I_rec,MATCH(inputs!$B$13+AA56,cpi_rec_u,0))/INDEX(I_rec,MATCH(inputs!$B$13,cpi_rec_u,0)) -> 109.42993 | AD56: =$AB$28*1.03^(AA56/12) -> 110.67953 | AF56: 72 | AG56: =IF($AF56<=85,1,IF($AF56<110,(110-$AF56)/25,0)) -> 1 | AH56: =1 -> 1 | AI56: =AH56*(1-$AG56*(0.01+0.01*AI$3)) -> 0.98 | AJ56: =AI56*(1-$AG56*(0.01+0.01*AJ$3)) -> 0.96047105 | AK56: =AJ56*(1-$AG56*(0.01+0.01*AK$3)) -> 0.94153056 | AL56: =AK56*(1-$AG56*(0.01+0.01*AL$3)) -> 0.92327193 | AM56: =AL56*(1-$AG56*(0.01+0.01*AM$3)) -> 0.90576669 | AN56: =AM56*(1-$AG56*(0.01+0.01*AN$3)) -> 0.88906662 | AO56: =AN56*(1-$AG56*(0.01+0.01*AO$3)) -> 0.87320567 | AP56: =AO56*(1-$AG56*(0.01+0.01*AP$3)) -> 0.85820182 | ... FC56: =FB56*(1-$AG56*(0.01+0.01*FC$3)) -> 0.25595353
A57: issue_date | B57: 46022 | C57: 46022 | F57: 75 | G57: =1-EXP(-inputs!$B$35-inputs!$B$36*inputs!$B$37^$F57*(inputs!$B$37-1)/LN(inputs!$B$37)) -> 0.018433156 | H57: =1-EXP(-inputs!$B$35-inputs!$B$36*inputs!$B$37^($F57-4)*(inputs!$B$37-1)/LN(inputs!$B$37)) -> 0.011670038 | I57: =0.96*G57 -> 0.01769583 | J57: =0.96*H57 -> 0.011203237 | L57: 55 | M57: =L57/12 -> 4.5833333 | N57: =0.04-0.015*EXP(-M57/10) -> 0.03051495 | O57: =EXP(-N57*M57) -> 0.86947979 | P57: =O57*EXP(-inputs!$B$27*L57/12) -> 0.84978079 | Q57: =0.045-0.015*EXP(-M57/10) -> 0.03551495 | R57: =EXP(-Q57*M57) -> 0.84978079 | S57: =R57*EXP(-inputs!$B$27*L57/12) -> 0.8305281 | T57: =INDEX(P_rec,MATCH(inputs!$B$13+L57,curve_t,0))/INDEX(P_rec,MATCH(inputs!$B$13,curve_t,0)) -> 0.84206 | U57: =T57/T56 -> 0.99657607 | V57: =T56/T57-1 -> 0.003435691 | X57: 31 | Y57: =IF(X57<=0,100*1.04^(X57/12),100*1.025^(X57/12)) -> 106.58677 | AA57: 29 | AC57: =$AB$28*INDEX(I_rec,MATCH(inputs!$B$13+AA57,cpi_rec_u,0))/INDEX(I_rec,MATCH(inputs!$B$13,cpi_rec_u,0)) -> 109.65534 | AD57: =$AB$28*1.03^(AA57/12) -> 110.95249 | AF57: 73 | AG57: =IF($AF57<=85,1,IF($AF57<110,(110-$AF57)/25,0)) -> 1 | AH57: =1 -> 1 | AI57: =AH57*(1-$AG57*(0.01+0.01*AI$3)) -> 0.98 | AJ57: =AI57*(1-$AG57*(0.01+0.01*AJ$3)) -> 0.96047105 | AK57: =AJ57*(1-$AG57*(0.01+0.01*AK$3)) -> 0.94153056 | AL57: =AK57*(1-$AG57*(0.01+0.01*AL$3)) -> 0.92327193 | AM57: =AL57*(1-$AG57*(0.01+0.01*AM$3)) -> 0.90576669 | AN57: =AM57*(1-$AG57*(0.01+0.01*AN$3)) -> 0.88906662 | AO57: =AN57*(1-$AG57*(0.01+0.01*AO$3)) -> 0.87320567 | AP57: =AO57*(1-$AG57*(0.01+0.01*AP$3)) -> 0.85820182 | ... FC57: =FB57*(1-$AG57*(0.01+0.01*FC$3)) -> 0.25595353
A58: annuity_start_date | B58: 46023 | C58: 46023 | F58: 76 | G58: =1-EXP(-inputs!$B$35-inputs!$B$36*inputs!$B$37^$F58*(inputs!$B$37-1)/LN(inputs!$B$37)) -> 0.020668344 | H58: =1-EXP(-inputs!$B$35-inputs!$B$36*inputs!$B$37^($F58-4)*(inputs!$B$37-1)/LN(inputs!$B$37)) -> 0.013080677 | I58: =0.96*G58 -> 0.01984161 | J58: =0.96*H58 -> 0.01255745 | L58: 56 | M58: =L58/12 -> 4.6666667 | N58: =0.04-0.015*EXP(-M58/10) -> 0.030593664 | O58: =EXP(-N58*M58) -> 0.86695307 | P58: =O58*EXP(-inputs!$B$27*L58/12) -> 0.84695835 | Q58: =0.045-0.015*EXP(-M58/10) -> 0.035593664 | R58: =EXP(-Q58*M58) -> 0.84695835 | S58: =R58*EXP(-inputs!$B$27*L58/12) -> 0.82742476 | T58: =INDEX(P_rec,MATCH(inputs!$B$13+L58,curve_t,0))/INDEX(P_rec,MATCH(inputs!$B$13,curve_t,0)) -> 0.83916964 | U58: =T58/T57 -> 0.99656751 | V58: =T57/T58-1 -> 0.0034443131 | X58: 32 | Y58: =IF(X58<=0,100*1.04^(X58/12),100*1.025^(X58/12)) -> 106.80633 | AA58: 30 | AC58: =$AB$28*INDEX(I_rec,MATCH(inputs!$B$13+AA58,cpi_rec_u,0))/INDEX(I_rec,MATCH(inputs!$B$13,cpi_rec_u,0)) -> 109.88121 | AD58: =$AB$28*1.03^(AA58/12) -> 111.22613 | AF58: 74 | AG58: =IF($AF58<=85,1,IF($AF58<110,(110-$AF58)/25,0)) -> 1 | AH58: =1 -> 1 | AI58: =AH58*(1-$AG58*(0.01+0.01*AI$3)) -> 0.98 | AJ58: =AI58*(1-$AG58*(0.01+0.01*AJ$3)) -> 0.96047105 | AK58: =AJ58*(1-$AG58*(0.01+0.01*AK$3)) -> 0.94153056 | AL58: =AK58*(1-$AG58*(0.01+0.01*AL$3)) -> 0.92327193 | AM58: =AL58*(1-$AG58*(0.01+0.01*AM$3)) -> 0.90576669 | AN58: =AM58*(1-$AG58*(0.01+0.01*AN$3)) -> 0.88906662 | AO58: =AN58*(1-$AG58*(0.01+0.01*AO$3)) -> 0.87320567 | AP58: =AO58*(1-$AG58*(0.01+0.01*AP$3)) -> 0.85820182 | ... FC58: =FB58*(1-$AG58*(0.01+0.01*FC$3)) -> 0.25595353
A59: pols_if_init at recognition | B59: 100 | C59: 50 | F59: 77 | G59: =1-EXP(-inputs!$B$35-inputs!$B$36*inputs!$B$37^$F59*(inputs!$B$37-1)/LN(inputs!$B$37)) -> 0.023174621 | H59: =1-EXP(-inputs!$B$35-inputs!$B$36*inputs!$B$37^($F59-4)*(inputs!$B$37-1)/LN(inputs!$B$37)) -> 0.014663832 | I59: =0.96*G59 -> 0.022247636 | J59: =0.96*H59 -> 0.014077278 | L59: 57 | M59: =L59/12 -> 4.75 | N59: =0.04-0.015*EXP(-M59/10) -> 0.030671724 | O59: =EXP(-N59*M59) -> 0.86442504 | P59: =O59*EXP(-inputs!$B$27*L59/12) -> 0.84413682 | Q59: =0.045-0.015*EXP(-M59/10) -> 0.035671724 | R59: =EXP(-Q59*M59) -> 0.84413682 | S59: =R59*EXP(-inputs!$B$27*L59/12) -> 0.82432477 | T59: =INDEX(P_rec,MATCH(inputs!$B$13+L59,curve_t,0))/INDEX(P_rec,MATCH(inputs!$B$13,curve_t,0)) -> 0.83628211 | U59: =T59/T58 -> 0.99655907 | V59: =T58/T59-1 -> 0.0034528142 | X59: 33 | Y59: =IF(X59<=0,100*1.04^(X59/12),100*1.025^(X59/12)) -> 107.02633 | AA59: 31 | AC59: =$AB$28*INDEX(I_rec,MATCH(inputs!$B$13+AA59,cpi_rec_u,0))/INDEX(I_rec,MATCH(inputs!$B$13,cpi_rec_u,0)) -> 110.10755 | AD59: =$AB$28*1.03^(AA59/12) -> 111.50045 | AF59: 75 | AG59: =IF($AF59<=85,1,IF($AF59<110,(110-$AF59)/25,0)) -> 1 | AH59: =1 -> 1 | AI59: =AH59*(1-$AG59*(0.01+0.01*AI$3)) -> 0.98 | AJ59: =AI59*(1-$AG59*(0.01+0.01*AJ$3)) -> 0.96047105 | AK59: =AJ59*(1-$AG59*(0.01+0.01*AK$3)) -> 0.94153056 | AL59: =AK59*(1-$AG59*(0.01+0.01*AL$3)) -> 0.92327193 | AM59: =AL59*(1-$AG59*(0.01+0.01*AM$3)) -> 0.90576669 | AN59: =AM59*(1-$AG59*(0.01+0.01*AN$3)) -> 0.88906662 | AO59: =AN59*(1-$AG59*(0.01+0.01*AO$3)) -> 0.87320567 | AP59: =AO59*(1-$AG59*(0.01+0.01*AP$3)) -> 0.85820182 | ... FC59: =FB59*(1-$AG59*(0.01+0.01*FC$3)) -> 0.25595353
A60: instalment_pm at recognition | B60: 1000 | C60: 800 | F60: 78 | G60: =1-EXP(-inputs!$B$35-inputs!$B$36*inputs!$B$37^$F60*(inputs!$B$37-1)/LN(inputs!$B$37)) -> 0.02598402 | H60: =1-EXP(-inputs!$B$35-inputs!$B$36*inputs!$B$37^($F60-4)*(inputs!$B$37-1)/LN(inputs!$B$37)) -> 0.016440266 | I60: =0.96*G60 -> 0.024944659 | J60: =0.96*H60 -> 0.015782655 | L60: 58 | M60: =L60/12 -> 4.8333333 | N60: =0.04-0.015*EXP(-M60/10) -> 0.030749137 | O60: =EXP(-N60*M60) -> 0.86189586 | P60: =O60*EXP(-inputs!$B$27*L60/12) -> 0.84131638 | Q60: =0.045-0.015*EXP(-M60/10) -> 0.035749137 | R60: =EXP(-Q60*M60) -> 0.84131638 | S60: =R60*EXP(-inputs!$B$27*L60/12) -> 0.82122828 | T60: =INDEX(P_rec,MATCH(inputs!$B$13+L60,curve_t,0))/INDEX(P_rec,MATCH(inputs!$B$13,curve_t,0)) -> 0.83339756 | U60: =T60/T59 -> 0.99655074 | V60: =T59/T60-1 -> 0.0034611958 | X60: 34 | Y60: =IF(X60<=0,100*1.04^(X60/12),100*1.025^(X60/12)) -> 107.24679 | AA60: 32 | AC60: =$AB$28*INDEX(I_rec,MATCH(inputs!$B$13+AA60,cpi_rec_u,0))/INDEX(I_rec,MATCH(inputs!$B$13,cpi_rec_u,0)) -> 110.33435 | AD60: =$AB$28*1.03^(AA60/12) -> 111.77544 | AF60: 76 | AG60: =IF($AF60<=85,1,IF($AF60<110,(110-$AF60)/25,0)) -> 1 | AH60: =1 -> 1 | AI60: =AH60*(1-$AG60*(0.01+0.01*AI$3)) -> 0.98 | AJ60: =AI60*(1-$AG60*(0.01+0.01*AJ$3)) -> 0.96047105 | AK60: =AJ60*(1-$AG60*(0.01+0.01*AK$3)) -> 0.94153056 | AL60: =AK60*(1-$AG60*(0.01+0.01*AL$3)) -> 0.92327193 | AM60: =AL60*(1-$AG60*(0.01+0.01*AM$3)) -> 0.90576669 | AN60: =AM60*(1-$AG60*(0.01+0.01*AN$3)) -> 0.88906662 | AO60: =AN60*(1-$AG60*(0.01+0.01*AO$3)) -> 0.87320567 | AP60: =AO60*(1-$AG60*(0.01+0.01*AP$3)) -> 0.85820182 | ... FC60: =FB60*(1-$AG60*(0.01+0.01*FC$3)) -> 0.25595353
A61: single_premium | B61: 118966.91 | C61: 125247.94 | F61: 79 | G61: =1-EXP(-inputs!$B$35-inputs!$B$36*inputs!$B$37^$F61*(inputs!$B$37-1)/LN(inputs!$B$37)) -> 0.029132141 | H61: =1-EXP(-inputs!$B$35-inputs!$B$36*inputs!$B$37^($F61-4)*(inputs!$B$37-1)/LN(inputs!$B$37)) -> 0.018433156 | I61: =0.96*G61 -> 0.027966855 | J61: =0.96*H61 -> 0.01769583 | L61: 59 | M61: =L61/12 -> 4.9166667 | N61: =0.04-0.015*EXP(-M61/10) -> 0.030825907 | O61: =EXP(-N61*M61) -> 0.85936571 | P61: =O61*EXP(-inputs!$B$27*L61/12) -> 0.8384972 | Q61: =0.045-0.015*EXP(-M61/10) -> 0.035825907 | R61: =EXP(-Q61*M61) -> 0.8384972 | S61: =R61*EXP(-inputs!$B$27*L61/12) -> 0.81813544 | T61: =INDEX(P_rec,MATCH(inputs!$B$13+L61,curve_t,0))/INDEX(P_rec,MATCH(inputs!$B$13,curve_t,0)) -> 0.83051612 | U61: =T61/T60 -> 0.99654254 | V61: =T60/T61-1 -> 0.0034694594 | X61: 35 | Y61: =IF(X61<=0,100*1.04^(X61/12),100*1.025^(X61/12)) -> 107.4677 | AA61: 33 | AC61: =$AB$28*INDEX(I_rec,MATCH(inputs!$B$13+AA61,cpi_rec_u,0))/INDEX(I_rec,MATCH(inputs!$B$13,cpi_rec_u,0)) -> 110.56162 | AD61: =$AB$28*1.03^(AA61/12) -> 112.0511 | AF61: 77 | AG61: =IF($AF61<=85,1,IF($AF61<110,(110-$AF61)/25,0)) -> 1 | AH61: =1 -> 1 | AI61: =AH61*(1-$AG61*(0.01+0.01*AI$3)) -> 0.98 | AJ61: =AI61*(1-$AG61*(0.01+0.01*AJ$3)) -> 0.96047105 | AK61: =AJ61*(1-$AG61*(0.01+0.01*AK$3)) -> 0.94153056 | AL61: =AK61*(1-$AG61*(0.01+0.01*AL$3)) -> 0.92327193 | AM61: =AL61*(1-$AG61*(0.01+0.01*AM$3)) -> 0.90576669 | AN61: =AM61*(1-$AG61*(0.01+0.01*AN$3)) -> 0.88906662 | AO61: =AN61*(1-$AG61*(0.01+0.01*AO$3)) -> 0.87320567 | AP61: =AO61*(1-$AG61*(0.01+0.01*AP$3)) -> 0.85820182 | ... FC61: =FB61*(1-$AG61*(0.01+0.01*FC$3)) -> 0.25595353
A62: pols_if_init at V (actual) | B62: 95 | C62: 47 | D62: the survivors of the period (3.2) | F62: 80 | G62: =1-EXP(-inputs!$B$35-inputs!$B$36*inputs!$B$37^$F62*(inputs!$B$37-1)/LN(inputs!$B$37)) -> 0.032658484 | H62: =1-EXP(-inputs!$B$35-inputs!$B$36*inputs!$B$37^($F62-4)*(inputs!$B$37-1)/LN(inputs!$B$37)) -> 0.020668344 | I62: =0.96*G62 -> 0.031352145 | J62: =0.96*H62 -> 0.01984161 | L62: 60 | M62: =L62/12 -> 5 | N62: =0.04-0.015*EXP(-M62/10) -> 0.03090204 | O62: =EXP(-N62*M62) -> 0.85683475 | P62: =O62*EXP(-inputs!$B$27*L62/12) -> 0.83567943 | Q62: =0.045-0.015*EXP(-M62/10) -> 0.03590204 | R62: =EXP(-Q62*M62) -> 0.83567943 | S62: =R62*EXP(-inputs!$B$27*L62/12) -> 0.81504643 | T62: =INDEX(P_rec,MATCH(inputs!$B$13+L62,curve_t,0))/INDEX(P_rec,MATCH(inputs!$B$13,curve_t,0)) -> 0.82763792 | U62: =T62/T61 -> 0.99653445 | V62: =T61/T62-1 -> 0.0034776062 | X62: 36 | Y62: =IF(X62<=0,100*1.04^(X62/12),100*1.025^(X62/12)) -> 107.68906 | AA62: 34 | AC62: =$AB$28*INDEX(I_rec,MATCH(inputs!$B$13+AA62,cpi_rec_u,0))/INDEX(I_rec,MATCH(inputs!$B$13,cpi_rec_u,0)) -> 110.78936 | AD62: =$AB$28*1.03^(AA62/12) -> 112.32745 | AF62: 78 | AG62: =IF($AF62<=85,1,IF($AF62<110,(110-$AF62)/25,0)) -> 1 | AH62: =1 -> 1 | AI62: =AH62*(1-$AG62*(0.01+0.01*AI$3)) -> 0.98 | AJ62: =AI62*(1-$AG62*(0.01+0.01*AJ$3)) -> 0.96047105 | AK62: =AJ62*(1-$AG62*(0.01+0.01*AK$3)) -> 0.94153056 | AL62: =AK62*(1-$AG62*(0.01+0.01*AL$3)) -> 0.92327193 | AM62: =AL62*(1-$AG62*(0.01+0.01*AM$3)) -> 0.90576669 | AN62: =AM62*(1-$AG62*(0.01+0.01*AN$3)) -> 0.88906662 | AO62: =AN62*(1-$AG62*(0.01+0.01*AO$3)) -> 0.87320567 | AP62: =AO62*(1-$AG62*(0.01+0.01*AP$3)) -> 0.85820182 | ... FC62: =FB62*(1-$AG62*(0.01+0.01*FC$3)) -> 0.25595353
A63: instalment_pm at V (actual) | B63: 1000 | C63: 800 | D63: equals the recognition instalment here (section 4) | F63: 81 | G63: =1-EXP(-inputs!$B$35-inputs!$B$36*inputs!$B$37^$F63*(inputs!$B$37-1)/LN(inputs!$B$37)) -> 0.036606808 | H63: =1-EXP(-inputs!$B$35-inputs!$B$36*inputs!$B$37^($F63-4)*(inputs!$B$37-1)/LN(inputs!$B$37)) -> 0.023174621 | I63: =0.96*G63 -> 0.035142536 | J63: =0.96*H63 -> 0.022247636 | L63: 61 | M63: =L63/12 -> 5.0833333 | N63: =0.04-0.015*EXP(-M63/10) -> 0.030977541 | O63: =EXP(-N63*M63) -> 0.85430315 | P63: =O63*EXP(-inputs!$B$27*L63/12) -> 0.83286323 | Q63: =0.045-0.015*EXP(-M63/10) -> 0.035977541 | R63: =EXP(-Q63*M63) -> 0.83286323 | S63: =R63*EXP(-inputs!$B$27*L63/12) -> 0.81196138 | T63: =INDEX(P_rec,MATCH(inputs!$B$13+L63,curve_t,0))/INDEX(P_rec,MATCH(inputs!$B$13,curve_t,0)) -> 0.8247631 | U63: =T63/T62 -> 0.99652647 | V63: =T62/T63-1 -> 0.0034856377 | X63: 37 | Y63: =IF(X63<=0,100*1.04^(X63/12),100*1.025^(X63/12)) -> 107.91088 | AA63: 35 | AC63: =$AB$28*INDEX(I_rec,MATCH(inputs!$B$13+AA63,cpi_rec_u,0))/INDEX(I_rec,MATCH(inputs!$B$13,cpi_rec_u,0)) -> 111.01757 | AD63: =$AB$28*1.03^(AA63/12) -> 112.60448 | AF63: 79 | AG63: =IF($AF63<=85,1,IF($AF63<110,(110-$AF63)/25,0)) -> 1 | AH63: =1 -> 1 | AI63: =AH63*(1-$AG63*(0.01+0.01*AI$3)) -> 0.98 | AJ63: =AI63*(1-$AG63*(0.01+0.01*AJ$3)) -> 0.96047105 | AK63: =AJ63*(1-$AG63*(0.01+0.01*AK$3)) -> 0.94153056 | AL63: =AK63*(1-$AG63*(0.01+0.01*AL$3)) -> 0.92327193 | AM63: =AL63*(1-$AG63*(0.01+0.01*AM$3)) -> 0.90576669 | AN63: =AM63*(1-$AG63*(0.01+0.01*AN$3)) -> 0.88906662 | AO63: =AN63*(1-$AG63*(0.01+0.01*AO$3)) -> 0.87320567 | AP63: =AO63*(1-$AG63*(0.01+0.01*AP$3)) -> 0.85820182 | ... FC63: =FB63*(1-$AG63*(0.01+0.01*FC$3)) -> 0.25595353
A64: portfolio | B64: IA | C64: IA | F64: 82 | G64: =1-EXP(-inputs!$B$35-inputs!$B$36*inputs!$B$37^$F64*(inputs!$B$37-1)/LN(inputs!$B$37)) -> 0.04102549 | H64: =1-EXP(-inputs!$B$35-inputs!$B$36*inputs!$B$37^($F64-4)*(inputs!$B$37-1)/LN(inputs!$B$37)) -> 0.02598402 | I64: =0.96*G64 -> 0.03938447 | J64: =0.96*H64 -> 0.024944659 | L64: 62 | M64: =L64/12 -> 5.1666667 | N64: =0.04-0.015*EXP(-M64/10) -> 0.031052416 | O64: =EXP(-N64*M64) -> 0.85177107 | P64: =O64*EXP(-inputs!$B$27*L64/12) -> 0.83004877 | Q64: =0.045-0.015*EXP(-M64/10) -> 0.036052416 | R64: =EXP(-Q64*M64) -> 0.83004877 | S64: =R64*EXP(-inputs!$B$27*L64/12) -> 0.80888045 | T64: =INDEX(P_rec,MATCH(inputs!$B$13+L64,curve_t,0))/INDEX(P_rec,MATCH(inputs!$B$13,curve_t,0)) -> 0.82189177 | U64: =T64/T63 -> 0.99651861 | V64: =T63/T64-1 -> 0.0034935552 | X64: 38 | Y64: =IF(X64<=0,100*1.04^(X64/12),100*1.025^(X64/12)) -> 108.13316 | AA64: 36 | AC64: =$AB$28*INDEX(I_rec,MATCH(inputs!$B$13+AA64,cpi_rec_u,0))/INDEX(I_rec,MATCH(inputs!$B$13,cpi_rec_u,0)) -> 111.24625 | AD64: =$AB$28*1.03^(AA64/12) -> 112.8822 | AF64: 80 | AG64: =IF($AF64<=85,1,IF($AF64<110,(110-$AF64)/25,0)) -> 1 | AH64: =1 -> 1 | AI64: =AH64*(1-$AG64*(0.01+0.01*AI$3)) -> 0.98 | AJ64: =AI64*(1-$AG64*(0.01+0.01*AJ$3)) -> 0.96047105 | AK64: =AJ64*(1-$AG64*(0.01+0.01*AK$3)) -> 0.94153056 | AL64: =AK64*(1-$AG64*(0.01+0.01*AL$3)) -> 0.92327193 | AM64: =AL64*(1-$AG64*(0.01+0.01*AM$3)) -> 0.90576669 | AN64: =AM64*(1-$AG64*(0.01+0.01*AN$3)) -> 0.88906662 | AO64: =AN64*(1-$AG64*(0.01+0.01*AO$3)) -> 0.87320567 | AP64: =AO64*(1-$AG64*(0.01+0.01*AP$3)) -> 0.85820182 | ... FC64: =FB64*(1-$AG64*(0.01+0.01*FC$3)) -> 0.25595353
A65: cohort | B65: 2025 | C65: 2025 | F65: 83 | G65: =1-EXP(-inputs!$B$35-inputs!$B$36*inputs!$B$37^$F65*(inputs!$B$37-1)/LN(inputs!$B$37)) -> 0.045967901 | H65: =1-EXP(-inputs!$B$35-inputs!$B$36*inputs!$B$37^($F65-4)*(inputs!$B$37-1)/LN(inputs!$B$37)) -> 0.029132141 | I65: =0.96*G65 -> 0.044129185 | J65: =0.96*H65 -> 0.027966855 | L65: 63 | M65: =L65/12 -> 5.25 | N65: =0.04-0.015*EXP(-M65/10) -> 0.03112667 | O65: =EXP(-N65*M65) -> 0.84923867 | P65: =O65*EXP(-inputs!$B$27*L65/12) -> 0.8272362 | Q65: =0.045-0.015*EXP(-M65/10) -> 0.03612667 | R65: =EXP(-Q65*M65) -> 0.8272362 | S65: =R65*EXP(-inputs!$B$27*L65/12) -> 0.80580378 | T65: =INDEX(P_rec,MATCH(inputs!$B$13+L65,curve_t,0))/INDEX(P_rec,MATCH(inputs!$B$13,curve_t,0)) -> 0.81902407 | U65: =T65/T64 -> 0.99651086 | V65: =T64/T65-1 -> 0.00350136 | X65: 39 | Y65: =IF(X65<=0,100*1.04^(X65/12),100*1.025^(X65/12)) -> 108.3559 | AA65: 37 | AC65: =$AB$28*INDEX(I_rec,MATCH(inputs!$B$13+AA65,cpi_rec_u,0))/INDEX(I_rec,MATCH(inputs!$B$13,cpi_rec_u,0)) -> 111.4754 | AD65: =$AB$28*1.03^(AA65/12) -> 113.16059 | AF65: 81 | AG65: =IF($AF65<=85,1,IF($AF65<110,(110-$AF65)/25,0)) -> 1 | AH65: =1 -> 1 | AI65: =AH65*(1-$AG65*(0.01+0.01*AI$3)) -> 0.98 | AJ65: =AI65*(1-$AG65*(0.01+0.01*AJ$3)) -> 0.96047105 | AK65: =AJ65*(1-$AG65*(0.01+0.01*AK$3)) -> 0.94153056 | AL65: =AK65*(1-$AG65*(0.01+0.01*AL$3)) -> 0.92327193 | AM65: =AL65*(1-$AG65*(0.01+0.01*AM$3)) -> 0.90576669 | AN65: =AM65*(1-$AG65*(0.01+0.01*AN$3)) -> 0.88906662 | AO65: =AN65*(1-$AG65*(0.01+0.01*AO$3)) -> 0.87320567 | AP65: =AO65*(1-$AG65*(0.01+0.01*AP$3)) -> 0.85820182 | ... FC65: =FB65*(1-$AG65*(0.01+0.01*FC$3)) -> 0.25595353
A66: profit_bucket | B66: ONEROUS | C66: ONEROUS | F66: 84 | G66: =1-EXP(-inputs!$B$35-inputs!$B$36*inputs!$B$37^$F66*(inputs!$B$37-1)/LN(inputs!$B$37)) -> 0.051492772 | H66: =1-EXP(-inputs!$B$35-inputs!$B$36*inputs!$B$37^($F66-4)*(inputs!$B$37-1)/LN(inputs!$B$37)) -> 0.032658484 | I66: =0.96*G66 -> 0.049433061 | J66: =0.96*H66 -> 0.031352145 | L66: 64 | M66: =L66/12 -> 5.3333333 | N66: =0.04-0.015*EXP(-M66/10) -> 0.031200307 | O66: =EXP(-N66*M66) -> 0.8467061 | P66: =O66*EXP(-inputs!$B$27*L66/12) -> 0.82442566 | Q66: =0.045-0.015*EXP(-M66/10) -> 0.036200307 | R66: =EXP(-Q66*M66) -> 0.82442566 | S66: =R66*EXP(-inputs!$B$27*L66/12) -> 0.80273152 | T66: =INDEX(P_rec,MATCH(inputs!$B$13+L66,curve_t,0))/INDEX(P_rec,MATCH(inputs!$B$13,curve_t,0)) -> 0.81616012 | U66: =T66/T65 -> 0.99650322 | V66: =T65/T66-1 -> 0.0035090535 | X66: 40 | Y66: =IF(X66<=0,100*1.04^(X66/12),100*1.025^(X66/12)) -> 108.5791 | AA66: 38 | AC66: =$AB$28*INDEX(I_rec,MATCH(inputs!$B$13+AA66,cpi_rec_u,0))/INDEX(I_rec,MATCH(inputs!$B$13,cpi_rec_u,0)) -> 111.70502 | AD66: =$AB$28*1.03^(AA66/12) -> 113.43968 | AF66: 82 | AG66: =IF($AF66<=85,1,IF($AF66<110,(110-$AF66)/25,0)) -> 1 | AH66: =1 -> 1 | AI66: =AH66*(1-$AG66*(0.01+0.01*AI$3)) -> 0.98 | AJ66: =AI66*(1-$AG66*(0.01+0.01*AJ$3)) -> 0.96047105 | AK66: =AJ66*(1-$AG66*(0.01+0.01*AK$3)) -> 0.94153056 | AL66: =AK66*(1-$AG66*(0.01+0.01*AL$3)) -> 0.92327193 | AM66: =AL66*(1-$AG66*(0.01+0.01*AM$3)) -> 0.90576669 | AN66: =AM66*(1-$AG66*(0.01+0.01*AN$3)) -> 0.88906662 | AO66: =AN66*(1-$AG66*(0.01+0.01*AO$3)) -> 0.87320567 | AP66: =AO66*(1-$AG66*(0.01+0.01*AP$3)) -> 0.85820182 | ... FC66: =FB66*(1-$AG66*(0.01+0.01*FC$3)) -> 0.25595353
A67: mi(date_of_birth) | B67: =12*YEAR(inputs!$B$56)+MONTH(inputs!$B$56)-1 -> 23371 | C67: =12*YEAR(inputs!$C$56)+MONTH(inputs!$C$56)-1 -> 23350 | F67: 85 | G67: =1-EXP(-inputs!$B$35-inputs!$B$36*inputs!$B$37^$F67*(inputs!$B$37-1)/LN(inputs!$B$37)) -> 0.057664543 | H67: =1-EXP(-inputs!$B$35-inputs!$B$36*inputs!$B$37^($F67-4)*(inputs!$B$37-1)/LN(inputs!$B$37)) -> 0.036606808 | I67: =0.96*G67 -> 0.055357961 | J67: =0.96*H67 -> 0.035142536 | L67: 65 | M67: =L67/12 -> 5.4166667 | N67: =0.04-0.015*EXP(-M67/10) -> 0.031273333 | O67: =EXP(-N67*M67) -> 0.84417351 | P67: =O67*EXP(-inputs!$B$27*L67/12) -> 0.82161731 | Q67: =0.045-0.015*EXP(-M67/10) -> 0.036273333 | R67: =EXP(-Q67*M67) -> 0.82161731 | S67: =R67*EXP(-inputs!$B$27*L67/12) -> 0.7996638 | T67: =INDEX(P_rec,MATCH(inputs!$B$13+L67,curve_t,0))/INDEX(P_rec,MATCH(inputs!$B$13,curve_t,0)) -> 0.81330004 | U67: =T67/T66 -> 0.99649569 | V67: =T66/T67-1 -> 0.0035166369 | X67: 41 | Y67: =IF(X67<=0,100*1.04^(X67/12),100*1.025^(X67/12)) -> 108.80275 | AA67: 39 | AC67: =$AB$28*INDEX(I_rec,MATCH(inputs!$B$13+AA67,cpi_rec_u,0))/INDEX(I_rec,MATCH(inputs!$B$13,cpi_rec_u,0)) -> 111.93511 | AD67: =$AB$28*1.03^(AA67/12) -> 113.71945 | AF67: 83 | AG67: =IF($AF67<=85,1,IF($AF67<110,(110-$AF67)/25,0)) -> 1 | AH67: =1 -> 1 | AI67: =AH67*(1-$AG67*(0.01+0.01*AI$3)) -> 0.98 | AJ67: =AI67*(1-$AG67*(0.01+0.01*AJ$3)) -> 0.96047105 | AK67: =AJ67*(1-$AG67*(0.01+0.01*AK$3)) -> 0.94153056 | AL67: =AK67*(1-$AG67*(0.01+0.01*AL$3)) -> 0.92327193 | AM67: =AL67*(1-$AG67*(0.01+0.01*AM$3)) -> 0.90576669 | AN67: =AM67*(1-$AG67*(0.01+0.01*AN$3)) -> 0.88906662 | AO67: =AN67*(1-$AG67*(0.01+0.01*AO$3)) -> 0.87320567 | AP67: =AO67*(1-$AG67*(0.01+0.01*AP$3)) -> 0.85820182 | ... FC67: =FB67*(1-$AG67*(0.01+0.01*FC$3)) -> 0.25595353
A68: a0 at recognition = m_rec - mi(date_of_birth) | B68: =inputs!$B$11-inputs!$B$67 -> 940 | C68: =inputs!$B$11-inputs!$C$67 -> 961 | F68: 86 | G68: =1-EXP(-inputs!$B$35-inputs!$B$36*inputs!$B$37^$F68*(inputs!$B$37-1)/LN(inputs!$B$37)) -> 0.06455369 | H68: =1-EXP(-inputs!$B$35-inputs!$B$36*inputs!$B$37^($F68-4)*(inputs!$B$37-1)/LN(inputs!$B$37)) -> 0.04102549 | I68: =0.96*G68 -> 0.061971543 | J68: =0.96*H68 -> 0.03938447 | L68: 66 | M68: =L68/12 -> 5.5 | N68: =0.04-0.015*EXP(-M68/10) -> 0.031345753 | O68: =EXP(-N68*M68) -> 0.84164107 | P68: =O68*EXP(-inputs!$B$27*L68/12) -> 0.81881129 | Q68: =0.045-0.015*EXP(-M68/10) -> 0.036345753 | R68: =EXP(-Q68*M68) -> 0.81881129 | S68: =R68*EXP(-inputs!$B$27*L68/12) -> 0.79660077 | T68: =INDEX(P_rec,MATCH(inputs!$B$13+L68,curve_t,0))/INDEX(P_rec,MATCH(inputs!$B$13,curve_t,0)) -> 0.81044395 | U68: =T68/T67 -> 0.99648826 | V68: =T67/T68-1 -> 0.0035241117 | X68: 42 | Y68: =IF(X68<=0,100*1.04^(X68/12),100*1.025^(X68/12)) -> 109.02687 | AA68: 40 | AC68: =$AB$28*INDEX(I_rec,MATCH(inputs!$B$13+AA68,cpi_rec_u,0))/INDEX(I_rec,MATCH(inputs!$B$13,cpi_rec_u,0)) -> 112.16568 | AD68: =$AB$28*1.03^(AA68/12) -> 113.99991 | AF68: 84 | AG68: =IF($AF68<=85,1,IF($AF68<110,(110-$AF68)/25,0)) -> 1 | AH68: =1 -> 1 | AI68: =AH68*(1-$AG68*(0.01+0.01*AI$3)) -> 0.98 | AJ68: =AI68*(1-$AG68*(0.01+0.01*AJ$3)) -> 0.96047105 | AK68: =AJ68*(1-$AG68*(0.01+0.01*AK$3)) -> 0.94153056 | AL68: =AK68*(1-$AG68*(0.01+0.01*AL$3)) -> 0.92327193 | AM68: =AL68*(1-$AG68*(0.01+0.01*AM$3)) -> 0.90576669 | AN68: =AM68*(1-$AG68*(0.01+0.01*AN$3)) -> 0.88906662 | AO68: =AN68*(1-$AG68*(0.01+0.01*AO$3)) -> 0.87320567 | AP68: =AO68*(1-$AG68*(0.01+0.01*AP$3)) -> 0.85820182 | ... FC68: =FB68*(1-$AG68*(0.01+0.01*FC$3)) -> 0.25595353
A69: a0 at V = m_V - mi(date_of_birth) | B69: =inputs!$B$10-inputs!$B$67 -> 952 | C69: =inputs!$B$10-inputs!$C$67 -> 973 | F69: 87 | G69: =1-EXP(-inputs!$B$35-inputs!$B$36*inputs!$B$37^$F69*(inputs!$B$37-1)/LN(inputs!$B$37)) -> 0.07223699 | H69: =1-EXP(-inputs!$B$35-inputs!$B$36*inputs!$B$37^($F69-4)*(inputs!$B$37-1)/LN(inputs!$B$37)) -> 0.045967901 | I69: =0.96*G69 -> 0.069347511 | J69: =0.96*H69 -> 0.044129185 | L69: 67 | M69: =L69/12 -> 5.5833333 | N69: =0.04-0.015*EXP(-M69/10) -> 0.031417572 | O69: =EXP(-N69*M69) -> 0.83910891 | P69: =O69*EXP(-inputs!$B$27*L69/12) -> 0.81600774 | Q69: =0.045-0.015*EXP(-M69/10) -> 0.036417572 | R69: =EXP(-Q69*M69) -> 0.81600774 | S69: =R69*EXP(-inputs!$B$27*L69/12) -> 0.79354256 | T69: =INDEX(P_rec,MATCH(inputs!$B$13+L69,curve_t,0))/INDEX(P_rec,MATCH(inputs!$B$13,curve_t,0)) -> 0.80759195 | U69: =T69/T68 -> 0.99648095 | V69: =T68/T69-1 -> 0.0035314789 | X69: 43 | Y69: =IF(X69<=0,100*1.04^(X69/12),100*1.025^(X69/12)) -> 109.25144 | AA69: 41 | AC69: =$AB$28*INDEX(I_rec,MATCH(inputs!$B$13+AA69,cpi_rec_u,0))/INDEX(I_rec,MATCH(inputs!$B$13,cpi_rec_u,0)) -> 112.39672 | AD69: =$AB$28*1.03^(AA69/12) -> 114.28107 | AF69: 85 | AG69: =IF($AF69<=85,1,IF($AF69<110,(110-$AF69)/25,0)) -> 1 | AH69: =1 -> 1 | AI69: =AH69*(1-$AG69*(0.01+0.01*AI$3)) -> 0.98 | AJ69: =AI69*(1-$AG69*(0.01+0.01*AJ$3)) -> 0.96047105 | AK69: =AJ69*(1-$AG69*(0.01+0.01*AK$3)) -> 0.94153056 | AL69: =AK69*(1-$AG69*(0.01+0.01*AL$3)) -> 0.92327193 | AM69: =AL69*(1-$AG69*(0.01+0.01*AM$3)) -> 0.90576669 | AN69: =AM69*(1-$AG69*(0.01+0.01*AN$3)) -> 0.88906662 | AO69: =AN69*(1-$AG69*(0.01+0.01*AO$3)) -> 0.87320567 | AP69: =AO69*(1-$AG69*(0.01+0.01*AP$3)) -> 0.85820182 | ... FC69: =FB69*(1-$AG69*(0.01+0.01*FC$3)) -> 0.25595353
A70: mi(annuity_start_date) | B70: =12*YEAR(inputs!$B$58)+MONTH(inputs!$B$58)-1 -> 24312 | C70: =12*YEAR(inputs!$C$58)+MONTH(inputs!$C$58)-1 -> 24312 | F70: 88 | G70: =1-EXP(-inputs!$B$35-inputs!$B$36*inputs!$B$37^$F70*(inputs!$B$37-1)/LN(inputs!$B$37)) -> 0.080797715 | H70: =1-EXP(-inputs!$B$35-inputs!$B$36*inputs!$B$37^($F70-4)*(inputs!$B$37-1)/LN(inputs!$B$37)) -> 0.051492772 | I70: =0.96*G70 -> 0.077565807 | J70: =0.96*H70 -> 0.049433061 | L70: 68 | M70: =L70/12 -> 5.6666667 | N70: =0.04-0.015*EXP(-M70/10) -> 0.031488795 | O70: =EXP(-N70*M70) -> 0.83657717 | P70: =O70*EXP(-inputs!$B$27*L70/12) -> 0.8132068 | Q70: =0.045-0.015*EXP(-M70/10) -> 0.036488795 | R70: =EXP(-Q70*M70) -> 0.8132068 | S70: =R70*EXP(-inputs!$B$27*L70/12) -> 0.79048929 | T70: =INDEX(P_rec,MATCH(inputs!$B$13+L70,curve_t,0))/INDEX(P_rec,MATCH(inputs!$B$13,curve_t,0)) -> 0.80474417 | U70: =T70/T69 -> 0.99647374 | V70: =T69/T70-1 -> 0.00353874 | X70: 44 | Y70: =IF(X70<=0,100*1.04^(X70/12),100*1.025^(X70/12)) -> 109.47648 | AA70: 42 | AC70: =$AB$28*INDEX(I_rec,MATCH(inputs!$B$13+AA70,cpi_rec_u,0))/INDEX(I_rec,MATCH(inputs!$B$13,cpi_rec_u,0)) -> 112.62824 | AD70: =$AB$28*1.03^(AA70/12) -> 114.56292 | AF70: 86 | AG70: =IF($AF70<=85,1,IF($AF70<110,(110-$AF70)/25,0)) -> 0.96 | AH70: =1 -> 1 | AI70: =AH70*(1-$AG70*(0.01+0.01*AI$3)) -> 0.9808 | AJ70: =AI70*(1-$AG70*(0.01+0.01*AJ$3)) -> 0.9620369 | AK70: =AJ70*(1-$AG70*(0.01+0.01*AK$3)) -> 0.94382439 | AL70: =AK70*(1-$AG70*(0.01+0.01*AL$3)) -> 0.9262534 | AM70: =AL70*(1-$AG70*(0.01+0.01*AM$3)) -> 0.90939411 | AN70: =AM70*(1-$AG70*(0.01+0.01*AN$3)) -> 0.89329783 | AO70: =AN70*(1-$AG70*(0.01+0.01*AO$3)) -> 0.87799886 | AP70: =AO70*(1-$AG70*(0.01+0.01*AP$3)) -> 0.86351609 | ... FC70: =FB70*(1-$AG70*(0.01+0.01*FC$3)) -> 0.27037411
A71: m_c at recognition = mi(annuity_start_date) - m_rec | B71: =inputs!$B$70-inputs!$B$11 -> 1 | C71: =inputs!$C$70-inputs!$B$11 -> 1 | F71: 89 | G71: =1-EXP(-inputs!$B$35-inputs!$B$36*inputs!$B$37^$F71*(inputs!$B$37-1)/LN(inputs!$B$37)) -> 0.090325714 | H71: =1-EXP(-inputs!$B$35-inputs!$B$36*inputs!$B$37^($F71-4)*(inputs!$B$37-1)/LN(inputs!$B$37)) -> 0.057664543 | I71: =0.96*G71 -> 0.086712686 | J71: =0.96*H71 -> 0.055357961 | L71: 69 | M71: =L71/12 -> 5.75 | N71: =0.04-0.015*EXP(-M71/10) -> 0.031559427 | O71: =EXP(-N71*M71) -> 0.83404601 | P71: =O71*EXP(-inputs!$B$27*L71/12) -> 0.81040861 | Q71: =0.045-0.015*EXP(-M71/10) -> 0.036559427 | R71: =EXP(-Q71*M71) -> 0.81040861 | S71: =R71*EXP(-inputs!$B$27*L71/12) -> 0.7874411 | T71: =INDEX(P_rec,MATCH(inputs!$B$13+L71,curve_t,0))/INDEX(P_rec,MATCH(inputs!$B$13,curve_t,0)) -> 0.80190072 | U71: =T71/T70 -> 0.99646663 | V71: =T70/T71-1 -> 0.0035458962 | X71: 45 | Y71: =IF(X71<=0,100*1.04^(X71/12),100*1.025^(X71/12)) -> 109.70199 | AA71: 43 | AC71: =$AB$28*INDEX(I_rec,MATCH(inputs!$B$13+AA71,cpi_rec_u,0))/INDEX(I_rec,MATCH(inputs!$B$13,cpi_rec_u,0)) -> 112.86024 | AD71: =$AB$28*1.03^(AA71/12) -> 114.84546 | AF71: 87 | AG71: =IF($AF71<=85,1,IF($AF71<110,(110-$AF71)/25,0)) -> 0.92 | AH71: =1 -> 1 | AI71: =AH71*(1-$AG71*(0.01+0.01*AI$3)) -> 0.9816 | AJ71: =AI71*(1-$AG71*(0.01+0.01*AJ$3)) -> 0.96360403 | AK71: =AJ71*(1-$AG71*(0.01+0.01*AK$3)) -> 0.94612194 | AL71: =AK71*(1-$AG71*(0.01+0.01*AL$3)) -> 0.92924209 | AM71: =AL71*(1-$AG71*(0.01+0.01*AM$3)) -> 0.91303313 | AN71: =AM71*(1-$AG71*(0.01+0.01*AN$3)) -> 0.89754581 | AO71: =AN71*(1-$AG71*(0.01+0.01*AO$3)) -> 0.88281457 | AP71: =AO71*(1-$AG71*(0.01+0.01*AP$3)) -> 0.86885912 | ... FC71: =FB71*(1-$AG71*(0.01+0.01*FC$3)) -> 0.28559995
A72: m_c at V = mi(annuity_start_date) - m_V | B72: =inputs!$B$70-inputs!$B$10 -> -11 | C72: =inputs!$C$70-inputs!$B$10 -> -11 | F72: 90 | G72: =1-EXP(-inputs!$B$35-inputs!$B$36*inputs!$B$37^$F72*(inputs!$B$37-1)/LN(inputs!$B$37)) -> 0.10091734 | H72: =1-EXP(-inputs!$B$35-inputs!$B$36*inputs!$B$37^($F72-4)*(inputs!$B$37-1)/LN(inputs!$B$37)) -> 0.06455369 | I72: =0.96*G72 -> 0.09688065 | J72: =0.96*H72 -> 0.061971543 | L72: 70 | M72: =L72/12 -> 5.8333333 | N72: =0.04-0.015*EXP(-M72/10) -> 0.031629473 | O72: =EXP(-N72*M72) -> 0.83151557 | P72: =O72*EXP(-inputs!$B$27*L72/12) -> 0.8076133 | Q72: =0.045-0.015*EXP(-M72/10) -> 0.036629473 | R72: =EXP(-Q72*M72) -> 0.8076133 | S72: =R72*EXP(-inputs!$B$27*L72/12) -> 0.78439811 | T72: =INDEX(P_rec,MATCH(inputs!$B$13+L72,curve_t,0))/INDEX(P_rec,MATCH(inputs!$B$13,curve_t,0)) -> 0.79906169 | U72: =T72/T71 -> 0.99645963 | V72: =T71/T72-1 -> 0.0035529486 | X72: 46 | Y72: =IF(X72<=0,100*1.04^(X72/12),100*1.025^(X72/12)) -> 109.92796 | AA72: 44 | AC72: =$AB$28*INDEX(I_rec,MATCH(inputs!$B$13+AA72,cpi_rec_u,0))/INDEX(I_rec,MATCH(inputs!$B$13,cpi_rec_u,0)) -> 113.09271 | AD72: =$AB$28*1.03^(AA72/12) -> 115.1287 | AF72: 88 | AG72: =IF($AF72<=85,1,IF($AF72<110,(110-$AF72)/25,0)) -> 0.88 | AH72: =1 -> 1 | AI72: =AH72*(1-$AG72*(0.01+0.01*AI$3)) -> 0.9824 | AJ72: =AI72*(1-$AG72*(0.01+0.01*AJ$3)) -> 0.96517244 | AK72: =AJ72*(1-$AG72*(0.01+0.01*AK$3)) -> 0.94842322 | AL72: =AK72*(1-$AG72*(0.01+0.01*AL$3)) -> 0.932238 | AM72: =AL72*(1-$AG72*(0.01+0.01*AM$3)) -> 0.91668379 | AN72: =AM72*(1-$AG72*(0.01+0.01*AN$3)) -> 0.9018106 | AO72: =AN72*(1-$AG72*(0.01+0.01*AO$3)) -> 0.88765289 | AP72: =AO72*(1-$AG72*(0.01+0.01*AP$3)) -> 0.87423105 | ... FC72: =FB72*(1-$AG72*(0.01+0.01*FC$3)) -> 0.30167562
A73: T_i at recognition | B73: =12*120+1-inputs!$B$68 -> 501 | C73: =12*120+1-inputs!$C$68 -> 480 | F73: 91 | G73: =1-EXP(-inputs!$B$35-inputs!$B$36*inputs!$B$37^$F73*(inputs!$B$37-1)/LN(inputs!$B$37)) -> 0.1126752 | H73: =1-EXP(-inputs!$B$35-inputs!$B$36*inputs!$B$37^($F73-4)*(inputs!$B$37-1)/LN(inputs!$B$37)) -> 0.07223699 | I73: =0.96*G73 -> 0.10816819 | J73: =0.96*H73 -> 0.069347511 | L73: 71 | M73: =L73/12 -> 5.9166667 | N73: =0.04-0.015*EXP(-M73/10) -> 0.031698937 | O73: =EXP(-N73*M73) -> 0.82898597 | P73: =O73*EXP(-inputs!$B$27*L73/12) -> 0.80482101 | Q73: =0.045-0.015*EXP(-M73/10) -> 0.036698937 | R73: =EXP(-Q73*M73) -> 0.80482101 | S73: =R73*EXP(-inputs!$B$27*L73/12) -> 0.78136045 | T73: =INDEX(P_rec,MATCH(inputs!$B$13+L73,curve_t,0))/INDEX(P_rec,MATCH(inputs!$B$13,curve_t,0)) -> 0.7962272 | U73: =T73/T72 -> 0.99645273 | V73: =T72/T73-1 -> 0.0035598987 | X73: 47 | Y73: =IF(X73<=0,100*1.04^(X73/12),100*1.025^(X73/12)) -> 110.15439 | AA73: 45 | AC73: =$AB$28*INDEX(I_rec,MATCH(inputs!$B$13+AA73,cpi_rec_u,0))/INDEX(I_rec,MATCH(inputs!$B$13,cpi_rec_u,0)) -> 113.32566 | AD73: =$AB$28*1.03^(AA73/12) -> 115.41264 | AF73: 89 | AG73: =IF($AF73<=85,1,IF($AF73<110,(110-$AF73)/25,0)) -> 0.84 | AH73: =1 -> 1 | AI73: =AH73*(1-$AG73*(0.01+0.01*AI$3)) -> 0.9832 | AJ73: =AI73*(1-$AG73*(0.01+0.01*AJ$3)) -> 0.96674212 | AK73: =AJ73*(1-$AG73*(0.01+0.01*AK$3)) -> 0.95072823 | AL73: =AK73*(1-$AG73*(0.01+0.01*AL$3)) -> 0.93524115 | AM73: =AL73*(1-$AG73*(0.01+0.01*AM$3)) -> 0.92034612 | AN73: =AM73*(1-$AG73*(0.01+0.01*AN$3)) -> 0.90609226 | AO73: =AN73*(1-$AG73*(0.01+0.01*AO$3)) -> 0.89251393 | AP73: =AO73*(1-$AG73*(0.01+0.01*AP$3)) -> 0.87963201 | ... FC73: =FB73*(1-$AG73*(0.01+0.01*FC$3)) -> 0.31864812
A74: T_i at V | B74: =12*120+1-inputs!$B$69 -> 489 | C74: =12*120+1-inputs!$C$69 -> 468 | F74: 92 | G74: =1-EXP(-inputs!$B$35-inputs!$B$36*inputs!$B$37^$F74*(inputs!$B$37-1)/LN(inputs!$B$37)) -> 0.12570758 | H74: =1-EXP(-inputs!$B$35-inputs!$B$36*inputs!$B$37^($F74-4)*(inputs!$B$37-1)/LN(inputs!$B$37)) -> 0.080797715 | I74: =0.96*G74 -> 0.12067928 | J74: =0.96*H74 -> 0.077565807 | L74: 72 | M74: =L74/12 -> 6 | N74: =0.04-0.015*EXP(-M74/10) -> 0.031767825 | O74: =EXP(-N74*M74) -> 0.82645736 | P74: =O74*EXP(-inputs!$B$27*L74/12) -> 0.80203185 | Q74: =0.045-0.015*EXP(-M74/10) -> 0.036767825 | R74: =EXP(-Q74*M74) -> 0.80203185 | S74: =R74*EXP(-inputs!$B$27*L74/12) -> 0.77832823 | T74: =INDEX(P_rec,MATCH(inputs!$B$13+L74,curve_t,0))/INDEX(P_rec,MATCH(inputs!$B$13,curve_t,0)) -> 0.79339736 | U74: =T74/T73 -> 0.99644593 | V74: =T73/T74-1 -> 0.0035667474 | X74: 48 | Y74: =IF(X74<=0,100*1.04^(X74/12),100*1.025^(X74/12)) -> 110.38129 | AA74: 46 | AC74: =$AB$28*INDEX(I_rec,MATCH(inputs!$B$13+AA74,cpi_rec_u,0))/INDEX(I_rec,MATCH(inputs!$B$13,cpi_rec_u,0)) -> 113.5591 | AD74: =$AB$28*1.03^(AA74/12) -> 115.69728 | AF74: 90 | AG74: =IF($AF74<=85,1,IF($AF74<110,(110-$AF74)/25,0)) -> 0.8 | AH74: =1 -> 1 | AI74: =AH74*(1-$AG74*(0.01+0.01*AI$3)) -> 0.984 | AJ74: =AI74*(1-$AG74*(0.01+0.01*AJ$3)) -> 0.96831307 | AK74: =AJ74*(1-$AG74*(0.01+0.01*AK$3)) -> 0.95303696 | AL74: =AK74*(1-$AG74*(0.01+0.01*AL$3)) -> 0.93825155 | AM74: =AL74*(1-$AG74*(0.01+0.01*AM$3)) -> 0.92402015 | AN74: =AM74*(1-$AG74*(0.01+0.01*AN$3)) -> 0.91039085 | AO74: =AN74*(1-$AG74*(0.01+0.01*AO$3)) -> 0.89739775 | AP74: =AO74*(1-$AG74*(0.01+0.01*AP$3)) -> 0.88506213 | ... FC74: =FB74*(1-$AG74*(0.01+0.01*FC$3)) -> 0.33656706
A75: year(issue_date) (G2: equals cohort) | B75: =YEAR(inputs!$B$57) -> 2025 | C75: =YEAR(inputs!$C$57) -> 2025 | F75: 93 | G75: =1-EXP(-inputs!$B$35-inputs!$B$36*inputs!$B$37^$F75*(inputs!$B$37-1)/LN(inputs!$B$37)) -> 0.14012763 | H75: =1-EXP(-inputs!$B$35-inputs!$B$36*inputs!$B$37^($F75-4)*(inputs!$B$37-1)/LN(inputs!$B$37)) -> 0.090325714 | I75: =0.96*G75 -> 0.13452253 | J75: =0.96*H75 -> 0.086712686 | L75: 73 | M75: =L75/12 -> 6.0833333 | N75: =0.04-0.015*EXP(-M75/10) -> 0.031836142 | O75: =EXP(-N75*M75) -> 0.82392987 | P75: =O75*EXP(-inputs!$B$27*L75/12) -> 0.79924597 | Q75: =0.045-0.015*EXP(-M75/10) -> 0.036836142 | R75: =EXP(-Q75*M75) -> 0.79924597 | S75: =R75*EXP(-inputs!$B$27*L75/12) -> 0.77530157 | T75: =INDEX(P_rec,MATCH(inputs!$B$13+L75,curve_t,0))/INDEX(P_rec,MATCH(inputs!$B$13,curve_t,0)) -> 0.79057225 | U75: =T75/T74 -> 0.99643923 | V75: =T74/T75-1 -> 0.0035734961 | X75: 49 | Y75: =IF(X75<=0,100*1.04^(X75/12),100*1.025^(X75/12)) -> 110.60866 | AA75: 47 | AC75: =$AB$28*INDEX(I_rec,MATCH(inputs!$B$13+AA75,cpi_rec_u,0))/INDEX(I_rec,MATCH(inputs!$B$13,cpi_rec_u,0)) -> 113.79301 | AD75: =$AB$28*1.03^(AA75/12) -> 115.98262 | AF75: 91 | AG75: =IF($AF75<=85,1,IF($AF75<110,(110-$AF75)/25,0)) -> 0.76 | AH75: =1 -> 1 | AI75: =AH75*(1-$AG75*(0.01+0.01*AI$3)) -> 0.9848 | AJ75: =AI75*(1-$AG75*(0.01+0.01*AJ$3)) -> 0.9698853 | AK75: =AJ75*(1-$AG75*(0.01+0.01*AK$3)) -> 0.95534944 | AL75: =AK75*(1-$AG75*(0.01+0.01*AL$3)) -> 0.94126921 | AM75: =AL75*(1-$AG75*(0.01+0.01*AM$3)) -> 0.9277059 | AN75: =AM75*(1-$AG75*(0.01+0.01*AN$3)) -> 0.91470642 | AO75: =AN75*(1-$AG75*(0.01+0.01*AO$3)) -> 0.90230446 | AP75: =AO75*(1-$AG75*(0.01+0.01*AP$3)) -> 0.89052154 | ... FC75: =FB75*(1-$AG75*(0.01+0.01*FC$3)) -> 0.35548472
A76: n_exp = pols_if^rec(tau), read from the REC sheet | B76: =INDEX('REC-21'!$G$2:$G$503,MATCH(inputs!$B$14,'REC-21'!$A$2:$A$503,0)) -> 97.350619 | C76: =INDEX('REC-22'!$G$2:$G$503,MATCH(inputs!$B$14,'REC-22'!$A$2:$A$503,0)) -> 48.977005 | D76: 3.4: the previous run's pols_if at its month tau | F76: 94 | G76: =1-EXP(-inputs!$B$35-inputs!$B$36*inputs!$B$37^$F76*(inputs!$B$37-1)/LN(inputs!$B$37)) -> 0.15605206 | H76: =1-EXP(-inputs!$B$35-inputs!$B$36*inputs!$B$37^($F76-4)*(inputs!$B$37-1)/LN(inputs!$B$37)) -> 0.10091734 | I76: =0.96*G76 -> 0.14980998 | J76: =0.96*H76 -> 0.09688065 | L76: 74 | M76: =L76/12 -> 6.1666667 | N76: =0.04-0.015*EXP(-M76/10) -> 0.031903891 | O76: =EXP(-N76*M76) -> 0.82140363 | P76: =O76*EXP(-inputs!$B$27*L76/12) -> 0.79646348 | Q76: =0.045-0.015*EXP(-M76/10) -> 0.036903891 | R76: =EXP(-Q76*M76) -> 0.79646348 | S76: =R76*EXP(-inputs!$B$27*L76/12) -> 0.7722806 | T76: =INDEX(P_rec,MATCH(inputs!$B$13+L76,curve_t,0))/INDEX(P_rec,MATCH(inputs!$B$13,curve_t,0)) -> 0.78775198 | U76: =T76/T75 -> 0.99643263 | V76: =T75/T76-1 -> 0.0035801459 | X76: 50 | Y76: =IF(X76<=0,100*1.04^(X76/12),100*1.025^(X76/12)) -> 110.83649 | AA76: 48 | AC76: =$AB$28*INDEX(I_rec,MATCH(inputs!$B$13+AA76,cpi_rec_u,0))/INDEX(I_rec,MATCH(inputs!$B$13,cpi_rec_u,0)) -> 114.0274 | AD76: =$AB$28*1.03^(AA76/12) -> 116.26866 | AF76: 92 | AG76: =IF($AF76<=85,1,IF($AF76<110,(110-$AF76)/25,0)) -> 0.72 | AH76: =1 -> 1 | AI76: =AH76*(1-$AG76*(0.01+0.01*AI$3)) -> 0.9856 | AJ76: =AI76*(1-$AG76*(0.01+0.01*AJ$3)) -> 0.97145881 | AK76: =AJ76*(1-$AG76*(0.01+0.01*AK$3)) -> 0.95766565 | AL76: =AK76*(1-$AG76*(0.01+0.01*AL$3)) -> 0.94429415 | AM76: =AL76*(1-$AG76*(0.01+0.01*AM$3)) -> 0.9314034 | AN76: =AM76*(1-$AG76*(0.01+0.01*AN$3)) -> 0.91903902 | AO76: =AN76*(1-$AG76*(0.01+0.01*AO$3)) -> 0.90723414 | AP76: =AO76*(1-$AG76*(0.01+0.01*AP$3)) -> 0.89601039 | ... FC76: =FB76*(1-$AG76*(0.01+0.01*FC$3)) -> 0.37545628
F77: 95 | G77: =1-EXP(-inputs!$B$35-inputs!$B$36*inputs!$B$37^$F77*(inputs!$B$37-1)/LN(inputs!$B$37)) -> 0.17359936 | H77: =1-EXP(-inputs!$B$35-inputs!$B$36*inputs!$B$37^($F77-4)*(inputs!$B$37-1)/LN(inputs!$B$37)) -> 0.1126752 | I77: =0.96*G77 -> 0.16665539 | J77: =0.96*H77 -> 0.10816819 | L77: 75 | M77: =L77/12 -> 6.25 | N77: =0.04-0.015*EXP(-M77/10) -> 0.031971079 | O77: =EXP(-N77*M77) -> 0.81887876 | P77: =O77*EXP(-inputs!$B$27*L77/12) -> 0.79368451 | Q77: =0.045-0.015*EXP(-M77/10) -> 0.036971079 | R77: =EXP(-Q77*M77) -> 0.79368451 | S77: =R77*EXP(-inputs!$B$27*L77/12) -> 0.7692654 | T77: =INDEX(P_rec,MATCH(inputs!$B$13+L77,curve_t,0))/INDEX(P_rec,MATCH(inputs!$B$13,curve_t,0)) -> 0.78493665 | U77: =T77/T76 -> 0.99642612 | V77: =T76/T77-1 -> 0.0035866981 | X77: 51 | Y77: =IF(X77<=0,100*1.04^(X77/12),100*1.025^(X77/12)) -> 111.0648 | AA77: 49 | AC77: =$AB$28*INDEX(I_rec,MATCH(inputs!$B$13+AA77,cpi_rec_u,0))/INDEX(I_rec,MATCH(inputs!$B$13,cpi_rec_u,0)) -> 114.26228 | AD77: =$AB$28*1.03^(AA77/12) -> 116.55541 | AF77: 93 | AG77: =IF($AF77<=85,1,IF($AF77<110,(110-$AF77)/25,0)) -> 0.68 | AH77: =1 -> 1 | AI77: =AH77*(1-$AG77*(0.01+0.01*AI$3)) -> 0.9864 | AJ77: =AI77*(1-$AG77*(0.01+0.01*AJ$3)) -> 0.97303359 | AK77: =AJ77*(1-$AG77*(0.01+0.01*AK$3)) -> 0.9599856 | AL77: =AK77*(1-$AG77*(0.01+0.01*AL$3)) -> 0.94732636 | AM77: =AL77*(1-$AG77*(0.01+0.01*AM$3)) -> 0.93511267 | AN77: =AM77*(1-$AG77*(0.01+0.01*AN$3)) -> 0.9233887 | AO77: =AN77*(1-$AG77*(0.01+0.01*AO$3)) -> 0.91218689 | AP77: =AO77*(1-$AG77*(0.01+0.01*AP$3)) -> 0.9015288 | ... FC77: =FB77*(1-$AG77*(0.01+0.01*FC$3)) -> 0.39653992
F78: 96 | G78: =1-EXP(-inputs!$B$35-inputs!$B$36*inputs!$B$37^$F78*(inputs!$B$37-1)/LN(inputs!$B$37)) -> 0.19288739 | H78: =1-EXP(-inputs!$B$35-inputs!$B$36*inputs!$B$37^($F78-4)*(inputs!$B$37-1)/LN(inputs!$B$37)) -> 0.12570758 | I78: =0.96*G78 -> 0.1851719 | J78: =0.96*H78 -> 0.12067928 | L78: 76 | M78: =L78/12 -> 6.3333333 | N78: =0.04-0.015*EXP(-M78/10) -> 0.032037708 | O78: =EXP(-N78*M78) -> 0.8163554 | P78: =O78*EXP(-inputs!$B$27*L78/12) -> 0.79090917 | Q78: =0.045-0.015*EXP(-M78/10) -> 0.037037708 | R78: =EXP(-Q78*M78) -> 0.79090917 | S78: =R78*EXP(-inputs!$B$27*L78/12) -> 0.76625611 | T78: =INDEX(P_rec,MATCH(inputs!$B$13+L78,curve_t,0))/INDEX(P_rec,MATCH(inputs!$B$13,curve_t,0)) -> 0.78212635 | U78: =T78/T77 -> 0.99641971 | V78: =T77/T78-1 -> 0.0035931537 | X78: 52 | Y78: =IF(X78<=0,100*1.04^(X78/12),100*1.025^(X78/12)) -> 111.29357 | AA78: 50 | AC78: =$AB$28*INDEX(I_rec,MATCH(inputs!$B$13+AA78,cpi_rec_u,0))/INDEX(I_rec,MATCH(inputs!$B$13,cpi_rec_u,0)) -> 114.49764 | AD78: =$AB$28*1.03^(AA78/12) -> 116.84287 | AF78: 94 | AG78: =IF($AF78<=85,1,IF($AF78<110,(110-$AF78)/25,0)) -> 0.64 | AH78: =1 -> 1 | AI78: =AH78*(1-$AG78*(0.01+0.01*AI$3)) -> 0.9872 | AJ78: =AI78*(1-$AG78*(0.01+0.01*AJ$3)) -> 0.97460965 | AK78: =AJ78*(1-$AG78*(0.01+0.01*AK$3)) -> 0.96230929 | AL78: =AK78*(1-$AG78*(0.01+0.01*AL$3)) -> 0.95036588 | AM78: =AL78*(1-$AG78*(0.01+0.01*AM$3)) -> 0.93883376 | AN78: =AM78*(1-$AG78*(0.01+0.01*AN$3)) -> 0.92775552 | AO78: =AN78*(1-$AG78*(0.01+0.01*AO$3)) -> 0.91716278 | AP78: =AO78*(1-$AG78*(0.01+0.01*AP$3)) -> 0.90707692 | ... FC78: =FB78*(1-$AG78*(0.01+0.01*FC$3)) -> 0.41879703
F79: 97 | G79: =1-EXP(-inputs!$B$35-inputs!$B$36*inputs!$B$37^$F79*(inputs!$B$37-1)/LN(inputs!$B$37)) -> 0.21403029 | H79: =1-EXP(-inputs!$B$35-inputs!$B$36*inputs!$B$37^($F79-4)*(inputs!$B$37-1)/LN(inputs!$B$37)) -> 0.14012763 | I79: =0.96*G79 -> 0.20546907 | J79: =0.96*H79 -> 0.13452253 | L79: 77 | M79: =L79/12 -> 6.4166667 | N79: =0.04-0.015*EXP(-M79/10) -> 0.032103785 | O79: =EXP(-N79*M79) -> 0.81383366 | P79: =O79*EXP(-inputs!$B$27*L79/12) -> 0.78813757 | Q79: =0.045-0.015*EXP(-M79/10) -> 0.037103785 | R79: =EXP(-Q79*M79) -> 0.78813757 | S79: =R79*EXP(-inputs!$B$27*L79/12) -> 0.76325282 | T79: =INDEX(P_rec,MATCH(inputs!$B$13+L79,curve_t,0))/INDEX(P_rec,MATCH(inputs!$B$13,curve_t,0)) -> 0.77932117 | U79: =T79/T78 -> 0.9964134 | V79: =T78/T79-1 -> 0.003599514 | X79: 53 | Y79: =IF(X79<=0,100*1.04^(X79/12),100*1.025^(X79/12)) -> 111.52282 | AA79: 51 | AC79: =$AB$28*INDEX(I_rec,MATCH(inputs!$B$13+AA79,cpi_rec_u,0))/INDEX(I_rec,MATCH(inputs!$B$13,cpi_rec_u,0)) -> 114.73349 | AD79: =$AB$28*1.03^(AA79/12) -> 117.13103 | AF79: 95 | AG79: =IF($AF79<=85,1,IF($AF79<110,(110-$AF79)/25,0)) -> 0.6 | AH79: =1 -> 1 | AI79: =AH79*(1-$AG79*(0.01+0.01*AI$3)) -> 0.988 | AJ79: =AI79*(1-$AG79*(0.01+0.01*AJ$3)) -> 0.97618698 | AK79: =AJ79*(1-$AG79*(0.01+0.01*AK$3)) -> 0.96463673 | AL79: =AK79*(1-$AG79*(0.01+0.01*AL$3)) -> 0.9534127 | AM79: =AL79*(1-$AG79*(0.01+0.01*AM$3)) -> 0.94256668 | AN79: =AM79*(1-$AG79*(0.01+0.01*AN$3)) -> 0.93213954 | AO79: =AN79*(1-$AG79*(0.01+0.01*AO$3)) -> 0.92216191 | AP79: =AO79*(1-$AG79*(0.01+0.01*AP$3)) -> 0.91265489 | ... FC79: =FB79*(1-$AG79*(0.01+0.01*FC$3)) -> 0.44229232
F80: 98 | G80: =1-EXP(-inputs!$B$35-inputs!$B$36*inputs!$B$37^$F80*(inputs!$B$37-1)/LN(inputs!$B$37)) -> 0.23713449 | H80: =1-EXP(-inputs!$B$35-inputs!$B$36*inputs!$B$37^($F80-4)*(inputs!$B$37-1)/LN(inputs!$B$37)) -> 0.15605206 | I80: =0.96*G80 -> 0.22764911 | J80: =0.96*H80 -> 0.14980998 | L80: 78 | M80: =L80/12 -> 6.5 | N80: =0.04-0.015*EXP(-M80/10) -> 0.032169313 | O80: =EXP(-N80*M80) -> 0.81131366 | P80: =O80*EXP(-inputs!$B$27*L80/12) -> 0.78536984 | Q80: =0.045-0.015*EXP(-M80/10) -> 0.037169313 | R80: =EXP(-Q80*M80) -> 0.78536984 | S80: =R80*EXP(-inputs!$B$27*L80/12) -> 0.76025564 | T80: =INDEX(P_rec,MATCH(inputs!$B$13+L80,curve_t,0))/INDEX(P_rec,MATCH(inputs!$B$13,curve_t,0)) -> 0.77652121 | U80: =T80/T79 -> 0.99640717 | V80: =T79/T80-1 -> 0.00360578 | X80: 54 | Y80: =IF(X80<=0,100*1.04^(X80/12),100*1.025^(X80/12)) -> 111.75254 | AA80: 52 | AC80: =$AB$28*INDEX(I_rec,MATCH(inputs!$B$13+AA80,cpi_rec_u,0))/INDEX(I_rec,MATCH(inputs!$B$13,cpi_rec_u,0)) -> 114.96982 | AD80: =$AB$28*1.03^(AA80/12) -> 117.41991 | AF80: 96 | AG80: =IF($AF80<=85,1,IF($AF80<110,(110-$AF80)/25,0)) -> 0.56 | AH80: =1 -> 1 | AI80: =AH80*(1-$AG80*(0.01+0.01*AI$3)) -> 0.9888 | AJ80: =AI80*(1-$AG80*(0.01+0.01*AJ$3)) -> 0.97776559 | AK80: =AJ80*(1-$AG80*(0.01+0.01*AK$3)) -> 0.96696792 | AL80: =AK80*(1-$AG80*(0.01+0.01*AL$3)) -> 0.95646685 | AM80: =AL80*(1-$AG80*(0.01+0.01*AM$3)) -> 0.94631146 | AN80: =AM80*(1-$AG80*(0.01+0.01*AN$3)) -> 0.9365408 | AO80: =AN80*(1-$AG80*(0.01+0.01*AO$3)) -> 0.92718438 | AP80: =AO80*(1-$AG80*(0.01+0.01*AP$3)) -> 0.91826283 | ... FC80: =FB80*(1-$AG80*(0.01+0.01*FC$3)) -> 0.46709407
F81: 99 | G81: =1-EXP(-inputs!$B$35-inputs!$B$36*inputs!$B$37^$F81*(inputs!$B$37-1)/LN(inputs!$B$37)) -> 0.2622939 | H81: =1-EXP(-inputs!$B$35-inputs!$B$36*inputs!$B$37^($F81-4)*(inputs!$B$37-1)/LN(inputs!$B$37)) -> 0.17359936 | I81: =0.96*G81 -> 0.25180214 | J81: =0.96*H81 -> 0.16665539 | L81: 79 | M81: =L81/12 -> 6.5833333 | N81: =0.04-0.015*EXP(-M81/10) -> 0.032234298 | O81: =EXP(-N81*M81) -> 0.80879554 | P81: =O81*EXP(-inputs!$B$27*L81/12) -> 0.78260608 | Q81: =0.045-0.015*EXP(-M81/10) -> 0.037234298 | R81: =EXP(-Q81*M81) -> 0.78260608 | S81: =R81*EXP(-inputs!$B$27*L81/12) -> 0.75726467 | T81: =INDEX(P_rec,MATCH(inputs!$B$13+L81,curve_t,0))/INDEX(P_rec,MATCH(inputs!$B$13,curve_t,0)) -> 0.77372654 | U81: =T81/T80 -> 0.99640105 | V81: =T80/T81-1 -> 0.0036119529 | X81: 55 | Y81: =IF(X81<=0,100*1.04^(X81/12),100*1.025^(X81/12)) -> 111.98273 | AA81: 53 | AC81: =$AB$28*INDEX(I_rec,MATCH(inputs!$B$13+AA81,cpi_rec_u,0))/INDEX(I_rec,MATCH(inputs!$B$13,cpi_rec_u,0)) -> 115.20664 | AD81: =$AB$28*1.03^(AA81/12) -> 117.7095 | AF81: 97 | AG81: =IF($AF81<=85,1,IF($AF81<110,(110-$AF81)/25,0)) -> 0.52 | AH81: =1 -> 1 | AI81: =AH81*(1-$AG81*(0.01+0.01*AI$3)) -> 0.9896 | AJ81: =AI81*(1-$AG81*(0.01+0.01*AJ$3)) -> 0.97934547 | AK81: =AJ81*(1-$AG81*(0.01+0.01*AK$3)) -> 0.96930287 | AL81: =AK81*(1-$AG81*(0.01+0.01*AL$3)) -> 0.95952832 | AM81: =AL81*(1-$AG81*(0.01+0.01*AM$3)) -> 0.95006814 | AN81: =AM81*(1-$AG81*(0.01+0.01*AN$3)) -> 0.94095936 | AO81: =AN81*(1-$AG81*(0.01+0.01*AO$3)) -> 0.93223027 | AP81: =AO81*(1-$AG81*(0.01+0.01*AP$3)) -> 0.92390088 | ... FC81: =FB81*(1-$AG81*(0.01+0.01*FC$3)) -> 0.49327427
F82: 100 | G82: =1-EXP(-inputs!$B$35-inputs!$B$36*inputs!$B$37^$F82*(inputs!$B$37-1)/LN(inputs!$B$37)) -> 0.28958395 | H82: =1-EXP(-inputs!$B$35-inputs!$B$36*inputs!$B$37^($F82-4)*(inputs!$B$37-1)/LN(inputs!$B$37)) -> 0.19288739 | I82: =0.96*G82 -> 0.27800059 | J82: =0.96*H82 -> 0.1851719 | L82: 80 | M82: =L82/12 -> 6.6666667 | N82: =0.04-0.015*EXP(-M82/10) -> 0.032298743 | O82: =EXP(-N82*M82) -> 0.80627939 | P82: =O82*EXP(-inputs!$B$27*L82/12) -> 0.77984641 | Q82: =0.045-0.015*EXP(-M82/10) -> 0.037298743 | R82: =EXP(-Q82*M82) -> 0.77984641 | S82: =R82*EXP(-inputs!$B$27*L82/12) -> 0.75428 | T82: =INDEX(P_rec,MATCH(inputs!$B$13+L82,curve_t,0))/INDEX(P_rec,MATCH(inputs!$B$13,curve_t,0)) -> 0.77093727 | U82: =T82/T81 -> 0.99639501 | V82: =T81/T82-1 -> 0.0036180338 | X82: 56 | Y82: =IF(X82<=0,100*1.04^(X82/12),100*1.025^(X82/12)) -> 112.2134 | AA82: 54 | AC82: =$AB$28*INDEX(I_rec,MATCH(inputs!$B$13+AA82,cpi_rec_u,0))/INDEX(I_rec,MATCH(inputs!$B$13,cpi_rec_u,0)) -> 115.44395 | AD82: =$AB$28*1.03^(AA82/12) -> 117.9998 | AF82: 98 | AG82: =IF($AF82<=85,1,IF($AF82<110,(110-$AF82)/25,0)) -> 0.48 | AH82: =1 -> 1 | AI82: =AH82*(1-$AG82*(0.01+0.01*AI$3)) -> 0.9904 | AJ82: =AI82*(1-$AG82*(0.01+0.01*AJ$3)) -> 0.98092663 | AK82: =AJ82*(1-$AG82*(0.01+0.01*AK$3)) -> 0.97164157 | AL82: =AK82*(1-$AG82*(0.01+0.01*AL$3)) -> 0.96259714 | AM82: =AL82*(1-$AG82*(0.01+0.01*AM$3)) -> 0.95383673 | AN82: =AM82*(1-$AG82*(0.01+0.01*AN$3)) -> 0.94539528 | AO82: =AN82*(1-$AG82*(0.01+0.01*AO$3)) -> 0.93729967 | AP82: =AO82*(1-$AG82*(0.01+0.01*AP$3)) -> 0.9295692 | ... FC82: =FB82*(1-$AG82*(0.01+0.01*FC$3)) -> 0.52090886
F83: 101 | G83: =1-EXP(-inputs!$B$35-inputs!$B$36*inputs!$B$37^$F83*(inputs!$B$37-1)/LN(inputs!$B$37)) -> 0.31905475 | H83: =1-EXP(-inputs!$B$35-inputs!$B$36*inputs!$B$37^($F83-4)*(inputs!$B$37-1)/LN(inputs!$B$37)) -> 0.21403029 | I83: =0.96*G83 -> 0.30629256 | J83: =0.96*H83 -> 0.20546907 | L83: 81 | M83: =L83/12 -> 6.75 | N83: =0.04-0.015*EXP(-M83/10) -> 0.032362654 | O83: =EXP(-N83*M83) -> 0.80376534 | P83: =O83*EXP(-inputs!$B$27*L83/12) -> 0.77709093 | Q83: =0.045-0.015*EXP(-M83/10) -> 0.037362654 | R83: =EXP(-Q83*M83) -> 0.77709093 | S83: =R83*EXP(-inputs!$B$27*L83/12) -> 0.75130175 | T83: =INDEX(P_rec,MATCH(inputs!$B$13+L83,curve_t,0))/INDEX(P_rec,MATCH(inputs!$B$13,curve_t,0)) -> 0.76815346 | U83: =T83/T82 -> 0.99638906 | V83: =T82/T83-1 -> 0.0036240238 | X83: 57 | Y83: =IF(X83<=0,100*1.04^(X83/12),100*1.025^(X83/12)) -> 112.44454 | AA83: 55 | AC83: =$AB$28*INDEX(I_rec,MATCH(inputs!$B$13+AA83,cpi_rec_u,0))/INDEX(I_rec,MATCH(inputs!$B$13,cpi_rec_u,0)) -> 115.68174 | AD83: =$AB$28*1.03^(AA83/12) -> 118.29082 | AF83: 99 | AG83: =IF($AF83<=85,1,IF($AF83<110,(110-$AF83)/25,0)) -> 0.44 | AH83: =1 -> 1 | AI83: =AH83*(1-$AG83*(0.01+0.01*AI$3)) -> 0.9912 | AJ83: =AI83*(1-$AG83*(0.01+0.01*AJ$3)) -> 0.98250906 | AK83: =AJ83*(1-$AG83*(0.01+0.01*AK$3)) -> 0.97398402 | AL83: =AK83*(1-$AG83*(0.01+0.01*AL$3)) -> 0.96567331 | AM83: =AL83*(1-$AG83*(0.01+0.01*AM$3)) -> 0.95761728 | AN83: =AM83*(1-$AG83*(0.01+0.01*AN$3)) -> 0.94984861 | AO83: =AN83*(1-$AG83*(0.01+0.01*AO$3)) -> 0.94239268 | AP83: =AO83*(1-$AG83*(0.01+0.01*AP$3)) -> 0.93526791 | ... FC83: =FB83*(1-$AG83*(0.01+0.01*FC$3)) -> 0.55007791
F84: 102 | G84: =1-EXP(-inputs!$B$35-inputs!$B$36*inputs!$B$37^$F84*(inputs!$B$37-1)/LN(inputs!$B$37)) -> 0.3507231 | H84: =1-EXP(-inputs!$B$35-inputs!$B$36*inputs!$B$37^($F84-4)*(inputs!$B$37-1)/LN(inputs!$B$37)) -> 0.23713449 | I84: =0.96*G84 -> 0.33669417 | J84: =0.96*H84 -> 0.22764911 | L84: 82 | M84: =L84/12 -> 6.8333333 | N84: =0.04-0.015*EXP(-M84/10) -> 0.032426034 | O84: =EXP(-N84*M84) -> 0.8012535 | P84: =O84*EXP(-inputs!$B$27*L84/12) -> 0.77433974 | Q84: =0.045-0.015*EXP(-M84/10) -> 0.037426034 | R84: =EXP(-Q84*M84) -> 0.77433974 | S84: =R84*EXP(-inputs!$B$27*L84/12) -> 0.74832999 | T84: =INDEX(P_rec,MATCH(inputs!$B$13+L84,curve_t,0))/INDEX(P_rec,MATCH(inputs!$B$13,curve_t,0)) -> 0.76537521 | U84: =T84/T83 -> 0.9963832 | V84: =T83/T84-1 -> 0.0036299239 | X84: 58 | Y84: =IF(X84<=0,100*1.04^(X84/12),100*1.025^(X84/12)) -> 112.67615 | AA84: 56 | AC84: =$AB$28*INDEX(I_rec,MATCH(inputs!$B$13+AA84,cpi_rec_u,0))/INDEX(I_rec,MATCH(inputs!$B$13,cpi_rec_u,0)) -> 115.92003 | AD84: =$AB$28*1.03^(AA84/12) -> 118.58256 | AF84: 100 | AG84: =IF($AF84<=85,1,IF($AF84<110,(110-$AF84)/25,0)) -> 0.4 | AH84: =1 -> 1 | AI84: =AH84*(1-$AG84*(0.01+0.01*AI$3)) -> 0.992 | AJ84: =AI84*(1-$AG84*(0.01+0.01*AJ$3)) -> 0.98409277 | AK84: =AJ84*(1-$AG84*(0.01+0.01*AK$3)) -> 0.97633024 | AL84: =AK84*(1-$AG84*(0.01+0.01*AL$3)) -> 0.96875685 | AM84: =AL84*(1-$AG84*(0.01+0.01*AM$3)) -> 0.9614098 | AN84: =AM84*(1-$AG84*(0.01+0.01*AN$3)) -> 0.9543194 | AO84: =AN84*(1-$AG84*(0.01+0.01*AO$3)) -> 0.94750938 | AP84: =AO84*(1-$AG84*(0.01+0.01*AP$3)) -> 0.94099715 | ... FC84: =FB84*(1-$AG84*(0.01+0.01*FC$3)) -> 0.58086586
F85: 103 | G85: =1-EXP(-inputs!$B$35-inputs!$B$36*inputs!$B$37^$F85*(inputs!$B$37-1)/LN(inputs!$B$37)) -> 0.38456369 | H85: =1-EXP(-inputs!$B$35-inputs!$B$36*inputs!$B$37^($F85-4)*(inputs!$B$37-1)/LN(inputs!$B$37)) -> 0.2622939 | I85: =0.96*G85 -> 0.36918114 | J85: =0.96*H85 -> 0.25180214 | L85: 83 | M85: =L85/12 -> 6.9166667 | N85: =0.04-0.015*EXP(-M85/10) -> 0.032488888 | O85: =EXP(-N85*M85) -> 0.79874398 | P85: =O85*EXP(-inputs!$B$27*L85/12) -> 0.77159294 | Q85: =0.045-0.015*EXP(-M85/10) -> 0.037488888 | R85: =EXP(-Q85*M85) -> 0.77159294 | S85: =R85*EXP(-inputs!$B$27*L85/12) -> 0.74536483 | T85: =INDEX(P_rec,MATCH(inputs!$B$13+L85,curve_t,0))/INDEX(P_rec,MATCH(inputs!$B$13,curve_t,0)) -> 0.76260259 | U85: =T85/T84 -> 0.99637744 | V85: =T84/T85-1 -> 0.0036357354 | X85: 59 | Y85: =IF(X85<=0,100*1.04^(X85/12),100*1.025^(X85/12)) -> 112.90825 | AA85: 57 | AC85: =$AB$28*INDEX(I_rec,MATCH(inputs!$B$13+AA85,cpi_rec_u,0))/INDEX(I_rec,MATCH(inputs!$B$13,cpi_rec_u,0)) -> 116.1588 | AD85: =$AB$28*1.03^(AA85/12) -> 118.87502 | AF85: 101 | AG85: =IF($AF85<=85,1,IF($AF85<110,(110-$AF85)/25,0)) -> 0.36 | AH85: =1 -> 1 | AI85: =AH85*(1-$AG85*(0.01+0.01*AI$3)) -> 0.9928 | AJ85: =AI85*(1-$AG85*(0.01+0.01*AJ$3)) -> 0.98567775 | AK85: =AJ85*(1-$AG85*(0.01+0.01*AK$3)) -> 0.97868023 | AL85: =AK85*(1-$AG85*(0.01+0.01*AL$3)) -> 0.97184777 | AM85: =AL85*(1-$AG85*(0.01+0.01*AM$3)) -> 0.96521432 | AN85: =AM85*(1-$AG85*(0.01+0.01*AN$3)) -> 0.95880771 | AO85: =AN85*(1-$AG85*(0.01+0.01*AO$3)) -> 0.95264987 | AP85: =AO85*(1-$AG85*(0.01+0.01*AP$3)) -> 0.94675706 | ... FC85: =FB85*(1-$AG85*(0.01+0.01*FC$3)) -> 0.61336176
F86: 104 | G86: =1-EXP(-inputs!$B$35-inputs!$B$36*inputs!$B$37^$F86*(inputs!$B$37-1)/LN(inputs!$B$37)) -> 0.4204997 | H86: =1-EXP(-inputs!$B$35-inputs!$B$36*inputs!$B$37^($F86-4)*(inputs!$B$37-1)/LN(inputs!$B$37)) -> 0.28958395 | I86: =0.96*G86 -> 0.40367971 | J86: =0.96*H86 -> 0.27800059 | L86: 84 | M86: =L86/12 -> 7 | N86: =0.04-0.015*EXP(-M86/10) -> 0.03255122 | O86: =EXP(-N86*M86) -> 0.79623689 | P86: =O86*EXP(-inputs!$B$27*L86/12) -> 0.76885065 | Q86: =0.045-0.015*EXP(-M86/10) -> 0.03755122 | R86: =EXP(-Q86*M86) -> 0.76885065 | S86: =R86*EXP(-inputs!$B$27*L86/12) -> 0.74240635 | T86: =INDEX(P_rec,MATCH(inputs!$B$13+L86,curve_t,0))/INDEX(P_rec,MATCH(inputs!$B$13,curve_t,0)) -> 0.75983568 | U86: =T86/T85 -> 0.99637175 | V86: =T85/T86-1 -> 0.0036414592 | X86: 60 | Y86: =IF(X86<=0,100*1.04^(X86/12),100*1.025^(X86/12)) -> 113.14082 | AA86: 58 | AC86: =$AB$28*INDEX(I_rec,MATCH(inputs!$B$13+AA86,cpi_rec_u,0))/INDEX(I_rec,MATCH(inputs!$B$13,cpi_rec_u,0)) -> 116.39807 | AD86: =$AB$28*1.03^(AA86/12) -> 119.16819 | AF86: 102 | AG86: =IF($AF86<=85,1,IF($AF86<110,(110-$AF86)/25,0)) -> 0.32 | AH86: =1 -> 1 | AI86: =AH86*(1-$AG86*(0.01+0.01*AI$3)) -> 0.9936 | AJ86: =AI86*(1-$AG86*(0.01+0.01*AJ$3)) -> 0.98726401 | AK86: =AJ86*(1-$AG86*(0.01+0.01*AK$3)) -> 0.98103398 | AL86: =AK86*(1-$AG86*(0.01+0.01*AL$3)) -> 0.97494608 | AM86: =AL86*(1-$AG86*(0.01+0.01*AM$3)) -> 0.96903088 | AN86: =AM86*(1-$AG86*(0.01+0.01*AN$3)) -> 0.9633136 | AO86: =AN86*(1-$AG86*(0.01+0.01*AO$3)) -> 0.95781424 | AP86: =AO86*(1-$AG86*(0.01+0.01*AP$3)) -> 0.95254779 | ... FC86: =FB86*(1-$AG86*(0.01+0.01*FC$3)) -> 0.64765951
F87: 105 | G87: =1-EXP(-inputs!$B$35-inputs!$B$36*inputs!$B$37^$F87*(inputs!$B$37-1)/LN(inputs!$B$37)) -> 0.45839312 | H87: =1-EXP(-inputs!$B$35-inputs!$B$36*inputs!$B$37^($F87-4)*(inputs!$B$37-1)/LN(inputs!$B$37)) -> 0.31905475 | I87: =0.96*G87 -> 0.4400574 | J87: =0.96*H87 -> 0.30629256 | L87: 85 | M87: =L87/12 -> 7.0833333 | N87: =0.04-0.015*EXP(-M87/10) -> 0.032613036 | O87: =EXP(-N87*M87) -> 0.79373232 | P87: =O87*EXP(-inputs!$B$27*L87/12) -> 0.76611295 | Q87: =0.045-0.015*EXP(-M87/10) -> 0.037613036 | R87: =EXP(-Q87*M87) -> 0.76611295 | S87: =R87*EXP(-inputs!$B$27*L87/12) -> 0.73945464 | T87: =INDEX(P_rec,MATCH(inputs!$B$13+L87,curve_t,0))/INDEX(P_rec,MATCH(inputs!$B$13,curve_t,0)) -> 0.75707455 | U87: =T87/T86 -> 0.99636616 | V87: =T86/T87-1 -> 0.0036470963 | X87: 61 | Y87: =IF(X87<=0,100*1.04^(X87/12),100*1.025^(X87/12)) -> 113.37387 | AA87: 59 | AC87: =$AB$28*INDEX(I_rec,MATCH(inputs!$B$13+AA87,cpi_rec_u,0))/INDEX(I_rec,MATCH(inputs!$B$13,cpi_rec_u,0)) -> 116.63783 | AD87: =$AB$28*1.03^(AA87/12) -> 119.4621 | AF87: 103 | AG87: =IF($AF87<=85,1,IF($AF87<110,(110-$AF87)/25,0)) -> 0.28 | AH87: =1 -> 1 | AI87: =AH87*(1-$AG87*(0.01+0.01*AI$3)) -> 0.9944 | AJ87: =AI87*(1-$AG87*(0.01+0.01*AJ$3)) -> 0.98885155 | AK87: =AJ87*(1-$AG87*(0.01+0.01*AK$3)) -> 0.9833915 | AL87: =AK87*(1-$AG87*(0.01+0.01*AL$3)) -> 0.97805179 | AM87: =AL87*(1-$AG87*(0.01+0.01*AM$3)) -> 0.9728595 | AN87: =AM87*(1-$AG87*(0.01+0.01*AN$3)) -> 0.96783712 | AO87: =AN87*(1-$AG87*(0.01+0.01*AO$3)) -> 0.96300258 | AP87: =AO87*(1-$AG87*(0.01+0.01*AP$3)) -> 0.95836948 | ... FC87: =FB87*(1-$AG87*(0.01+0.01*FC$3)) -> 0.68385815
F88: 106 | G88: =1-EXP(-inputs!$B$35-inputs!$B$36*inputs!$B$37^$F88*(inputs!$B$37-1)/LN(inputs!$B$37)) -> 0.49803567 | H88: =1-EXP(-inputs!$B$35-inputs!$B$36*inputs!$B$37^($F88-4)*(inputs!$B$37-1)/LN(inputs!$B$37)) -> 0.3507231 | I88: =0.96*G88 -> 0.47811424 | J88: =0.96*H88 -> 0.33669417 | L88: 86 | M88: =L88/12 -> 7.1666667 | N88: =0.04-0.015*EXP(-M88/10) -> 0.032674338 | O88: =EXP(-N88*M88) -> 0.79123039 | P88: =O88*EXP(-inputs!$B$27*L88/12) -> 0.76337994 | Q88: =0.045-0.015*EXP(-M88/10) -> 0.037674338 | R88: =EXP(-Q88*M88) -> 0.76337994 | S88: =R88*EXP(-inputs!$B$27*L88/12) -> 0.73650979 | T88: =INDEX(P_rec,MATCH(inputs!$B$13+L88,curve_t,0))/INDEX(P_rec,MATCH(inputs!$B$13,curve_t,0)) -> 0.75431929 | U88: =T88/T87 -> 0.99636065 | V88: =T87/T88-1 -> 0.0036526479 | X88: 62 | Y88: =IF(X88<=0,100*1.04^(X88/12),100*1.025^(X88/12)) -> 113.6074 | AA88: 60 | AC88: =$AB$28*INDEX(I_rec,MATCH(inputs!$B$13+AA88,cpi_rec_u,0))/INDEX(I_rec,MATCH(inputs!$B$13,cpi_rec_u,0)) -> 116.87809 | AD88: =$AB$28*1.03^(AA88/12) -> 119.75672 | AF88: 104 | AG88: =IF($AF88<=85,1,IF($AF88<110,(110-$AF88)/25,0)) -> 0.24 | AH88: =1 -> 1 | AI88: =AH88*(1-$AG88*(0.01+0.01*AI$3)) -> 0.9952 | AJ88: =AI88*(1-$AG88*(0.01+0.01*AJ$3)) -> 0.99044036 | AK88: =AJ88*(1-$AG88*(0.01+0.01*AK$3)) -> 0.9857528 | AL88: =AK88*(1-$AG88*(0.01+0.01*AL$3)) -> 0.98116491 | AM88: =AL88*(1-$AG88*(0.01+0.01*AM$3)) -> 0.97670022 | AN88: =AM88*(1-$AG88*(0.01+0.01*AN$3)) -> 0.97237832 | AO88: =AN88*(1-$AG88*(0.01+0.01*AO$3)) -> 0.96821498 | AP88: =AO88*(1-$AG88*(0.01+0.01*AP$3)) -> 0.96422226 | ... FC88: =FB88*(1-$AG88*(0.01+0.01*FC$3)) -> 0.72206207
... F101: 119 | G101: =1-EXP(-inputs!$B$35-inputs!$B$36*inputs!$B$37^$F101*(inputs!$B$37-1)/LN(inputs!$B$37)) -> 0.95711833 | H101: =1-EXP(-inputs!$B$35-inputs!$B$36*inputs!$B$37^($F101-4)*(inputs!$B$37-1)/LN(inputs!$B$37)) -> 0.86098696 | I101: =0.96*G101 -> 0.9188336 | J101: =0.96*H101 -> 0.82654748 | L101: 99 | M101: =L101/12 -> 8.25 | N101: =0.04-0.015*EXP(-M101/10) -> 0.033426475 | O101: =EXP(-N101*M101) -> 0.75898868 | P101: =O101*EXP(-inputs!$B$27*L101/12) -> 0.72831734 | Q101: =0.045-0.015*EXP(-M101/10) -> 0.038426475 | R101: =EXP(-Q101*M101) -> 0.72831734 | S101: =R101*EXP(-inputs!$B$27*L101/12) -> 0.69888546 | T101: =INDEX(P_rec,MATCH(inputs!$B$13+L101,curve_t,0))/INDEX(P_rec,MATCH(inputs!$B$13,curve_t,0)) -> 0.71906478 | U101: =T101/T100 -> 0.99629628 | V101: =T100/T101-1 -> 0.0037174858 | X101: 75 | Y101: =IF(X101<=0,100*1.04^(X101/12),100*1.025^(X101/12)) -> 116.68745 | AA101: 73 | AC101: =$AB$28*INDEX(I_rec,MATCH(inputs!$B$13+AA101,cpi_rec_u,0))/INDEX(I_rec,MATCH(inputs!$B$13,cpi_rec_u,0)) -> 120.04681 | AD101: =$AB$28*1.03^(AA101/12) -> 123.65364 | AF101: 117 | AG101: =IF($AF101<=85,1,IF($AF101<110,(110-$AF101)/25,0)) -> 0 | AH101: =1 -> 1 | AI101: =AH101*(1-$AG101*(0.01+0.01*AI$3)) -> 1 | AJ101: =AI101*(1-$AG101*(0.01+0.01*AJ$3)) -> 1 | AK101: =AJ101*(1-$AG101*(0.01+0.01*AK$3)) -> 1 | AL101: =AK101*(1-$AG101*(0.01+0.01*AL$3)) -> 1 | AM101: =AL101*(1-$AG101*(0.01+0.01*AM$3)) -> 1 | AN101: =AM101*(1-$AG101*(0.01+0.01*AN$3)) -> 1 | AO101: =AN101*(1-$AG101*(0.01+0.01*AO$3)) -> 1 | AP101: =AO101*(1-$AG101*(0.01+0.01*AP$3)) -> 1 | ... FC101: =FB101*(1-$AG101*(0.01+0.01*FC$3)) -> 1
F102: 120 | G102: =1 -> 1 | H102: =1 -> 1 | I102: =1 -> 1 | J102: =1 -> 1 | L102: 100 | M102: =L102/12 -> 8.3333333 | N102: =0.04-0.015*EXP(-M102/10) -> 0.033481027 | O102: =EXP(-N102*M102) -> 0.75653343 | P102: =O102*EXP(-inputs!$B$27*L102/12) -> 0.72565889 | Q102: =0.045-0.015*EXP(-M102/10) -> 0.038481027 | R102: =EXP(-Q102*M102) -> 0.72565889 | S102: =R102*EXP(-inputs!$B$27*L102/12) -> 0.69604436 | T102: =INDEX(P_rec,MATCH(inputs!$B$13+L102,curve_t,0))/INDEX(P_rec,MATCH(inputs!$B$13,curve_t,0)) -> 0.71639839 | U102: =T102/T101 -> 0.99629186 | V102: =T101/T102-1 -> 0.0037219428 | X102: 76 | Y102: =IF(X102<=0,100*1.04^(X102/12),100*1.025^(X102/12)) -> 116.92781 | AA102: 74 | AC102: =$AB$28*INDEX(I_rec,MATCH(inputs!$B$13+AA102,cpi_rec_u,0))/INDEX(I_rec,MATCH(inputs!$B$13,cpi_rec_u,0)) -> 120.29409 | AD102: =$AB$28*1.03^(AA102/12) -> 123.9586 | AF102: 118 | AG102: =IF($AF102<=85,1,IF($AF102<110,(110-$AF102)/25,0)) -> 0 | AH102: =1 -> 1 | AI102: =AH102*(1-$AG102*(0.01+0.01*AI$3)) -> 1 | AJ102: =AI102*(1-$AG102*(0.01+0.01*AJ$3)) -> 1 | AK102: =AJ102*(1-$AG102*(0.01+0.01*AK$3)) -> 1 | AL102: =AK102*(1-$AG102*(0.01+0.01*AL$3)) -> 1 | AM102: =AL102*(1-$AG102*(0.01+0.01*AM$3)) -> 1 | AN102: =AM102*(1-$AG102*(0.01+0.01*AN$3)) -> 1 | AO102: =AN102*(1-$AG102*(0.01+0.01*AO$3)) -> 1 | AP102: =AO102*(1-$AG102*(0.01+0.01*AP$3)) -> 1 | ... FC102: =FB102*(1-$AG102*(0.01+0.01*FC$3)) -> 1
L103: 101 | M103: =L103/12 -> 8.4166667 | N103: =0.04-0.015*EXP(-M103/10) -> 0.033535126 | O103: =EXP(-N103*M103) -> 0.75408214 | P103: =O103*EXP(-inputs!$B$27*L103/12) -> 0.72300632 | Q103: =0.045-0.015*EXP(-M103/10) -> 0.038535126 | R103: =EXP(-Q103*M103) -> 0.72300632 | S103: =R103*EXP(-inputs!$B$27*L103/12) -> 0.69321115 | T103: =INDEX(P_rec,MATCH(inputs!$B$13+L103,curve_t,0))/INDEX(P_rec,MATCH(inputs!$B$13,curve_t,0)) -> 0.71373876 | U103: =T103/T102 -> 0.99628751 | V103: =T102/T103-1 -> 0.0037263285 | X103: 77 | Y103: =IF(X103<=0,100*1.04^(X103/12),100*1.025^(X103/12)) -> 117.16866 | AA103: 75 | AC103: =$AB$28*INDEX(I_rec,MATCH(inputs!$B$13+AA103,cpi_rec_u,0))/INDEX(I_rec,MATCH(inputs!$B$13,cpi_rec_u,0)) -> 120.54187 | AD103: =$AB$28*1.03^(AA103/12) -> 124.26431 | AF103: 119 | AG103: =IF($AF103<=85,1,IF($AF103<110,(110-$AF103)/25,0)) -> 0 | AH103: =1 -> 1 | AI103: =AH103*(1-$AG103*(0.01+0.01*AI$3)) -> 1 | AJ103: =AI103*(1-$AG103*(0.01+0.01*AJ$3)) -> 1 | AK103: =AJ103*(1-$AG103*(0.01+0.01*AK$3)) -> 1 | AL103: =AK103*(1-$AG103*(0.01+0.01*AL$3)) -> 1 | AM103: =AL103*(1-$AG103*(0.01+0.01*AM$3)) -> 1 | AN103: =AM103*(1-$AG103*(0.01+0.01*AN$3)) -> 1 | AO103: =AN103*(1-$AG103*(0.01+0.01*AO$3)) -> 1 | AP103: =AO103*(1-$AG103*(0.01+0.01*AP$3)) -> 1 | ... FC103: =FB103*(1-$AG103*(0.01+0.01*FC$3)) -> 1
L104: 102 | M104: =L104/12 -> 8.5 | N104: =0.04-0.015*EXP(-M104/10) -> 0.033588776 | O104: =EXP(-N104*M104) -> 0.75163489 | P104: =O104*EXP(-inputs!$B$27*L104/12) -> 0.72035971 | Q104: =0.045-0.015*EXP(-M104/10) -> 0.038588776 | R104: =EXP(-Q104*M104) -> 0.72035971 | S104: =R104*EXP(-inputs!$B$27*L104/12) -> 0.69038588 | T104: =INDEX(P_rec,MATCH(inputs!$B$13+L104,curve_t,0))/INDEX(P_rec,MATCH(inputs!$B$13,curve_t,0)) -> 0.71108595 | U104: =T104/T103 -> 0.99628322 | V104: =T103/T104-1 -> 0.0037306438 | X104: 78 | Y104: =IF(X104<=0,100*1.04^(X104/12),100*1.025^(X104/12)) -> 117.41001 | AA104: 76 | AC104: =$AB$28*INDEX(I_rec,MATCH(inputs!$B$13+AA104,cpi_rec_u,0))/INDEX(I_rec,MATCH(inputs!$B$13,cpi_rec_u,0)) -> 120.79017 | AD104: =$AB$28*1.03^(AA104/12) -> 124.57078 | AF104: 120 | AG104: =IF($AF104<=85,1,IF($AF104<110,(110-$AF104)/25,0)) -> 0 | AH104: =1 -> 1 | AI104: =AH104*(1-$AG104*(0.01+0.01*AI$3)) -> 1 | AJ104: =AI104*(1-$AG104*(0.01+0.01*AJ$3)) -> 1 | AK104: =AJ104*(1-$AG104*(0.01+0.01*AK$3)) -> 1 | AL104: =AK104*(1-$AG104*(0.01+0.01*AL$3)) -> 1 | AM104: =AL104*(1-$AG104*(0.01+0.01*AM$3)) -> 1 | AN104: =AM104*(1-$AG104*(0.01+0.01*AN$3)) -> 1 | AO104: =AN104*(1-$AG104*(0.01+0.01*AO$3)) -> 1 | AP104: =AO104*(1-$AG104*(0.01+0.01*AP$3)) -> 1 | ... FC104: =FB104*(1-$AG104*(0.01+0.01*FC$3)) -> 1
L105: 103 | M105: =L105/12 -> 8.5833333 | N105: =0.04-0.015*EXP(-M105/10) -> 0.033641981 | O105: =EXP(-N105*M105) -> 0.74919174 | P105: =O105*EXP(-inputs!$B$27*L105/12) -> 0.71771911 | Q105: =0.045-0.015*EXP(-M105/10) -> 0.038641981 | R105: =EXP(-Q105*M105) -> 0.71771911 | S105: =R105*EXP(-inputs!$B$27*L105/12) -> 0.6875686 | T105: =INDEX(P_rec,MATCH(inputs!$B$13+L105,curve_t,0))/INDEX(P_rec,MATCH(inputs!$B$13,curve_t,0)) -> 0.70844001 | U105: =T105/T104 -> 0.99627901 | V105: =T104/T105-1 -> 0.0037348896 | X105: 79 | Y105: =IF(X105<=0,100*1.04^(X105/12),100*1.025^(X105/12)) -> 117.65186 | AA105: 77 | AC105: =$AB$28*INDEX(I_rec,MATCH(inputs!$B$13+AA105,cpi_rec_u,0))/INDEX(I_rec,MATCH(inputs!$B$13,cpi_rec_u,0)) -> 121.03898 | AD105: =$AB$28*1.03^(AA105/12) -> 124.87801
L106: 104 | M106: =L106/12 -> 8.6666667 | N106: =0.04-0.015*EXP(-M106/10) -> 0.033694744 | O106: =EXP(-N106*M106) -> 0.74675277 | P106: =O106*EXP(-inputs!$B$27*L106/12) -> 0.71508458 | Q106: =0.045-0.015*EXP(-M106/10) -> 0.038694744 | R106: =EXP(-Q106*M106) -> 0.71508458 | S106: =R106*EXP(-inputs!$B$27*L106/12) -> 0.68475937 | T106: =INDEX(P_rec,MATCH(inputs!$B$13+L106,curve_t,0))/INDEX(P_rec,MATCH(inputs!$B$13,curve_t,0)) -> 0.70580097 | U106: =T106/T105 -> 0.99627486 | V106: =T105/T106-1 -> 0.0037390668 | X106: 80 | Y106: =IF(X106<=0,100*1.04^(X106/12),100*1.025^(X106/12)) -> 117.8942 | AA106: 78 | AC106: =$AB$28*INDEX(I_rec,MATCH(inputs!$B$13+AA106,cpi_rec_u,0))/INDEX(I_rec,MATCH(inputs!$B$13,cpi_rec_u,0)) -> 121.2883 | AD106: =$AB$28*1.03^(AA106/12) -> 125.18599
L107: 105 | M107: =L107/12 -> 8.75 | N107: =0.04-0.015*EXP(-M107/10) -> 0.03374707 | O107: =EXP(-N107*M107) -> 0.74431804 | P107: =O107*EXP(-inputs!$B$27*L107/12) -> 0.71245619 | Q107: =0.045-0.015*EXP(-M107/10) -> 0.03874707 | R107: =EXP(-Q107*M107) -> 0.71245619 | S107: =R107*EXP(-inputs!$B$27*L107/12) -> 0.68195824 | T107: =INDEX(P_rec,MATCH(inputs!$B$13+L107,curve_t,0))/INDEX(P_rec,MATCH(inputs!$B$13,curve_t,0)) -> 0.70316889 | U107: =T107/T106 -> 0.99627078 | V107: =T106/T107-1 -> 0.0037431762 | X107: 81 | Y107: =IF(X107<=0,100*1.04^(X107/12),100*1.025^(X107/12)) -> 118.13704 | AA107: 79 | AC107: =$AB$28*INDEX(I_rec,MATCH(inputs!$B$13+AA107,cpi_rec_u,0))/INDEX(I_rec,MATCH(inputs!$B$13,cpi_rec_u,0)) -> 121.53813 | AD107: =$AB$28*1.03^(AA107/12) -> 125.49473
L108: 106 | M108: =L108/12 -> 8.8333333 | N108: =0.04-0.015*EXP(-M108/10) -> 0.033798961 | O108: =EXP(-N108*M108) -> 0.74188763 | P108: =O108*EXP(-inputs!$B$27*L108/12) -> 0.70983399 | Q108: =0.045-0.015*EXP(-M108/10) -> 0.038798961 | R108: =EXP(-Q108*M108) -> 0.70983399 | S108: =R108*EXP(-inputs!$B$27*L108/12) -> 0.67916524 | T108: =INDEX(P_rec,MATCH(inputs!$B$13+L108,curve_t,0))/INDEX(P_rec,MATCH(inputs!$B$13,curve_t,0)) -> 0.7005438 | U108: =T108/T107 -> 0.99626677 | V108: =T107/T108-1 -> 0.0037472187 | X108: 82 | Y108: =IF(X108<=0,100*1.04^(X108/12),100*1.025^(X108/12)) -> 118.38038 | AA108: 80 | AC108: =$AB$28*INDEX(I_rec,MATCH(inputs!$B$13+AA108,cpi_rec_u,0))/INDEX(I_rec,MATCH(inputs!$B$13,cpi_rec_u,0)) -> 121.78848 | AD108: =$AB$28*1.03^(AA108/12) -> 125.80424
L109: 107 | M109: =L109/12 -> 8.9166667 | N109: =0.04-0.015*EXP(-M109/10) -> 0.033850422 | O109: =EXP(-N109*M109) -> 0.7394616 | P109: =O109*EXP(-inputs!$B$27*L109/12) -> 0.70721804 | Q109: =0.045-0.015*EXP(-M109/10) -> 0.038850422 | R109: =EXP(-Q109*M109) -> 0.70721804 | S109: =R109*EXP(-inputs!$B$27*L109/12) -> 0.67638043 | T109: =INDEX(P_rec,MATCH(inputs!$B$13+L109,curve_t,0))/INDEX(P_rec,MATCH(inputs!$B$13,curve_t,0)) -> 0.69792574 | U109: =T109/T108 -> 0.99626282 | V109: =T108/T109-1 -> 0.0037511951 | X109: 83 | Y109: =IF(X109<=0,100*1.04^(X109/12),100*1.025^(X109/12)) -> 118.62423 | AA109: 81 | AC109: =$AB$28*INDEX(I_rec,MATCH(inputs!$B$13+AA109,cpi_rec_u,0))/INDEX(I_rec,MATCH(inputs!$B$13,cpi_rec_u,0)) -> 122.03934 | AD109: =$AB$28*1.03^(AA109/12) -> 126.11451
L110: 108 | M110: =L110/12 -> 9 | N110: =0.04-0.015*EXP(-M110/10) -> 0.033901455 | O110: =EXP(-N110*M110) -> 0.73704001 | P110: =O110*EXP(-inputs!$B$27*L110/12) -> 0.7046084 | Q110: =0.045-0.015*EXP(-M110/10) -> 0.038901455 | R110: =EXP(-Q110*M110) -> 0.7046084 | S110: =R110*EXP(-inputs!$B$27*L110/12) -> 0.67360385 | T110: =INDEX(P_rec,MATCH(inputs!$B$13+L110,curve_t,0))/INDEX(P_rec,MATCH(inputs!$B$13,curve_t,0)) -> 0.69531476 | U110: =T110/T109 -> 0.99625894 | V110: =T109/T110-1 -> 0.0037551061 | X110: 84 | Y110: =IF(X110<=0,100*1.04^(X110/12),100*1.025^(X110/12)) -> 118.86858 | AA110: 82 | AC110: =$AB$28*INDEX(I_rec,MATCH(inputs!$B$13+AA110,cpi_rec_u,0))/INDEX(I_rec,MATCH(inputs!$B$13,cpi_rec_u,0)) -> 122.29073 | AD110: =$AB$28*1.03^(AA110/12) -> 126.42554
L111: 109 | M111: =L111/12 -> 9.0833333 | N111: =0.04-0.015*EXP(-M111/10) -> 0.033952065 | O111: =EXP(-N111*M111) -> 0.73462293 | P111: =O111*EXP(-inputs!$B$27*L111/12) -> 0.70200511 | Q111: =0.045-0.015*EXP(-M111/10) -> 0.038952065 | R111: =EXP(-Q111*M111) -> 0.70200511 | S111: =R111*EXP(-inputs!$B$27*L111/12) -> 0.67083555 | T111: =INDEX(P_rec,MATCH(inputs!$B$13+L111,curve_t,0))/INDEX(P_rec,MATCH(inputs!$B$13,curve_t,0)) -> 0.69271089 | U111: =T111/T110 -> 0.99625512 | V111: =T110/T111-1 -> 0.0037589526 | X111: 85 | Y111: =IF(X111<=0,100*1.04^(X111/12),100*1.025^(X111/12)) -> 119.11343 | AA111: 83 | AC111: =$AB$28*INDEX(I_rec,MATCH(inputs!$B$13+AA111,cpi_rec_u,0))/INDEX(I_rec,MATCH(inputs!$B$13,cpi_rec_u,0)) -> 122.54262 | AD111: =$AB$28*1.03^(AA111/12) -> 126.73734
L112: 110 | M112: =L112/12 -> 9.1666667 | N112: =0.04-0.015*EXP(-M112/10) -> 0.034002255 | O112: =EXP(-N112*M112) -> 0.73221043 | P112: =O112*EXP(-inputs!$B$27*L112/12) -> 0.69940824 | Q112: =0.045-0.015*EXP(-M112/10) -> 0.039002255 | R112: =EXP(-Q112*M112) -> 0.69940824 | S112: =R112*EXP(-inputs!$B$27*L112/12) -> 0.66807555 | T112: =INDEX(P_rec,MATCH(inputs!$B$13+L112,curve_t,0))/INDEX(P_rec,MATCH(inputs!$B$13,curve_t,0)) -> 0.69011417 | U112: =T112/T111 -> 0.99625137 | V112: =T111/T112-1 -> 0.0037627355 | X112: 86 | Y112: =IF(X112<=0,100*1.04^(X112/12),100*1.025^(X112/12)) -> 119.35878 | AA112: 84 | AC112: =$AB$28*INDEX(I_rec,MATCH(inputs!$B$13+AA112,cpi_rec_u,0))/INDEX(I_rec,MATCH(inputs!$B$13,cpi_rec_u,0)) -> 122.79504 | AD112: =$AB$28*1.03^(AA112/12) -> 127.04991
...

Sheet REC-21
A1: t | B1: x | C1: Y | D1: q_ann | E1: q_mth | F1: deaths | G1: pols_if | H1: anniv | I1: esc_factor | J1: ann_pp | K1: exp_pp | L1: ann_out | M1: exp_out | N1: df | O1: v | P1: s_pp | Q1: q_ann_st | R1: q_mth_st | S1: s_pp_st | T1: cu | U1: bel | V1: inv_exp | W1: v_be | X1: v_st | Y1: ra | Z1: df(t-1) * ann_out(t) | AA1: df(t-1) * exp_out(t) + df(t) * inv_exp(t) | AB1: n_K (I9) | AC1: instalment_pm * I(n_K - L) / I(n_0 - L) | AD1: chk_I1 | AE1: chk_I2 | AF1: chk_I3 | AG1: chk_I4 | AH1: chk_I7 | AI1: chk_I9 | AK1: constant | AL1: value | AN1: scalar (7.2) | AO1: value | AQ1: check (12.1) | AR1: value
A2: 0 | G2: =$AL$6 -> 100 | J2: =$AL$7 -> 1000 | N2: =INDEX(P_rec,MATCH(A2,curve_t,0)) -> 1 | U2: =L3+M3+V3*O3+O3*U3 -> 11816430 | W2: =P3+(1-E3)*(O3*(W3+$AL$14*W3)) -> 118164.3 | X2: =S3+(1-R3)*(O3*(X3+$AL$14*X3)) -> 121394.8 | Y2: =G2*(X2-W2) -> 323049.89 | AF2: =IF(A2>$AL$11,AND(G2=0,U2=0,Y2=0),TRUE) -> TRUE | AH2: =Y2>=0 -> TRUE | AK2: run | AL2: REC | AN2: bel(0) | AO2: =U2 -> 11816430 | AQ2: I1 | AR2: =AND(AD3:AD503) -> TRUE
A3: 1 | B3: =MIN(120,INT(($AL$9+A3-1)/12)) -> 78 | C3: =INT(($AL$8+A3)/12) -> 2026 | D3: =IF(B3>=120,1,INDEX(mort_v1_M,MATCH(B3,mort_age,0))*INDEX(cif,MATCH(B3,cif_age,0),MATCH(C3,cif_year,0))) -> 0.025464339 | E3: =1-(1-D3)^(1/12) -> 0.0021472054 | F3: =G2*E3 -> 0.21472054 | G3: =G2-F3 -> 99.785279 | H3: =AND(A3-$AL$10>0,MOD(A3-$AL$10,12)=0) -> FALSE | I3: =IF($AL$4="CPI",IF(H3,INDEX(I_rec,MATCH(A3-$AL$13,cpi_rec_u,0))/INDEX(I_rec,MATCH(A3-$AL$13-12,cpi_rec_u,0)),1),1) -> 1 | J3: =J2*I3 -> 1000 | K3: =$AL$17*(INDEX(I_rec,MATCH(A3-1,cpi_rec_u,0))/$AL$18) -> 5 | L3: =G2*J3 -> 100000 | M3: =G2*K3 -> 500 | N3: =INDEX(P_rec,MATCH(A3,curve_t,0)) -> 0.99749277 | O3: =N3/N2 -> 0.99749277 | P3: =J3+K3 -> 1005 | Q3: =IF(B3>=120,1,D3*$AL$15) -> 0.023684718 | R3: =1-(1-Q3)^(1/12) -> 0.0019954822 | S3: =J3+K3*$AL$16 -> 1005.3222 | T3: =L3 -> 100000 | U3: =L4+M4+V4*O4+O4*U4 -> 11743912 | V3: =$AL$14*U3 -> 1466.9807 | W3: =P4+(1-E4)*(O4*(W4+$AL$14*W4)) -> 117691.83 | X3: =S4+(1-R4)*(O4*(X4+$AL$14*X4)) -> 120918.3 | Y3: =G3*(X3-W3) -> 321954.52 | Z3: =N2*L3 -> 100000 | AA3: =N2*M3+N3*V3 -> 1963.3026 | AD3: =AND(G3>=0,G3<=G2) -> TRUE | AE3: =AND(D3>=0,D3<=1,E3>=0,E3<=1,Q3>=0,Q3<=1,R3>=0,R3<=1,F3<=G2) -> TRUE | AF3: =IF(A3>$AL$11,AND(G3=0,U3=0,Y3=0),TRUE) -> TRUE | AG3: =ABS(U3-((U2-L3-M3)/O3-V3))<=0.000000000001*((ABS(U2)+ABS(L3)+ABS(M3))/O3+ABS(V3)) -> TRUE | AH3: =Y3>=0 -> TRUE | AK3: policy_id | AL3: =inputs!$B$53 -> 21 | AN3: ra(0) | AO3: =Y2 -> 323049.89 | AQ3: I2 | AR3: =AND(AE3:AE503) -> TRUE
A4: 2 | B4: =MIN(120,INT(($AL$9+A4-1)/12)) -> 78 | C4: =INT(($AL$8+A4)/12) -> 2026 | D4: =IF(B4>=120,1,INDEX(mort_v1_M,MATCH(B4,mort_age,0))*INDEX(cif,MATCH(B4,cif_age,0),MATCH(C4,cif_year,0))) -> 0.025464339 | E4: =1-(1-D4)^(1/12) -> 0.0021472054 | F4: =G3*E4 -> 0.21425949 | G4: =G3-F4 -> 99.57102 | H4: =AND(A4-$AL$10>0,MOD(A4-$AL$10,12)=0) -> FALSE | I4: =IF($AL$4="CPI",IF(H4,INDEX(I_rec,MATCH(A4-$AL$13,cpi_rec_u,0))/INDEX(I_rec,MATCH(A4-$AL$13-12,cpi_rec_u,0)),1),1) -> 1 | J4: =J3*I4 -> 1000 | K4: =$AL$17*(INDEX(I_rec,MATCH(A4-1,cpi_rec_u,0))/$AL$18) -> 5.0102992 | L4: =G3*J4 -> 99785.279 | M4: =G3*K4 -> 499.9541 | N4: =INDEX(P_rec,MATCH(A4,curve_t,0)) -> 0.99497136 | O4: =N4/N3 -> 0.99747225 | P4: =J4+K4 -> 1005.0103 | Q4: =IF(B4>=120,1,D4*$AL$15) -> 0.023684718 | R4: =1-(1-Q4)^(1/12) -> 0.0019954822 | S4: =J4+K4*$AL$16 -> 1005.3332 | T4: =L4 -> 99785.279 | U4: =L5+M5+V5*O5+O5*U5 -> 11671675 | V4: =$AL$14*U4 -> 1457.9573 | W4: =P5+(1-E5)*(O5*(W5+$AL$14*W5)) -> 117219.6 | X4: =S5+(1-R5)*(O5*(X5+$AL$14*X5)) -> 120442.17 | Y4: =G4*(X4-W4) -> 320874.34 | Z4: =N3*L4 -> 99535.095 | AA4: =N3*M4+N4*V4 -> 1949.3264 | AD4: =AND(G4>=0,G4<=G3) -> TRUE | AE4: =AND(D4>=0,D4<=1,E4>=0,E4<=1,Q4>=0,Q4<=1,R4>=0,R4<=1,F4<=G3) -> TRUE | AF4: =IF(A4>$AL$11,AND(G4=0,U4=0,Y4=0),TRUE) -> TRUE | AG4: =ABS(U4-((U3-L4-M4)/O4-V4))<=0.000000000001*((ABS(U3)+ABS(L4)+ABS(M4))/O4+ABS(V4)) -> TRUE | AH4: =Y4>=0 -> TRUE | AK4: class | AL4: =inputs!$B$54 -> level | AN4: pva | AO4: =SUM(Z3:Z503) -> 11624246 | AQ4: I3 | AR4: =AND(U503=0,W503=0,X503=0,INDEX(D2:D503,MATCH($AL$11,A2:A503,0))=1,INDEX(G2:G503,MATCH($AL$11,A2:A503,0))=0,AND(AF2:AF503)) -> TRUE
A5: 3 | B5: =MIN(120,INT(($AL$9+A5-1)/12)) -> 78 | C5: =INT(($AL$8+A5)/12) -> 2026 | D5: =IF(B5>=120,1,INDEX(mort_v1_M,MATCH(B5,mort_age,0))*INDEX(cif,MATCH(B5,cif_age,0),MATCH(C5,cif_year,0))) -> 0.025464339 | E5: =1-(1-D5)^(1/12) -> 0.0021472054 | F5: =G4*E5 -> 0.21379943 | G5: =G4-F5 -> 99.357221 | H5: =AND(A5-$AL$10>0,MOD(A5-$AL$10,12)=0) -> FALSE | I5: =IF($AL$4="CPI",IF(H5,INDEX(I_rec,MATCH(A5-$AL$13,cpi_rec_u,0))/INDEX(I_rec,MATCH(A5-$AL$13-12,cpi_rec_u,0)),1),1) -> 1 | J5: =J4*I5 -> 1000 | K5: =$AL$17*(INDEX(I_rec,MATCH(A5-1,cpi_rec_u,0))/$AL$18) -> 5.0206196 | L5: =G4*J5 -> 99571.02 | M5: =G4*K5 -> 499.90821 | N5: =INDEX(P_rec,MATCH(A5,curve_t,0)) -> 0.99243616 | O5: =N5/N4 -> 0.99745199 | P5: =J5+K5 -> 1005.0206 | Q5: =IF(B5>=120,1,D5*$AL$15) -> 0.023684718 | R5: =1-(1-Q5)^(1/12) -> 0.0019954822 | S5: =J5+K5*$AL$16 -> 1005.3441 | T5: =L5 -> 99571.02 | U5: =L6+M6+V6*O6+O6*U6 -> 11599715 | V5: =$AL$14*U5 -> 1448.9685 | W5: =P6+(1-E6)*(O6*(W6+$AL$14*W6)) -> 116747.58 | X5: =S6+(1-R6)*(O6*(X6+$AL$14*X6)) -> 119966.36 | Y5: =G5*(X5-W5) -> 319809.19 | Z5: =N4*L5 -> 99070.314 | AA5: =N4*M5+N5*V5 -> 1935.4031 | AD5: =AND(G5>=0,G5<=G4) -> TRUE | AE5: =AND(D5>=0,D5<=1,E5>=0,E5<=1,Q5>=0,Q5<=1,R5>=0,R5<=1,F5<=G4) -> TRUE | AF5: =IF(A5>$AL$11,AND(G5=0,U5=0,Y5=0),TRUE) -> TRUE | AG5: =ABS(U5-((U4-L5-M5)/O5-V5))<=0.000000000001*((ABS(U4)+ABS(L5)+ABS(M5))/O5+ABS(V5)) -> TRUE | AH5: =Y5>=0 -> TRUE | AK5: sex | AL5: =inputs!$B$55 -> M | AN5: pve | AO5: =SUM(AA3:AA503) -> 192184.28 | AQ5: I4 | AR5: =AND(AG3:AG503) -> TRUE
A6: 4 | B6: =MIN(120,INT(($AL$9+A6-1)/12)) -> 78 | C6: =INT(($AL$8+A6)/12) -> 2026 | D6: =IF(B6>=120,1,INDEX(mort_v1_M,MATCH(B6,mort_age,0))*INDEX(cif,MATCH(B6,cif_age,0),MATCH(C6,cif_year,0))) -> 0.025464339 | E6: =1-(1-D6)^(1/12) -> 0.0021472054 | F6: =G5*E6 -> 0.21334036 | G6: =G5-F6 -> 99.14388 | H6: =AND(A6-$AL$10>0,MOD(A6-$AL$10,12)=0) -> FALSE | I6: =IF($AL$4="CPI",IF(H6,INDEX(I_rec,MATCH(A6-$AL$13,cpi_rec_u,0))/INDEX(I_rec,MATCH(A6-$AL$13-12,cpi_rec_u,0)),1),1) -> 1 | J6: =J5*I6 -> 1000 | K6: =$AL$17*(INDEX(I_rec,MATCH(A6-1,cpi_rec_u,0))/$AL$18) -> 5.0309612 | L6: =G5*J6 -> 99357.221 | M6: =G5*K6 -> 499.86232 | N6: =INDEX(P_rec,MATCH(A6,curve_t,0)) -> 0.98988756 | O6: =N6/N5 -> 0.99743197 | P6: =J6+K6 -> 1005.031 | Q6: =IF(B6>=120,1,D6*$AL$15) -> 0.023684718 | R6: =1-(1-Q6)^(1/12) -> 0.0019954822 | S6: =J6+K6*$AL$16 -> 1005.3552 | T6: =L6 -> 99357.221 | U6: =L7+M7+V7*O7+O7*U7 -> 11528026 | V6: =$AL$14*U6 -> 1440.0135 | W6: =P7+(1-E7)*(O7*(W7+$AL$14*W7)) -> 116275.72 | X6: =S7+(1-R7)*(O7*(X7+$AL$14*X7)) -> 119490.84 | Y6: =G6*(X6-W6) -> 318758.94 | Z6: =N5*L6 -> 98605.699 | AA6: =N5*M6+N6*V6 -> 1921.5329 | AD6: =AND(G6>=0,G6<=G5) -> TRUE | AE6: =AND(D6>=0,D6<=1,E6>=0,E6<=1,Q6>=0,Q6<=1,R6>=0,R6<=1,F6<=G5) -> TRUE | AF6: =IF(A6>$AL$11,AND(G6=0,U6=0,Y6=0),TRUE) -> TRUE | AG6: =ABS(U6-((U5-L6-M6)/O6-V6))<=0.000000000001*((ABS(U5)+ABS(L6)+ABS(M6))/O6+ABS(V6)) -> TRUE | AH6: =Y6>=0 -> TRUE | AK6: pols_if_init | AL6: =inputs!$B$59 -> 100 | AN6: ann_pp(1) | AO6: =J3 -> 1000 | AQ6: I5 | AR6: =ABS($AO$2-($AO$4+$AO$5))<=0.000000000001*MAX(ABS($AO$2),ABS(($AO$4+$AO$5))) -> TRUE
A7: 5 | B7: =MIN(120,INT(($AL$9+A7-1)/12)) -> 78 | C7: =INT(($AL$8+A7)/12) -> 2026 | D7: =IF(B7>=120,1,INDEX(mort_v1_M,MATCH(B7,mort_age,0))*INDEX(cif,MATCH(B7,cif_age,0),MATCH(C7,cif_year,0))) -> 0.025464339 | E7: =1-(1-D7)^(1/12) -> 0.0021472054 | F7: =G6*E7 -> 0.21288227 | G7: =G6-F7 -> 98.930998 | H7: =AND(A7-$AL$10>0,MOD(A7-$AL$10,12)=0) -> FALSE | I7: =IF($AL$4="CPI",IF(H7,INDEX(I_rec,MATCH(A7-$AL$13,cpi_rec_u,0))/INDEX(I_rec,MATCH(A7-$AL$13-12,cpi_rec_u,0)),1),1) -> 1 | J7: =J6*I7 -> 1000 | K7: =$AL$17*(INDEX(I_rec,MATCH(A7-1,cpi_rec_u,0))/$AL$18) -> 5.0413242 | L7: =G6*J7 -> 99143.88 | M7: =G6*K7 -> 499.81644 | N7: =INDEX(P_rec,MATCH(A7,curve_t,0)) -> 0.98732594 | O7: =N7/N6 -> 0.99741221 | P7: =J7+K7 -> 1005.0413 | Q7: =IF(B7>=120,1,D7*$AL$15) -> 0.023684718 | R7: =1-(1-Q7)^(1/12) -> 0.0019954822 | S7: =J7+K7*$AL$16 -> 1005.3662 | T7: =L7 -> 99143.88 | U7: =L8+M8+V8*O8+O8*U8 -> 11456602 | V7: =$AL$14*U7 -> 1431.0917 | W7: =P8+(1-E8)*(O8*(W8+$AL$14*W8)) -> 115803.97 | X7: =S8+(1-R8)*(O8*(X8+$AL$14*X8)) -> 119015.54 | Y7: =G7*(X7-W7) -> 317723.48 | Z7: =N6*L7 -> 98141.294 | AA7: =N6*M7+N7*V7 -> 1907.716 | AD7: =AND(G7>=0,G7<=G6) -> TRUE | AE7: =AND(D7>=0,D7<=1,E7>=0,E7<=1,Q7>=0,Q7<=1,R7>=0,R7<=1,F7<=G6) -> TRUE | AF7: =IF(A7>$AL$11,AND(G7=0,U7=0,Y7=0),TRUE) -> TRUE | AG7: =ABS(U7-((U6-L7-M7)/O7-V7))<=0.000000000001*((ABS(U6)+ABS(L7)+ABS(M7))/O7+ABS(V7)) -> TRUE | AH7: =Y7>=0 -> TRUE | AK7: instalment_pm | AL7: =inputs!$B$60 -> 1000 | AN7: v_be(0) | AO7: =W2 -> 118164.3 | AQ7: I7 | AR7: =AND(AH2:AH503) -> TRUE
A8: 6 | B8: =MIN(120,INT(($AL$9+A8-1)/12)) -> 78 | C8: =INT(($AL$8+A8)/12) -> 2026 | D8: =IF(B8>=120,1,INDEX(mort_v1_M,MATCH(B8,mort_age,0))*INDEX(cif,MATCH(B8,cif_age,0),MATCH(C8,cif_year,0))) -> 0.025464339 | E8: =1-(1-D8)^(1/12) -> 0.0021472054 | F8: =G7*E8 -> 0.21242517 | G8: =G7-F8 -> 98.718573 | H8: =AND(A8-$AL$10>0,MOD(A8-$AL$10,12)=0) -> FALSE | I8: =IF($AL$4="CPI",IF(H8,INDEX(I_rec,MATCH(A8-$AL$13,cpi_rec_u,0))/INDEX(I_rec,MATCH(A8-$AL$13-12,cpi_rec_u,0)),1),1) -> 1 | J8: =J7*I8 -> 1000 | K8: =$AL$17*(INDEX(I_rec,MATCH(A8-1,cpi_rec_u,0))/$AL$18) -> 5.0517085 | L8: =G7*J8 -> 98930.998 | M8: =G7*K8 -> 499.77056 | N8: =INDEX(P_rec,MATCH(A8,curve_t,0)) -> 0.98475167 | O8: =N8/N7 -> 0.99739269 | P8: =J8+K8 -> 1005.0517 | Q8: =IF(B8>=120,1,D8*$AL$15) -> 0.023684718 | R8: =1-(1-Q8)^(1/12) -> 0.0019954822 | S8: =J8+K8*$AL$16 -> 1005.3772 | T8: =L8 -> 98930.998 | U8: =L9+M9+V9*O9+O9*U9 -> 11385439 | V8: =$AL$14*U8 -> 1422.2023 | W8: =P9+(1-E9)*(O9*(W9+$AL$14*W9)) -> 115332.28 | X8: =S9+(1-R9)*(O9*(X9+$AL$14*X9)) -> 118540.42 | Y8: =G8*(X8-W8) -> 316702.67 | Z8: =N7*L8 -> 97677.14 | AA8: =N7*M8+N8*V8 -> 1893.9526 | AD8: =AND(G8>=0,G8<=G7) -> TRUE | AE8: =AND(D8>=0,D8<=1,E8>=0,E8<=1,Q8>=0,Q8<=1,R8>=0,R8<=1,F8<=G7) -> TRUE | AF8: =IF(A8>$AL$11,AND(G8=0,U8=0,Y8=0),TRUE) -> TRUE | AG8: =ABS(U8-((U7-L8-M8)/O8-V8))<=0.000000000001*((ABS(U7)+ABS(L8)+ABS(M8))/O8+ABS(V8)) -> TRUE | AH8: =Y8>=0 -> TRUE | AK8: m_V (the run's valuation month) | AL8: =inputs!$B$11 -> 24311 | AN8: v_st(0) | AO8: =X2 -> 121394.8 | AQ8: I9 | AR8: n/a (level class)
A9: 7 | B9: =MIN(120,INT(($AL$9+A9-1)/12)) -> 78 | C9: =INT(($AL$8+A9)/12) -> 2026 | D9: =IF(B9>=120,1,INDEX(mort_v1_M,MATCH(B9,mort_age,0))*INDEX(cif,MATCH(B9,cif_age,0),MATCH(C9,cif_year,0))) -> 0.025464339 | E9: =1-(1-D9)^(1/12) -> 0.0021472054 | F9: =G8*E9 -> 0.21196905 | G9: =G8-F9 -> 98.506604 | H9: =AND(A9-$AL$10>0,MOD(A9-$AL$10,12)=0) -> FALSE | I9: =IF($AL$4="CPI",IF(H9,INDEX(I_rec,MATCH(A9-$AL$13,cpi_rec_u,0))/INDEX(I_rec,MATCH(A9-$AL$13-12,cpi_rec_u,0)),1),1) -> 1 | J9: =J8*I9 -> 1000 | K9: =$AL$17*(INDEX(I_rec,MATCH(A9-1,cpi_rec_u,0))/$AL$18) -> 5.0621142 | L9: =G8*J9 -> 98718.573 | M9: =G8*K9 -> 499.72469 | N9: =INDEX(P_rec,MATCH(A9,curve_t,0)) -> 0.98216514 | O9: =N9/N8 -> 0.99737342 | P9: =J9+K9 -> 1005.0621 | Q9: =IF(B9>=120,1,D9*$AL$15) -> 0.023684718 | R9: =1-(1-Q9)^(1/12) -> 0.0019954822 | S9: =J9+K9*$AL$16 -> 1005.3883 | T9: =L9 -> 98718.573 | U9: =L10+M10+V10*O10+O10*U10 -> 11314529 | V9: =$AL$14*U9 -> 1413.3447 | W9: =P10+(1-E10)*(O10*(W10+$AL$14*W10)) -> 114860.62 | X9: =S10+(1-R10)*(O10*(X10+$AL$14*X10)) -> 118065.44 | Y9: =G9*(X9-W9) -> 315696.39 | Z9: =N8*L9 -> 97213.28 | AA9: =N8*M9+N9*V9 -> 1880.2427 | AD9: =AND(G9>=0,G9<=G8) -> TRUE | AE9: =AND(D9>=0,D9<=1,E9>=0,E9<=1,Q9>=0,Q9<=1,R9>=0,R9<=1,F9<=G8) -> TRUE | AF9: =IF(A9>$AL$11,AND(G9=0,U9=0,Y9=0),TRUE) -> TRUE | AG9: =ABS(U9-((U8-L9-M9)/O9-V9))<=0.000000000001*((ABS(U8)+ABS(L9)+ABS(M9))/O9+ABS(V9)) -> TRUE | AH9: =Y9>=0 -> TRUE | AK9: a0 | AL9: =inputs!$B$68 -> 940
A10: 8 | B10: =MIN(120,INT(($AL$9+A10-1)/12)) -> 78 | C10: =INT(($AL$8+A10)/12) -> 2026 | D10: =IF(B10>=120,1,INDEX(mort_v1_M,MATCH(B10,mort_age,0))*INDEX(cif,MATCH(B10,cif_age,0),MATCH(C10,cif_year,0))) -> 0.025464339 | E10: =1-(1-D10)^(1/12) -> 0.0021472054 | F10: =G9*E10 -> 0.21151391 | G10: =G9-F10 -> 98.29509 | H10: =AND(A10-$AL$10>0,MOD(A10-$AL$10,12)=0) -> FALSE | I10: =IF($AL$4="CPI",IF(H10,INDEX(I_rec,MATCH(A10-$AL$13,cpi_rec_u,0))/INDEX(I_rec,MATCH(A10-$AL$13-12,cpi_rec_u,0)),1),1) -> 1 | J10: =J9*I10 -> 1000 | K10: =$AL$17*(INDEX(I_rec,MATCH(A10-1,cpi_rec_u,0))/$AL$18) -> 5.0725413 | L10: =G9*J10 -> 98506.604 | M10: =G9*K10 -> 499.67882 | N10: =INDEX(P_rec,MATCH(A10,curve_t,0)) -> 0.97956672 | O10: =N10/N9 -> 0.99735439 | P10: =J10+K10 -> 1005.0725 | Q10: =IF(B10>=120,1,D10*$AL$15) -> 0.023684718 | R10: =1-(1-Q10)^(1/12) -> 0.0019954822 | S10: =J10+K10*$AL$16 -> 1005.3994 | T10: =L10 -> 98506.604 | U10: =L11+M11+V11*O11+O11*U11 -> 11243869 | V10: =$AL$14*U10 -> 1404.5183 | W10: =P11+(1-E11)*(O11*(W11+$AL$14*W11)) -> 114388.92 | X10: =S11+(1-R11)*(O11*(X11+$AL$14*X11)) -> 117590.55 | Y10: =G10*(X10-W10) -> 314704.52 | Z10: =N9*L10 -> 96749.753 | AA10: =N9*M10+N10*V10 -> 1866.5865 | AD10: =AND(G10>=0,G10<=G9) -> TRUE | AE10: =AND(D10>=0,D10<=1,E10>=0,E10<=1,Q10>=0,Q10<=1,R10>=0,R10<=1,F10<=G9) -> TRUE | AF10: =IF(A10>$AL$11,AND(G10=0,U10=0,Y10=0),TRUE) -> TRUE | AG10: =ABS(U10-((U9-L10-M10)/O10-V10))<=0.000000000001*((ABS(U9)+ABS(L10)+ABS(M10))/O10+ABS(V10)) -> TRUE | AH10: =Y10>=0 -> TRUE | AK10: m_c | AL10: =inputs!$B$71 -> 1
A11: 9 | B11: =MIN(120,INT(($AL$9+A11-1)/12)) -> 79 | C11: =INT(($AL$8+A11)/12) -> 2026 | D11: =IF(B11>=120,1,INDEX(mort_v1_M,MATCH(B11,mort_age,0))*INDEX(cif,MATCH(B11,cif_age,0),MATCH(C11,cif_year,0))) -> 0.028549498 | E11: =1-(1-D11)^(1/12) -> 0.002410836 | F11: =G10*E11 -> 0.23697335 | G11: =G10-F11 -> 98.058116 | H11: =AND(A11-$AL$10>0,MOD(A11-$AL$10,12)=0) -> FALSE | I11: =IF($AL$4="CPI",IF(H11,INDEX(I_rec,MATCH(A11-$AL$13,cpi_rec_u,0))/INDEX(I_rec,MATCH(A11-$AL$13-12,cpi_rec_u,0)),1),1) -> 1 | J11: =J10*I11 -> 1000 | K11: =$AL$17*(INDEX(I_rec,MATCH(A11-1,cpi_rec_u,0))/$AL$18) -> 5.0829899 | L11: =G10*J11 -> 98295.09 | M11: =G10*K11 -> 499.63295 | N11: =INDEX(P_rec,MATCH(A11,curve_t,0)) -> 0.97695676 | O11: =N11/N10 -> 0.9973356 | P11: =J11+K11 -> 1005.083 | Q11: =IF(B11>=120,1,D11*$AL$15) -> 0.026554265 | R11: =1-(1-Q11)^(1/12) -> 0.0022402534 | S11: =J11+K11*$AL$16 -> 1005.4105 | T11: =L11 -> 98295.09 | U11: =L12+M12+V12*O12+O12*U12 -> 11173453 | V11: =$AL$14*U11 -> 1395.7223 | W11: =P12+(1-E12)*(O12*(W12+$AL$14*W12)) -> 113947.25 | X11: =S12+(1-R12)*(O12*(X12+$AL$14*X12)) -> 117144.43 | Y11: =G11*(X11-W11) -> 313509.36 | Z11: =N10*L11 -> 96286.598 | AA11: =N10*M11+N11*V11 -> 1852.9841 | AD11: =AND(G11>=0,G11<=G10) -> TRUE | AE11: =AND(D11>=0,D11<=1,E11>=0,E11<=1,Q11>=0,Q11<=1,R11>=0,R11<=1,F11<=G10) -> TRUE | AF11: =IF(A11>$AL$11,AND(G11=0,U11=0,Y11=0),TRUE) -> TRUE | AG11: =ABS(U11-((U10-L11-M11)/O11-V11))<=0.000000000001*((ABS(U10)+ABS(L11)+ABS(M11))/O11+ABS(V11)) -> TRUE | AH11: =Y11>=0 -> TRUE | AK11: T_i | AL11: =inputs!$B$73 -> 501
A12: 10 | B12: =MIN(120,INT(($AL$9+A12-1)/12)) -> 79 | C12: =INT(($AL$8+A12)/12) -> 2026 | D12: =IF(B12>=120,1,INDEX(mort_v1_M,MATCH(B12,mort_age,0))*INDEX(cif,MATCH(B12,cif_age,0),MATCH(C12,cif_year,0))) -> 0.028549498 | E12: =1-(1-D12)^(1/12) -> 0.002410836 | F12: =G11*E12 -> 0.23640204 | G12: =G11-F12 -> 97.821714 | H12: =AND(A12-$AL$10>0,MOD(A12-$AL$10,12)=0) -> FALSE | I12: =IF($AL$4="CPI",IF(H12,INDEX(I_rec,MATCH(A12-$AL$13,cpi_rec_u,0))/INDEX(I_rec,MATCH(A12-$AL$13-12,cpi_rec_u,0)),1),1) -> 1 | J12: =J11*I12 -> 1000 | K12: =$AL$17*(INDEX(I_rec,MATCH(A12-1,cpi_rec_u,0))/$AL$18) -> 5.09346 | L12: =G11*J12 -> 98058.116 | M12: =G11*K12 -> 499.4551 | N12: =INDEX(P_rec,MATCH(A12,curve_t,0)) -> 0.97433563 | O12: =N12/N11 -> 0.99731705 | P12: =J12+K12 -> 1005.0935 | Q12: =IF(B12>=120,1,D12*$AL$15) -> 0.026554265 | R12: =1-(1-Q12)^(1/12) -> 0.0022402534 | S12: =J12+K12*$AL$16 -> 1005.4217 | T12: =L12 -> 98058.116 | U12: =L13+M13+V13*O13+O13*U13 -> 11103302 | V12: =$AL$14*U12 -> 1386.9594 | W12: =P13+(1-E13)*(O13*(W13+$AL$14*W13)) -> 113505.49 | X12: =S13+(1-R13)*(O13*(X13+$AL$14*X13)) -> 116698.33 | Y12: =G12*(X12-W12) -> 312329.21 | Z12: =N11*L12 -> 95798.54 | AA12: =N11*M12+N12*V12 -> 1839.31 | AD12: =AND(G12>=0,G12<=G11) -> TRUE | AE12: =AND(D12>=0,D12<=1,E12>=0,E12<=1,Q12>=0,Q12<=1,R12>=0,R12<=1,F12<=G11) -> TRUE | AF12: =IF(A12>$AL$11,AND(G12=0,U12=0,Y12=0),TRUE) -> TRUE | AG12: =ABS(U12-((U11-L12-M12)/O12-V12))<=0.000000000001*((ABS(U11)+ABS(L12)+ABS(M12))/O12+ABS(V12)) -> TRUE | AH12: =Y12>=0 -> TRUE | AK12: T | AL12: =inputs!$B$19 -> 501
A13: 11 | B13: =MIN(120,INT(($AL$9+A13-1)/12)) -> 79 | C13: =INT(($AL$8+A13)/12) -> 2026 | D13: =IF(B13>=120,1,INDEX(mort_v1_M,MATCH(B13,mort_age,0))*INDEX(cif,MATCH(B13,cif_age,0),MATCH(C13,cif_year,0))) -> 0.028549498 | E13: =1-(1-D13)^(1/12) -> 0.002410836 | F13: =G12*E13 -> 0.23583211 | G13: =G12-F13 -> 97.585882 | H13: =AND(A13-$AL$10>0,MOD(A13-$AL$10,12)=0) -> FALSE | I13: =IF($AL$4="CPI",IF(H13,INDEX(I_rec,MATCH(A13-$AL$13,cpi_rec_u,0))/INDEX(I_rec,MATCH(A13-$AL$13-12,cpi_rec_u,0)),1),1) -> 1 | J13: =J12*I13 -> 1000 | K13: =$AL$17*(INDEX(I_rec,MATCH(A13-1,cpi_rec_u,0))/$AL$18) -> 5.1039517 | L13: =G12*J13 -> 97821.714 | M13: =G12*K13 -> 499.27731 | N13: =INDEX(P_rec,MATCH(A13,curve_t,0)) -> 0.97170368 | O13: =N13/N12 -> 0.99729873 | P13: =J13+K13 -> 1005.104 | Q13: =IF(B13>=120,1,D13*$AL$15) -> 0.026554265 | R13: =1-(1-Q13)^(1/12) -> 0.0022402534 | S13: =J13+K13*$AL$16 -> 1005.4329 | T13: =L13 -> 97821.714 | U13: =L14+M14+V14*O14+O14*U14 -> 11033410 | V13: =$AL$14*U13 -> 1378.229 | W13: =P14+(1-E14)*(O14*(W14+$AL$14*W14)) -> 113063.59 | X13: =S14+(1-R14)*(O14*(X14+$AL$14*X14)) -> 116252.21 | Y13: =G13*(X13-W13) -> 311163.95 | Z13: =N12*L13 -> 95311.182 | AA13: =N12*M13+N13*V13 -> 1825.6939 | AD13: =AND(G13>=0,G13<=G12) -> TRUE | AE13: =AND(D13>=0,D13<=1,E13>=0,E13<=1,Q13>=0,Q13<=1,R13>=0,R13<=1,F13<=G12) -> TRUE | AF13: =IF(A13>$AL$11,AND(G13=0,U13=0,Y13=0),TRUE) -> TRUE | AG13: =ABS(U13-((U12-L13-M13)/O13-V13))<=0.000000000001*((ABS(U12)+ABS(L13)+ABS(M13))/O13+ABS(V13)) -> TRUE | AH13: =Y13>=0 -> TRUE | AK13: L | AL13: =inputs!$B$15 -> 3
A14: 12 | B14: =MIN(120,INT(($AL$9+A14-1)/12)) -> 79 | C14: =INT(($AL$8+A14)/12) -> 2026 | D14: =IF(B14>=120,1,INDEX(mort_v1_M,MATCH(B14,mort_age,0))*INDEX(cif,MATCH(B14,cif_age,0),MATCH(C14,cif_year,0))) -> 0.028549498 | E14: =1-(1-D14)^(1/12) -> 0.002410836 | F14: =G13*E14 -> 0.23526356 | G14: =G13-F14 -> 97.350619 | H14: =AND(A14-$AL$10>0,MOD(A14-$AL$10,12)=0) -> FALSE | I14: =IF($AL$4="CPI",IF(H14,INDEX(I_rec,MATCH(A14-$AL$13,cpi_rec_u,0))/INDEX(I_rec,MATCH(A14-$AL$13-12,cpi_rec_u,0)),1),1) -> 1 | J14: =J13*I14 -> 1000 | K14: =$AL$17*(INDEX(I_rec,MATCH(A14-1,cpi_rec_u,0))/$AL$18) -> 5.114465 | L14: =G13*J14 -> 97585.882 | M14: =G13*K14 -> 499.09958 | N14: =INDEX(P_rec,MATCH(A14,curve_t,0)) -> 0.96906127 | O14: =N14/N13 -> 0.99728064 | P14: =J14+K14 -> 1005.1145 | Q14: =IF(B14>=120,1,D14*$AL$15) -> 0.026554265 | R14: =1-(1-Q14)^(1/12) -> 0.0022402534 | S14: =J14+K14*$AL$16 -> 1005.444 | T14: =L14 -> 97585.882 | U14: =L15+M15+V15*O15+O15*U15 -> 10963774 | V14: =$AL$14*U14 -> 1369.5305 | W14: =P15+(1-E15)*(O15*(W15+$AL$14*W15)) -> 112621.51 | X14: =S15+(1-R15)*(O15*(X15+$AL$14*X15)) -> 115806.02 | Y14: =G14*(X14-W14) -> 310013.45 | Z14: =N13*L14 -> 94824.561 | AA14: =N13*M14+N14*V14 -> 1812.1358 | AD14: =AND(G14>=0,G14<=G13) -> TRUE | AE14: =AND(D14>=0,D14<=1,E14>=0,E14<=1,Q14>=0,Q14<=1,R14>=0,R14<=1,F14<=G13) -> TRUE | AF14: =IF(A14>$AL$11,AND(G14=0,U14=0,Y14=0),TRUE) -> TRUE | AG14: =ABS(U14-((U13-L14-M14)/O14-V14))<=0.000000000001*((ABS(U13)+ABS(L14)+ABS(M14))/O14+ABS(V14)) -> TRUE | AH14: =Y14>=0 -> TRUE | AK14: ie_m | AL14: =inputs!$B$32 -> 0.00012491414
A15: 13 | B15: =MIN(120,INT(($AL$9+A15-1)/12)) -> 79 | C15: =INT(($AL$8+A15)/12) -> 2027 | D15: =IF(B15>=120,1,INDEX(mort_v1_M,MATCH(B15,mort_age,0))*INDEX(cif,MATCH(B15,cif_age,0),MATCH(C15,cif_year,0))) -> 0.027980578 | E15: =1-(1-D15)^(1/12) -> 0.0023621634 | F15: =G14*E15 -> 0.22995807 | G15: =G14-F15 -> 97.120661 | H15: =AND(A15-$AL$10>0,MOD(A15-$AL$10,12)=0) -> TRUE | I15: =IF($AL$4="CPI",IF(H15,INDEX(I_rec,MATCH(A15-$AL$13,cpi_rec_u,0))/INDEX(I_rec,MATCH(A15-$AL$13-12,cpi_rec_u,0)),1),1) -> 1 | J15: =J14*I15 -> 1000 | K15: =$AL$17*(INDEX(I_rec,MATCH(A15-1,cpi_rec_u,0))/$AL$18) -> 5.125 | L15: =G14*J15 -> 97350.619 | M15: =G14*K15 -> 498.92192 | N15: =INDEX(P_rec,MATCH(A15,curve_t,0)) -> 0.96640874 | O15: =N15/N14 -> 0.99726278 | P15: =J15+K15 -> 1005.125 | Q15: =IF(B15>=120,1,D15*$AL$15) -> 0.026025105 | R15: =1-(1-Q15)^(1/12) -> 0.0021950665 | S15: =J15+K15*$AL$16 -> 1005.4553 | T15: =L15 -> 97350.619 | U15: =L16+M16+V16*O16+O16*U16 -> 10894388 | V15: =$AL$14*U15 -> 1360.8631 | W15: =P16+(1-E16)*(O16*(W16+$AL$14*W16)) -> 112173.74 | X15: =S16+(1-R16)*(O16*(X16+$AL$14*X16)) -> 115354.49 | Y15: =G15*(X15-W15) -> 308916.82 | Z15: =N14*L15 -> 94338.714 | AA15: =N14*M15+N15*V15 -> 1798.6359 | AD15: =AND(G15>=0,G15<=G14) -> TRUE | AE15: =AND(D15>=0,D15<=1,E15>=0,E15<=1,Q15>=0,Q15<=1,R15>=0,R15<=1,F15<=G14) -> TRUE | AF15: =IF(A15>$AL$11,AND(G15=0,U15=0,Y15=0),TRUE) -> TRUE | AG15: =ABS(U15-((U14-L15-M15)/O15-V15))<=0.000000000001*((ABS(U14)+ABS(L15)+ABS(M15))/O15+ABS(V15)) -> TRUE | AH15: =Y15>=0 -> TRUE | AK15: mort_mult | AL15: =inputs!$B$33 -> 0.9301132
A16: 14 | B16: =MIN(120,INT(($AL$9+A16-1)/12)) -> 79 | C16: =INT(($AL$8+A16)/12) -> 2027 | D16: =IF(B16>=120,1,INDEX(mort_v1_M,MATCH(B16,mort_age,0))*INDEX(cif,MATCH(B16,cif_age,0),MATCH(C16,cif_year,0))) -> 0.027980578 | E16: =1-(1-D16)^(1/12) -> 0.0023621634 | F16: =G15*E16 -> 0.22941487 | G16: =G15-F16 -> 96.891246 | H16: =AND(A16-$AL$10>0,MOD(A16-$AL$10,12)=0) -> FALSE | I16: =IF($AL$4="CPI",IF(H16,INDEX(I_rec,MATCH(A16-$AL$13,cpi_rec_u,0))/INDEX(I_rec,MATCH(A16-$AL$13-12,cpi_rec_u,0)),1),1) -> 1 | J16: =J15*I16 -> 1000 | K16: =$AL$17*(INDEX(I_rec,MATCH(A16-1,cpi_rec_u,0))/$AL$18) -> 5.1355567 | L16: =G15*J16 -> 97120.661 | M16: =G15*K16 -> 498.76866 | N16: =INDEX(P_rec,MATCH(A16,curve_t,0)) -> 0.96374642 | O16: =N16/N15 -> 0.99724515 | P16: =J16+K16 -> 1005.1356 | Q16: =IF(B16>=120,1,D16*$AL$15) -> 0.026025105 | R16: =1-(1-Q16)^(1/12) -> 0.0021950665 | S16: =J16+K16*$AL$16 -> 1005.4665 | T16: =L16 -> 97120.661 | U16: =L17+M17+V17*O17+O17*U17 -> 10825242 | V16: =$AL$14*U16 -> 1352.2258 | W16: =P17+(1-E17)*(O17*(W17+$AL$14*W17)) -> 111725.69 | X16: =S17+(1-R17)*(O17*(X17+$AL$14*X17)) -> 114902.81 | Y16: =G16*(X16-W16) -> 307834.57 | Z16: =N15*L16 -> 93858.255 | AA16: =N15*M16+N16*V16 -> 1785.2172 | AD16: =AND(G16>=0,G16<=G15) -> TRUE | AE16: =AND(D16>=0,D16<=1,E16>=0,E16<=1,Q16>=0,Q16<=1,R16>=0,R16<=1,F16<=G15) -> TRUE | AF16: =IF(A16>$AL$11,AND(G16=0,U16=0,Y16=0),TRUE) -> TRUE | AG16: =ABS(U16-((U15-L16-M16)/O16-V16))<=0.000000000001*((ABS(U15)+ABS(L16)+ABS(M16))/O16+ABS(V16)) -> TRUE | AH16: =Y16>=0 -> TRUE | AK16: exp_mult | AL16: =inputs!$B$34 -> 1.0644401
A17: 15 | B17: =MIN(120,INT(($AL$9+A17-1)/12)) -> 79 | C17: =INT(($AL$8+A17)/12) -> 2027 | D17: =IF(B17>=120,1,INDEX(mort_v1_M,MATCH(B17,mort_age,0))*INDEX(cif,MATCH(B17,cif_age,0),MATCH(C17,cif_year,0))) -> 0.027980578 | E17: =1-(1-D17)^(1/12) -> 0.0023621634 | F17: =G16*E17 -> 0.22887296 | G17: =G16-F17 -> 96.662373 | H17: =AND(A17-$AL$10>0,MOD(A17-$AL$10,12)=0) -> FALSE | I17: =IF($AL$4="CPI",IF(H17,INDEX(I_rec,MATCH(A17-$AL$13,cpi_rec_u,0))/INDEX(I_rec,MATCH(A17-$AL$13-12,cpi_rec_u,0)),1),1) -> 1 | J17: =J16*I17 -> 1000 | K17: =$AL$17*(INDEX(I_rec,MATCH(A17-1,cpi_rec_u,0))/$AL$18) -> 5.1461351 | L17: =G16*J17 -> 96891.246 | M17: =G16*K17 -> 498.61544 | N17: =INDEX(P_rec,MATCH(A17,curve_t,0)) -> 0.96107466 | O17: =N17/N16 -> 0.99722774 | P17: =J17+K17 -> 1005.1461 | Q17: =IF(B17>=120,1,D17*$AL$15) -> 0.026025105 | R17: =1-(1-Q17)^(1/12) -> 0.0021950665 | S17: =J17+K17*$AL$16 -> 1005.4778 | T17: =L17 -> 96891.246 | U17: =L18+M18+V18*O18+O18*U18 -> 10756331 | V17: =$AL$14*U17 -> 1343.6179 | W17: =P18+(1-E18)*(O18*(W18+$AL$14*W18)) -> 111277.34 | X17: =S18+(1-R18)*(O18*(X18+$AL$14*X18)) -> 114450.92 | Y17: =G17*(X17-W17) -> 306766.58 | Z17: =N16*L17 -> 93378.591 | AA17: =N16*M17+N17*V17 -> 1771.856 | AD17: =AND(G17>=0,G17<=G16) -> TRUE | AE17: =AND(D17>=0,D17<=1,E17>=0,E17<=1,Q17>=0,Q17<=1,R17>=0,R17<=1,F17<=G16) -> TRUE | AF17: =IF(A17>$AL$11,AND(G17=0,U17=0,Y17=0),TRUE) -> TRUE | AG17: =ABS(U17-((U16-L17-M17)/O17-V17))<=0.000000000001*((ABS(U16)+ABS(L17)+ABS(M17))/O17+ABS(V17)) -> TRUE | AH17: =Y17>=0 -> TRUE | AK17: maint_pm | AL17: =inputs!$B$23 -> 5
A18: 16 | B18: =MIN(120,INT(($AL$9+A18-1)/12)) -> 79 | C18: =INT(($AL$8+A18)/12) -> 2027 | D18: =IF(B18>=120,1,INDEX(mort_v1_M,MATCH(B18,mort_age,0))*INDEX(cif,MATCH(B18,cif_age,0),MATCH(C18,cif_year,0))) -> 0.027980578 | E18: =1-(1-D18)^(1/12) -> 0.0023621634 | F18: =G17*E18 -> 0.22833232 | G18: =G17-F18 -> 96.434041 | H18: =AND(A18-$AL$10>0,MOD(A18-$AL$10,12)=0) -> FALSE | I18: =IF($AL$4="CPI",IF(H18,INDEX(I_rec,MATCH(A18-$AL$13,cpi_rec_u,0))/INDEX(I_rec,MATCH(A18-$AL$13-12,cpi_rec_u,0)),1),1) -> 1 | J18: =J17*I18 -> 1000 | K18: =$AL$17*(INDEX(I_rec,MATCH(A18-1,cpi_rec_u,0))/$AL$18) -> 5.1567353 | L18: =G17*J18 -> 96662.373 | M18: =G17*K18 -> 498.46227 | N18: =INDEX(P_rec,MATCH(A18,curve_t,0)) -> 0.95839379 | O18: =N18/N17 -> 0.99721055 | P18: =J18+K18 -> 1005.1567 | Q18: =IF(B18>=120,1,D18*$AL$15) -> 0.026025105 | R18: =1-(1-Q18)^(1/12) -> 0.0021950665 | S18: =J18+K18*$AL$16 -> 1005.489 | T18: =L18 -> 96662.373 | U18: =L19+M19+V19*O19+O19*U19 -> 10687652 | V18: =$AL$14*U18 -> 1335.0389 | W18: =P19+(1-E19)*(O19*(W19+$AL$14*W19)) -> 110828.62 | X18: =S19+(1-R19)*(O19*(X19+$AL$14*X19)) -> 113998.8 | Y18: =G18*(X18-W18) -> 305712.75 | Z18: =N17*L18 -> 92899.757 | AA18: =N17*M18+N18*V18 -> 1758.5524 | AD18: =AND(G18>=0,G18<=G17) -> TRUE | AE18: =AND(D18>=0,D18<=1,E18>=0,E18<=1,Q18>=0,Q18<=1,R18>=0,R18<=1,F18<=G17) -> TRUE | AF18: =IF(A18>$AL$11,AND(G18=0,U18=0,Y18=0),TRUE) -> TRUE | AG18: =ABS(U18-((U17-L18-M18)/O18-V18))<=0.000000000001*((ABS(U17)+ABS(L18)+ABS(M18))/O18+ABS(V18)) -> TRUE | AH18: =Y18>=0 -> TRUE | AK18: I(0) | AL18: =INDEX(I_rec,MATCH(0,cpi_rec_u,0)) -> 100
A19: 17 | B19: =MIN(120,INT(($AL$9+A19-1)/12)) -> 79 | C19: =INT(($AL$8+A19)/12) -> 2027 | D19: =IF(B19>=120,1,INDEX(mort_v1_M,MATCH(B19,mort_age,0))*INDEX(cif,MATCH(B19,cif_age,0),MATCH(C19,cif_year,0))) -> 0.027980578 | E19: =1-(1-D19)^(1/12) -> 0.0023621634 | F19: =G18*E19 -> 0.22779296 | G19: =G18-F19 -> 96.206248 | H19: =AND(A19-$AL$10>0,MOD(A19-$AL$10,12)=0) -> FALSE | I19: =IF($AL$4="CPI",IF(H19,INDEX(I_rec,MATCH(A19-$AL$13,cpi_rec_u,0))/INDEX(I_rec,MATCH(A19-$AL$13-12,cpi_rec_u,0)),1),1) -> 1 | J19: =J18*I19 -> 1000 | K19: =$AL$17*(INDEX(I_rec,MATCH(A19-1,cpi_rec_u,0))/$AL$18) -> 5.1673573 | L19: =G18*J19 -> 96434.041 | M19: =G18*K19 -> 498.30914 | N19: =INDEX(P_rec,MATCH(A19,curve_t,0)) -> 0.95570413 | O19: =N19/N18 -> 0.99719358 | P19: =J19+K19 -> 1005.1674 | Q19: =IF(B19>=120,1,D19*$AL$15) -> 0.026025105 | R19: =1-(1-Q19)^(1/12) -> 0.0021950665 | S19: =J19+K19*$AL$16 -> 1005.5003 | T19: =L19 -> 96434.041 | U19: =L20+M20+V20*O20+O20*U20 -> 10619199 | V19: =$AL$14*U19 -> 1326.4881 | W19: =P20+(1-E20)*(O20*(W20+$AL$14*W20)) -> 110379.51 | X19: =S20+(1-R20)*(O20*(X20+$AL$14*X20)) -> 113546.39 | Y19: =G19*(X19-W19) -> 304672.97 | Z19: =N18*L19 -> 92421.785 | AA19: =N18*M19+N19*V19 -> 1745.3066 | AD19: =AND(G19>=0,G19<=G18) -> TRUE | AE19: =AND(D19>=0,D19<=1,E19>=0,E19<=1,Q19>=0,Q19<=1,R19>=0,R19<=1,F19<=G18) -> TRUE | AF19: =IF(A19>$AL$11,AND(G19=0,U19=0,Y19=0),TRUE) -> TRUE | AG19: =ABS(U19-((U18-L19-M19)/O19-V19))<=0.000000000001*((ABS(U18)+ABS(L19)+ABS(M19))/O19+ABS(V19)) -> TRUE | AH19: =Y19>=0 -> TRUE | AK19: mort_base (defined name read) | AL19: mort_v1_M
A20: 18 | B20: =MIN(120,INT(($AL$9+A20-1)/12)) -> 79 | C20: =INT(($AL$8+A20)/12) -> 2027 | D20: =IF(B20>=120,1,INDEX(mort_v1_M,MATCH(B20,mort_age,0))*INDEX(cif,MATCH(B20,cif_age,0),MATCH(C20,cif_year,0))) -> 0.027980578 | E20: =1-(1-D20)^(1/12) -> 0.0023621634 | F20: =G19*E20 -> 0.22725488 | G20: =G19-F20 -> 95.978993 | H20: =AND(A20-$AL$10>0,MOD(A20-$AL$10,12)=0) -> FALSE | I20: =IF($AL$4="CPI",IF(H20,INDEX(I_rec,MATCH(A20-$AL$13,cpi_rec_u,0))/INDEX(I_rec,MATCH(A20-$AL$13-12,cpi_rec_u,0)),1),1) -> 1 | J20: =J19*I20 -> 1000 | K20: =$AL$17*(INDEX(I_rec,MATCH(A20-1,cpi_rec_u,0))/$AL$18) -> 5.1780012 | L20: =G19*J20 -> 96206.248 | M20: =G19*K20 -> 498.15607 | N20: =INDEX(P_rec,MATCH(A20,curve_t,0)) -> 0.95300601 | O20: =N20/N19 -> 0.99717682 | P20: =J20+K20 -> 1005.178 | Q20: =IF(B20>=120,1,D20*$AL$15) -> 0.026025105 | R20: =1-(1-Q20)^(1/12) -> 0.0021950665 | S20: =J20+K20*$AL$16 -> 1005.5117 | T20: =L20 -> 96206.248 | U20: =L21+M21+V21*O21+O21*U21 -> 10550967 | V20: =$AL$14*U20 -> 1317.9651 | W20: =P21+(1-E21)*(O21*(W21+$AL$14*W21)) -> 109929.97 | X20: =S21+(1-R21)*(O21*(X21+$AL$14*X21)) -> 113093.65 | Y20: =G20*(X20-W20) -> 303647.13 | Z20: =N19*L20 -> 91944.708 | AA20: =N19*M20+N20*V20 -> 1732.1184 | AD20: =AND(G20>=0,G20<=G19) -> TRUE | AE20: =AND(D20>=0,D20<=1,E20>=0,E20<=1,Q20>=0,Q20<=1,R20>=0,R20<=1,F20<=G19) -> TRUE | AF20: =IF(A20>$AL$11,AND(G20=0,U20=0,Y20=0),TRUE) -> TRUE | AG20: =ABS(U20-((U19-L20-M20)/O20-V20))<=0.000000000001*((ABS(U19)+ABS(L20)+ABS(M20))/O20+ABS(V20)) -> TRUE | AH20: =Y20>=0 -> TRUE | AK20: df(t) (defined name read) | AL20: P_rec
A21: 19 | B21: =MIN(120,INT(($AL$9+A21-1)/12)) -> 79 | C21: =INT(($AL$8+A21)/12) -> 2027 | D21: =IF(B21>=120,1,INDEX(mort_v1_M,MATCH(B21,mort_age,0))*INDEX(cif,MATCH(B21,cif_age,0),MATCH(C21,cif_year,0))) -> 0.027980578 | E21: =1-(1-D21)^(1/12) -> 0.0023621634 | F21: =G20*E21 -> 0.22671807 | G21: =G20-F21 -> 95.752275 | H21: =AND(A21-$AL$10>0,MOD(A21-$AL$10,12)=0) -> FALSE | I21: =IF($AL$4="CPI",IF(H21,INDEX(I_rec,MATCH(A21-$AL$13,cpi_rec_u,0))/INDEX(I_rec,MATCH(A21-$AL$13-12,cpi_rec_u,0)),1),1) -> 1 | J21: =J20*I21 -> 1000 | K21: =$AL$17*(INDEX(I_rec,MATCH(A21-1,cpi_rec_u,0))/$AL$18) -> 5.188667 | L21: =G20*J21 -> 95978.993 | M21: =G20*K21 -> 498.00304 | N21: =INDEX(P_rec,MATCH(A21,curve_t,0)) -> 0.95029974 | O21: =N21/N20 -> 0.99716028 | P21: =J21+K21 -> 1005.1887 | Q21: =IF(B21>=120,1,D21*$AL$15) -> 0.026025105 | R21: =1-(1-Q21)^(1/12) -> 0.0021950665 | S21: =J21+K21*$AL$16 -> 1005.523 | T21: =L21 -> 95978.993 | U21: =L22+M22+V22*O22+O22*U22 -> 10482953 | V21: =$AL$14*U21 -> 1309.4691 | W21: =P22+(1-E22)*(O22*(W22+$AL$14*W22)) -> 109479.94 | X21: =S22+(1-R22)*(O22*(X22+$AL$14*X22)) -> 112640.54 | Y21: =G21*(X21-W21) -> 302635.14 | Z21: =N20*L21 -> 91468.557 | AA21: =N20*M21+N21*V21 -> 1718.9881 | AD21: =AND(G21>=0,G21<=G20) -> TRUE | AE21: =AND(D21>=0,D21<=1,E21>=0,E21<=1,Q21>=0,Q21<=1,R21>=0,R21<=1,F21<=G20) -> TRUE | AF21: =IF(A21>$AL$11,AND(G21=0,U21=0,Y21=0),TRUE) -> TRUE | AG21: =ABS(U21-((U20-L21-M21)/O21-V21))<=0.000000000001*((ABS(U20)+ABS(L21)+ABS(M21))/O21+ABS(V21)) -> TRUE | AH21: =Y21>=0 -> TRUE | AK21: I(u) (defined name read) | AL21: I_rec
A22: 20 | B22: =MIN(120,INT(($AL$9+A22-1)/12)) -> 79 | C22: =INT(($AL$8+A22)/12) -> 2027 | D22: =IF(B22>=120,1,INDEX(mort_v1_M,MATCH(B22,mort_age,0))*INDEX(cif,MATCH(B22,cif_age,0),MATCH(C22,cif_year,0))) -> 0.027980578 | E22: =1-(1-D22)^(1/12) -> 0.0023621634 | F22: =G21*E22 -> 0.22618252 | G22: =G21-F22 -> 95.526092 | H22: =AND(A22-$AL$10>0,MOD(A22-$AL$10,12)=0) -> FALSE | I22: =IF($AL$4="CPI",IF(H22,INDEX(I_rec,MATCH(A22-$AL$13,cpi_rec_u,0))/INDEX(I_rec,MATCH(A22-$AL$13-12,cpi_rec_u,0)),1),1) -> 1 | J22: =J21*I22 -> 1000 | K22: =$AL$17*(INDEX(I_rec,MATCH(A22-1,cpi_rec_u,0))/$AL$18) -> 5.1993548 | L22: =G21*J22 -> 95752.275 | M22: =G21*K22 -> 497.85005 | N22: =INDEX(P_rec,MATCH(A22,curve_t,0)) -> 0.94758564 | O22: =N22/N21 -> 0.99714396 | P22: =J22+K22 -> 1005.1994 | Q22: =IF(B22>=120,1,D22*$AL$15) -> 0.026025105 | R22: =1-(1-Q22)^(1/12) -> 0.0021950665 | S22: =J22+K22*$AL$16 -> 1005.5344 | T22: =L22 -> 95752.275 | U22: =L23+M23+V23*O23+O23*U23 -> 10415152 | V22: =$AL$14*U22 -> 1300.9998 | W22: =P23+(1-E23)*(O23*(W23+$AL$14*W23)) -> 109029.39 | X22: =S23+(1-R23)*(O23*(X23+$AL$14*X23)) -> 112187.03 | Y22: =G22*(X22-W22) -> 301636.9 | Z22: =N21*L22 -> 90993.362 | AA22: =N21*M22+N22*V22 -> 1705.9155 | AD22: =AND(G22>=0,G22<=G21) -> TRUE | AE22: =AND(D22>=0,D22<=1,E22>=0,E22<=1,Q22>=0,Q22<=1,R22>=0,R22<=1,F22<=G21) -> TRUE | AF22: =IF(A22>$AL$11,AND(G22=0,U22=0,Y22=0),TRUE) -> TRUE | AG22: =ABS(U22-((U21-L22-M22)/O22-V22))<=0.000000000001*((ABS(U21)+ABS(L22)+ABS(M22))/O22+ABS(V22)) -> TRUE | AH22: =Y22>=0 -> TRUE
A23: 21 | B23: =MIN(120,INT(($AL$9+A23-1)/12)) -> 80 | C23: =INT(($AL$8+A23)/12) -> 2027 | D23: =IF(B23>=120,1,INDEX(mort_v1_M,MATCH(B23,mort_age,0))*INDEX(cif,MATCH(B23,cif_age,0),MATCH(C23,cif_year,0))) -> 0.031367529 | E23: =1-(1-D23)^(1/12) -> 0.0026523119 | F23: =G22*E23 -> 0.25336499 | G23: =G22-F23 -> 95.272727 | H23: =AND(A23-$AL$10>0,MOD(A23-$AL$10,12)=0) -> FALSE | I23: =IF($AL$4="CPI",IF(H23,INDEX(I_rec,MATCH(A23-$AL$13,cpi_rec_u,0))/INDEX(I_rec,MATCH(A23-$AL$13-12,cpi_rec_u,0)),1),1) -> 1 | J23: =J22*I23 -> 1000 | K23: =$AL$17*(INDEX(I_rec,MATCH(A23-1,cpi_rec_u,0))/$AL$18) -> 5.2100647 | L23: =G22*J23 -> 95526.092 | M23: =G22*K23 -> 497.69712 | N23: =INDEX(P_rec,MATCH(A23,curve_t,0)) -> 0.94486402 | O23: =N23/N22 -> 0.99712784 | P23: =J23+K23 -> 1005.2101 | Q23: =IF(B23>=120,1,D23*$AL$15) -> 0.029175353 | R23: =1-(1-Q23)^(1/12) -> 0.0024644097 | S23: =J23+K23*$AL$16 -> 1005.5458 | T23: =L23 -> 95526.092 | U23: =L24+M24+V24*O24+O24*U24 -> 10347559 | V23: =$AL$14*U23 -> 1292.5565 | W23: =P24+(1-E24)*(O24*(W24+$AL$14*W24)) -> 108609.88 | X23: =S24+(1-R24)*(O24*(X24+$AL$14*X24)) -> 111763.24 | Y23: =G23*(X23-W23) -> 300429.7 | Z23: =N22*L23 -> 90519.153 | AA23: =N22*M23+N23*V23 -> 1692.9008 | AD23: =AND(G23>=0,G23<=G22) -> TRUE | AE23: =AND(D23>=0,D23<=1,E23>=0,E23<=1,Q23>=0,Q23<=1,R23>=0,R23<=1,F23<=G22) -> TRUE | AF23: =IF(A23>$AL$11,AND(G23=0,U23=0,Y23=0),TRUE) -> TRUE | AG23: =ABS(U23-((U22-L23-M23)/O23-V23))<=0.000000000001*((ABS(U22)+ABS(L23)+ABS(M23))/O23+ABS(V23)) -> TRUE | AH23: =Y23>=0 -> TRUE
A24: 22 | B24: =MIN(120,INT(($AL$9+A24-1)/12)) -> 80 | C24: =INT(($AL$8+A24)/12) -> 2027 | D24: =IF(B24>=120,1,INDEX(mort_v1_M,MATCH(B24,mort_age,0))*INDEX(cif,MATCH(B24,cif_age,0),MATCH(C24,cif_year,0))) -> 0.031367529 | E24: =1-(1-D24)^(1/12) -> 0.0026523119 | F24: =G23*E24 -> 0.25269298 | G24: =G23-F24 -> 95.020034 | H24: =AND(A24-$AL$10>0,MOD(A24-$AL$10,12)=0) -> FALSE | I24: =IF($AL$4="CPI",IF(H24,INDEX(I_rec,MATCH(A24-$AL$13,cpi_rec_u,0))/INDEX(I_rec,MATCH(A24-$AL$13-12,cpi_rec_u,0)),1),1) -> 1 | J24: =J23*I24 -> 1000 | K24: =$AL$17*(INDEX(I_rec,MATCH(A24-1,cpi_rec_u,0))/$AL$18) -> 5.2207965 | L24: =G23*J24 -> 95272.727 | M24: =G23*K24 -> 497.39952 | N24: =INDEX(P_rec,MATCH(A24,curve_t,0)) -> 0.94213518 | O24: =N24/N23 -> 0.99711192 | P24: =J24+K24 -> 1005.2208 | Q24: =IF(B24>=120,1,D24*$AL$15) -> 0.029175353 | R24: =1-(1-Q24)^(1/12) -> 0.0024644097 | S24: =J24+K24*$AL$16 -> 1005.5572 | T24: =L24 -> 95272.727 | U24: =L25+M25+V25*O25+O25*U25 -> 10280199 | V24: =$AL$14*U24 -> 1284.1422 | W24: =P25+(1-E25)*(O25*(W25+$AL$14*W25)) -> 108189.8 | X24: =S25+(1-R25)*(O25*(X25+$AL$14*X25)) -> 111339 | Y24: =G24*(X24-W24) -> 299236.92 | Z24: =N23*L24 -> 90019.772 | AA24: =N23*M24+N24*V24 -> 1679.8105 | AD24: =AND(G24>=0,G24<=G23) -> TRUE | AE24: =AND(D24>=0,D24<=1,E24>=0,E24<=1,Q24>=0,Q24<=1,R24>=0,R24<=1,F24<=G23) -> TRUE | AF24: =IF(A24>$AL$11,AND(G24=0,U24=0,Y24=0),TRUE) -> TRUE | AG24: =ABS(U24-((U23-L24-M24)/O24-V24))<=0.000000000001*((ABS(U23)+ABS(L24)+ABS(M24))/O24+ABS(V24)) -> TRUE | AH24: =Y24>=0 -> TRUE
A25: 23 | B25: =MIN(120,INT(($AL$9+A25-1)/12)) -> 80 | C25: =INT(($AL$8+A25)/12) -> 2027 | D25: =IF(B25>=120,1,INDEX(mort_v1_M,MATCH(B25,mort_age,0))*INDEX(cif,MATCH(B25,cif_age,0),MATCH(C25,cif_year,0))) -> 0.031367529 | E25: =1-(1-D25)^(1/12) -> 0.0026523119 | F25: =G24*E25 -> 0.25202276 | G25: =G24-F25 -> 94.768011 | H25: =AND(A25-$AL$10>0,MOD(A25-$AL$10,12)=0) -> FALSE | I25: =IF($AL$4="CPI",IF(H25,INDEX(I_rec,MATCH(A25-$AL$13,cpi_rec_u,0))/INDEX(I_rec,MATCH(A25-$AL$13-12,cpi_rec_u,0)),1),1) -> 1 | J25: =J24*I25 -> 1000 | K25: =$AL$17*(INDEX(I_rec,MATCH(A25-1,cpi_rec_u,0))/$AL$18) -> 5.2315505 | L25: =G24*J25 -> 95020.034 | M25: =G24*K25 -> 497.10211 | N25: =INDEX(P_rec,MATCH(A25,curve_t,0)) -> 0.93939943 | O25: =N25/N24 -> 0.99709622 | P25: =J25+K25 -> 1005.2316 | Q25: =IF(B25>=120,1,D25*$AL$15) -> 0.029175353 | R25: =1-(1-Q25)^(1/12) -> 0.0024644097 | S25: =J25+K25*$AL$16 -> 1005.5687 | T25: =L25 -> 95020.034 | U25: =L26+M26+V26*O26+O26*U26 -> 10213066 | V25: =$AL$14*U25 -> 1275.7564 | W25: =P26+(1-E26)*(O26*(W26+$AL$14*W26)) -> 107769.13 | X25: =S26+(1-R26)*(O26*(X26+$AL$14*X26)) -> 110914.27 | Y25: =G25*(X25-W25) -> 298058.45 | Z25: =N24*L25 -> 89521.717 | AA25: =N24*M25+N25*V25 -> 1666.7822 | AD25: =AND(G25>=0,G25<=G24) -> TRUE | AE25: =AND(D25>=0,D25<=1,E25>=0,E25<=1,Q25>=0,Q25<=1,R25>=0,R25<=1,F25<=G24) -> TRUE | AF25: =IF(A25>$AL$11,AND(G25=0,U25=0,Y25=0),TRUE) -> TRUE | AG25: =ABS(U25-((U24-L25-M25)/O25-V25))<=0.000000000001*((ABS(U24)+ABS(L25)+ABS(M25))/O25+ABS(V25)) -> TRUE | AH25: =Y25>=0 -> TRUE
A26: 24 | B26: =MIN(120,INT(($AL$9+A26-1)/12)) -> 80 | C26: =INT(($AL$8+A26)/12) -> 2027 | D26: =IF(B26>=120,1,INDEX(mort_v1_M,MATCH(B26,mort_age,0))*INDEX(cif,MATCH(B26,cif_age,0),MATCH(C26,cif_year,0))) -> 0.031367529 | E26: =1-(1-D26)^(1/12) -> 0.0026523119 | F26: =G25*E26 -> 0.25135432 | G26: =G25-F26 -> 94.516657 | H26: =AND(A26-$AL$10>0,MOD(A26-$AL$10,12)=0) -> FALSE | I26: =IF($AL$4="CPI",IF(H26,INDEX(I_rec,MATCH(A26-$AL$13,cpi_rec_u,0))/INDEX(I_rec,MATCH(A26-$AL$13-12,cpi_rec_u,0)),1),1) -> 1 | J26: =J25*I26 -> 1000 | K26: =$AL$17*(INDEX(I_rec,MATCH(A26-1,cpi_rec_u,0))/$AL$18) -> 5.2423267 | L26: =G25*J26 -> 94768.011 | M26: =G25*K26 -> 496.80487 | N26: =INDEX(P_rec,MATCH(A26,curve_t,0)) -> 0.93665705 | O26: =N26/N25 -> 0.99708071 | P26: =J26+K26 -> 1005.2423 | Q26: =IF(B26>=120,1,D26*$AL$15) -> 0.029175353 | R26: =1-(1-Q26)^(1/12) -> 0.0024644097 | S26: =J26+K26*$AL$16 -> 1005.5801 | T26: =L26 -> 94768.011 | U26: =L27+M27+V27*O27+O27*U27 -> 10146157 | V26: =$AL$14*U26 -> 1267.3985 | W26: =P27+(1-E27)*(O27*(W27+$AL$14*W27)) -> 107347.82 | X26: =S27+(1-R27)*(O27*(X27+$AL$14*X27)) -> 110489 | Y26: =G26*(X26-W26) -> 296894.19 | Z26: =N25*L26 -> 89025.015 | AA26: =N25*M26+N26*V26 -> 1653.816 | AD26: =AND(G26>=0,G26<=G25) -> TRUE | AE26: =AND(D26>=0,D26<=1,E26>=0,E26<=1,Q26>=0,Q26<=1,R26>=0,R26<=1,F26<=G25) -> TRUE | AF26: =IF(A26>$AL$11,AND(G26=0,U26=0,Y26=0),TRUE) -> TRUE | AG26: =ABS(U26-((U25-L26-M26)/O26-V26))<=0.000000000001*((ABS(U25)+ABS(L26)+ABS(M26))/O26+ABS(V26)) -> TRUE | AH26: =Y26>=0 -> TRUE
A27: 25 | B27: =MIN(120,INT(($AL$9+A27-1)/12)) -> 80 | C27: =INT(($AL$8+A27)/12) -> 2028 | D27: =IF(B27>=120,1,INDEX(mort_v1_M,MATCH(B27,mort_age,0))*INDEX(cif,MATCH(B27,cif_age,0),MATCH(C27,cif_year,0))) -> 0.030748961 | E27: =1-(1-D27)^(1/12) -> 0.002599252 | F27: =G26*E27 -> 0.24567261 | G27: =G26-F27 -> 94.270984 | H27: =AND(A27-$AL$10>0,MOD(A27-$AL$10,12)=0) -> TRUE | I27: =IF($AL$4="CPI",IF(H27,INDEX(I_rec,MATCH(A27-$AL$13,cpi_rec_u,0))/INDEX(I_rec,MATCH(A27-$AL$13-12,cpi_rec_u,0)),1),1) -> 1 | J27: =J26*I27 -> 1000 | K27: =$AL$17*(INDEX(I_rec,MATCH(A27-1,cpi_rec_u,0))/$AL$18) -> 5.253125 | L27: =G26*J27 -> 94516.657 | M27: =G26*K27 -> 496.50781 | N27: =INDEX(P_rec,MATCH(A27,curve_t,0)) -> 0.93390833 | O27: =N27/N26 -> 0.9970654 | P27: =J27+K27 -> 1005.2531 | Q27: =IF(B27>=120,1,D27*$AL$15) -> 0.028600015 | R27: =1-(1-Q27)^(1/12) -> 0.0024151592 | S27: =J27+K27*$AL$16 -> 1005.5916 | T27: =L27 -> 94516.657 | U27: =L28+M28+V28*O28+O28*U28 -> 10079468 | V27: =$AL$14*U27 -> 1259.0681 | W27: =P28+(1-E28)*(O28*(W28+$AL$14*W28)) -> 106920.15 | X27: =S28+(1-R28)*(O28*(X28+$AL$14*X28)) -> 110057.74 | Y27: =G27*(X27-W27) -> 295783.75 | Z27: =N26*L27 -> 88529.693 | AA27: =N26*M27+N27*V27 -> 1640.9117 | AD27: =AND(G27>=0,G27<=G26) -> TRUE | AE27: =AND(D27>=0,D27<=1,E27>=0,E27<=1,Q27>=0,Q27<=1,R27>=0,R27<=1,F27<=G26) -> TRUE | AF27: =IF(A27>$AL$11,AND(G27=0,U27=0,Y27=0),TRUE) -> TRUE | AG27: =ABS(U27-((U26-L27-M27)/O27-V27))<=0.000000000001*((ABS(U26)+ABS(L27)+ABS(M27))/O27+ABS(V27)) -> TRUE | AH27: =Y27>=0 -> TRUE
